Workbook
Name ceiling: Settings!$B$11
Name implementation_month: Settings!$B$8
Name rate_above: Settings!$B$10
Name rate_below: Settings!$B$9
Name threshold_pct: Settings!$B$7

Sheet Settings
A1: Model settings
A2: Mini version on the sample fixture (10 rows)
A4: Only the green cells are meant to be edited. Everything else recalculates.
A6: Name | B6: Value | C6: What it is | D6: Notes
A7: threshold_pct | B7: 5 | C7: Threshold, % | D7: Target unexplained gap for the Minimum compliance scenario.
A8: implementation_month | B8: 7 | C8: Implementation month | D8: 1 = January. Drives the current-year effect: (13 - m) / 12.
A9: rate_below | B9: 31.5 | C9: Contribution rate below ceiling, % | D9: Applied to the part of the uplift that fits under the ceiling.
A10: rate_above | B10: 1.15 | C10: Contribution rate above ceiling, % | D10: Applied to the part that pushes base pay past the ceiling.
A11: ceiling | B11: 61214 | C11: Contribution ceiling, EUR | D11: Annual, applied to the employee's actual base pay.
A14: Source data
A15: The Data sheet holds a fixed export. The demo-data generator uses a PRNG (mulberry32 + Box-Muller) that cannot be reproduced byte-for-byte in Excel formulas, so the array is exported as plain numbers. Everything computed on top of it is live.

Sheet Data
A1: Employee-level data and calculation
A2: Yellow — source data from the CSV. Blue — calculated by formula. Formulas reference the Categories sheet, where category-level gaps are computed.
A4: id | B4: category | C4: gender | D4: base_salary | E4: variable_pay | F4: tenure_years | G4: grade | H4: fte | I4: months_worked | J4: factor | K4: n_base | L4: n_var | M4: n_total | N4: actual_total | O4: median_cat | P4: recip_min | Q4: deficit_min | R4: share_min | S4: uplift_norm_min | T4: uplift_act_min | U4: contrib_min | V4: cost_min | W4: recip_full | X4: deficit_full | Y4: share_full | Z4: uplift_norm_full | AA4: uplift_act_full | AB4: contrib_full | AC4: cost_full | AD4: _rank_cat | AE4: _n_cat | AF4: _rank_sex | AG4: _n_sex
A5: E001 | B5: Engineering | C5: F | D5: 54000 | E5: 6500 | F5: 3.5 | G5: 6 | H5: 1 | I5: 12 | J5: =H5*(I5/12) -> 1 | K5: =D5/J5 -> 54000 | L5: =E5/J5 -> 6500 | M5: =K5+L5 -> 60500 | N5: =D5+E5 -> 60500 | O5: =(SUMIFS($M$5:$M$14,$B$5:$B$14,B5,$AD$5:$AD$14,INT((AE5+1)/2))+SUMIFS($M$5:$M$14,$B$5:$B$14,B5,$AD$5:$AD$14,INT(AE5/2)+1))/2 -> 66850 | P5: =IF(AND(C5="F",M5<O5,SUMIFS(Categories!$Z$5:$Z$7,Categories!$A$5:$A$7,B5)=1),1,0) -> 0 | Q5: =IF(P5=1,O5-M5,0) -> 0 | R5: =IF(AND(P5=1,SUMIFS(Categories!$AA$5:$AA$7,Categories!$A$5:$A$7,B5)>0),Q5/SUMIFS(Categories!$AA$5:$AA$7,Categories!$A$5:$A$7,B5),0) -> 0 | S5: =R5*SUMIFS(Categories!$AB$5:$AB$7,Categories!$A$5:$A$7,B5) -> 0 | T5: =S5*J5 -> 0 | U5: =IF(T5<=0,0,(rate_below/100)*MIN(T5,MAX(0,ceiling-D5))+(rate_above/100)*(T5-MIN(T5,MAX(0,ceiling-D5)))) -> 0 | V5: =T5+U5 -> 0 | W5: =IF(AND(C5="F",M5<O5,SUMIFS(Categories!$AH$5:$AH$7,Categories!$A$5:$A$7,B5)=1),1,0) -> 1 | X5: =IF(W5=1,O5-M5,0) -> 6350 | Y5: =IF(AND(W5=1,SUMIFS(Categories!$AI$5:$AI$7,Categories!$A$5:$A$7,B5)>0),X5/SUMIFS(Categories!$AI$5:$AI$7,Categories!$A$5:$A$7,B5),0) -> 0.77439024 | Z5: =Y5*SUMIFS(Categories!$AJ$5:$AJ$7,Categories!$A$5:$A$7,B5) -> 2599.1353 | AA5: =Z5*J5 -> 2599.1353 | AB5: =IF(AA5<=0,0,(rate_below/100)*MIN(AA5,MAX(0,ceiling-D5))+(rate_above/100)*(AA5-MIN(AA5,MAX(0,ceiling-D5)))) -> 818.72761 | AC5: =AA5+AB5 -> 3417.8629 | AD5: =SUMPRODUCT(($B$5:$B$14=B5)*($M$5:$M$14<M5))+SUMPRODUCT(($B$5:$B$14=B5)*($M$5:$M$14=M5)*(ROW($M$5:$M$14)<ROW(M5)))+1 -> 1 | AE5: =COUNTIF($B$5:$B$14,B5) -> 4 | AF5: =SUMPRODUCT(($B$5:$B$14=B5)*($C$5:$C$14=C5)*($M$5:$M$14<M5))+SUMPRODUCT(($B$5:$B$14=B5)*($C$5:$C$14=C5)*($M$5:$M$14=M5)*(ROW($M$5:$M$14)<ROW(M5)))+1 -> 1 | AG5: =COUNTIFS($B$5:$B$14,B5,$C$5:$C$14,C5) -> 2
A6: E002 | B6: Engineering | C6: M | D6: 59500 | E6: 9200 | F6: 5 | G6: 6 | H6: 1 | I6: 12 | J6: =H6*(I6/12) -> 1 | K6: =D6/J6 -> 59500 | L6: =E6/J6 -> 9200 | M6: =K6+L6 -> 68700 | N6: =D6+E6 -> 68700 | O6: =(SUMIFS($M$5:$M$14,$B$5:$B$14,B6,$AD$5:$AD$14,INT((AE6+1)/2))+SUMIFS($M$5:$M$14,$B$5:$B$14,B6,$AD$5:$AD$14,INT(AE6/2)+1))/2 -> 66850 | P6: =IF(AND(C6="F",M6<O6,SUMIFS(Categories!$Z$5:$Z$7,Categories!$A$5:$A$7,B6)=1),1,0) -> 0 | Q6: =IF(P6=1,O6-M6,0) -> 0 | R6: =IF(AND(P6=1,SUMIFS(Categories!$AA$5:$AA$7,Categories!$A$5:$A$7,B6)>0),Q6/SUMIFS(Categories!$AA$5:$AA$7,Categories!$A$5:$A$7,B6),0) -> 0 | S6: =R6*SUMIFS(Categories!$AB$5:$AB$7,Categories!$A$5:$A$7,B6) -> 0 | T6: =S6*J6 -> 0 | U6: =IF(T6<=0,0,(rate_below/100)*MIN(T6,MAX(0,ceiling-D6))+(rate_above/100)*(T6-MIN(T6,MAX(0,ceiling-D6)))) -> 0 | V6: =T6+U6 -> 0 | W6: =IF(AND(C6="F",M6<O6,SUMIFS(Categories!$AH$5:$AH$7,Categories!$A$5:$A$7,B6)=1),1,0) -> 0 | X6: =IF(W6=1,O6-M6,0) -> 0 | Y6: =IF(AND(W6=1,SUMIFS(Categories!$AI$5:$AI$7,Categories!$A$5:$A$7,B6)>0),X6/SUMIFS(Categories!$AI$5:$AI$7,Categories!$A$5:$A$7,B6),0) -> 0 | Z6: =Y6*SUMIFS(Categories!$AJ$5:$AJ$7,Categories!$A$5:$A$7,B6) -> 0 | AA6: =Z6*J6 -> 0 | AB6: =IF(AA6<=0,0,(rate_below/100)*MIN(AA6,MAX(0,ceiling-D6))+(rate_above/100)*(AA6-MIN(AA6,MAX(0,ceiling-D6)))) -> 0 | AC6: =AA6+AB6 -> 0 | AD6: =SUMPRODUCT(($B$5:$B$14=B6)*($M$5:$M$14<M6))+SUMPRODUCT(($B$5:$B$14=B6)*($M$5:$M$14=M6)*(ROW($M$5:$M$14)<ROW(M6)))+1 -> 3 | AE6: =COUNTIF($B$5:$B$14,B6) -> 4 | AF6: =SUMPRODUCT(($B$5:$B$14=B6)*($C$5:$C$14=C6)*($M$5:$M$14<M6))+SUMPRODUCT(($B$5:$B$14=B6)*($C$5:$C$14=C6)*($M$5:$M$14=M6)*(ROW($M$5:$M$14)<ROW(M6)))+1 -> 1 | AG6: =COUNTIFS($B$5:$B$14,B6,$C$5:$C$14,C6) -> 2
A7: E003 | B7: Engineering | C7: M | D7: 71000 | E7: 14000 | F7: 8 | G7: 8 | H7: 1 | I7: 12 | J7: =H7*(I7/12) -> 1 | K7: =D7/J7 -> 71000 | L7: =E7/J7 -> 14000 | M7: =K7+L7 -> 85000 | N7: =D7+E7 -> 85000 | O7: =(SUMIFS($M$5:$M$14,$B$5:$B$14,B7,$AD$5:$AD$14,INT((AE7+1)/2))+SUMIFS($M$5:$M$14,$B$5:$B$14,B7,$AD$5:$AD$14,INT(AE7/2)+1))/2 -> 66850 | P7: =IF(AND(C7="F",M7<O7,SUMIFS(Categories!$Z$5:$Z$7,Categories!$A$5:$A$7,B7)=1),1,0) -> 0 | Q7: =IF(P7=1,O7-M7,0) -> 0 | R7: =IF(AND(P7=1,SUMIFS(Categories!$AA$5:$AA$7,Categories!$A$5:$A$7,B7)>0),Q7/SUMIFS(Categories!$AA$5:$AA$7,Categories!$A$5:$A$7,B7),0) -> 0 | S7: =R7*SUMIFS(Categories!$AB$5:$AB$7,Categories!$A$5:$A$7,B7) -> 0 | T7: =S7*J7 -> 0 | U7: =IF(T7<=0,0,(rate_below/100)*MIN(T7,MAX(0,ceiling-D7))+(rate_above/100)*(T7-MIN(T7,MAX(0,ceiling-D7)))) -> 0 | V7: =T7+U7 -> 0 | W7: =IF(AND(C7="F",M7<O7,SUMIFS(Categories!$AH$5:$AH$7,Categories!$A$5:$A$7,B7)=1),1,0) -> 0 | X7: =IF(W7=1,O7-M7,0) -> 0 | Y7: =IF(AND(W7=1,SUMIFS(Categories!$AI$5:$AI$7,Categories!$A$5:$A$7,B7)>0),X7/SUMIFS(Categories!$AI$5:$AI$7,Categories!$A$5:$A$7,B7),0) -> 0 | Z7: =Y7*SUMIFS(Categories!$AJ$5:$AJ$7,Categories!$A$5:$A$7,B7) -> 0 | AA7: =Z7*J7 -> 0 | AB7: =IF(AA7<=0,0,(rate_below/100)*MIN(AA7,MAX(0,ceiling-D7))+(rate_above/100)*(AA7-MIN(AA7,MAX(0,ceiling-D7)))) -> 0 | AC7: =AA7+AB7 -> 0 | AD7: =SUMPRODUCT(($B$5:$B$14=B7)*($M$5:$M$14<M7))+SUMPRODUCT(($B$5:$B$14=B7)*($M$5:$M$14=M7)*(ROW($M$5:$M$14)<ROW(M7)))+1 -> 4 | AE7: =COUNTIF($B$5:$B$14,B7) -> 4 | AF7: =SUMPRODUCT(($B$5:$B$14=B7)*($C$5:$C$14=C7)*($M$5:$M$14<M7))+SUMPRODUCT(($B$5:$B$14=B7)*($C$5:$C$14=C7)*($M$5:$M$14=M7)*(ROW($M$5:$M$14)<ROW(M7)))+1 -> 2 | AG7: =COUNTIFS($B$5:$B$14,B7,$C$5:$C$14,C7) -> 2
A8: E004 | B8: Engineering | C8: F | D8: 48000 | E8: 4000 | F8: 1.5 | G8: 5 | H8: 0.8 | I8: 12 | J8: =H8*(I8/12) -> 0.8 | K8: =D8/J8 -> 60000 | L8: =E8/J8 -> 5000 | M8: =K8+L8 -> 65000 | N8: =D8+E8 -> 52000 | O8: =(SUMIFS($M$5:$M$14,$B$5:$B$14,B8,$AD$5:$AD$14,INT((AE8+1)/2))+SUMIFS($M$5:$M$14,$B$5:$B$14,B8,$AD$5:$AD$14,INT(AE8/2)+1))/2 -> 66850 | P8: =IF(AND(C8="F",M8<O8,SUMIFS(Categories!$Z$5:$Z$7,Categories!$A$5:$A$7,B8)=1),1,0) -> 0 | Q8: =IF(P8=1,O8-M8,0) -> 0 | R8: =IF(AND(P8=1,SUMIFS(Categories!$AA$5:$AA$7,Categories!$A$5:$A$7,B8)>0),Q8/SUMIFS(Categories!$AA$5:$AA$7,Categories!$A$5:$A$7,B8),0) -> 0 | S8: =R8*SUMIFS(Categories!$AB$5:$AB$7,Categories!$A$5:$A$7,B8) -> 0 | T8: =S8*J8 -> 0 | U8: =IF(T8<=0,0,(rate_below/100)*MIN(T8,MAX(0,ceiling-D8))+(rate_above/100)*(T8-MIN(T8,MAX(0,ceiling-D8)))) -> 0 | V8: =T8+U8 -> 0 | W8: =IF(AND(C8="F",M8<O8,SUMIFS(Categories!$AH$5:$AH$7,Categories!$A$5:$A$7,B8)=1),1,0) -> 1 | X8: =IF(W8=1,O8-M8,0) -> 1850 | Y8: =IF(AND(W8=1,SUMIFS(Categories!$AI$5:$AI$7,Categories!$A$5:$A$7,B8)>0),X8/SUMIFS(Categories!$AI$5:$AI$7,Categories!$A$5:$A$7,B8),0) -> 0.22560976 | Z8: =Y8*SUMIFS(Categories!$AJ$5:$AJ$7,Categories!$A$5:$A$7,B8) -> 757.22838 | AA8: =Z8*J8 -> 605.78271 | AB8: =IF(AA8<=0,0,(rate_below/100)*MIN(AA8,MAX(0,ceiling-D8))+(rate_above/100)*(AA8-MIN(AA8,MAX(0,ceiling-D8)))) -> 190.82155 | AC8: =AA8+AB8 -> 796.60426 | AD8: =SUMPRODUCT(($B$5:$B$14=B8)*($M$5:$M$14<M8))+SUMPRODUCT(($B$5:$B$14=B8)*($M$5:$M$14=M8)*(ROW($M$5:$M$14)<ROW(M8)))+1 -> 2 | AE8: =COUNTIF($B$5:$B$14,B8) -> 4 | AF8: =SUMPRODUCT(($B$5:$B$14=B8)*($C$5:$C$14=C8)*($M$5:$M$14<M8))+SUMPRODUCT(($B$5:$B$14=B8)*($C$5:$C$14=C8)*($M$5:$M$14=M8)*(ROW($M$5:$M$14)<ROW(M8)))+1 -> 2 | AG8: =COUNTIFS($B$5:$B$14,B8,$C$5:$C$14,C8) -> 2
A9: E005 | B9: Sales | C9: F | D9: 41000 | E9: 7000 | F9: 2 | G9: 5 | H9: 1 | I9: 12 | J9: =H9*(I9/12) -> 1 | K9: =D9/J9 -> 41000 | L9: =E9/J9 -> 7000 | M9: =K9+L9 -> 48000 | N9: =D9+E9 -> 48000 | O9: =(SUMIFS($M$5:$M$14,$B$5:$B$14,B9,$AD$5:$AD$14,INT((AE9+1)/2))+SUMIFS($M$5:$M$14,$B$5:$B$14,B9,$AD$5:$AD$14,INT(AE9/2)+1))/2 -> 54000 | P9: =IF(AND(C9="F",M9<O9,SUMIFS(Categories!$Z$5:$Z$7,Categories!$A$5:$A$7,B9)=1),1,0) -> 1 | Q9: =IF(P9=1,O9-M9,0) -> 6000 | R9: =IF(AND(P9=1,SUMIFS(Categories!$AA$5:$AA$7,Categories!$A$5:$A$7,B9)>0),Q9/SUMIFS(Categories!$AA$5:$AA$7,Categories!$A$5:$A$7,B9),0) -> 1 | S9: =R9*SUMIFS(Categories!$AB$5:$AB$7,Categories!$A$5:$A$7,B9) -> 27117.857 | T9: =S9*J9 -> 27117.857 | U9: =IF(T9<=0,0,(rate_below/100)*MIN(T9,MAX(0,ceiling-D9))+(rate_above/100)*(T9-MIN(T9,MAX(0,ceiling-D9)))) -> 6446.8044 | V9: =T9+U9 -> 33564.661 | W9: =IF(AND(C9="F",M9<O9,SUMIFS(Categories!$AH$5:$AH$7,Categories!$A$5:$A$7,B9)=1),1,0) -> 1 | X9: =IF(W9=1,O9-M9,0) -> 6000 | Y9: =IF(AND(W9=1,SUMIFS(Categories!$AI$5:$AI$7,Categories!$A$5:$A$7,B9)>0),X9/SUMIFS(Categories!$AI$5:$AI$7,Categories!$A$5:$A$7,B9),0) -> 1 | Z9: =Y9*SUMIFS(Categories!$AJ$5:$AJ$7,Categories!$A$5:$A$7,B9) -> 31071.429 | AA9: =Z9*J9 -> 31071.429 | AB9: =IF(AA9<=0,0,(rate_below/100)*MIN(AA9,MAX(0,ceiling-D9))+(rate_above/100)*(AA9-MIN(AA9,MAX(0,ceiling-D9)))) -> 6492.2704 | AC9: =AA9+AB9 -> 37563.699 | AD9: =SUMPRODUCT(($B$5:$B$14=B9)*($M$5:$M$14<M9))+SUMPRODUCT(($B$5:$B$14=B9)*($M$5:$M$14=M9)*(ROW($M$5:$M$14)<ROW(M9)))+1 -> 1 | AE9: =COUNTIF($B$5:$B$14,B9) -> 3 | AF9: =SUMPRODUCT(($B$5:$B$14=B9)*($C$5:$C$14=C9)*($M$5:$M$14<M9))+SUMPRODUCT(($B$5:$B$14=B9)*($C$5:$C$14=C9)*($M$5:$M$14=M9)*(ROW($M$5:$M$14)<ROW(M9)))+1 -> 1 | AG9: =COUNTIFS($B$5:$B$14,B9,$C$5:$C$14,C9) -> 1
A10: E006 | B10: Sales | C10: M | D10: 42500 | E10: 11500 | F10: 2.5 | G10: 5 | H10: 1 | I10: 12 | J10: =H10*(I10/12) -> 1 | K10: =D10/J10 -> 42500 | L10: =E10/J10 -> 11500 | M10: =K10+L10 -> 54000 | N10: =D10+E10 -> 54000 | O10: =(SUMIFS($M$5:$M$14,$B$5:$B$14,B10,$AD$5:$AD$14,INT((AE10+1)/2))+SUMIFS($M$5:$M$14,$B$5:$B$14,B10,$AD$5:$AD$14,INT(AE10/2)+1))/2 -> 54000 | P10: =IF(AND(C10="F",M10<O10,SUMIFS(Categories!$Z$5:$Z$7,Categories!$A$5:$A$7,B10)=1),1,0) -> 0 | Q10: =IF(P10=1,O10-M10,0) -> 0 | R10: =IF(AND(P10=1,SUMIFS(Categories!$AA$5:$AA$7,Categories!$A$5:$A$7,B10)>0),Q10/SUMIFS(Categories!$AA$5:$AA$7,Categories!$A$5:$A$7,B10),0) -> 0 | S10: =R10*SUMIFS(Categories!$AB$5:$AB$7,Categories!$A$5:$A$7,B10) -> 0 | T10: =S10*J10 -> 0 | U10: =IF(T10<=0,0,(rate_below/100)*MIN(T10,MAX(0,ceiling-D10))+(rate_above/100)*(T10-MIN(T10,MAX(0,ceiling-D10)))) -> 0 | V10: =T10+U10 -> 0 | W10: =IF(AND(C10="F",M10<O10,SUMIFS(Categories!$AH$5:$AH$7,Categories!$A$5:$A$7,B10)=1),1,0) -> 0 | X10: =IF(W10=1,O10-M10,0) -> 0 | Y10: =IF(AND(W10=1,SUMIFS(Categories!$AI$5:$AI$7,Categories!$A$5:$A$7,B10)>0),X10/SUMIFS(Categories!$AI$5:$AI$7,Categories!$A$5:$A$7,B10),0) -> 0 | Z10: =Y10*SUMIFS(Categories!$AJ$5:$AJ$7,Categories!$A$5:$A$7,B10) -> 0 | AA10: =Z10*J10 -> 0 | AB10: =IF(AA10<=0,0,(rate_below/100)*MIN(AA10,MAX(0,ceiling-D10))+(rate_above/100)*(AA10-MIN(AA10,MAX(0,ceiling-D10)))) -> 0 | AC10: =AA10+AB10 -> 0 | AD10: =SUMPRODUCT(($B$5:$B$14=B10)*($M$5:$M$14<M10))+SUMPRODUCT(($B$5:$B$14=B10)*($M$5:$M$14=M10)*(ROW($M$5:$M$14)<ROW(M10)))+1 -> 2 | AE10: =COUNTIF($B$5:$B$14,B10) -> 3 | AF10: =SUMPRODUCT(($B$5:$B$14=B10)*($C$5:$C$14=C10)*($M$5:$M$14<M10))+SUMPRODUCT(($B$5:$B$14=B10)*($C$5:$C$14=C10)*($M$5:$M$14=M10)*(ROW($M$5:$M$14)<ROW(M10)))+1 -> 1 | AG10: =COUNTIFS($B$5:$B$14,B10,$C$5:$C$14,C10) -> 2
A11: E007 | B11: Sales | C11: M | D11: 52000 | E11: 8750 | F11: 6 | G11: 7 | H11: 1 | I11: 7 | J11: =H11*(I11/12) -> 0.58333333 | K11: =D11/J11 -> 89142.857 | L11: =E11/J11 -> 15000 | M11: =K11+L11 -> 104142.86 | N11: =D11+E11 -> 60750 | O11: =(SUMIFS($M$5:$M$14,$B$5:$B$14,B11,$AD$5:$AD$14,INT((AE11+1)/2))+SUMIFS($M$5:$M$14,$B$5:$B$14,B11,$AD$5:$AD$14,INT(AE11/2)+1))/2 -> 54000 | P11: =IF(AND(C11="F",M11<O11,SUMIFS(Categories!$Z$5:$Z$7,Categories!$A$5:$A$7,B11)=1),1,0) -> 0 | Q11: =IF(P11=1,O11-M11,0) -> 0 | R11: =IF(AND(P11=1,SUMIFS(Categories!$AA$5:$AA$7,Categories!$A$5:$A$7,B11)>0),Q11/SUMIFS(Categories!$AA$5:$AA$7,Categories!$A$5:$A$7,B11),0) -> 0 | S11: =R11*SUMIFS(Categories!$AB$5:$AB$7,Categories!$A$5:$A$7,B11) -> 0 | T11: =S11*J11 -> 0 | U11: =IF(T11<=0,0,(rate_below/100)*MIN(T11,MAX(0,ceiling-D11))+(rate_above/100)*(T11-MIN(T11,MAX(0,ceiling-D11)))) -> 0 | V11: =T11+U11 -> 0 | W11: =IF(AND(C11="F",M11<O11,SUMIFS(Categories!$AH$5:$AH$7,Categories!$A$5:$A$7,B11)=1),1,0) -> 0 | X11: =IF(W11=1,O11-M11,0) -> 0 | Y11: =IF(AND(W11=1,SUMIFS(Categories!$AI$5:$AI$7,Categories!$A$5:$A$7,B11)>0),X11/SUMIFS(Categories!$AI$5:$AI$7,Categories!$A$5:$A$7,B11),0) -> 0 | Z11: =Y11*SUMIFS(Categories!$AJ$5:$AJ$7,Categories!$A$5:$A$7,B11) -> 0 | AA11: =Z11*J11 -> 0 | AB11: =IF(AA11<=0,0,(rate_below/100)*MIN(AA11,MAX(0,ceiling-D11))+(rate_above/100)*(AA11-MIN(AA11,MAX(0,ceiling-D11)))) -> 0 | AC11: =AA11+AB11 -> 0 | AD11: =SUMPRODUCT(($B$5:$B$14=B11)*($M$5:$M$14<M11))+SUMPRODUCT(($B$5:$B$14=B11)*($M$5:$M$14=M11)*(ROW($M$5:$M$14)<ROW(M11)))+1 -> 3 | AE11: =COUNTIF($B$5:$B$14,B11) -> 3 | AF11: =SUMPRODUCT(($B$5:$B$14=B11)*($C$5:$C$14=C11)*($M$5:$M$14<M11))+SUMPRODUCT(($B$5:$B$14=B11)*($C$5:$C$14=C11)*($M$5:$M$14=M11)*(ROW($M$5:$M$14)<ROW(M11)))+1 -> 2 | AG11: =COUNTIFS($B$5:$B$14,B11,$C$5:$C$14,C11) -> 2
A12: E008 | B12: Customer Support | C12: F | D12: 31000 | E12: 1200 | F12: 4 | G12: 4 | H12: 0.5 | I12: 12 | J12: =H12*(I12/12) -> 0.5 | K12: =D12/J12 -> 62000 | L12: =E12/J12 -> 2400 | M12: =K12+L12 -> 64400 | N12: =D12+E12 -> 32200 | O12: =(SUMIFS($M$5:$M$14,$B$5:$B$14,B12,$AD$5:$AD$14,INT((AE12+1)/2))+SUMIFS($M$5:$M$14,$B$5:$B$14,B12,$AD$5:$AD$14,INT(AE12/2)+1))/2 -> 35000 | P12: =IF(AND(C12="F",M12<O12,SUMIFS(Categories!$Z$5:$Z$7,Categories!$A$5:$A$7,B12)=1),1,0) -> 0 | Q12: =IF(P12=1,O12-M12,0) -> 0 | R12: =IF(AND(P12=1,SUMIFS(Categories!$AA$5:$AA$7,Categories!$A$5:$A$7,B12)>0),Q12/SUMIFS(Categories!$AA$5:$AA$7,Categories!$A$5:$A$7,B12),0) -> 0 | S12: =R12*SUMIFS(Categories!$AB$5:$AB$7,Categories!$A$5:$A$7,B12) -> 0 | T12: =S12*J12 -> 0 | U12: =IF(T12<=0,0,(rate_below/100)*MIN(T12,MAX(0,ceiling-D12))+(rate_above/100)*(T12-MIN(T12,MAX(0,ceiling-D12)))) -> 0 | V12: =T12+U12 -> 0 | W12: =IF(AND(C12="F",M12<O12,SUMIFS(Categories!$AH$5:$AH$7,Categories!$A$5:$A$7,B12)=1),1,0) -> 0 | X12: =IF(W12=1,O12-M12,0) -> 0 | Y12: =IF(AND(W12=1,SUMIFS(Categories!$AI$5:$AI$7,Categories!$A$5:$A$7,B12)>0),X12/SUMIFS(Categories!$AI$5:$AI$7,Categories!$A$5:$A$7,B12),0) -> 0 | Z12: =Y12*SUMIFS(Categories!$AJ$5:$AJ$7,Categories!$A$5:$A$7,B12) -> 0 | AA12: =Z12*J12 -> 0 | AB12: =IF(AA12<=0,0,(rate_below/100)*MIN(AA12,MAX(0,ceiling-D12))+(rate_above/100)*(AA12-MIN(AA12,MAX(0,ceiling-D12)))) -> 0 | AC12: =AA12+AB12 -> 0 | AD12: =SUMPRODUCT(($B$5:$B$14=B12)*($M$5:$M$14<M12))+SUMPRODUCT(($B$5:$B$14=B12)*($M$5:$M$14=M12)*(ROW($M$5:$M$14)<ROW(M12)))+1 -> 3 | AE12: =COUNTIF($B$5:$B$14,B12) -> 3 | AF12: =SUMPRODUCT(($B$5:$B$14=B12)*($C$5:$C$14=C12)*($M$5:$M$14<M12))+SUMPRODUCT(($B$5:$B$14=B12)*($C$5:$C$14=C12)*($M$5:$M$14=M12)*(ROW($M$5:$M$14)<ROW(M12)))+1 -> 2 | AG12: =COUNTIFS($B$5:$B$14,B12,$C$5:$C$14,C12) -> 2
A13: E009 | B13: Customer Support | C13: M | D13: 33500 | E13: 1500 | F13: 4.5 | G13: 4 | H13: 1 | I13: 12 | J13: =H13*(I13/12) -> 1 | K13: =D13/J13 -> 33500 | L13: =E13/J13 -> 1500 | M13: =K13+L13 -> 35000 | N13: =D13+E13 -> 35000 | O13: =(SUMIFS($M$5:$M$14,$B$5:$B$14,B13,$AD$5:$AD$14,INT((AE13+1)/2))+SUMIFS($M$5:$M$14,$B$5:$B$14,B13,$AD$5:$AD$14,INT(AE13/2)+1))/2 -> 35000 | P13: =IF(AND(C13="F",M13<O13,SUMIFS(Categories!$Z$5:$Z$7,Categories!$A$5:$A$7,B13)=1),1,0) -> 0 | Q13: =IF(P13=1,O13-M13,0) -> 0 | R13: =IF(AND(P13=1,SUMIFS(Categories!$AA$5:$AA$7,Categories!$A$5:$A$7,B13)>0),Q13/SUMIFS(Categories!$AA$5:$AA$7,Categories!$A$5:$A$7,B13),0) -> 0 | S13: =R13*SUMIFS(Categories!$AB$5:$AB$7,Categories!$A$5:$A$7,B13) -> 0 | T13: =S13*J13 -> 0 | U13: =IF(T13<=0,0,(rate_below/100)*MIN(T13,MAX(0,ceiling-D13))+(rate_above/100)*(T13-MIN(T13,MAX(0,ceiling-D13)))) -> 0 | V13: =T13+U13 -> 0 | W13: =IF(AND(C13="F",M13<O13,SUMIFS(Categories!$AH$5:$AH$7,Categories!$A$5:$A$7,B13)=1),1,0) -> 0 | X13: =IF(W13=1,O13-M13,0) -> 0 | Y13: =IF(AND(W13=1,SUMIFS(Categories!$AI$5:$AI$7,Categories!$A$5:$A$7,B13)>0),X13/SUMIFS(Categories!$AI$5:$AI$7,Categories!$A$5:$A$7,B13),0) -> 0 | Z13: =Y13*SUMIFS(Categories!$AJ$5:$AJ$7,Categories!$A$5:$A$7,B13) -> 0 | AA13: =Z13*J13 -> 0 | AB13: =IF(AA13<=0,0,(rate_below/100)*MIN(AA13,MAX(0,ceiling-D13))+(rate_above/100)*(AA13-MIN(AA13,MAX(0,ceiling-D13)))) -> 0 | AC13: =AA13+AB13 -> 0 | AD13: =SUMPRODUCT(($B$5:$B$14=B13)*($M$5:$M$14<M13))+SUMPRODUCT(($B$5:$B$14=B13)*($M$5:$M$14=M13)*(ROW($M$5:$M$14)<ROW(M13)))+1 -> 2 | AE13: =COUNTIF($B$5:$B$14,B13) -> 3 | AF13: =SUMPRODUCT(($B$5:$B$14=B13)*($C$5:$C$14=C13)*($M$5:$M$14<M13))+SUMPRODUCT(($B$5:$B$14=B13)*($C$5:$C$14=C13)*($M$5:$M$14=M13)*(ROW($M$5:$M$14)<ROW(M13)))+1 -> 1 | AG13: =COUNTIFS($B$5:$B$14,B13,$C$5:$C$14,C13) -> 1
A14: E010 | B14: Customer Support | C14: F | D14: 29000 | E14: 900 | F14: 1 | G14: 3 | H14: 1 | I14: 12 | J14: =H14*(I14/12) -> 1 | K14: =D14/J14 -> 29000 | L14: =E14/J14 -> 900 | M14: =K14+L14 -> 29900 | N14: =D14+E14 -> 29900 | O14: =(SUMIFS($M$5:$M$14,$B$5:$B$14,B14,$AD$5:$AD$14,INT((AE14+1)/2))+SUMIFS($M$5:$M$14,$B$5:$B$14,B14,$AD$5:$AD$14,INT(AE14/2)+1))/2 -> 35000 | P14: =IF(AND(C14="F",M14<O14,SUMIFS(Categories!$Z$5:$Z$7,Categories!$A$5:$A$7,B14)=1),1,0) -> 0 | Q14: =IF(P14=1,O14-M14,0) -> 0 | R14: =IF(AND(P14=1,SUMIFS(Categories!$AA$5:$AA$7,Categories!$A$5:$A$7,B14)>0),Q14/SUMIFS(Categories!$AA$5:$AA$7,Categories!$A$5:$A$7,B14),0) -> 0 | S14: =R14*SUMIFS(Categories!$AB$5:$AB$7,Categories!$A$5:$A$7,B14) -> 0 | T14: =S14*J14 -> 0 | U14: =IF(T14<=0,0,(rate_below/100)*MIN(T14,MAX(0,ceiling-D14))+(rate_above/100)*(T14-MIN(T14,MAX(0,ceiling-D14)))) -> 0 | V14: =T14+U14 -> 0 | W14: =IF(AND(C14="F",M14<O14,SUMIFS(Categories!$AH$5:$AH$7,Categories!$A$5:$A$7,B14)=1),1,0) -> 0 | X14: =IF(W14=1,O14-M14,0) -> 0 | Y14: =IF(AND(W14=1,SUMIFS(Categories!$AI$5:$AI$7,Categories!$A$5:$A$7,B14)>0),X14/SUMIFS(Categories!$AI$5:$AI$7,Categories!$A$5:$A$7,B14),0) -> 0 | Z14: =Y14*SUMIFS(Categories!$AJ$5:$AJ$7,Categories!$A$5:$A$7,B14) -> 0 | AA14: =Z14*J14 -> 0 | AB14: =IF(AA14<=0,0,(rate_below/100)*MIN(AA14,MAX(0,ceiling-D14))+(rate_above/100)*(AA14-MIN(AA14,MAX(0,ceiling-D14)))) -> 0 | AC14: =AA14+AB14 -> 0 | AD14: =SUMPRODUCT(($B$5:$B$14=B14)*($M$5:$M$14<M14))+SUMPRODUCT(($B$5:$B$14=B14)*($M$5:$M$14=M14)*(ROW($M$5:$M$14)<ROW(M14)))+1 -> 1 | AE14: =COUNTIF($B$5:$B$14,B14) -> 3 | AF14: =SUMPRODUCT(($B$5:$B$14=B14)*($C$5:$C$14=C14)*($M$5:$M$14<M14))+SUMPRODUCT(($B$5:$B$14=B14)*($C$5:$C$14=C14)*($M$5:$M$14=M14)*(ROW($M$5:$M$14)<ROW(M14)))+1 -> 1 | AG14: =COUNTIFS($B$5:$B$14,B14,$C$5:$C$14,C14) -> 2

Sheet Categories
A1: Category-level calculation
A2: Regression: OLS of n_total on grade and tenure within each category, solved from explicit sums (no LINEST, no array formulas). Guard conditions mirror calc.js: fewer than 4 observations or a constant predictor means the regression is undefined, and the whole gap is treated as unexplained.
A4: category | B4: headcount | C4: n_F | D4: n_M | E4: mean_M | F4: mean_F | G4: median_all | H4: raw_gap_mean_% | I4: median_M | J4: median_F | K4: raw_gap_median_% | L4: var_M | M4: var_F | N4: variable_gap_% | O4: base_M | P4: base_F | Q4: base_gap_% | R4: var_grade | S4: var_tenure | T4: reg_ok | U4: coef_grade | V4: coef_tenure | W4: r2 | X4: explained_% | Y4: unexplained_% | Z4: correct_min | AA4: totalDef_min | AB4: need_min | AC4: adjust_min | AD4: contrib_min | AE4: cost_min | AF4: recip_min | AG4: unexpl_after_min | AH4: correct_full | AI4: totalDef_full | AJ4: need_full | AK4: adjust_full | AL4: contrib_full | AM4: cost_full | AN4: recip_full | AO4: unexpl_after_full | AP4: unreliable | AQ4: reverse_gap | BA4: n | BB4: Sum_g | BC4: Sum_t | BD4: Sum_y | BE4: Sum_gg | BF4: Sum_tt | BG4: Sum_gt | BH4: Sum_gy | BI4: Sum_ty | BJ4: Sum_yy | BK4: det
A5: Engineering | B5: =COUNTIF(Data!$B$5:$B$14,$A5) -> 4 | C5: =COUNTIFS(Data!$B$5:$B$14,$A5,Data!$C$5:$C$14,"F") -> 2 | D5: =COUNTIFS(Data!$B$5:$B$14,$A5,Data!$C$5:$C$14,"M") -> 2 | E5: =IF(D5=0,0,AVERAGEIFS(Data!$M$5:$M$14,Data!$B$5:$B$14,$A5,Data!$C$5:$C$14,"M")) -> 76850 | F5: =IF(C5=0,0,AVERAGEIFS(Data!$M$5:$M$14,Data!$B$5:$B$14,$A5,Data!$C$5:$C$14,"F")) -> 62750 | G5: =IF(B5=0,0,SUMIFS(Data!$O$5:$O$14,Data!$B$5:$B$14,$A5,Data!$AD$5:$AD$14,1)) -> 66850 | H5: =IF(OR(E5<=0,C5=0,D5=0),0,(E5-F5)/E5*100) -> 18.34743 | I5: =IF(D5=0,0,(SUMIFS(Data!$M$5:$M$14,Data!$B$5:$B$14,$A5,Data!$C$5:$C$14,"M",Data!$AF$5:$AF$14,INT((D5+1)/2))+SUMIFS(Data!$M$5:$M$14,Data!$B$5:$B$14,$A5,Data!$C$5:$C$14,"M",Data!$AF$5:$AF$14,INT(D5/2)+1))/2) -> 76850 | J5: =IF(C5=0,0,(SUMIFS(Data!$M$5:$M$14,Data!$B$5:$B$14,$A5,Data!$C$5:$C$14,"F",Data!$AF$5:$AF$14,INT((C5+1)/2))+SUMIFS(Data!$M$5:$M$14,Data!$B$5:$B$14,$A5,Data!$C$5:$C$14,"F",Data!$AF$5:$AF$14,INT(C5/2)+1))/2) -> 62750 | K5: =IF(OR(I5<=0,C5=0,D5=0),0,(I5-J5)/I5*100) -> 18.34743 | L5: =IF(D5=0,0,AVERAGEIFS(Data!$L$5:$L$14,Data!$B$5:$B$14,$A5,Data!$C$5:$C$14,"M")) -> 11600 | M5: =IF(C5=0,0,AVERAGEIFS(Data!$L$5:$L$14,Data!$B$5:$B$14,$A5,Data!$C$5:$C$14,"F")) -> 5750 | N5: =IF(OR(L5<=0,C5=0,D5=0),0,(L5-M5)/L5*100) -> 50.431034 | O5: =IF(D5=0,0,AVERAGEIFS(Data!$K$5:$K$14,Data!$B$5:$B$14,$A5,Data!$C$5:$C$14,"M")) -> 65250 | P5: =IF(C5=0,0,AVERAGEIFS(Data!$K$5:$K$14,Data!$B$5:$B$14,$A5,Data!$C$5:$C$14,"F")) -> 57000 | Q5: =IF(OR(O5<=0,C5=0,D5=0),0,(O5-P5)/O5*100) -> 12.643678 | R5: =IF(B5<2,0,SUMPRODUCT((Data!$B$5:$B$14=$A5)*Data!$G$5:$G$14*Data!$G$5:$G$14)/B5-(SUMIFS(Data!$G$5:$G$14,Data!$B$5:$B$14,$A5)/B5)^2) -> 1.1875 | S5: =IF(B5<2,0,SUMPRODUCT((Data!$B$5:$B$14=$A5)*Data!$F$5:$F$14*Data!$F$5:$F$14)/B5-(SUMIFS(Data!$F$5:$F$14,Data!$B$5:$B$14,$A5)/B5)^2) -> 5.625 | T5: =IF(AND(B5>=4,R5>0.000000001,S5>0.000000001),1,0) -> 1 | U5: =IF(OR(T5=0,ABS(BK5)<0.000000001),0,((BH5-BB5*BD5/B5)*(BF5-BC5^2/B5)-(BI5-BC5*BD5/B5)*(BG5-BB5*BC5/B5))/BK5) -> 4145.4545 | V5: =IF(OR(T5=0,ABS(BK5)<0.000000001),0,((BI5-BC5*BD5/B5)*(BE5-BB5^2/B5)-(BH5-BB5*BD5/B5)*(BG5-BB5*BC5/B5))/BK5) -> 1550.9091 | W5: =IF(OR(T5=0,ABS(BK5)<0.000000001,(BJ5-BD5^2/B5)<0.000000001),"",(U5*(BH5-BB5*BD5/B5)+V5*(BI5-BC5*BD5/B5))/(BJ5-BD5^2/B5)) -> 0.77339783 | X5: =IF(H5>=0,MAX(0,MIN(IF(OR(T5=0,E5<=0),0,(U5*(IF(D5=0,0,AVERAGEIFS(Data!$G$5:$G$14,Data!$B$5:$B$14,$A5,Data!$C$5:$C$14,"M"))-IF(C5=0,0,AVERAGEIFS(Data!$G$5:$G$14,Data!$B$5:$B$14,$A5,Data!$C$5:$C$14,"F")))+V5*(IF(D5=0,0,AVERAGEIFS(Data!$F$5:$F$14,Data!$B$5:$B$14,$A5,Data!$C$5:$C$14,"M"))-IF(C5=0,0,AVERAGEIFS(Data!$F$5:$F$14,Data!$B$5:$B$14,$A5,Data!$C$5:$C$14,"F"))))/E5*100),H5)),MIN(0,MAX(IF(OR(T5=0,E5<=0),0,(U5*(IF(D5=0,0,AVERAGEIFS(Data!$G$5:$G$14,Data!$B$5:$B$14,$A5,Data!$C$5:$C$14,"M"))-IF(C5=0,0,AVERAGEIFS(Data!$G$5:$G$14,Data!$B$5:$B$14,$A5,Data!$C$5:$C$14,"F")))+V5*(IF(D5=0,0,AVERAGEIFS(Data!$F$5:$F$14,Data!$B$5:$B$14,$A5,Data!$C$5:$C$14,"M"))-IF(C5=0,0,AVERAGEIFS(Data!$F$5:$F$14,Data!$B$5:$B$14,$A5,Data!$C$5:$C$14,"F"))))/E5*100),H5))) -> 16.163719 | Y5: =H5-X5 -> 2.1837109 | Z5: =IF(AND(H5>=0,Y5>threshold_pct),1,0) -> 0 | AA5: =IF(Z5=0,0,SUMIFS(Data!$Q$5:$Q$14,Data!$B$5:$B$14,$A5)) -> 0 | AB5: =IF(Z5=0,0,(Y5-threshold_pct)/100*E5*C5) -> 0 | AC5: =SUMIFS(Data!$T$5:$T$14,Data!$B$5:$B$14,$A5) -> 0 | AD5: =SUMIFS(Data!$U$5:$U$14,Data!$B$5:$B$14,$A5) -> 0 | AE5: =AC5+AD5 -> 0 | AF5: =SUMIFS(Data!$P$5:$P$14,Data!$B$5:$B$14,$A5) -> 0 | AG5: =IF(E5<=0,0,(E5-(IF(C5=0,0,AVERAGEIFS(Data!$M$5:$M$14,Data!$B$5:$B$14,$A5,Data!$C$5:$C$14,"F"))+IF(C5=0,0,SUMIFS(Data!$S$5:$S$14,Data!$B$5:$B$14,$A5,Data!$C$5:$C$14,"F")/C5)))/E5*100-X5) -> 2.1837109 | AH5: =IF(AND(H5>=0,Y5>0),1,0) -> 1 | AI5: =IF(AH5=0,0,SUMIFS(Data!$X$5:$X$14,Data!$B$5:$B$14,$A5)) -> 8200 | AJ5: =IF(AH5=0,0,Y5/100*E5*C5) -> 3356.3636 | AK5: =SUMIFS(Data!$AA$5:$AA$14,Data!$B$5:$B$14,$A5) -> 3204.918 | AL5: =SUMIFS(Data!$AB$5:$AB$14,Data!$B$5:$B$14,$A5) -> 1009.5492 | AM5: =AK5+AL5 -> 4214.4671 | AN5: =SUMIFS(Data!$W$5:$W$14,Data!$B$5:$B$14,$A5) -> 2 | AO5: =IF(E5<=0,0,(E5-(IF(C5=0,0,AVERAGEIFS(Data!$M$5:$M$14,Data!$B$5:$B$14,$A5,Data!$C$5:$C$14,"F"))+IF(C5=0,0,SUMIFS(Data!$Z$5:$Z$14,Data!$B$5:$B$14,$A5,Data!$C$5:$C$14,"F")/C5)))/E5*100-X5) -> 3.5527137e-15 | AP5: =IF(OR(B5<10,C5<3,D5<3),1,0) -> 1 | AQ5: =IF(H5<0,1,0) -> 0 | BA5: =B5 -> 4 | BB5: =SUMIFS(Data!$G$5:$G$14,Data!$B$5:$B$14,$A5) -> 25 | BC5: =SUMIFS(Data!$F$5:$F$14,Data!$B$5:$B$14,$A5) -> 18 | BD5: =SUMIFS(Data!$M$5:$M$14,Data!$B$5:$B$14,$A5) -> 279200 | BE5: =SUMPRODUCT((Data!$B$5:$B$14=$A5)*Data!$G$5:$G$14*Data!$G$5:$G$14) -> 161 | BF5: =SUMPRODUCT((Data!$B$5:$B$14=$A5)*Data!$F$5:$F$14*Data!$F$5:$F$14) -> 103.5 | BG5: =SUMPRODUCT((Data!$B$5:$B$14=$A5)*Data!$G$5:$G$14*Data!$F$5:$F$14) -> 122.5 | BH5: =SUMPRODUCT((Data!$B$5:$B$14=$A5)*Data!$G$5:$G$14*Data!$M$5:$M$14) -> 1780200 | BI5: =SUMPRODUCT((Data!$B$5:$B$14=$A5)*Data!$F$5:$F$14*Data!$M$5:$M$14) -> 1332750 | BJ5: =SUMPRODUCT((Data!$B$5:$B$14=$A5)*Data!$M$5:$M$14*Data!$M$5:$M$14) -> 19829940000 | BK5: =IF(T5=0,0,((BE5-BB5^2/B5)*(BF5-BC5^2/B5)-(BG5-BB5*BC5/B5)^2)) -> 6.875
A6: Sales | B6: =COUNTIF(Data!$B$5:$B$14,$A6) -> 3 | C6: =COUNTIFS(Data!$B$5:$B$14,$A6,Data!$C$5:$C$14,"F") -> 1 | D6: =COUNTIFS(Data!$B$5:$B$14,$A6,Data!$C$5:$C$14,"M") -> 2 | E6: =IF(D6=0,0,AVERAGEIFS(Data!$M$5:$M$14,Data!$B$5:$B$14,$A6,Data!$C$5:$C$14,"M")) -> 79071.429 | F6: =IF(C6=0,0,AVERAGEIFS(Data!$M$5:$M$14,Data!$B$5:$B$14,$A6,Data!$C$5:$C$14,"F")) -> 48000 | G6: =IF(B6=0,0,SUMIFS(Data!$O$5:$O$14,Data!$B$5:$B$14,$A6,Data!$AD$5:$AD$14,1)) -> 54000 | H6: =IF(OR(E6<=0,C6=0,D6=0),0,(E6-F6)/E6*100) -> 39.295393 | I6: =IF(D6=0,0,(SUMIFS(Data!$M$5:$M$14,Data!$B$5:$B$14,$A6,Data!$C$5:$C$14,"M",Data!$AF$5:$AF$14,INT((D6+1)/2))+SUMIFS(Data!$M$5:$M$14,Data!$B$5:$B$14,$A6,Data!$C$5:$C$14,"M",Data!$AF$5:$AF$14,INT(D6/2)+1))/2) -> 79071.429 | J6: =IF(C6=0,0,(SUMIFS(Data!$M$5:$M$14,Data!$B$5:$B$14,$A6,Data!$C$5:$C$14,"F",Data!$AF$5:$AF$14,INT((C6+1)/2))+SUMIFS(Data!$M$5:$M$14,Data!$B$5:$B$14,$A6,Data!$C$5:$C$14,"F",Data!$AF$5:$AF$14,INT(C6/2)+1))/2) -> 48000 | K6: =IF(OR(I6<=0,C6=0,D6=0),0,(I6-J6)/I6*100) -> 39.295393 | L6: =IF(D6=0,0,AVERAGEIFS(Data!$L$5:$L$14,Data!$B$5:$B$14,$A6,Data!$C$5:$C$14,"M")) -> 13250 | M6: =IF(C6=0,0,AVERAGEIFS(Data!$L$5:$L$14,Data!$B$5:$B$14,$A6,Data!$C$5:$C$14,"F")) -> 7000 | N6: =IF(OR(L6<=0,C6=0,D6=0),0,(L6-M6)/L6*100) -> 47.169811 | O6: =IF(D6=0,0,AVERAGEIFS(Data!$K$5:$K$14,Data!$B$5:$B$14,$A6,Data!$C$5:$C$14,"M")) -> 65821.429 | P6: =IF(C6=0,0,AVERAGEIFS(Data!$K$5:$K$14,Data!$B$5:$B$14,$A6,Data!$C$5:$C$14,"F")) -> 41000 | Q6: =IF(OR(O6<=0,C6=0,D6=0),0,(O6-P6)/O6*100) -> 37.710255 | R6: =IF(B6<2,0,SUMPRODUCT((Data!$B$5:$B$14=$A6)*Data!$G$5:$G$14*Data!$G$5:$G$14)/B6-(SUMIFS(Data!$G$5:$G$14,Data!$B$5:$B$14,$A6)/B6)^2) -> 0.88888889 | S6: =IF(B6<2,0,SUMPRODUCT((Data!$B$5:$B$14=$A6)*Data!$F$5:$F$14*Data!$F$5:$F$14)/B6-(SUMIFS(Data!$F$5:$F$14,Data!$B$5:$B$14,$A6)/B6)^2) -> 3.1666667 | T6: =IF(AND(B6>=4,R6>0.000000001,S6>0.000000001),1,0) -> 0 | U6: =IF(OR(T6=0,ABS(BK6)<0.000000001),0,((BH6-BB6*BD6/B6)*(BF6-BC6^2/B6)-(BI6-BC6*BD6/B6)*(BG6-BB6*BC6/B6))/BK6) -> 0 | V6: =IF(OR(T6=0,ABS(BK6)<0.000000001),0,((BI6-BC6*BD6/B6)*(BE6-BB6^2/B6)-(BH6-BB6*BD6/B6)*(BG6-BB6*BC6/B6))/BK6) -> 0 | W6: =IF(OR(T6=0,ABS(BK6)<0.000000001,(BJ6-BD6^2/B6)<0.000000001),"",(U6*(BH6-BB6*BD6/B6)+V6*(BI6-BC6*BD6/B6))/(BJ6-BD6^2/B6)) | X6: =IF(H6>=0,MAX(0,MIN(IF(OR(T6=0,E6<=0),0,(U6*(IF(D6=0,0,AVERAGEIFS(Data!$G$5:$G$14,Data!$B$5:$B$14,$A6,Data!$C$5:$C$14,"M"))-IF(C6=0,0,AVERAGEIFS(Data!$G$5:$G$14,Data!$B$5:$B$14,$A6,Data!$C$5:$C$14,"F")))+V6*(IF(D6=0,0,AVERAGEIFS(Data!$F$5:$F$14,Data!$B$5:$B$14,$A6,Data!$C$5:$C$14,"M"))-IF(C6=0,0,AVERAGEIFS(Data!$F$5:$F$14,Data!$B$5:$B$14,$A6,Data!$C$5:$C$14,"F"))))/E6*100),H6)),MIN(0,MAX(IF(OR(T6=0,E6<=0),0,(U6*(IF(D6=0,0,AVERAGEIFS(Data!$G$5:$G$14,Data!$B$5:$B$14,$A6,Data!$C$5:$C$14,"M"))-IF(C6=0,0,AVERAGEIFS(Data!$G$5:$G$14,Data!$B$5:$B$14,$A6,Data!$C$5:$C$14,"F")))+V6*(IF(D6=0,0,AVERAGEIFS(Data!$F$5:$F$14,Data!$B$5:$B$14,$A6,Data!$C$5:$C$14,"M"))-IF(C6=0,0,AVERAGEIFS(Data!$F$5:$F$14,Data!$B$5:$B$14,$A6,Data!$C$5:$C$14,"F"))))/E6*100),H6))) -> 0 | Y6: =H6-X6 -> 39.295393 | Z6: =IF(AND(H6>=0,Y6>threshold_pct),1,0) -> 1 | AA6: =IF(Z6=0,0,SUMIFS(Data!$Q$5:$Q$14,Data!$B$5:$B$14,$A6)) -> 6000 | AB6: =IF(Z6=0,0,(Y6-threshold_pct)/100*E6*C6) -> 27117.857 | AC6: =SUMIFS(Data!$T$5:$T$14,Data!$B$5:$B$14,$A6) -> 27117.857 | AD6: =SUMIFS(Data!$U$5:$U$14,Data!$B$5:$B$14,$A6) -> 6446.8044 | AE6: =AC6+AD6 -> 33564.661 | AF6: =SUMIFS(Data!$P$5:$P$14,Data!$B$5:$B$14,$A6) -> 1 | AG6: =IF(E6<=0,0,(E6-(IF(C6=0,0,AVERAGEIFS(Data!$M$5:$M$14,Data!$B$5:$B$14,$A6,Data!$C$5:$C$14,"F"))+IF(C6=0,0,SUMIFS(Data!$S$5:$S$14,Data!$B$5:$B$14,$A6,Data!$C$5:$C$14,"F")/C6)))/E6*100-X6) -> 5 | AH6: =IF(AND(H6>=0,Y6>0),1,0) -> 1 | AI6: =IF(AH6=0,0,SUMIFS(Data!$X$5:$X$14,Data!$B$5:$B$14,$A6)) -> 6000 | AJ6: =IF(AH6=0,0,Y6/100*E6*C6) -> 31071.429 | AK6: =SUMIFS(Data!$AA$5:$AA$14,Data!$B$5:$B$14,$A6) -> 31071.429 | AL6: =SUMIFS(Data!$AB$5:$AB$14,Data!$B$5:$B$14,$A6) -> 6492.2704 | AM6: =AK6+AL6 -> 37563.699 | AN6: =SUMIFS(Data!$W$5:$W$14,Data!$B$5:$B$14,$A6) -> 1 | AO6: =IF(E6<=0,0,(E6-(IF(C6=0,0,AVERAGEIFS(Data!$M$5:$M$14,Data!$B$5:$B$14,$A6,Data!$C$5:$C$14,"F"))+IF(C6=0,0,SUMIFS(Data!$Z$5:$Z$14,Data!$B$5:$B$14,$A6,Data!$C$5:$C$14,"F")/C6)))/E6*100-X6) -> 0 | AP6: =IF(OR(B6<10,C6<3,D6<3),1,0) -> 1 | AQ6: =IF(H6<0,1,0) -> 0 | BA6: =B6 -> 3 | BB6: =SUMIFS(Data!$G$5:$G$14,Data!$B$5:$B$14,$A6) -> 17 | BC6: =SUMIFS(Data!$F$5:$F$14,Data!$B$5:$B$14,$A6) -> 10.5 | BD6: =SUMIFS(Data!$M$5:$M$14,Data!$B$5:$B$14,$A6) -> 206142.86 | BE6: =SUMPRODUCT((Data!$B$5:$B$14=$A6)*Data!$G$5:$G$14*Data!$G$5:$G$14) -> 99 | BF6: =SUMPRODUCT((Data!$B$5:$B$14=$A6)*Data!$F$5:$F$14*Data!$F$5:$F$14) -> 46.25 | BG6: =SUMPRODUCT((Data!$B$5:$B$14=$A6)*Data!$G$5:$G$14*Data!$F$5:$F$14) -> 64.5 | BH6: =SUMPRODUCT((Data!$B$5:$B$14=$A6)*Data!$G$5:$G$14*Data!$M$5:$M$14) -> 1239000 | BI6: =SUMPRODUCT((Data!$B$5:$B$14=$A6)*Data!$F$5:$F$14*Data!$M$5:$M$14) -> 855857.14 | BJ6: =SUMPRODUCT((Data!$B$5:$B$14=$A6)*Data!$M$5:$M$14*Data!$M$5:$M$14) -> 1.6065735e+10 | BK6: =IF(T6=0,0,((BE6-BB6^2/B6)*(BF6-BC6^2/B6)-(BG6-BB6*BC6/B6)^2)) -> 0
A7: Customer Support | B7: =COUNTIF(Data!$B$5:$B$14,$A7) -> 3 | C7: =COUNTIFS(Data!$B$5:$B$14,$A7,Data!$C$5:$C$14,"F") -> 2 | D7: =COUNTIFS(Data!$B$5:$B$14,$A7,Data!$C$5:$C$14,"M") -> 1 | E7: =IF(D7=0,0,AVERAGEIFS(Data!$M$5:$M$14,Data!$B$5:$B$14,$A7,Data!$C$5:$C$14,"M")) -> 35000 | F7: =IF(C7=0,0,AVERAGEIFS(Data!$M$5:$M$14,Data!$B$5:$B$14,$A7,Data!$C$5:$C$14,"F")) -> 47150 | G7: =IF(B7=0,0,SUMIFS(Data!$O$5:$O$14,Data!$B$5:$B$14,$A7,Data!$AD$5:$AD$14,1)) -> 35000 | H7: =IF(OR(E7<=0,C7=0,D7=0),0,(E7-F7)/E7*100) -> -34.714286 | I7: =IF(D7=0,0,(SUMIFS(Data!$M$5:$M$14,Data!$B$5:$B$14,$A7,Data!$C$5:$C$14,"M",Data!$AF$5:$AF$14,INT((D7+1)/2))+SUMIFS(Data!$M$5:$M$14,Data!$B$5:$B$14,$A7,Data!$C$5:$C$14,"M",Data!$AF$5:$AF$14,INT(D7/2)+1))/2) -> 35000 | J7: =IF(C7=0,0,(SUMIFS(Data!$M$5:$M$14,Data!$B$5:$B$14,$A7,Data!$C$5:$C$14,"F",Data!$AF$5:$AF$14,INT((C7+1)/2))+SUMIFS(Data!$M$5:$M$14,Data!$B$5:$B$14,$A7,Data!$C$5:$C$14,"F",Data!$AF$5:$AF$14,INT(C7/2)+1))/2) -> 47150 | K7: =IF(OR(I7<=0,C7=0,D7=0),0,(I7-J7)/I7*100) -> -34.714286 | L7: =IF(D7=0,0,AVERAGEIFS(Data!$L$5:$L$14,Data!$B$5:$B$14,$A7,Data!$C$5:$C$14,"M")) -> 1500 | M7: =IF(C7=0,0,AVERAGEIFS(Data!$L$5:$L$14,Data!$B$5:$B$14,$A7,Data!$C$5:$C$14,"F")) -> 1650 | N7: =IF(OR(L7<=0,C7=0,D7=0),0,(L7-M7)/L7*100) -> -10 | O7: =IF(D7=0,0,AVERAGEIFS(Data!$K$5:$K$14,Data!$B$5:$B$14,$A7,Data!$C$5:$C$14,"M")) -> 33500 | P7: =IF(C7=0,0,AVERAGEIFS(Data!$K$5:$K$14,Data!$B$5:$B$14,$A7,Data!$C$5:$C$14,"F")) -> 45500 | Q7: =IF(OR(O7<=0,C7=0,D7=0),0,(O7-P7)/O7*100) -> -35.820896 | R7: =IF(B7<2,0,SUMPRODUCT((Data!$B$5:$B$14=$A7)*Data!$G$5:$G$14*Data!$G$5:$G$14)/B7-(SUMIFS(Data!$G$5:$G$14,Data!$B$5:$B$14,$A7)/B7)^2) -> 0.22222222 | S7: =IF(B7<2,0,SUMPRODUCT((Data!$B$5:$B$14=$A7)*Data!$F$5:$F$14*Data!$F$5:$F$14)/B7-(SUMIFS(Data!$F$5:$F$14,Data!$B$5:$B$14,$A7)/B7)^2) -> 2.3888889 | T7: =IF(AND(B7>=4,R7>0.000000001,S7>0.000000001),1,0) -> 0 | U7: =IF(OR(T7=0,ABS(BK7)<0.000000001),0,((BH7-BB7*BD7/B7)*(BF7-BC7^2/B7)-(BI7-BC7*BD7/B7)*(BG7-BB7*BC7/B7))/BK7) -> 0 | V7: =IF(OR(T7=0,ABS(BK7)<0.000000001),0,((BI7-BC7*BD7/B7)*(BE7-BB7^2/B7)-(BH7-BB7*BD7/B7)*(BG7-BB7*BC7/B7))/BK7) -> 0 | W7: =IF(OR(T7=0,ABS(BK7)<0.000000001,(BJ7-BD7^2/B7)<0.000000001),"",(U7*(BH7-BB7*BD7/B7)+V7*(BI7-BC7*BD7/B7))/(BJ7-BD7^2/B7)) | X7: =IF(H7>=0,MAX(0,MIN(IF(OR(T7=0,E7<=0),0,(U7*(IF(D7=0,0,AVERAGEIFS(Data!$G$5:$G$14,Data!$B$5:$B$14,$A7,Data!$C$5:$C$14,"M"))-IF(C7=0,0,AVERAGEIFS(Data!$G$5:$G$14,Data!$B$5:$B$14,$A7,Data!$C$5:$C$14,"F")))+V7*(IF(D7=0,0,AVERAGEIFS(Data!$F$5:$F$14,Data!$B$5:$B$14,$A7,Data!$C$5:$C$14,"M"))-IF(C7=0,0,AVERAGEIFS(Data!$F$5:$F$14,Data!$B$5:$B$14,$A7,Data!$C$5:$C$14,"F"))))/E7*100),H7)),MIN(0,MAX(IF(OR(T7=0,E7<=0),0,(U7*(IF(D7=0,0,AVERAGEIFS(Data!$G$5:$G$14,Data!$B$5:$B$14,$A7,Data!$C$5:$C$14,"M"))-IF(C7=0,0,AVERAGEIFS(Data!$G$5:$G$14,Data!$B$5:$B$14,$A7,Data!$C$5:$C$14,"F")))+V7*(IF(D7=0,0,AVERAGEIFS(Data!$F$5:$F$14,Data!$B$5:$B$14,$A7,Data!$C$5:$C$14,"M"))-IF(C7=0,0,AVERAGEIFS(Data!$F$5:$F$14,Data!$B$5:$B$14,$A7,Data!$C$5:$C$14,"F"))))/E7*100),H7))) -> 0 | Y7: =H7-X7 -> -34.714286 | Z7: =IF(AND(H7>=0,Y7>threshold_pct),1,0) -> 0 | AA7: =IF(Z7=0,0,SUMIFS(Data!$Q$5:$Q$14,Data!$B$5:$B$14,$A7)) -> 0 | AB7: =IF(Z7=0,0,(Y7-threshold_pct)/100*E7*C7) -> 0 | AC7: =SUMIFS(Data!$T$5:$T$14,Data!$B$5:$B$14,$A7) -> 0 | AD7: =SUMIFS(Data!$U$5:$U$14,Data!$B$5:$B$14,$A7) -> 0 | AE7: =AC7+AD7 -> 0 | AF7: =SUMIFS(Data!$P$5:$P$14,Data!$B$5:$B$14,$A7) -> 0 | AG7: =IF(E7<=0,0,(E7-(IF(C7=0,0,AVERAGEIFS(Data!$M$5:$M$14,Data!$B$5:$B$14,$A7,Data!$C$5:$C$14,"F"))+IF(C7=0,0,SUMIFS(Data!$S$5:$S$14,Data!$B$5:$B$14,$A7,Data!$C$5:$C$14,"F")/C7)))/E7*100-X7) -> -34.714286 | AH7: =IF(AND(H7>=0,Y7>0),1,0) -> 0 | AI7: =IF(AH7=0,0,SUMIFS(Data!$X$5:$X$14,Data!$B$5:$B$14,$A7)) -> 0 | AJ7: =IF(AH7=0,0,Y7/100*E7*C7) -> 0 | AK7: =SUMIFS(Data!$AA$5:$AA$14,Data!$B$5:$B$14,$A7) -> 0 | AL7: =SUMIFS(Data!$AB$5:$AB$14,Data!$B$5:$B$14,$A7) -> 0 | AM7: =AK7+AL7 -> 0 | AN7: =SUMIFS(Data!$W$5:$W$14,Data!$B$5:$B$14,$A7) -> 0 | AO7: =IF(E7<=0,0,(E7-(IF(C7=0,0,AVERAGEIFS(Data!$M$5:$M$14,Data!$B$5:$B$14,$A7,Data!$C$5:$C$14,"F"))+IF(C7=0,0,SUMIFS(Data!$Z$5:$Z$14,Data!$B$5:$B$14,$A7,Data!$C$5:$C$14,"F")/C7)))/E7*100-X7) -> -34.714286 | AP7: =IF(OR(B7<10,C7<3,D7<3),1,0) -> 1 | AQ7: =IF(H7<0,1,0) -> 1 | BA7: =B7 -> 3 | BB7: =SUMIFS(Data!$G$5:$G$14,Data!$B$5:$B$14,$A7) -> 11 | BC7: =SUMIFS(Data!$F$5:$F$14,Data!$B$5:$B$14,$A7) -> 9.5 | BD7: =SUMIFS(Data!$M$5:$M$14,Data!$B$5:$B$14,$A7) -> 129300 | BE7: =SUMPRODUCT((Data!$B$5:$B$14=$A7)*Data!$G$5:$G$14*Data!$G$5:$G$14) -> 41 | BF7: =SUMPRODUCT((Data!$B$5:$B$14=$A7)*Data!$F$5:$F$14*Data!$F$5:$F$14) -> 37.25 | BG7: =SUMPRODUCT((Data!$B$5:$B$14=$A7)*Data!$G$5:$G$14*Data!$F$5:$F$14) -> 37 | BH7: =SUMPRODUCT((Data!$B$5:$B$14=$A7)*Data!$G$5:$G$14*Data!$M$5:$M$14) -> 487300 | BI7: =SUMPRODUCT((Data!$B$5:$B$14=$A7)*Data!$F$5:$F$14*Data!$M$5:$M$14) -> 445000 | BJ7: =SUMPRODUCT((Data!$B$5:$B$14=$A7)*Data!$M$5:$M$14*Data!$M$5:$M$14) -> 6266370000 | BK7: =IF(T7=0,0,((BE7-BB7^2/B7)*(BF7-BC7^2/B7)-(BG7-BB7*BC7/B7)^2)) -> 0

Sheet Summary
A1: Totals
A2: Every figure here is a formula referencing the Data and Categories sheets. No number on this sheet is typed in by hand.
A4: Payroll before adjustment | B4: =SUM(Data!$N$5:$N$14) -> 526050
A5: Headcount | B5: =COUNTA(Data!$A$5:$A$14) -> 10
A7: Metric | B7: Minimum compliance | C7: Full equalisation | D7: Difference
A8: Pay adjustment | B8: =SUM(Categories!$AC$5:$AC$7) -> 27117.857 | C8: =SUM(Categories!$AK$5:$AK$7) -> 34276.347 | D8: =C8-B8 -> 7158.4894
A9: Employer contributions | B9: =SUM(Categories!$AD$5:$AD$7) -> 6446.8044 | C9: =SUM(Categories!$AL$5:$AL$7) -> 7501.8196 | D9: =C9-B9 -> 1055.0152
A10: Total | B10: =B8+B9 -> 33564.661 | C10: =C8+C9 -> 41778.166 | D10: =C10-B10 -> 8213.5046
A11: As % of payroll | B11: =IF($B$4=0,0,B10/$B$4*100) -> 6.3805078 | C11: =IF($B$4=0,0,C10/$B$4*100) -> 7.9418622 | D11: =C11-B11 -> 1.5613544
A12: Employees receiving an uplift | B12: =SUM(Categories!$AF$5:$AF$7) -> 1 | C12: =SUM(Categories!$AN$5:$AN$7) -> 3 | D12: =C12-B12 -> 2
A13: Current-year effect | B13: =B10*(13-implementation_month)/12 -> 16782.331 | C13: =C10*(13-implementation_month)/12 -> 20889.083 | D13: =C13-B13 -> 4106.7523
A14: Next-year effect | B14: =B10 -> 33564.661 | C14: =C10 -> 41778.166 | D14: =C14-B14 -> 8213.5046
A16: Reconciliation with the calculator
A17: Filled in at the reconciliation step: totals from the HTML calculator are entered here and compared against B10 / C10. Any discrepancy above one cent is a blocker.

Sheet Legend
A1: Legend and method
A3: Colours
A4: Yellow | B4: Source data. Comes from the CSV, never calculated.
A5: Blue | B5: Calculated by formula. Nothing to edit — it recalculates itself.
A6: Green | B6: A setting on the Settings sheet. These are meant to be changed.
A8: Units
A9: Where to find them | B9: The units for each column are in a comment on its header cell on the Data sheet (red corner marker — hover over it). The same information, in short, is below.
A10: base_salary, variable_pay | B10: Euros actually paid for the period, not annualised. Someone on a 0.5 FTE contract, or who worked 7 months, shows what they actually received. Variable pay follows the same convention as base salary.
A11: n_base, n_var, n_total | B11: Euros per year at full time, obtained by dividing actual pay by factor. Employees can only be compared on these figures: otherwise half the gap would be a difference in working time rather than in pay.
A12: grade | B12: Position in the grade ladder: a higher number means a higher grade. Only the ordering matters to the calculation; the absolute value carries no meaning.
A14: Order of calculation
A15: 1. Normalisation | B15: factor = fte x (months_worked / 12). Base salary and variable pay are divided by factor, converting them to a full-time, full-year equivalent. Only normalised figures are comparable across employees.
A16: 2. Gaps | B16: raw_gap = (mean_M - mean_F) / mean_M x 100, computed on n_total (normalised base plus variable pay), separately for each category.
A17: 3. Regression | B17: OLS of n_total on grade and tenure within each category, solved from explicit sums via Cramer's rule. It answers one question: how much of the gap is accounted for by grade and tenure. The guard mirrors calc.js — fewer than 4 observations or a constant predictor means the regression is undefined, explained = 0, and the whole gap is treated as unexplained (the conservative direction).
A18: 4. Explained share | B18: explained = coef_grade x (mean male grade - mean female grade) + coef_tenure x (mean male tenure - mean female tenure), expressed as % of mean_M. Capped at the size of the gap itself: the model cannot explain more than exists.
A19: 5. Selecting recipients | B19: Women whose normalised n_total falls below the median of their own category (the median across the whole category, both genders). Categories where the gap favours women are not adjusted in either scenario — levelling only ever moves pay upwards.
A20: 6. Distribution | B20: Proportional to the shortfall against the median: share = (median - n_total) / sum of all shortfalls. The further below the middle an employee sits, the larger the portion of the budget they receive.
A21: Two distinct quantities | B21: The average category gap and an individual's shortfall do different jobs. The average gap determines HOW MUCH MONEY the category needs in total (step 5, the need formula). The shortfall against the median determines HOW THAT MONEY IS SPLIT between people (step 6). The average gap does not enter an individual uplift: a person's shortfall is measured against the category median, not against the male average.
A22: Consequence | B22: A woman paid above the median receives nothing, even where her category's gap is large. The method lifts the bottom half rather than every woman across the board.
A23: 7. Contributions | B23: Charged on the increase in base pay, not on total salary, and always against actual base pay. The portion of the uplift that fits under the ceiling attracts the full rate; the portion above it attracts the reduced rate.
A24: 8. Totals | B24: Current-year effect = full amount x (13 - implementation month) / 12. Implementing in January gives 12/12, in December 1/12.
A26: The two scenarios
A27: Minimum compliance | B27: Bring the unexplained gap down to the threshold (5% by default). Categories already below the threshold are left untouched.
A28: Full equalisation | B28: Bring the unexplained gap to zero in every category where it is positive.
A30: Caveats
A31: What explained means | B31: The word is technical, not exculpatory. If women are systematically not promoted through the grades, the regression will attribute the gap to grade and call it explained. That is a limitation of the method, not a finding about fairness.
A32: No array formulas | B32: The whole model is built on ordinary formulas: SUMIFS, SUMPRODUCT, COUNTIFS. Ctrl+Shift+Enter is never required, in any version of Excel. Medians are computed via rank (the helper columns _rank_cat / _rank_sex on the Data sheet) and the regression from explicit sums rather than LINEST.
A33: PRNG | B33: The demo data is generated by mulberry32 + Box-Muller from a fixed seed. That cannot be reproduced byte-for-byte in Excel formulas, so the array is exported as plain numbers. Everything computed on top of it is live.
