Workbook
Name AboveCeilingTier1: Inputs!$B$15
Name AboveCeilingTier2: Inputs!$B$16
Name AboveCeilingTier3: Inputs!$B$17
Name Ceiling: Inputs!$B$14
Name ClipAtMax: Inputs!$B$11
Name CompanyTarget: Inputs!$B$12
Name EffDate: Inputs!$B$4
Name EffMonth: Inputs!$B$5
Name InYearFactor: Inputs!$B$6
Name MaxIncrease: Inputs!$B$10
Name MinMonthsChange: Inputs!$B$9
Name MinMonthsHire: Inputs!$B$8
Name PoolPct: Inputs!$B$7
Name RateBelow: Inputs!$B$13

Sheet Summary
A1: Summary: what the review costs
B3: Value
A4: Headcount | B4: =COUNT(Calc!$I:$I) -> 212
A5: Eligible for merit | B5: =SUM(Calc!$AH:$AH) -> 209
A7: PAYROLL COST: full year, incl. employer contributions
A8: Current payroll cost | B8: =SUM(Calc!$BA:$BA)+SUM(Calc!$BB:$BB) -> 16557322
A9: of which total cash (base + bonus) | B9: =SUM(Calc!$BA:$BA) -> 12970151
A10: of which employer contributions | B10: =SUM(Calc!$BB:$BB) -> 3587171
A11: Payroll cost after pay equity | B11: =SUM(Calc!$BC:$BC)+SUM(Calc!$BD:$BD) -> 16890080
A12: Payroll cost after merit review | B12: =SUM(Calc!$BE:$BE)+SUM(Calc!$BF:$BF) -> 17676509
A13: Change: pay equity | B13: =B11-B8 -> 332757.14
A14: Change: merit review | B14: =B12-B11 -> 786429.76
A15: Change: total | B15: =B12-B8 -> 1119186.9
A16: Change: total, % of current payroll cost | B16: =IF(B8>0,B15/B8,0) -> 0.067594679
A18: THIS YEAR: from the effective month
A19: Change this year: pay equity | B19: =B13*InYearFactor -> 249567.85
A20: Change this year: merit review | B20: =B14*InYearFactor -> 589822.32
A21: Change this year: total | B21: =B19+B20 -> 839390.17
A22: Change this year, % of current payroll cost | B22: =IF(B8>0,B21/B8,0) -> 0.050696009
A24: PAY EQUITY ADJUSTMENT (Calc step 2), breakdown
A25: Base adjustment | B25: =SUM(Calc!$BG:$BG) -> 257991.67
A26: Bonus effect | B26: =SUM(Calc!$BH:$BH) -> 27282.115
A27: Employer contributions | B27: =SUM(Calc!$BI:$BI) -> 47483.359
A28: Total, full year | B28: =B25+B26+B27 -> 332757.14
A29: Total, this year | B29: =B28*InYearFactor -> 249567.85
A31: MERIT INCREASE from the aligned base (Calc step 5), breakdown
A32: Merit increase (base) | B32: =SUM(Calc!$BJ:$BJ) -> 637569.71
A33: Bonus effect | B33: =SUM(Calc!$BK:$BK) -> 90440.597
A34: Employer contributions | B34: =SUM(Calc!$BL:$BL) -> 58419.452
A35: Total, full year | B35: =B32+B33+B34 -> 786429.76
A36: Total, this year | B36: =B35*InYearFactor -> 589822.32
A38: MERIT REVIEW VS TARGET BUDGET, incl. bonus and employer contributions
A39: Eligible base payroll | B39: =SUM(Calc!$BM:$BM) -> 11819694
A40: Target merit increase, % of eligible base payroll (change on Inputs) | B40: =PoolPct -> 0.04
A41: Merit increase as calculated, % of eligible base payroll | B41: =IF(B39>0,B32/B39,0) -> 0.053941305
A42: Variance vs target, pp (+ over, − under) | B42: =(B41-B40)*100 -> 1.3941305
A43: Target budget, full year | B43: =B44+B45+B46 -> 586858.83
A44: of which base | B44: =SUM(Calc!$BO:$BO) -> 472787.75
A45: of which bonus | B45: =SUM(Calc!$BP:$BP) -> 51551.713
A46: of which employer contributions | B46: =SUM(Calc!$BS:$BS) -> 62519.368
A47: Variance vs target budget, € full year (+ over) | B47: =B35-B43 -> 199570.92
A48: Target budget, this year | B48: =B43*InYearFactor -> 440144.13
A49: Variance vs target budget, € this year (+ over) | B49: =B36-B48 -> 149678.19
A51: FLAGS
A52: Above range max after equity adjustment (amber: check, not an error) | B52: =SUM(Calc!$AE:$AE) -> 7
A53: At or above range max: no merit increase (red-circled if above) | B53: =SUM(Calc!$AS:$AS) -> 10
A54: Below range min after review | B54: =SUM(Calc!$AZ:$AZ) -> 1
A56: DATA CHECKS: all should be 0
A57: Employee rows not in the calculation | B57: =COUNTA(Employees!$A:$A)-1-B4 -> 0
A58: Employees without a range on Bands | B58: =B4-SUM(Calc!$L:$L) -> 0
A59: Employees in categories missing from Categories | B59: =B4-SUM(Categories!$B:$B) -> 0
A60: Employees with a rating missing from the rating table | B60: =B4-SUMPRODUCT(COUNTIFS(Calc!$F:$F,Inputs!$A$21:$A$25)) -> 0

Sheet Inputs
A1: Inputs: change the yellow cells
A3: Setting | B3: Value | C3: Note
A4: Effective from (pick a month) | B4: 46478 | C4: Increases take effect on the 1st of this month. Eligibility is counted up to it. Pick from the list.
A5: Effective month | B5: =MONTH(EffDate) -> 4 | C5: Month number of the effective date.
A6: In-year proration factor | B6: =(13-EffMonth)/12 -> 0.75 | C6: Months from the effective month to December inclusive, ÷ 12; the increase is assumed to start on the 1st of that month.
A7: Target merit increase, % of eligible base payroll | B7: 0.04 | C7: The planned average increase, as % of eligible staff's annual base after the pay equity step, FTE-weighted. The target budget on Summary is this % given to every eligible person, with bonus and employer contributions.
A8: Minimum tenure, months | B8: 6 | C8: Hired fewer months before the effective date than this: not in the review. Hired after the effective date: never in it.
A9: No individual pay change in the last, months | B9: 3 | C9: Individual pay change fewer months before the effective date than this: not in the review.
A10: Increase cap per person, % of aligned base | B10: 0.3 | C10: A safety limit. The increase is each person's gap to target, or the rating minimum if higher; the cap only cuts it if it is larger. 'No cap' (or an empty cell, or 0%) = no limit.
A11: Clip increases at range maximum | B11: Yes | C11: Yes: a merit increase never takes base pay above the range maximum. The pay equity adjustment is not clipped.
A12: Pay policy position, % of range midpoint | B12: 1 | C12: Leave at 100% if your range midpoints already reflect your pay policy.
A13: Employer contribution rate up to the ceiling | B13: 0.3215 | C13: Default: Spain 2026, 30.65% (permanent contracts; fixed-term 31.85%) + AT/EP occupational accident and disease premium, office-work rate 1.50% (RDL 3/2026, Cuadro II a) = 32.15%. Use your activity's AT/EP rate. These are 2026 rates. Rates for 2027 are already set and slightly higher (MEI employer share 0.83%, higher solidarity rates); 2026 rates are kept, so the contribution cost of a 2027 review is slightly understated.
A14: Annual contribution ceiling | B14: 61214.4 | C14: Default: Spain 2026, €5,101.20 a month × 12 (Orden PJC/297/2026). 2027 not yet published: 2026 assumed.
A15: Rate above the ceiling, tier 1: up to 10% over the ceiling | B15: 0.0096 | C15: Employer rate on the part of pay above the ceiling. Set 0% in all three tiers if your country charges nothing above it. Default: Spain 2026 (cuota de solidaridad), employer share, 0.96%.
A16: Rate above the ceiling, tier 2: 10% to 50% over the ceiling | B16: 0.0104 | C16: Default: Spain 2026, employer share, 1.04%.
A17: Rate above the ceiling, tier 3: more than 50% over the ceiling | B17: 0.0122 | C17: Default: Spain 2026, employer share, 1.22%.
A19: Targets by performance rating (illustrative assumption: set your own)
A20: Rating | B20: Label | C20: Target compa-ratio | D20: Minimum increase, % of aligned base
A21: 1 | B21: Unsatisfactory | C21: 0 | D21: 0
A22: 2 | B22: Partially meets | C22: 0.95 | D22: 0
A23: 3 | B23: Meets | C23: 1 | D23: 0
A24: 4 | B24: Exceeds | C24: 1.05 | D24: 0.01
A25: 5 | B25: Outstanding | C25: 1.1 | D25: 0.02
A26: Target compa-ratio: the compa-ratio each rating is raised to. The increase is the gap from aligned base to mid × pay policy position × this target. Set 0% to give a rating no increase at all. A target above a grade's range max (max / mid) is cut at the max when 'Clip increases at range maximum' = Yes.
A27: Minimum increase: a floor for a rating, paid even when the person is already at or above the target. 0% = no floor. It does not apply at or above the range maximum or to ineligible staff, and it is limited by the per-person cap and, when the clip at max is on, by the headroom to the max.
A29: Compa-ratio zones: only for the Matrix sheet view | C29: Increases do not depend on zones. Zones only group people into the classic rating × compa-ratio grid on the Matrix sheet.
A30: Zone | B30: Lower bound (CR from)
A31: 1 | B31: 0
A32: 2 | B32: 0.9
A33: 3 | B33: 1
A34: 4 | B34: 1.1

Sheet Lists
A1: Effective from | B1: Minimum tenure, months | C1: No pay change in the last, months | D1: Increase cap | E1: Clip at range max
A2: 46327 | B2: 0 | C2: 0 | D2: No cap | E2: Yes
A3: 46357 | B3: 1 | C3: 1 | D3: 0.1 | E3: No
A4: 46388 | B4: 2 | C4: 2 | D4: 0.15
A5: 46419 | B5: 3 | C5: 3 | D5: 0.2
A6: 46447 | B6: 6 | C6: 6 | D6: 0.25
A7: 46478 | B7: 9 | C7: 9 | D7: 0.3
A8: 46508 | B8: 12 | C8: 12 | D8: 0.4
A9: 46539 | D9: 0.5
A10: 46569 | D10: 0.75
A11: 46600 | D11: 1
A12: 46631
A13: 46661
A14: 46692
A15: 46722
A16: 46753
A17: 46784
A18: 46813
A19: 46844
A20: 46874
A21: 46905
A22: 46935
A23: 46966
... A27: 47088

Sheet Bands
A1: Category | B1: Grade | C1: Range min | D1: Range mid | E1: Range max | F1: Lookup key
A2: Customer Support | B2: 3 | C2: 25700 | D2: 29500 | E2: 33400 | F2: =A2&"|"&B2 -> Customer Support|3
A3: Customer Support | B3: 4 | C3: 29800 | D3: 34300 | E3: 38700 | F3: =A3&"|"&B3 -> Customer Support|4
A4: Customer Support | B4: 5 | C4: 34500 | D4: 39700 | E4: 44900 | F4: =A4&"|"&B4 -> Customer Support|5
A5: Customer Support | B5: 6 | C5: 38300 | D5: 46000 | E5: 53600 | F5: =A5&"|"&B5 -> Customer Support|6
A6: Manufacturing | B6: 4 | C6: 30400 | D6: 35000 | E6: 39500 | F6: =A6&"|"&B6 -> Manufacturing|4
A7: Manufacturing | B7: 5 | C7: 35600 | D7: 40900 | E7: 46300 | F7: =A7&"|"&B7 -> Manufacturing|5
A8: Manufacturing | B8: 6 | C8: 39700 | D8: 47600 | E8: 55600 | F8: =A8&"|"&B8 -> Manufacturing|6
A9: Manufacturing | B9: 7 | C9: 46200 | D9: 55400 | E9: 64700 | F9: =A9&"|"&B9 -> Manufacturing|7
A10: Manufacturing | B10: 8 | C10: 53700 | D10: 64400 | E10: 75200 | F10: =A10&"|"&B10 -> Manufacturing|8
A11: Operations | B11: 5 | C11: 33700 | D11: 38800 | E11: 43800 | F11: =A11&"|"&B11 -> Operations|5
A12: Operations | B12: 6 | C12: 37000 | D12: 44400 | E12: 51800 | F12: =A12&"|"&B12 -> Operations|6
A13: Operations | B13: 7 | C13: 42300 | D13: 50800 | E13: 59200 | F13: =A13&"|"&B13 -> Operations|7
... A36: Legal | B36: 12 | C36: 76700 | D36: 99700 | E36: 122700 | F36: =A36&"|"&B36 -> Legal|12

Sheet Employees
A1: id | B1: category | C1: gender | D1: grade | E1: rating | F1: hire_date | G1: last_change_date | H1: base_salary | I1: bonus_pct | J1: fte
A2: E001 | B2: Engineering | C2: M | D2: 8 | E2: 4 | F2: 44433 | G2: 46270 | H2: 56987.18 | I2: 14.33 | J2: 1
A3: E002 | B3: Engineering | C3: M | D3: 9 | E3: 2 | F3: 43227 | G3: 46113 | H3: 65996.64 | I3: 13.38 | J3: 1
A4: E003 | B4: Engineering | C4: M | D4: 11 | E4: 3 | F4: 42168 | G4: 46113 | H4: 79747.78 | I4: 14.12 | J4: 1
A5: E004 | B5: Engineering | C5: M | D5: 10 | E5: 2 | F5: 43775 | G5: 46113 | H5: 73284.69 | I5: 11.99 | J5: 1
A6: E005 | B6: Engineering | C6: F | D6: 10 | E6: 4 | F6: 44067 | G6: 46113 | H6: 69538.46 | I6: 9.57 | J6: 1
A7: E006 | B7: Engineering | C7: M | D7: 9 | E7: 5 | F7: 44469 | G7: 46113 | H7: 60248.19 | I7: 10.4 | J7: 1
A8: E007 | B8: Engineering | C8: M | D8: 7 | E8: 5 | F8: 44725 | G8: 46113 | H8: 47983.14 | I8: 11.81 | J8: 1
A9: E008 | B9: Engineering | C9: M | D9: 11 | E9: 2 | F9: 44067 | G9: 46113 | H9: 79273.59 | I9: 9.24 | J9: 1
A10: E009 | B10: Engineering | C10: M | D10: 8 | E10: 3 | F10: 44323 | G10: 46113 | H10: 56597.91 | I10: 10.73 | J10: 1
A11: E010 | B11: Engineering | C11: M | D11: 10 | E11: 3 | F11: 42935 | G11: 46113 | H11: 75607.45 | I11: 11.99 | J11: 1
A12: E011 | B12: Engineering | C12: M | D12: 7 | E12: 2 | F12: 45455 | G12: 46113 | H12: 37697.15 | I12: 14.04 | J12: 1
A13: E012 | B13: Engineering | C13: M | D13: 9 | E13: 3 | F13: 43666 | G13: 46113 | H13: 60920.28 | I13: 12.28 | J13: 1
... A213: E212 | B213: Sales | C213: M | D213: 9 | E213: 3 | F213: 45127 | G213: 46113 | H213: 54620.08 | I213: 26 | J213: 1

Sheet Calc
A1: Step 0: Input | L1: Step 1: Range and total cash | R1: Step 2: Pay equity adjustment (unexplained gap closed in full) | AF1: Step 3: Eligibility | AI1: Step 4: Target salary | AO1: Step 5: Merit increase | BA1: Step 6: Cost (annual, FTE-weighted) | BN1: Step 6a: Target budget, the target % to every eligible person | BT1: Step 7: Total cash for the gap check
A2: Row number in the list. | B2: The n-th ID on Employees. | C2: Category of workers (same work or work of equal value); looked up by ID. | D2: F or M. | F2: 1 to 5. | H2: Last individual change. | I2: Annual gross base, full time; in Spain including the extra payments (pagas extra). | J2: Bonus as a share of base. | K2: 1 = full time. | L2: 0: no row for this category and grade on Bands; totals show #N/A until it is added. | M2: From Bands by category and grade. | P2: Years from hire to effective date. | Q2: Base plus bonus, full time. | R2: Helper sums for the regression on Categories. | W2: Rounded to the cent so that ranking compares exact values. | X2: Order by total cash within the category, for the median. | Y2: From Categories. | Z2: 1: woman below the category median, and the category has an unexplained gap against women. | AB2: Category amount shared in proportion to each shortfall. | AC2: Paid through base; the bonus follows the base. | AD2: Merit is computed from this base. | AE2: Amber flag, not an error. The adjustment is paid in full. The category's amount is shared in proportion to each woman's shortfall to the category median, and a category spans several grades, so her new pay can sit above her grade's range maximum. Worth a look: her grade, the range, or how the category is defined. | AF2: Complete months up to the effective date; −1 if hired after it. | AG2: −1 if the change is after the effective date. | AH2: 1: in the review. | AI2: Aligned base / range mid. | AJ2: Not used in the increase. Only places the person in a column of the Matrix sheet grid (rating × compa-ratio). | AK2: From the rating table. | AL2: Floor for the rating, paid even at or above target; see Inputs. | AM2: Mid × pay policy position × target compa-ratio. | AN2: 0 if already at or above target. | AO2: 0: 'No cap', empty or 0% on Inputs. | AP2: Largest increase for this person: the cap × their aligned base; 0 when there is no cap. | AR2: Gap to target, at least the minimum, never above the cap (if there is one). | AS2: At or above range max: no merit increase. | AT2: Already at or above max: increase set to 0, whatever the rule gave. | AU2: Range max − aligned base: the most an increase can add without leaving the range. | AV2: If 'Clip increases at range maximum' = Yes, an increase larger than the headroom is cut to the headroom, so new base = range max. | AW2: Annual full-time base increase. | AZ2: Flag. | BA2: (Annual base + bonus) × FTE. | BB2: Full rate up to the contribution ceiling, tiered rates above it (Inputs). | BH2: Bonus grows with base. | BI2: Extra employer contributions on the increase. | BM2: Aligned base of eligible staff, FTE-weighted: the denominator for the target %. | BN2: Aligned base × target %, full time. A benchmark, not a payout. | BP2: Each person's own bonus %. | BS2: Depends on where each person sits against the ceiling, so it is not a flat rate on the target base. | BV2: Helper sums for the regression after merit on Categories.
A4: No. | B4: ID | C4: Category | D4: Gender | E4: Grade | F4: Rating | G4: Hire date | H4: Last pay change | I4: Base salary | J4: Bonus % of base | K4: FTE | L4: Range found | M4: Range min | N4: Range mid | O4: Range max | P4: Tenure, years | Q4: Total cash | R4: grade² | S4: tenure² | T4: grade×tenure | U4: grade×cash | V4: tenure×cash | W4: Total cash, rounded | X4: Rank in category | Y4: Category median total cash | Z4: Receives adjustment | AA4: Shortfall to median | AB4: Adjustment, total cash | AC4: Adjustment, base | AD4: Aligned base | AE4: Above range max after equity adjustment | AF4: Months since hire | AG4: Months since change | AH4: Eligible | AI4: Compa-ratio | AJ4: Compa-ratio zone | AK4: Target compa-ratio for rating | AL4: Minimum increase | AM4: Target salary | AN4: Gap to target | AO4: Cap applies | AP4: Increase cap, € | AQ4: Minimum increase, € | AR4: Increase before range limits | AS4: At or above range max (red-circled) | AT4: After red-circle rule | AU4: Headroom to range max | AV4: After clip at max | AW4: Merit increase | AX4: Increase % | AY4: New base | AZ4: Below range min after review | BA4: Total cash before equity, at actual FTE | BB4: Employer contributions before equity | BC4: Total cash after equity, at actual FTE | BD4: Employer contributions after equity | BE4: Total cash after merit, at actual FTE | BF4: Employer contributions after merit | BG4: Equity: base | BH4: Equity: bonus | BI4: Equity: employer contributions | BJ4: Merit: base | BK4: Merit: bonus | BL4: Merit: employer contributions | BM4: Eligible base | BN4: Target increase | BO4: Target: base | BP4: Target: bonus | BQ4: Total cash at target, at actual FTE | BR4: Employer contributions at target | BS4: Target: employer contributions | BT4: Total cash after equity, full time | BU4: Total cash after merit, full time | BV4: grade×cash after merit | BW4: tenure×cash after merit
A5: =ROW()-4 -> 1 | B5: =INDEX(Employees!$A:$A,A5+1) -> E001 | C5: =INDEX(Employees!$A:$Z,MATCH(B5,Employees!$A:$A,0),MATCH("category",Employees!$1:$1,0)) -> Engineering | D5: =INDEX(Employees!$A:$Z,MATCH(B5,Employees!$A:$A,0),MATCH("gender",Employees!$1:$1,0)) -> M | E5: =INDEX(Employees!$A:$Z,MATCH(B5,Employees!$A:$A,0),MATCH("grade",Employees!$1:$1,0)) -> 8 | F5: =INDEX(Employees!$A:$Z,MATCH(B5,Employees!$A:$A,0),MATCH("rating",Employees!$1:$1,0)) -> 4 | G5: =INDEX(Employees!$A:$Z,MATCH(B5,Employees!$A:$A,0),MATCH("hire_date",Employees!$1:$1,0)) -> 44433 | H5: =INDEX(Employees!$A:$Z,MATCH(B5,Employees!$A:$A,0),MATCH("last_change_date",Employees!$1:$1,0)) -> 46270 | I5: =INDEX(Employees!$A:$Z,MATCH(B5,Employees!$A:$A,0),MATCH("base_salary",Employees!$1:$1,0)) -> 56987.18 | J5: =INDEX(Employees!$A:$Z,MATCH(B5,Employees!$A:$A,0),MATCH("bonus_pct",Employees!$1:$1,0))/100 -> 0.1433 | K5: =INDEX(Employees!$A:$Z,MATCH(B5,Employees!$A:$A,0),MATCH("fte",Employees!$1:$1,0)) -> 1 | L5: =IF(ISNA(MATCH(C5&"|"&E5,Bands!$F:$F,0)),0,1) -> 1 | M5: =INDEX(Bands!$C:$C,MATCH(C5&"|"&E5,Bands!$F:$F,0)) -> 47700 | N5: =INDEX(Bands!$D:$D,MATCH(C5&"|"&E5,Bands!$F:$F,0)) -> 57200 | O5: =INDEX(Bands!$E:$E,MATCH(C5&"|"&E5,Bands!$F:$F,0)) -> 66800 | P5: =(EffDate-G5)/365.25 -> 5.5989049 | Q5: =I5*(1+J5) -> 65153.443 | R5: =E5^2 -> 64 | S5: =P5^2 -> 31.347736 | T5: =E5*P5 -> 44.791239 | U5: =E5*Q5 -> 521227.54 | V5: =P5*Q5 -> 364787.93 | W5: =ROUND(Q5,2) -> 65153.44 | X5: =COUNTIFS($C:$C,C5,$W:$W,"<"&W5)+COUNTIFS($C:$C,C5,$W:$W,W5,$B:$B,"<"&B5)+1 -> 17 | Y5: =INDEX(Categories!$AH:$AH,MATCH(C5,Categories!$A:$A,0)) -> 71955.394 | Z5: =IF(AND(D5="F",Q5<Y5,INDEX(Categories!$AI:$AI,MATCH(C5,Categories!$A:$A,0))>0),1,0) -> 0 | AA5: =IF(Z5=1,Y5-Q5,0) -> 0 | AB5: =IF(Z5=1,INDEX(Categories!$AI:$AI,MATCH(C5,Categories!$A:$A,0))*AA5/INDEX(Categories!$AJ:$AJ,MATCH(C5,Categories!$A:$A,0)),0) -> 0 | AC5: =AB5/(1+J5) -> 0 | AD5: =I5+AC5 -> 56987.18 | AE5: =IF(AND(AC5>0,AD5>O5),1,0) -> 0 | AF5: =IF(G5>EffDate,-1,DATEDIF(G5,EffDate,"m")) -> 67 | AG5: =IF(H5>EffDate,-1,DATEDIF(H5,EffDate,"m")) -> 6 | AH5: =IF(AND(AF5>=MinMonthsHire,AG5>=MinMonthsChange),1,0) -> 1 | AI5: =AD5/N5 -> 0.99627937 | AJ5: =MATCH(AI5,Inputs!$B$31:$B$34,1) -> 2 | AK5: =INDEX(Inputs!$C$21:$C$25,MATCH(F5,Inputs!$A$21:$A$25,0)) -> 1.05 | AL5: =INDEX(Inputs!$D$21:$D$25,MATCH(F5,Inputs!$A$21:$A$25,0)) -> 0.01 | AM5: =N5*CompanyTarget*AK5 -> 60060 | AN5: =MAX(0,AM5-AD5) -> 3072.82 | AO5: =IF(AND(ISNUMBER(MaxIncrease),MaxIncrease>0),1,0) -> 1 | AP5: =IF(AO5=1,AD5*MaxIncrease,0) -> 17096.154 | AQ5: =AD5*AL5 -> 569.8718 | AR5: =IF(AK5=0,0,IF(AO5=1,MIN(MAX(AN5,AQ5),AP5),MAX(AN5,AQ5))) -> 3072.82 | AS5: =IF(AD5>=O5,1,0) -> 0 | AT5: =IF(AS5=1,0,AR5) -> 3072.82 | AU5: =MAX(0,O5-AD5) -> 9812.82 | AV5: =IF(ClipAtMax="No",AT5,MIN(AT5,AU5)) -> 3072.82 | AW5: =IF(AH5=1,AV5,0) -> 3072.82 | AX5: =IF(AD5>0,AW5/AD5,0) -> 0.05392125 | AY5: =AD5+AW5 -> 60060 | AZ5: =IF(AY5<M5,1,0) -> 0 | BA5: =Q5*K5 -> 65153.443 | BB5: =RateBelow*MIN(BA5,Ceiling)+AboveCeilingTier1*MIN(MAX(0,BA5-Ceiling),0.1*Ceiling)+AboveCeilingTier2*MIN(MAX(0,BA5-1.1*Ceiling),0.4*Ceiling)+AboveCeilingTier3*MAX(0,BA5-1.5*Ceiling) -> 19718.244 | BC5: =AD5*(1+J5)*K5 -> 65153.443 | BD5: =RateBelow*MIN(BC5,Ceiling)+AboveCeilingTier1*MIN(MAX(0,BC5-Ceiling),0.1*Ceiling)+AboveCeilingTier2*MIN(MAX(0,BC5-1.1*Ceiling),0.4*Ceiling)+AboveCeilingTier3*MAX(0,BC5-1.5*Ceiling) -> 19718.244 | BE5: =AY5*(1+J5)*K5 -> 68666.598 | BF5: =RateBelow*MIN(BE5,Ceiling)+AboveCeilingTier1*MIN(MAX(0,BE5-Ceiling),0.1*Ceiling)+AboveCeilingTier2*MIN(MAX(0,BE5-1.1*Ceiling),0.4*Ceiling)+AboveCeilingTier3*MAX(0,BE5-1.5*Ceiling) -> 19753.035 | BG5: =AC5*K5 -> 0 | BH5: =AC5*J5*K5 -> 0 | BI5: =BD5-BB5 -> 0 | BJ5: =AW5*K5 -> 3072.82 | BK5: =AW5*J5*K5 -> 440.33511 | BL5: =BF5-BD5 -> 34.790895 | BM5: =IF(AH5=1,AD5*K5,0) -> 56987.18 | BN5: =IF(AH5=1,AD5*PoolPct,0) -> 2279.4872 | BO5: =BN5*K5 -> 2279.4872 | BP5: =BN5*J5*K5 -> 326.65052 | BQ5: =(AD5+BN5)*(1+J5)*K5 -> 67759.581 | BR5: =RateBelow*MIN(BQ5,Ceiling)+AboveCeilingTier1*MIN(MAX(0,BQ5-Ceiling),0.1*Ceiling)+AboveCeilingTier2*MIN(MAX(0,BQ5-1.1*Ceiling),0.4*Ceiling)+AboveCeilingTier3*MAX(0,BQ5-1.5*Ceiling) -> 19743.602 | BS5: =BR5-BD5 -> 25.357915 | BT5: =AD5*(1+J5) -> 65153.443 | BU5: =AY5*(1+J5) -> 68666.598 | BV5: =E5*BU5 -> 549332.78 | BW5: =P5*BU5 -> 384457.75
A6: =ROW()-4 -> 2 | B6: =INDEX(Employees!$A:$A,A6+1) -> E002 | C6: =INDEX(Employees!$A:$Z,MATCH(B6,Employees!$A:$A,0),MATCH("category",Employees!$1:$1,0)) -> Engineering | D6: =INDEX(Employees!$A:$Z,MATCH(B6,Employees!$A:$A,0),MATCH("gender",Employees!$1:$1,0)) -> M | E6: =INDEX(Employees!$A:$Z,MATCH(B6,Employees!$A:$A,0),MATCH("grade",Employees!$1:$1,0)) -> 9 | F6: =INDEX(Employees!$A:$Z,MATCH(B6,Employees!$A:$A,0),MATCH("rating",Employees!$1:$1,0)) -> 2 | G6: =INDEX(Employees!$A:$Z,MATCH(B6,Employees!$A:$A,0),MATCH("hire_date",Employees!$1:$1,0)) -> 43227 | H6: =INDEX(Employees!$A:$Z,MATCH(B6,Employees!$A:$A,0),MATCH("last_change_date",Employees!$1:$1,0)) -> 46113 | I6: =INDEX(Employees!$A:$Z,MATCH(B6,Employees!$A:$A,0),MATCH("base_salary",Employees!$1:$1,0)) -> 65996.64 | J6: =INDEX(Employees!$A:$Z,MATCH(B6,Employees!$A:$A,0),MATCH("bonus_pct",Employees!$1:$1,0))/100 -> 0.1338 | K6: =INDEX(Employees!$A:$Z,MATCH(B6,Employees!$A:$A,0),MATCH("fte",Employees!$1:$1,0)) -> 1 | L6: =IF(ISNA(MATCH(C6&"|"&E6,Bands!$F:$F,0)),0,1) -> 1 | M6: =INDEX(Bands!$C:$C,MATCH(C6&"|"&E6,Bands!$F:$F,0)) -> 54500 | N6: =INDEX(Bands!$D:$D,MATCH(C6&"|"&E6,Bands!$F:$F,0)) -> 65400 | O6: =INDEX(Bands!$E:$E,MATCH(C6&"|"&E6,Bands!$F:$F,0)) -> 76300 | P6: =(EffDate-G6)/365.25 -> 8.9007529 | Q6: =I6*(1+J6) -> 74826.99 | R6: =E6^2 -> 81 | S6: =P6^2 -> 79.223402 | T6: =E6*P6 -> 80.106776 | U6: =E6*Q6 -> 673442.91 | V6: =P6*Q6 -> 666016.55 | W6: =ROUND(Q6,2) -> 74826.99 | X6: =COUNTIFS($C:$C,C6,$W:$W,"<"&W6)+COUNTIFS($C:$C,C6,$W:$W,W6,$B:$B,"<"&B6)+1 -> 25 | Y6: =INDEX(Categories!$AH:$AH,MATCH(C6,Categories!$A:$A,0)) -> 71955.394 | Z6: =IF(AND(D6="F",Q6<Y6,INDEX(Categories!$AI:$AI,MATCH(C6,Categories!$A:$A,0))>0),1,0) -> 0 | AA6: =IF(Z6=1,Y6-Q6,0) -> 0 | AB6: =IF(Z6=1,INDEX(Categories!$AI:$AI,MATCH(C6,Categories!$A:$A,0))*AA6/INDEX(Categories!$AJ:$AJ,MATCH(C6,Categories!$A:$A,0)),0) -> 0 | AC6: =AB6/(1+J6) -> 0 | AD6: =I6+AC6 -> 65996.64 | AE6: =IF(AND(AC6>0,AD6>O6),1,0) -> 0 | AF6: =IF(G6>EffDate,-1,DATEDIF(G6,EffDate,"m")) -> 106 | AG6: =IF(H6>EffDate,-1,DATEDIF(H6,EffDate,"m")) -> 12 | AH6: =IF(AND(AF6>=MinMonthsHire,AG6>=MinMonthsChange),1,0) -> 1 | AI6: =AD6/N6 -> 1.0091229 | AJ6: =MATCH(AI6,Inputs!$B$31:$B$34,1) -> 3 | AK6: =INDEX(Inputs!$C$21:$C$25,MATCH(F6,Inputs!$A$21:$A$25,0)) -> 0.95 | AL6: =INDEX(Inputs!$D$21:$D$25,MATCH(F6,Inputs!$A$21:$A$25,0)) -> 0 | AM6: =N6*CompanyTarget*AK6 -> 62130 | AN6: =MAX(0,AM6-AD6) -> 0 | AO6: =IF(AND(ISNUMBER(MaxIncrease),MaxIncrease>0),1,0) -> 1 | AP6: =IF(AO6=1,AD6*MaxIncrease,0) -> 19798.992 | AQ6: =AD6*AL6 -> 0 | AR6: =IF(AK6=0,0,IF(AO6=1,MIN(MAX(AN6,AQ6),AP6),MAX(AN6,AQ6))) -> 0 | AS6: =IF(AD6>=O6,1,0) -> 0 | AT6: =IF(AS6=1,0,AR6) -> 0 | AU6: =MAX(0,O6-AD6) -> 10303.36 | AV6: =IF(ClipAtMax="No",AT6,MIN(AT6,AU6)) -> 0 | AW6: =IF(AH6=1,AV6,0) -> 0 | AX6: =IF(AD6>0,AW6/AD6,0) -> 0 | AY6: =AD6+AW6 -> 65996.64 | AZ6: =IF(AY6<M6,1,0) -> 0 | BA6: =Q6*K6 -> 74826.99 | BB6: =RateBelow*MIN(BA6,Ceiling)+AboveCeilingTier1*MIN(MAX(0,BA6-Ceiling),0.1*Ceiling)+AboveCeilingTier2*MIN(MAX(0,BA6-1.1*Ceiling),0.4*Ceiling)+AboveCeilingTier3*MAX(0,BA6-1.5*Ceiling) -> 19817.103 | BC6: =AD6*(1+J6)*K6 -> 74826.99 | BD6: =RateBelow*MIN(BC6,Ceiling)+AboveCeilingTier1*MIN(MAX(0,BC6-Ceiling),0.1*Ceiling)+AboveCeilingTier2*MIN(MAX(0,BC6-1.1*Ceiling),0.4*Ceiling)+AboveCeilingTier3*MAX(0,BC6-1.5*Ceiling) -> 19817.103 | BE6: =AY6*(1+J6)*K6 -> 74826.99 | BF6: =RateBelow*MIN(BE6,Ceiling)+AboveCeilingTier1*MIN(MAX(0,BE6-Ceiling),0.1*Ceiling)+AboveCeilingTier2*MIN(MAX(0,BE6-1.1*Ceiling),0.4*Ceiling)+AboveCeilingTier3*MAX(0,BE6-1.5*Ceiling) -> 19817.103 | BG6: =AC6*K6 -> 0 | BH6: =AC6*J6*K6 -> 0 | BI6: =BD6-BB6 -> 0 | BJ6: =AW6*K6 -> 0 | BK6: =AW6*J6*K6 -> 0 | BL6: =BF6-BD6 -> 0 | BM6: =IF(AH6=1,AD6*K6,0) -> 65996.64 | BN6: =IF(AH6=1,AD6*PoolPct,0) -> 2639.8656 | BO6: =BN6*K6 -> 2639.8656 | BP6: =BN6*J6*K6 -> 353.21402 | BQ6: =(AD6+BN6)*(1+J6)*K6 -> 77820.07 | BR6: =RateBelow*MIN(BQ6,Ceiling)+AboveCeilingTier1*MIN(MAX(0,BQ6-Ceiling),0.1*Ceiling)+AboveCeilingTier2*MIN(MAX(0,BQ6-1.1*Ceiling),0.4*Ceiling)+AboveCeilingTier3*MAX(0,BQ6-1.5*Ceiling) -> 19848.231 | BS6: =BR6-BD6 -> 31.128028 | BT6: =AD6*(1+J6) -> 74826.99 | BU6: =AY6*(1+J6) -> 74826.99 | BV6: =E6*BU6 -> 673442.91 | BW6: =P6*BU6 -> 666016.55
A7: =ROW()-4 -> 3 | B7: =INDEX(Employees!$A:$A,A7+1) -> E003 | C7: =INDEX(Employees!$A:$Z,MATCH(B7,Employees!$A:$A,0),MATCH("category",Employees!$1:$1,0)) -> Engineering | D7: =INDEX(Employees!$A:$Z,MATCH(B7,Employees!$A:$A,0),MATCH("gender",Employees!$1:$1,0)) -> M | E7: =INDEX(Employees!$A:$Z,MATCH(B7,Employees!$A:$A,0),MATCH("grade",Employees!$1:$1,0)) -> 11 | F7: =INDEX(Employees!$A:$Z,MATCH(B7,Employees!$A:$A,0),MATCH("rating",Employees!$1:$1,0)) -> 3 | G7: =INDEX(Employees!$A:$Z,MATCH(B7,Employees!$A:$A,0),MATCH("hire_date",Employees!$1:$1,0)) -> 42168 | H7: =INDEX(Employees!$A:$Z,MATCH(B7,Employees!$A:$A,0),MATCH("last_change_date",Employees!$1:$1,0)) -> 46113 | I7: =INDEX(Employees!$A:$Z,MATCH(B7,Employees!$A:$A,0),MATCH("base_salary",Employees!$1:$1,0)) -> 79747.78 | J7: =INDEX(Employees!$A:$Z,MATCH(B7,Employees!$A:$A,0),MATCH("bonus_pct",Employees!$1:$1,0))/100 -> 0.1412 | K7: =INDEX(Employees!$A:$Z,MATCH(B7,Employees!$A:$A,0),MATCH("fte",Employees!$1:$1,0)) -> 1 | L7: =IF(ISNA(MATCH(C7&"|"&E7,Bands!$F:$F,0)),0,1) -> 1 | M7: =INDEX(Bands!$C:$C,MATCH(C7&"|"&E7,Bands!$F:$F,0)) -> 68400 | N7: =INDEX(Bands!$D:$D,MATCH(C7&"|"&E7,Bands!$F:$F,0)) -> 85500 | O7: =INDEX(Bands!$E:$E,MATCH(C7&"|"&E7,Bands!$F:$F,0)) -> 102600 | P7: =(EffDate-G7)/365.25 -> 11.800137 | Q7: =I7*(1+J7) -> 91008.167 | R7: =E7^2 -> 121 | S7: =P7^2 -> 139.24323 | T7: =E7*P7 -> 129.80151 | U7: =E7*Q7 -> 1001089.8 | V7: =P7*Q7 -> 1073908.8 | W7: =ROUND(Q7,2) -> 91008.17 | X7: =COUNTIFS($C:$C,C7,$W:$W,"<"&W7)+COUNTIFS($C:$C,C7,$W:$W,W7,$B:$B,"<"&B7)+1 -> 40 | Y7: =INDEX(Categories!$AH:$AH,MATCH(C7,Categories!$A:$A,0)) -> 71955.394 | Z7: =IF(AND(D7="F",Q7<Y7,INDEX(Categories!$AI:$AI,MATCH(C7,Categories!$A:$A,0))>0),1,0) -> 0 | AA7: =IF(Z7=1,Y7-Q7,0) -> 0 | AB7: =IF(Z7=1,INDEX(Categories!$AI:$AI,MATCH(C7,Categories!$A:$A,0))*AA7/INDEX(Categories!$AJ:$AJ,MATCH(C7,Categories!$A:$A,0)),0) -> 0 | AC7: =AB7/(1+J7) -> 0 | AD7: =I7+AC7 -> 79747.78 | AE7: =IF(AND(AC7>0,AD7>O7),1,0) -> 0 | AF7: =IF(G7>EffDate,-1,DATEDIF(G7,EffDate,"m")) -> 141 | AG7: =IF(H7>EffDate,-1,DATEDIF(H7,EffDate,"m")) -> 12 | AH7: =IF(AND(AF7>=MinMonthsHire,AG7>=MinMonthsChange),1,0) -> 1 | AI7: =AD7/N7 -> 0.93272257 | AJ7: =MATCH(AI7,Inputs!$B$31:$B$34,1) -> 2 | AK7: =INDEX(Inputs!$C$21:$C$25,MATCH(F7,Inputs!$A$21:$A$25,0)) -> 1 | AL7: =INDEX(Inputs!$D$21:$D$25,MATCH(F7,Inputs!$A$21:$A$25,0)) -> 0 | AM7: =N7*CompanyTarget*AK7 -> 85500 | AN7: =MAX(0,AM7-AD7) -> 5752.22 | AO7: =IF(AND(ISNUMBER(MaxIncrease),MaxIncrease>0),1,0) -> 1 | AP7: =IF(AO7=1,AD7*MaxIncrease,0) -> 23924.334 | AQ7: =AD7*AL7 -> 0 | AR7: =IF(AK7=0,0,IF(AO7=1,MIN(MAX(AN7,AQ7),AP7),MAX(AN7,AQ7))) -> 5752.22 | AS7: =IF(AD7>=O7,1,0) -> 0 | AT7: =IF(AS7=1,0,AR7) -> 5752.22 | AU7: =MAX(0,O7-AD7) -> 22852.22 | AV7: =IF(ClipAtMax="No",AT7,MIN(AT7,AU7)) -> 5752.22 | AW7: =IF(AH7=1,AV7,0) -> 5752.22 | AX7: =IF(AD7>0,AW7/AD7,0) -> 0.072130158 | AY7: =AD7+AW7 -> 85500 | AZ7: =IF(AY7<M7,1,0) -> 0 | BA7: =Q7*K7 -> 91008.167 | BB7: =RateBelow*MIN(BA7,Ceiling)+AboveCeilingTier1*MIN(MAX(0,BA7-Ceiling),0.1*Ceiling)+AboveCeilingTier2*MIN(MAX(0,BA7-1.1*Ceiling),0.4*Ceiling)+AboveCeilingTier3*MAX(0,BA7-1.5*Ceiling) -> 19985.388 | BC7: =AD7*(1+J7)*K7 -> 91008.167 | BD7: =RateBelow*MIN(BC7,Ceiling)+AboveCeilingTier1*MIN(MAX(0,BC7-Ceiling),0.1*Ceiling)+AboveCeilingTier2*MIN(MAX(0,BC7-1.1*Ceiling),0.4*Ceiling)+AboveCeilingTier3*MAX(0,BC7-1.5*Ceiling) -> 19985.388 | BE7: =AY7*(1+J7)*K7 -> 97572.6 | BF7: =RateBelow*MIN(BE7,Ceiling)+AboveCeilingTier1*MIN(MAX(0,BE7-Ceiling),0.1*Ceiling)+AboveCeilingTier2*MIN(MAX(0,BE7-1.1*Ceiling),0.4*Ceiling)+AboveCeilingTier3*MAX(0,BE7-1.5*Ceiling) -> 20064.01 | BG7: =AC7*K7 -> 0 | BH7: =AC7*J7*K7 -> 0 | BI7: =BD7-BB7 -> 0 | BJ7: =AW7*K7 -> 5752.22 | BK7: =AW7*J7*K7 -> 812.21346 | BL7: =BF7-BD7 -> 78.621908 | BM7: =IF(AH7=1,AD7*K7,0) -> 79747.78 | BN7: =IF(AH7=1,AD7*PoolPct,0) -> 3189.9112 | BO7: =BN7*K7 -> 3189.9112 | BP7: =BN7*J7*K7 -> 450.41546 | BQ7: =(AD7+BN7)*(1+J7)*K7 -> 94648.493 | BR7: =RateBelow*MIN(BQ7,Ceiling)+AboveCeilingTier1*MIN(MAX(0,BQ7-Ceiling),0.1*Ceiling)+AboveCeilingTier2*MIN(MAX(0,BQ7-1.1*Ceiling),0.4*Ceiling)+AboveCeilingTier3*MAX(0,BQ7-1.5*Ceiling) -> 20028.335 | BS7: =BR7-BD7 -> 42.947805 | BT7: =AD7*(1+J7) -> 91008.167 | BU7: =AY7*(1+J7) -> 97572.6 | BV7: =E7*BU7 -> 1073298.6 | BW7: =P7*BU7 -> 1151370
A8: =ROW()-4 -> 4 | B8: =INDEX(Employees!$A:$A,A8+1) -> E004 | C8: =INDEX(Employees!$A:$Z,MATCH(B8,Employees!$A:$A,0),MATCH("category",Employees!$1:$1,0)) -> Engineering | D8: =INDEX(Employees!$A:$Z,MATCH(B8,Employees!$A:$A,0),MATCH("gender",Employees!$1:$1,0)) -> M | E8: =INDEX(Employees!$A:$Z,MATCH(B8,Employees!$A:$A,0),MATCH("grade",Employees!$1:$1,0)) -> 10 | F8: =INDEX(Employees!$A:$Z,MATCH(B8,Employees!$A:$A,0),MATCH("rating",Employees!$1:$1,0)) -> 2 | G8: =INDEX(Employees!$A:$Z,MATCH(B8,Employees!$A:$A,0),MATCH("hire_date",Employees!$1:$1,0)) -> 43775 | H8: =INDEX(Employees!$A:$Z,MATCH(B8,Employees!$A:$A,0),MATCH("last_change_date",Employees!$1:$1,0)) -> 46113 | I8: =INDEX(Employees!$A:$Z,MATCH(B8,Employees!$A:$A,0),MATCH("base_salary",Employees!$1:$1,0)) -> 73284.69 | J8: =INDEX(Employees!$A:$Z,MATCH(B8,Employees!$A:$A,0),MATCH("bonus_pct",Employees!$1:$1,0))/100 -> 0.1199 | K8: =INDEX(Employees!$A:$Z,MATCH(B8,Employees!$A:$A,0),MATCH("fte",Employees!$1:$1,0)) -> 1 | L8: =IF(ISNA(MATCH(C8&"|"&E8,Bands!$F:$F,0)),0,1) -> 1 | M8: =INDEX(Bands!$C:$C,MATCH(C8&"|"&E8,Bands!$F:$F,0)) -> 59800 | N8: =INDEX(Bands!$D:$D,MATCH(C8&"|"&E8,Bands!$F:$F,0)) -> 74800 | O8: =INDEX(Bands!$E:$E,MATCH(C8&"|"&E8,Bands!$F:$F,0)) -> 89700 | P8: =(EffDate-G8)/365.25 -> 7.4004107 | Q8: =I8*(1+J8) -> 82071.524 | R8: =E8^2 -> 100 | S8: =P8^2 -> 54.766078 | T8: =E8*P8 -> 74.004107 | U8: =E8*Q8 -> 820715.24 | V8: =P8*Q8 -> 607362.98 | W8: =ROUND(Q8,2) -> 82071.52 | X8: =COUNTIFS($C:$C,C8,$W:$W,"<"&W8)+COUNTIFS($C:$C,C8,$W:$W,W8,$B:$B,"<"&B8)+1 -> 33 | Y8: =INDEX(Categories!$AH:$AH,MATCH(C8,Categories!$A:$A,0)) -> 71955.394 | Z8: =IF(AND(D8="F",Q8<Y8,INDEX(Categories!$AI:$AI,MATCH(C8,Categories!$A:$A,0))>0),1,0) -> 0 | AA8: =IF(Z8=1,Y8-Q8,0) -> 0 | AB8: =IF(Z8=1,INDEX(Categories!$AI:$AI,MATCH(C8,Categories!$A:$A,0))*AA8/INDEX(Categories!$AJ:$AJ,MATCH(C8,Categories!$A:$A,0)),0) -> 0 | AC8: =AB8/(1+J8) -> 0 | AD8: =I8+AC8 -> 73284.69 | AE8: =IF(AND(AC8>0,AD8>O8),1,0) -> 0 | AF8: =IF(G8>EffDate,-1,DATEDIF(G8,EffDate,"m")) -> 88 | AG8: =IF(H8>EffDate,-1,DATEDIF(H8,EffDate,"m")) -> 12 | AH8: =IF(AND(AF8>=MinMonthsHire,AG8>=MinMonthsChange),1,0) -> 1 | AI8: =AD8/N8 -> 0.97974184 | AJ8: =MATCH(AI8,Inputs!$B$31:$B$34,1) -> 2 | AK8: =INDEX(Inputs!$C$21:$C$25,MATCH(F8,Inputs!$A$21:$A$25,0)) -> 0.95 | AL8: =INDEX(Inputs!$D$21:$D$25,MATCH(F8,Inputs!$A$21:$A$25,0)) -> 0 | AM8: =N8*CompanyTarget*AK8 -> 71060 | AN8: =MAX(0,AM8-AD8) -> 0 | AO8: =IF(AND(ISNUMBER(MaxIncrease),MaxIncrease>0),1,0) -> 1 | AP8: =IF(AO8=1,AD8*MaxIncrease,0) -> 21985.407 | AQ8: =AD8*AL8 -> 0 | AR8: =IF(AK8=0,0,IF(AO8=1,MIN(MAX(AN8,AQ8),AP8),MAX(AN8,AQ8))) -> 0 | AS8: =IF(AD8>=O8,1,0) -> 0 | AT8: =IF(AS8=1,0,AR8) -> 0 | AU8: =MAX(0,O8-AD8) -> 16415.31 | AV8: =IF(ClipAtMax="No",AT8,MIN(AT8,AU8)) -> 0 | AW8: =IF(AH8=1,AV8,0) -> 0 | AX8: =IF(AD8>0,AW8/AD8,0) -> 0 | AY8: =AD8+AW8 -> 73284.69 | AZ8: =IF(AY8<M8,1,0) -> 0 | BA8: =Q8*K8 -> 82071.524 | BB8: =RateBelow*MIN(BA8,Ceiling)+AboveCeilingTier1*MIN(MAX(0,BA8-Ceiling),0.1*Ceiling)+AboveCeilingTier2*MIN(MAX(0,BA8-1.1*Ceiling),0.4*Ceiling)+AboveCeilingTier3*MAX(0,BA8-1.5*Ceiling) -> 19892.447 | BC8: =AD8*(1+J8)*K8 -> 82071.524 | BD8: =RateBelow*MIN(BC8,Ceiling)+AboveCeilingTier1*MIN(MAX(0,BC8-Ceiling),0.1*Ceiling)+AboveCeilingTier2*MIN(MAX(0,BC8-1.1*Ceiling),0.4*Ceiling)+AboveCeilingTier3*MAX(0,BC8-1.5*Ceiling) -> 19892.447 | BE8: =AY8*(1+J8)*K8 -> 82071.524 | BF8: =RateBelow*MIN(BE8,Ceiling)+AboveCeilingTier1*MIN(MAX(0,BE8-Ceiling),0.1*Ceiling)+AboveCeilingTier2*MIN(MAX(0,BE8-1.1*Ceiling),0.4*Ceiling)+AboveCeilingTier3*MAX(0,BE8-1.5*Ceiling) -> 19892.447 | BG8: =AC8*K8 -> 0 | BH8: =AC8*J8*K8 -> 0 | BI8: =BD8-BB8 -> 0 | BJ8: =AW8*K8 -> 0 | BK8: =AW8*J8*K8 -> 0 | BL8: =BF8-BD8 -> 0 | BM8: =IF(AH8=1,AD8*K8,0) -> 73284.69 | BN8: =IF(AH8=1,AD8*PoolPct,0) -> 2931.3876 | BO8: =BN8*K8 -> 2931.3876 | BP8: =BN8*J8*K8 -> 351.47337 | BQ8: =(AD8+BN8)*(1+J8)*K8 -> 85354.385 | BR8: =RateBelow*MIN(BQ8,Ceiling)+AboveCeilingTier1*MIN(MAX(0,BQ8-Ceiling),0.1*Ceiling)+AboveCeilingTier2*MIN(MAX(0,BQ8-1.1*Ceiling),0.4*Ceiling)+AboveCeilingTier3*MAX(0,BQ8-1.5*Ceiling) -> 19926.588 | BS8: =BR8-BD8 -> 34.141754 | BT8: =AD8*(1+J8) -> 82071.524 | BU8: =AY8*(1+J8) -> 82071.524 | BV8: =E8*BU8 -> 820715.24 | BW8: =P8*BU8 -> 607362.98
A9: =ROW()-4 -> 5 | B9: =INDEX(Employees!$A:$A,A9+1) -> E005 | C9: =INDEX(Employees!$A:$Z,MATCH(B9,Employees!$A:$A,0),MATCH("category",Employees!$1:$1,0)) -> Engineering | D9: =INDEX(Employees!$A:$Z,MATCH(B9,Employees!$A:$A,0),MATCH("gender",Employees!$1:$1,0)) -> F | E9: =INDEX(Employees!$A:$Z,MATCH(B9,Employees!$A:$A,0),MATCH("grade",Employees!$1:$1,0)) -> 10 | F9: =INDEX(Employees!$A:$Z,MATCH(B9,Employees!$A:$A,0),MATCH("rating",Employees!$1:$1,0)) -> 4 | G9: =INDEX(Employees!$A:$Z,MATCH(B9,Employees!$A:$A,0),MATCH("hire_date",Employees!$1:$1,0)) -> 44067 | H9: =INDEX(Employees!$A:$Z,MATCH(B9,Employees!$A:$A,0),MATCH("last_change_date",Employees!$1:$1,0)) -> 46113 | I9: =INDEX(Employees!$A:$Z,MATCH(B9,Employees!$A:$A,0),MATCH("base_salary",Employees!$1:$1,0)) -> 69538.46 | J9: =INDEX(Employees!$A:$Z,MATCH(B9,Employees!$A:$A,0),MATCH("bonus_pct",Employees!$1:$1,0))/100 -> 0.0957 | K9: =INDEX(Employees!$A:$Z,MATCH(B9,Employees!$A:$A,0),MATCH("fte",Employees!$1:$1,0)) -> 1 | L9: =IF(ISNA(MATCH(C9&"|"&E9,Bands!$F:$F,0)),0,1) -> 1 | M9: =INDEX(Bands!$C:$C,MATCH(C9&"|"&E9,Bands!$F:$F,0)) -> 59800 | N9: =INDEX(Bands!$D:$D,MATCH(C9&"|"&E9,Bands!$F:$F,0)) -> 74800 | O9: =INDEX(Bands!$E:$E,MATCH(C9&"|"&E9,Bands!$F:$F,0)) -> 89700 | P9: =(EffDate-G9)/365.25 -> 6.6009582 | Q9: =I9*(1+J9) -> 76193.291 | R9: =E9^2 -> 100 | S9: =P9^2 -> 43.57265 | T9: =E9*P9 -> 66.009582 | U9: =E9*Q9 -> 761932.91 | V9: =P9*Q9 -> 502948.73 | W9: =ROUND(Q9,2) -> 76193.29 | X9: =COUNTIFS($C:$C,C9,$W:$W,"<"&W9)+COUNTIFS($C:$C,C9,$W:$W,W9,$B:$B,"<"&B9)+1 -> 26 | Y9: =INDEX(Categories!$AH:$AH,MATCH(C9,Categories!$A:$A,0)) -> 71955.394 | Z9: =IF(AND(D9="F",Q9<Y9,INDEX(Categories!$AI:$AI,MATCH(C9,Categories!$A:$A,0))>0),1,0) -> 0 | AA9: =IF(Z9=1,Y9-Q9,0) -> 0 | AB9: =IF(Z9=1,INDEX(Categories!$AI:$AI,MATCH(C9,Categories!$A:$A,0))*AA9/INDEX(Categories!$AJ:$AJ,MATCH(C9,Categories!$A:$A,0)),0) -> 0 | AC9: =AB9/(1+J9) -> 0 | AD9: =I9+AC9 -> 69538.46 | AE9: =IF(AND(AC9>0,AD9>O9),1,0) -> 0 | AF9: =IF(G9>EffDate,-1,DATEDIF(G9,EffDate,"m")) -> 79 | AG9: =IF(H9>EffDate,-1,DATEDIF(H9,EffDate,"m")) -> 12 | AH9: =IF(AND(AF9>=MinMonthsHire,AG9>=MinMonthsChange),1,0) -> 1 | AI9: =AD9/N9 -> 0.92965856 | AJ9: =MATCH(AI9,Inputs!$B$31:$B$34,1) -> 2 | AK9: =INDEX(Inputs!$C$21:$C$25,MATCH(F9,Inputs!$A$21:$A$25,0)) -> 1.05 | AL9: =INDEX(Inputs!$D$21:$D$25,MATCH(F9,Inputs!$A$21:$A$25,0)) -> 0.01 | AM9: =N9*CompanyTarget*AK9 -> 78540 | AN9: =MAX(0,AM9-AD9) -> 9001.54 | AO9: =IF(AND(ISNUMBER(MaxIncrease),MaxIncrease>0),1,0) -> 1 | AP9: =IF(AO9=1,AD9*MaxIncrease,0) -> 20861.538 | AQ9: =AD9*AL9 -> 695.3846 | AR9: =IF(AK9=0,0,IF(AO9=1,MIN(MAX(AN9,AQ9),AP9),MAX(AN9,AQ9))) -> 9001.54 | AS9: =IF(AD9>=O9,1,0) -> 0 | AT9: =IF(AS9=1,0,AR9) -> 9001.54 | AU9: =MAX(0,O9-AD9) -> 20161.54 | AV9: =IF(ClipAtMax="No",AT9,MIN(AT9,AU9)) -> 9001.54 | AW9: =IF(AH9=1,AV9,0) -> 9001.54 | AX9: =IF(AD9>0,AW9/AD9,0) -> 0.12944693 | AY9: =AD9+AW9 -> 78540 | AZ9: =IF(AY9<M9,1,0) -> 0 | BA9: =Q9*K9 -> 76193.291 | BB9: =RateBelow*MIN(BA9,Ceiling)+AboveCeilingTier1*MIN(MAX(0,BA9-Ceiling),0.1*Ceiling)+AboveCeilingTier2*MIN(MAX(0,BA9-1.1*Ceiling),0.4*Ceiling)+AboveCeilingTier3*MAX(0,BA9-1.5*Ceiling) -> 19831.313 | BC9: =AD9*(1+J9)*K9 -> 76193.291 | BD9: =RateBelow*MIN(BC9,Ceiling)+AboveCeilingTier1*MIN(MAX(0,BC9-Ceiling),0.1*Ceiling)+AboveCeilingTier2*MIN(MAX(0,BC9-1.1*Ceiling),0.4*Ceiling)+AboveCeilingTier3*MAX(0,BC9-1.5*Ceiling) -> 19831.313 | BE9: =AY9*(1+J9)*K9 -> 86056.278 | BF9: =RateBelow*MIN(BE9,Ceiling)+AboveCeilingTier1*MIN(MAX(0,BE9-Ceiling),0.1*Ceiling)+AboveCeilingTier2*MIN(MAX(0,BE9-1.1*Ceiling),0.4*Ceiling)+AboveCeilingTier3*MAX(0,BE9-1.5*Ceiling) -> 19933.888 | BG9: =AC9*K9 -> 0 | BH9: =AC9*J9*K9 -> 0 | BI9: =BD9-BB9 -> 0 | BJ9: =AW9*K9 -> 9001.54 | BK9: =AW9*J9*K9 -> 861.44738 | BL9: =BF9-BD9 -> 102.57507 | BM9: =IF(AH9=1,AD9*K9,0) -> 69538.46 | BN9: =IF(AH9=1,AD9*PoolPct,0) -> 2781.5384 | BO9: =BN9*K9 -> 2781.5384 | BP9: =BN9*J9*K9 -> 266.19322 | BQ9: =(AD9+BN9)*(1+J9)*K9 -> 79241.022 | BR9: =RateBelow*MIN(BQ9,Ceiling)+AboveCeilingTier1*MIN(MAX(0,BQ9-Ceiling),0.1*Ceiling)+AboveCeilingTier2*MIN(MAX(0,BQ9-1.1*Ceiling),0.4*Ceiling)+AboveCeilingTier3*MAX(0,BQ9-1.5*Ceiling) -> 19863.009 | BS9: =BR9-BD9 -> 31.696409 | BT9: =AD9*(1+J9) -> 76193.291 | BU9: =AY9*(1+J9) -> 86056.278 | BV9: =E9*BU9 -> 860562.78 | BW9: =P9*BU9 -> 568053.9
A10: =ROW()-4 -> 6 | B10: =INDEX(Employees!$A:$A,A10+1) -> E006 | C10: =INDEX(Employees!$A:$Z,MATCH(B10,Employees!$A:$A,0),MATCH("category",Employees!$1:$1,0)) -> Engineering | D10: =INDEX(Employees!$A:$Z,MATCH(B10,Employees!$A:$A,0),MATCH("gender",Employees!$1:$1,0)) -> M | E10: =INDEX(Employees!$A:$Z,MATCH(B10,Employees!$A:$A,0),MATCH("grade",Employees!$1:$1,0)) -> 9 | F10: =INDEX(Employees!$A:$Z,MATCH(B10,Employees!$A:$A,0),MATCH("rating",Employees!$1:$1,0)) -> 5 | G10: =INDEX(Employees!$A:$Z,MATCH(B10,Employees!$A:$A,0),MATCH("hire_date",Employees!$1:$1,0)) -> 44469 | H10: =INDEX(Employees!$A:$Z,MATCH(B10,Employees!$A:$A,0),MATCH("last_change_date",Employees!$1:$1,0)) -> 46113 | I10: =INDEX(Employees!$A:$Z,MATCH(B10,Employees!$A:$A,0),MATCH("base_salary",Employees!$1:$1,0)) -> 60248.19 | J10: =INDEX(Employees!$A:$Z,MATCH(B10,Employees!$A:$A,0),MATCH("bonus_pct",Employees!$1:$1,0))/100 -> 0.104 | K10: =INDEX(Employees!$A:$Z,MATCH(B10,Employees!$A:$A,0),MATCH("fte",Employees!$1:$1,0)) -> 1 | L10: =IF(ISNA(MATCH(C10&"|"&E10,Bands!$F:$F,0)),0,1) -> 1 | M10: =INDEX(Bands!$C:$C,MATCH(C10&"|"&E10,Bands!$F:$F,0)) -> 54500 | N10: =INDEX(Bands!$D:$D,MATCH(C10&"|"&E10,Bands!$F:$F,0)) -> 65400 | O10: =INDEX(Bands!$E:$E,MATCH(C10&"|"&E10,Bands!$F:$F,0)) -> 76300 | P10: =(EffDate-G10)/365.25 -> 5.5003422 | Q10: =I10*(1+J10) -> 66514.002 | R10: =E10^2 -> 81 | S10: =P10^2 -> 30.253765 | T10: =E10*P10 -> 49.50308 | U10: =E10*Q10 -> 598626.02 | V10: =P10*Q10 -> 365849.77 | W10: =ROUND(Q10,2) -> 66514 | X10: =COUNTIFS($C:$C,C10,$W:$W,"<"&W10)+COUNTIFS($C:$C,C10,$W:$W,W10,$B:$B,"<"&B10)+1 -> 18 | Y10: =INDEX(Categories!$AH:$AH,MATCH(C10,Categories!$A:$A,0)) -> 71955.394 | Z10: =IF(AND(D10="F",Q10<Y10,INDEX(Categories!$AI:$AI,MATCH(C10,Categories!$A:$A,0))>0),1,0) -> 0 | AA10: =IF(Z10=1,Y10-Q10,0) -> 0 | AB10: =IF(Z10=1,INDEX(Categories!$AI:$AI,MATCH(C10,Categories!$A:$A,0))*AA10/INDEX(Categories!$AJ:$AJ,MATCH(C10,Categories!$A:$A,0)),0) -> 0 | AC10: =AB10/(1+J10) -> 0 | AD10: =I10+AC10 -> 60248.19 | AE10: =IF(AND(AC10>0,AD10>O10),1,0) -> 0 | AF10: =IF(G10>EffDate,-1,DATEDIF(G10,EffDate,"m")) -> 66 | AG10: =IF(H10>EffDate,-1,DATEDIF(H10,EffDate,"m")) -> 12 | AH10: =IF(AND(AF10>=MinMonthsHire,AG10>=MinMonthsChange),1,0) -> 1 | AI10: =AD10/N10 -> 0.92122615 | AJ10: =MATCH(AI10,Inputs!$B$31:$B$34,1) -> 2 | AK10: =INDEX(Inputs!$C$21:$C$25,MATCH(F10,Inputs!$A$21:$A$25,0)) -> 1.1 | AL10: =INDEX(Inputs!$D$21:$D$25,MATCH(F10,Inputs!$A$21:$A$25,0)) -> 0.02 | AM10: =N10*CompanyTarget*AK10 -> 71940 | AN10: =MAX(0,AM10-AD10) -> 11691.81 | AO10: =IF(AND(ISNUMBER(MaxIncrease),MaxIncrease>0),1,0) -> 1 | AP10: =IF(AO10=1,AD10*MaxIncrease,0) -> 18074.457 | AQ10: =AD10*AL10 -> 1204.9638 | AR10: =IF(AK10=0,0,IF(AO10=1,MIN(MAX(AN10,AQ10),AP10),MAX(AN10,AQ10))) -> 11691.81 | AS10: =IF(AD10>=O10,1,0) -> 0 | AT10: =IF(AS10=1,0,AR10) -> 11691.81 | AU10: =MAX(0,O10-AD10) -> 16051.81 | AV10: =IF(ClipAtMax="No",AT10,MIN(AT10,AU10)) -> 11691.81 | AW10: =IF(AH10=1,AV10,0) -> 11691.81 | AX10: =IF(AD10>0,AW10/AD10,0) -> 0.19406077 | AY10: =AD10+AW10 -> 71940 | AZ10: =IF(AY10<M10,1,0) -> 0 | BA10: =Q10*K10 -> 66514.002 | BB10: =RateBelow*MIN(BA10,Ceiling)+AboveCeilingTier1*MIN(MAX(0,BA10-Ceiling),0.1*Ceiling)+AboveCeilingTier2*MIN(MAX(0,BA10-1.1*Ceiling),0.4*Ceiling)+AboveCeilingTier3*MAX(0,BA10-1.5*Ceiling) -> 19731.306 | BC10: =AD10*(1+J10)*K10 -> 66514.002 | BD10: =RateBelow*MIN(BC10,Ceiling)+AboveCeilingTier1*MIN(MAX(0,BC10-Ceiling),0.1*Ceiling)+AboveCeilingTier2*MIN(MAX(0,BC10-1.1*Ceiling),0.4*Ceiling)+AboveCeilingTier3*MAX(0,BC10-1.5*Ceiling) -> 19731.306 | BE10: =AY10*(1+J10)*K10 -> 79421.76 | BF10: =RateBelow*MIN(BE10,Ceiling)+AboveCeilingTier1*MIN(MAX(0,BE10-Ceiling),0.1*Ceiling)+AboveCeilingTier2*MIN(MAX(0,BE10-1.1*Ceiling),0.4*Ceiling)+AboveCeilingTier3*MAX(0,BE10-1.5*Ceiling) -> 19864.889 | BG10: =AC10*K10 -> 0 | BH10: =AC10*J10*K10 -> 0 | BI10: =BD10-BB10 -> 0 | BJ10: =AW10*K10 -> 11691.81 | BK10: =AW10*J10*K10 -> 1215.9482 | BL10: =BF10-BD10 -> 133.58322 | BM10: =IF(AH10=1,AD10*K10,0) -> 60248.19 | BN10: =IF(AH10=1,AD10*PoolPct,0) -> 2409.9276 | BO10: =BN10*K10 -> 2409.9276 | BP10: =BN10*J10*K10 -> 250.63247 | BQ10: =(AD10+BN10)*(1+J10)*K10 -> 69174.562 | BR10: =RateBelow*MIN(BQ10,Ceiling)+AboveCeilingTier1*MIN(MAX(0,BQ10-Ceiling),0.1*Ceiling)+AboveCeilingTier2*MIN(MAX(0,BQ10-1.1*Ceiling),0.4*Ceiling)+AboveCeilingTier3*MAX(0,BQ10-1.5*Ceiling) -> 19758.318 | BS10: =BR10-BD10 -> 27.012354 | BT10: =AD10*(1+J10) -> 66514.002 | BU10: =AY10*(1+J10) -> 79421.76 | BV10: =E10*BU10 -> 714795.84 | BW10: =P10*BU10 -> 436846.86
A11: =ROW()-4 -> 7 | B11: =INDEX(Employees!$A:$A,A11+1) -> E007 | C11: =INDEX(Employees!$A:$Z,MATCH(B11,Employees!$A:$A,0),MATCH("category",Employees!$1:$1,0)) -> Engineering | D11: =INDEX(Employees!$A:$Z,MATCH(B11,Employees!$A:$A,0),MATCH("gender",Employees!$1:$1,0)) -> M | E11: =INDEX(Employees!$A:$Z,MATCH(B11,Employees!$A:$A,0),MATCH("grade",Employees!$1:$1,0)) -> 7 | F11: =INDEX(Employees!$A:$Z,MATCH(B11,Employees!$A:$A,0),MATCH("rating",Employees!$1:$1,0)) -> 5 | G11: =INDEX(Employees!$A:$Z,MATCH(B11,Employees!$A:$A,0),MATCH("hire_date",Employees!$1:$1,0)) -> 44725 | H11: =INDEX(Employees!$A:$Z,MATCH(B11,Employees!$A:$A,0),MATCH("last_change_date",Employees!$1:$1,0)) -> 46113 | I11: =INDEX(Employees!$A:$Z,MATCH(B11,Employees!$A:$A,0),MATCH("base_salary",Employees!$1:$1,0)) -> 47983.14 | J11: =INDEX(Employees!$A:$Z,MATCH(B11,Employees!$A:$A,0),MATCH("bonus_pct",Employees!$1:$1,0))/100 -> 0.1181 | K11: =INDEX(Employees!$A:$Z,MATCH(B11,Employees!$A:$A,0),MATCH("fte",Employees!$1:$1,0)) -> 1 | L11: =IF(ISNA(MATCH(C11&"|"&E11,Bands!$F:$F,0)),0,1) -> 1 | M11: =INDEX(Bands!$C:$C,MATCH(C11&"|"&E11,Bands!$F:$F,0)) -> 41600 | N11: =INDEX(Bands!$D:$D,MATCH(C11&"|"&E11,Bands!$F:$F,0)) -> 49900 | O11: =INDEX(Bands!$E:$E,MATCH(C11&"|"&E11,Bands!$F:$F,0)) -> 58200 | P11: =(EffDate-G11)/365.25 -> 4.7994524 | Q11: =I11*(1+J11) -> 53649.949 | R11: =E11^2 -> 49 | S11: =P11^2 -> 23.034744 | T11: =E11*P11 -> 33.596167 | U11: =E11*Q11 -> 375549.64 | V11: =P11*Q11 -> 257490.38 | W11: =ROUND(Q11,2) -> 53649.95 | X11: =COUNTIFS($C:$C,C11,$W:$W,"<"&W11)+COUNTIFS($C:$C,C11,$W:$W,W11,$B:$B,"<"&B11)+1 -> 7 | Y11: =INDEX(Categories!$AH:$AH,MATCH(C11,Categories!$A:$A,0)) -> 71955.394 | Z11: =IF(AND(D11="F",Q11<Y11,INDEX(Categories!$AI:$AI,MATCH(C11,Categories!$A:$A,0))>0),1,0) -> 0 | AA11: =IF(Z11=1,Y11-Q11,0) -> 0 | AB11: =IF(Z11=1,INDEX(Categories!$AI:$AI,MATCH(C11,Categories!$A:$A,0))*AA11/INDEX(Categories!$AJ:$AJ,MATCH(C11,Categories!$A:$A,0)),0) -> 0 | AC11: =AB11/(1+J11) -> 0 | AD11: =I11+AC11 -> 47983.14 | AE11: =IF(AND(AC11>0,AD11>O11),1,0) -> 0 | AF11: =IF(G11>EffDate,-1,DATEDIF(G11,EffDate,"m")) -> 57 | AG11: =IF(H11>EffDate,-1,DATEDIF(H11,EffDate,"m")) -> 12 | AH11: =IF(AND(AF11>=MinMonthsHire,AG11>=MinMonthsChange),1,0) -> 1 | AI11: =AD11/N11 -> 0.96158597 | AJ11: =MATCH(AI11,Inputs!$B$31:$B$34,1) -> 2 | AK11: =INDEX(Inputs!$C$21:$C$25,MATCH(F11,Inputs!$A$21:$A$25,0)) -> 1.1 | AL11: =INDEX(Inputs!$D$21:$D$25,MATCH(F11,Inputs!$A$21:$A$25,0)) -> 0.02 | AM11: =N11*CompanyTarget*AK11 -> 54890 | AN11: =MAX(0,AM11-AD11) -> 6906.86 | AO11: =IF(AND(ISNUMBER(MaxIncrease),MaxIncrease>0),1,0) -> 1 | AP11: =IF(AO11=1,AD11*MaxIncrease,0) -> 14394.942 | AQ11: =AD11*AL11 -> 959.6628 | AR11: =IF(AK11=0,0,IF(AO11=1,MIN(MAX(AN11,AQ11),AP11),MAX(AN11,AQ11))) -> 6906.86 | AS11: =IF(AD11>=O11,1,0) -> 0 | AT11: =IF(AS11=1,0,AR11) -> 6906.86 | AU11: =MAX(0,O11-AD11) -> 10216.86 | AV11: =IF(ClipAtMax="No",AT11,MIN(AT11,AU11)) -> 6906.86 | AW11: =IF(AH11=1,AV11,0) -> 6906.86 | AX11: =IF(AD11>0,AW11/AD11,0) -> 0.14394348 | AY11: =AD11+AW11 -> 54890 | AZ11: =IF(AY11<M11,1,0) -> 0 | BA11: =Q11*K11 -> 53649.949 | BB11: =RateBelow*MIN(BA11,Ceiling)+AboveCeilingTier1*MIN(MAX(0,BA11-Ceiling),0.1*Ceiling)+AboveCeilingTier2*MIN(MAX(0,BA11-1.1*Ceiling),0.4*Ceiling)+AboveCeilingTier3*MAX(0,BA11-1.5*Ceiling) -> 17248.459 | BC11: =AD11*(1+J11)*K11 -> 53649.949 | BD11: =RateBelow*MIN(BC11,Ceiling)+AboveCeilingTier1*MIN(MAX(0,BC11-Ceiling),0.1*Ceiling)+AboveCeilingTier2*MIN(MAX(0,BC11-1.1*Ceiling),0.4*Ceiling)+AboveCeilingTier3*MAX(0,BC11-1.5*Ceiling) -> 17248.459 | BE11: =AY11*(1+J11)*K11 -> 61372.509 | BF11: =RateBelow*MIN(BE11,Ceiling)+AboveCeilingTier1*MIN(MAX(0,BE11-Ceiling),0.1*Ceiling)+AboveCeilingTier2*MIN(MAX(0,BE11-1.1*Ceiling),0.4*Ceiling)+AboveCeilingTier3*MAX(0,BE11-1.5*Ceiling) -> 19681.947 | BG11: =AC11*K11 -> 0 | BH11: =AC11*J11*K11 -> 0 | BI11: =BD11-BB11 -> 0 | BJ11: =AW11*K11 -> 6906.86 | BK11: =AW11*J11*K11 -> 815.70017 | BL11: =BF11-BD11 -> 2433.4889 | BM11: =IF(AH11=1,AD11*K11,0) -> 47983.14 | BN11: =IF(AH11=1,AD11*PoolPct,0) -> 1919.3256 | BO11: =BN11*K11 -> 1919.3256 | BP11: =BN11*J11*K11 -> 226.67235 | BQ11: =(AD11+BN11)*(1+J11)*K11 -> 55795.947 | BR11: =RateBelow*MIN(BQ11,Ceiling)+AboveCeilingTier1*MIN(MAX(0,BQ11-Ceiling),0.1*Ceiling)+AboveCeilingTier2*MIN(MAX(0,BQ11-1.1*Ceiling),0.4*Ceiling)+AboveCeilingTier3*MAX(0,BQ11-1.5*Ceiling) -> 17938.397 | BS11: =BR11-BD11 -> 689.93834 | BT11: =AD11*(1+J11) -> 53649.949 | BU11: =AY11*(1+J11) -> 61372.509 | BV11: =E11*BU11 -> 429607.56 | BW11: =P11*BU11 -> 294554.44
A12: =ROW()-4 -> 8 | B12: =INDEX(Employees!$A:$A,A12+1) -> E008 | C12: =INDEX(Employees!$A:$Z,MATCH(B12,Employees!$A:$A,0),MATCH("category",Employees!$1:$1,0)) -> Engineering | D12: =INDEX(Employees!$A:$Z,MATCH(B12,Employees!$A:$A,0),MATCH("gender",Employees!$1:$1,0)) -> M | E12: =INDEX(Employees!$A:$Z,MATCH(B12,Employees!$A:$A,0),MATCH("grade",Employees!$1:$1,0)) -> 11 | F12: =INDEX(Employees!$A:$Z,MATCH(B12,Employees!$A:$A,0),MATCH("rating",Employees!$1:$1,0)) -> 2 | G12: =INDEX(Employees!$A:$Z,MATCH(B12,Employees!$A:$A,0),MATCH("hire_date",Employees!$1:$1,0)) -> 44067 | H12: =INDEX(Employees!$A:$Z,MATCH(B12,Employees!$A:$A,0),MATCH("last_change_date",Employees!$1:$1,0)) -> 46113 | I12: =INDEX(Employees!$A:$Z,MATCH(B12,Employees!$A:$A,0),MATCH("base_salary",Employees!$1:$1,0)) -> 79273.59 | J12: =INDEX(Employees!$A:$Z,MATCH(B12,Employees!$A:$A,0),MATCH("bonus_pct",Employees!$1:$1,0))/100 -> 0.0924 | K12: =INDEX(Employees!$A:$Z,MATCH(B12,Employees!$A:$A,0),MATCH("fte",Employees!$1:$1,0)) -> 1 | L12: =IF(ISNA(MATCH(C12&"|"&E12,Bands!$F:$F,0)),0,1) -> 1 | M12: =INDEX(Bands!$C:$C,MATCH(C12&"|"&E12,Bands!$F:$F,0)) -> 68400 | N12: =INDEX(Bands!$D:$D,MATCH(C12&"|"&E12,Bands!$F:$F,0)) -> 85500 | O12: =INDEX(Bands!$E:$E,MATCH(C12&"|"&E12,Bands!$F:$F,0)) -> 102600 | P12: =(EffDate-G12)/365.25 -> 6.6009582 | Q12: =I12*(1+J12) -> 86598.47 | R12: =E12^2 -> 121 | S12: =P12^2 -> 43.57265 | T12: =E12*P12 -> 72.610541 | U12: =E12*Q12 -> 952583.17 | V12: =P12*Q12 -> 571632.88 | W12: =ROUND(Q12,2) -> 86598.47 | X12: =COUNTIFS($C:$C,C12,$W:$W,"<"&W12)+COUNTIFS($C:$C,C12,$W:$W,W12,$B:$B,"<"&B12)+1 -> 37 | Y12: =INDEX(Categories!$AH:$AH,MATCH(C12,Categories!$A:$A,0)) -> 71955.394 | Z12: =IF(AND(D12="F",Q12<Y12,INDEX(Categories!$AI:$AI,MATCH(C12,Categories!$A:$A,0))>0),1,0) -> 0 | AA12: =IF(Z12=1,Y12-Q12,0) -> 0 | AB12: =IF(Z12=1,INDEX(Categories!$AI:$AI,MATCH(C12,Categories!$A:$A,0))*AA12/INDEX(Categories!$AJ:$AJ,MATCH(C12,Categories!$A:$A,0)),0) -> 0 | AC12: =AB12/(1+J12) -> 0 | AD12: =I12+AC12 -> 79273.59 | AE12: =IF(AND(AC12>0,AD12>O12),1,0) -> 0 | AF12: =IF(G12>EffDate,-1,DATEDIF(G12,EffDate,"m")) -> 79 | AG12: =IF(H12>EffDate,-1,DATEDIF(H12,EffDate,"m")) -> 12 | AH12: =IF(AND(AF12>=MinMonthsHire,AG12>=MinMonthsChange),1,0) -> 1 | AI12: =AD12/N12 -> 0.92717649 | AJ12: =MATCH(AI12,Inputs!$B$31:$B$34,1) -> 2 | AK12: =INDEX(Inputs!$C$21:$C$25,MATCH(F12,Inputs!$A$21:$A$25,0)) -> 0.95 | AL12: =INDEX(Inputs!$D$21:$D$25,MATCH(F12,Inputs!$A$21:$A$25,0)) -> 0 | AM12: =N12*CompanyTarget*AK12 -> 81225 | AN12: =MAX(0,AM12-AD12) -> 1951.41 | AO12: =IF(AND(ISNUMBER(MaxIncrease),MaxIncrease>0),1,0) -> 1 | AP12: =IF(AO12=1,AD12*MaxIncrease,0) -> 23782.077 | AQ12: =AD12*AL12 -> 0 | AR12: =IF(AK12=0,0,IF(AO12=1,MIN(MAX(AN12,AQ12),AP12),MAX(AN12,AQ12))) -> 1951.41 | AS12: =IF(AD12>=O12,1,0) -> 0 | AT12: =IF(AS12=1,0,AR12) -> 1951.41 | AU12: =MAX(0,O12-AD12) -> 23326.41 | AV12: =IF(ClipAtMax="No",AT12,MIN(AT12,AU12)) -> 1951.41 | AW12: =IF(AH12=1,AV12,0) -> 1951.41 | AX12: =IF(AD12>0,AW12/AD12,0) -> 0.024616143 | AY12: =AD12+AW12 -> 81225 | AZ12: =IF(AY12<M12,1,0) -> 0 | BA12: =Q12*K12 -> 86598.47 | BB12: =RateBelow*MIN(BA12,Ceiling)+AboveCeilingTier1*MIN(MAX(0,BA12-Ceiling),0.1*Ceiling)+AboveCeilingTier2*MIN(MAX(0,BA12-1.1*Ceiling),0.4*Ceiling)+AboveCeilingTier3*MAX(0,BA12-1.5*Ceiling) -> 19939.527 | BC12: =AD12*(1+J12)*K12 -> 86598.47 | BD12: =RateBelow*MIN(BC12,Ceiling)+AboveCeilingTier1*MIN(MAX(0,BC12-Ceiling),0.1*Ceiling)+AboveCeilingTier2*MIN(MAX(0,BC12-1.1*Ceiling),0.4*Ceiling)+AboveCeilingTier3*MAX(0,BC12-1.5*Ceiling) -> 19939.527 | BE12: =AY12*(1+J12)*K12 -> 88730.19 | BF12: =RateBelow*MIN(BE12,Ceiling)+AboveCeilingTier1*MIN(MAX(0,BE12-Ceiling),0.1*Ceiling)+AboveCeilingTier2*MIN(MAX(0,BE12-1.1*Ceiling),0.4*Ceiling)+AboveCeilingTier3*MAX(0,BE12-1.5*Ceiling) -> 19961.697 | BG12: =AC12*K12 -> 0 | BH12: =AC12*J12*K12 -> 0 | BI12: =BD12-BB12 -> 0 | BJ12: =AW12*K12 -> 1951.41 | BK12: =AW12*J12*K12 -> 180.31028 | BL12: =BF12-BD12 -> 22.169891 | BM12: =IF(AH12=1,AD12*K12,0) -> 79273.59 | BN12: =IF(AH12=1,AD12*PoolPct,0) -> 3170.9436 | BO12: =BN12*K12 -> 3170.9436 | BP12: =BN12*J12*K12 -> 292.99519 | BQ12: =(AD12+BN12)*(1+J12)*K12 -> 90062.409 | BR12: =RateBelow*MIN(BQ12,Ceiling)+AboveCeilingTier1*MIN(MAX(0,BQ12-Ceiling),0.1*Ceiling)+AboveCeilingTier2*MIN(MAX(0,BQ12-1.1*Ceiling),0.4*Ceiling)+AboveCeilingTier3*MAX(0,BQ12-1.5*Ceiling) -> 19975.552 | BS12: =BR12-BD12 -> 36.024963 | BT12: =AD12*(1+J12) -> 86598.47 | BU12: =AY12*(1+J12) -> 88730.19 | BV12: =E12*BU12 -> 976032.09 | BW12: =P12*BU12 -> 585704.28
A13: =ROW()-4 -> 9 | B13: =INDEX(Employees!$A:$A,A13+1) -> E009 | C13: =INDEX(Employees!$A:$Z,MATCH(B13,Employees!$A:$A,0),MATCH("category",Employees!$1:$1,0)) -> Engineering | D13: =INDEX(Employees!$A:$Z,MATCH(B13,Employees!$A:$A,0),MATCH("gender",Employees!$1:$1,0)) -> M | E13: =INDEX(Employees!$A:$Z,MATCH(B13,Employees!$A:$A,0),MATCH("grade",Employees!$1:$1,0)) -> 8 | F13: =INDEX(Employees!$A:$Z,MATCH(B13,Employees!$A:$A,0),MATCH("rating",Employees!$1:$1,0)) -> 3 | G13: =INDEX(Employees!$A:$Z,MATCH(B13,Employees!$A:$A,0),MATCH("hire_date",Employees!$1:$1,0)) -> 44323 | H13: =INDEX(Employees!$A:$Z,MATCH(B13,Employees!$A:$A,0),MATCH("last_change_date",Employees!$1:$1,0)) -> 46113 | I13: =INDEX(Employees!$A:$Z,MATCH(B13,Employees!$A:$A,0),MATCH("base_salary",Employees!$1:$1,0)) -> 56597.91 | J13: =INDEX(Employees!$A:$Z,MATCH(B13,Employees!$A:$A,0),MATCH("bonus_pct",Employees!$1:$1,0))/100 -> 0.1073 | K13: =INDEX(Employees!$A:$Z,MATCH(B13,Employees!$A:$A,0),MATCH("fte",Employees!$1:$1,0)) -> 1 | L13: =IF(ISNA(MATCH(C13&"|"&E13,Bands!$F:$F,0)),0,1) -> 1 | M13: =INDEX(Bands!$C:$C,MATCH(C13&"|"&E13,Bands!$F:$F,0)) -> 47700 | N13: =INDEX(Bands!$D:$D,MATCH(C13&"|"&E13,Bands!$F:$F,0)) -> 57200 | O13: =INDEX(Bands!$E:$E,MATCH(C13&"|"&E13,Bands!$F:$F,0)) -> 66800 | P13: =(EffDate-G13)/365.25 -> 5.9000684 | Q13: =I13*(1+J13) -> 62670.866 | R13: =E13^2 -> 64 | S13: =P13^2 -> 34.810808 | T13: =E13*P13 -> 47.200548 | U13: =E13*Q13 -> 501366.93 | V13: =P13*Q13 -> 369762.4 | W13: =ROUND(Q13,2) -> 62670.87 | X13: =COUNTIFS($C:$C,C13,$W:$W,"<"&W13)+COUNTIFS($C:$C,C13,$W:$W,W13,$B:$B,"<"&B13)+1 -> 15 | Y13: =INDEX(Categories!$AH:$AH,MATCH(C13,Categories!$A:$A,0)) -> 71955.394 | Z13: =IF(AND(D13="F",Q13<Y13,INDEX(Categories!$AI:$AI,MATCH(C13,Categories!$A:$A,0))>0),1,0) -> 0 | AA13: =IF(Z13=1,Y13-Q13,0) -> 0 | AB13: =IF(Z13=1,INDEX(Categories!$AI:$AI,MATCH(C13,Categories!$A:$A,0))*AA13/INDEX(Categories!$AJ:$AJ,MATCH(C13,Categories!$A:$A,0)),0) -> 0 | AC13: =AB13/(1+J13) -> 0 | AD13: =I13+AC13 -> 56597.91 | AE13: =IF(AND(AC13>0,AD13>O13),1,0) -> 0 | AF13: =IF(G13>EffDate,-1,DATEDIF(G13,EffDate,"m")) -> 70 | AG13: =IF(H13>EffDate,-1,DATEDIF(H13,EffDate,"m")) -> 12 | AH13: =IF(AND(AF13>=MinMonthsHire,AG13>=MinMonthsChange),1,0) -> 1 | AI13: =AD13/N13 -> 0.98947395 | AJ13: =MATCH(AI13,Inputs!$B$31:$B$34,1) -> 2 | AK13: =INDEX(Inputs!$C$21:$C$25,MATCH(F13,Inputs!$A$21:$A$25,0)) -> 1 | AL13: =INDEX(Inputs!$D$21:$D$25,MATCH(F13,Inputs!$A$21:$A$25,0)) -> 0 | AM13: =N13*CompanyTarget*AK13 -> 57200 | AN13: =MAX(0,AM13-AD13) -> 602.09 | AO13: =IF(AND(ISNUMBER(MaxIncrease),MaxIncrease>0),1,0) -> 1 | AP13: =IF(AO13=1,AD13*MaxIncrease,0) -> 16979.373 | AQ13: =AD13*AL13 -> 0 | AR13: =IF(AK13=0,0,IF(AO13=1,MIN(MAX(AN13,AQ13),AP13),MAX(AN13,AQ13))) -> 602.09 | AS13: =IF(AD13>=O13,1,0) -> 0 | AT13: =IF(AS13=1,0,AR13) -> 602.09 | AU13: =MAX(0,O13-AD13) -> 10202.09 | AV13: =IF(ClipAtMax="No",AT13,MIN(AT13,AU13)) -> 602.09 | AW13: =IF(AH13=1,AV13,0) -> 602.09 | AX13: =IF(AD13>0,AW13/AD13,0) -> 0.010638025 | AY13: =AD13+AW13 -> 57200 | AZ13: =IF(AY13<M13,1,0) -> 0 | BA13: =Q13*K13 -> 62670.866 | BB13: =RateBelow*MIN(BA13,Ceiling)+AboveCeilingTier1*MIN(MAX(0,BA13-Ceiling),0.1*Ceiling)+AboveCeilingTier2*MIN(MAX(0,BA13-1.1*Ceiling),0.4*Ceiling)+AboveCeilingTier3*MAX(0,BA13-1.5*Ceiling) -> 19694.412 | BC13: =AD13*(1+J13)*K13 -> 62670.866 | BD13: =RateBelow*MIN(BC13,Ceiling)+AboveCeilingTier1*MIN(MAX(0,BC13-Ceiling),0.1*Ceiling)+AboveCeilingTier2*MIN(MAX(0,BC13-1.1*Ceiling),0.4*Ceiling)+AboveCeilingTier3*MAX(0,BC13-1.5*Ceiling) -> 19694.412 | BE13: =AY13*(1+J13)*K13 -> 63337.56 | BF13: =RateBelow*MIN(BE13,Ceiling)+AboveCeilingTier1*MIN(MAX(0,BE13-Ceiling),0.1*Ceiling)+AboveCeilingTier2*MIN(MAX(0,BE13-1.1*Ceiling),0.4*Ceiling)+AboveCeilingTier3*MAX(0,BE13-1.5*Ceiling) -> 19700.812 | BG13: =AC13*K13 -> 0 | BH13: =AC13*J13*K13 -> 0 | BI13: =BD13-BB13 -> 0 | BJ13: =AW13*K13 -> 602.09 | BK13: =AW13*J13*K13 -> 64.604257 | BL13: =BF13-BD13 -> 6.4002649 | BM13: =IF(AH13=1,AD13*K13,0) -> 56597.91 | BN13: =IF(AH13=1,AD13*PoolPct,0) -> 2263.9164 | BO13: =BN13*K13 -> 2263.9164 | BP13: =BN13*J13*K13 -> 242.91823 | BQ13: =(AD13+BN13)*(1+J13)*K13 -> 65177.7 | BR13: =RateBelow*MIN(BQ13,Ceiling)+AboveCeilingTier1*MIN(MAX(0,BQ13-Ceiling),0.1*Ceiling)+AboveCeilingTier2*MIN(MAX(0,BQ13-1.1*Ceiling),0.4*Ceiling)+AboveCeilingTier3*MAX(0,BQ13-1.5*Ceiling) -> 19718.477 | BS13: =BR13-BD13 -> 24.065612 | BT13: =AD13*(1+J13) -> 62670.866 | BU13: =AY13*(1+J13) -> 63337.56 | BV13: =E13*BU13 -> 506700.48 | BW13: =P13*BU13 -> 373695.94
A14: =ROW()-4 -> 10 | B14: =INDEX(Employees!$A:$A,A14+1) -> E010 | C14: =INDEX(Employees!$A:$Z,MATCH(B14,Employees!$A:$A,0),MATCH("category",Employees!$1:$1,0)) -> Engineering | D14: =INDEX(Employees!$A:$Z,MATCH(B14,Employees!$A:$A,0),MATCH("gender",Employees!$1:$1,0)) -> M | E14: =INDEX(Employees!$A:$Z,MATCH(B14,Employees!$A:$A,0),MATCH("grade",Employees!$1:$1,0)) -> 10 | F14: =INDEX(Employees!$A:$Z,MATCH(B14,Employees!$A:$A,0),MATCH("rating",Employees!$1:$1,0)) -> 3 | G14: =INDEX(Employees!$A:$Z,MATCH(B14,Employees!$A:$A,0),MATCH("hire_date",Employees!$1:$1,0)) -> 42935 | H14: =INDEX(Employees!$A:$Z,MATCH(B14,Employees!$A:$A,0),MATCH("last_change_date",Employees!$1:$1,0)) -> 46113 | I14: =INDEX(Employees!$A:$Z,MATCH(B14,Employees!$A:$A,0),MATCH("base_salary",Employees!$1:$1,0)) -> 75607.45 | J14: =INDEX(Employees!$A:$Z,MATCH(B14,Employees!$A:$A,0),MATCH("bonus_pct",Employees!$1:$1,0))/100 -> 0.1199 | K14: =INDEX(Employees!$A:$Z,MATCH(B14,Employees!$A:$A,0),MATCH("fte",Employees!$1:$1,0)) -> 1 | L14: =IF(ISNA(MATCH(C14&"|"&E14,Bands!$F:$F,0)),0,1) -> 1 | M14: =INDEX(Bands!$C:$C,MATCH(C14&"|"&E14,Bands!$F:$F,0)) -> 59800 | N14: =INDEX(Bands!$D:$D,MATCH(C14&"|"&E14,Bands!$F:$F,0)) -> 74800 | O14: =INDEX(Bands!$E:$E,MATCH(C14&"|"&E14,Bands!$F:$F,0)) -> 89700 | P14: =(EffDate-G14)/365.25 -> 9.7002053 | Q14: =I14*(1+J14) -> 84672.783 | R14: =E14^2 -> 100 | S14: =P14^2 -> 94.093984 | T14: =E14*P14 -> 97.002053 | U14: =E14*Q14 -> 846727.83 | V14: =P14*Q14 -> 821343.38 | W14: =ROUND(Q14,2) -> 84672.78 | X14: =COUNTIFS($C:$C,C14,$W:$W,"<"&W14)+COUNTIFS($C:$C,C14,$W:$W,W14,$B:$B,"<"&B14)+1 -> 36 | Y14: =INDEX(Categories!$AH:$AH,MATCH(C14,Categories!$A:$A,0)) -> 71955.394 | Z14: =IF(AND(D14="F",Q14<Y14,INDEX(Categories!$AI:$AI,MATCH(C14,Categories!$A:$A,0))>0),1,0) -> 0 | AA14: =IF(Z14=1,Y14-Q14,0) -> 0 | AB14: =IF(Z14=1,INDEX(Categories!$AI:$AI,MATCH(C14,Categories!$A:$A,0))*AA14/INDEX(Categories!$AJ:$AJ,MATCH(C14,Categories!$A:$A,0)),0) -> 0 | AC14: =AB14/(1+J14) -> 0 | AD14: =I14+AC14 -> 75607.45 | AE14: =IF(AND(AC14>0,AD14>O14),1,0) -> 0 | AF14: =IF(G14>EffDate,-1,DATEDIF(G14,EffDate,"m")) -> 116 | AG14: =IF(H14>EffDate,-1,DATEDIF(H14,EffDate,"m")) -> 12 | AH14: =IF(AND(AF14>=MinMonthsHire,AG14>=MinMonthsChange),1,0) -> 1 | AI14: =AD14/N14 -> 1.0107948 | AJ14: =MATCH(AI14,Inputs!$B$31:$B$34,1) -> 3 | AK14: =INDEX(Inputs!$C$21:$C$25,MATCH(F14,Inputs!$A$21:$A$25,0)) -> 1 | AL14: =INDEX(Inputs!$D$21:$D$25,MATCH(F14,Inputs!$A$21:$A$25,0)) -> 0 | AM14: =N14*CompanyTarget*AK14 -> 74800 | AN14: =MAX(0,AM14-AD14) -> 0 | AO14: =IF(AND(ISNUMBER(MaxIncrease),MaxIncrease>0),1,0) -> 1 | AP14: =IF(AO14=1,AD14*MaxIncrease,0) -> 22682.235 | AQ14: =AD14*AL14 -> 0 | AR14: =IF(AK14=0,0,IF(AO14=1,MIN(MAX(AN14,AQ14),AP14),MAX(AN14,AQ14))) -> 0 | AS14: =IF(AD14>=O14,1,0) -> 0 | AT14: =IF(AS14=1,0,AR14) -> 0 | AU14: =MAX(0,O14-AD14) -> 14092.55 | AV14: =IF(ClipAtMax="No",AT14,MIN(AT14,AU14)) -> 0 | AW14: =IF(AH14=1,AV14,0) -> 0 | AX14: =IF(AD14>0,AW14/AD14,0) -> 0 | AY14: =AD14+AW14 -> 75607.45 | AZ14: =IF(AY14<M14,1,0) -> 0 | BA14: =Q14*K14 -> 84672.783 | BB14: =RateBelow*MIN(BA14,Ceiling)+AboveCeilingTier1*MIN(MAX(0,BA14-Ceiling),0.1*Ceiling)+AboveCeilingTier2*MIN(MAX(0,BA14-1.1*Ceiling),0.4*Ceiling)+AboveCeilingTier3*MAX(0,BA14-1.5*Ceiling) -> 19919.5 | BC14: =AD14*(1+J14)*K14 -> 84672.783 | BD14: =RateBelow*MIN(BC14,Ceiling)+AboveCeilingTier1*MIN(MAX(0,BC14-Ceiling),0.1*Ceiling)+AboveCeilingTier2*MIN(MAX(0,BC14-1.1*Ceiling),0.4*Ceiling)+AboveCeilingTier3*MAX(0,BC14-1.5*Ceiling) -> 19919.5 | BE14: =AY14*(1+J14)*K14 -> 84672.783 | BF14: =RateBelow*MIN(BE14,Ceiling)+AboveCeilingTier1*MIN(MAX(0,BE14-Ceiling),0.1*Ceiling)+AboveCeilingTier2*MIN(MAX(0,BE14-1.1*Ceiling),0.4*Ceiling)+AboveCeilingTier3*MAX(0,BE14-1.5*Ceiling) -> 19919.5 | BG14: =AC14*K14 -> 0 | BH14: =AC14*J14*K14 -> 0 | BI14: =BD14-BB14 -> 0 | BJ14: =AW14*K14 -> 0 | BK14: =AW14*J14*K14 -> 0 | BL14: =BF14-BD14 -> 0 | BM14: =IF(AH14=1,AD14*K14,0) -> 75607.45 | BN14: =IF(AH14=1,AD14*PoolPct,0) -> 3024.298 | BO14: =BN14*K14 -> 3024.298 | BP14: =BN14*J14*K14 -> 362.61333 | BQ14: =(AD14+BN14)*(1+J14)*K14 -> 88059.695 | BR14: =RateBelow*MIN(BQ14,Ceiling)+AboveCeilingTier1*MIN(MAX(0,BQ14-Ceiling),0.1*Ceiling)+AboveCeilingTier2*MIN(MAX(0,BQ14-1.1*Ceiling),0.4*Ceiling)+AboveCeilingTier3*MAX(0,BQ14-1.5*Ceiling) -> 19954.724 | BS14: =BR14-BD14 -> 35.223878 | BT14: =AD14*(1+J14) -> 84672.783 | BU14: =AY14*(1+J14) -> 84672.783 | BV14: =E14*BU14 -> 846727.83 | BW14: =P14*BU14 -> 821343.38
A15: =ROW()-4 -> 11 | B15: =INDEX(Employees!$A:$A,A15+1) -> E011 | C15: =INDEX(Employees!$A:$Z,MATCH(B15,Employees!$A:$A,0),MATCH("category",Employees!$1:$1,0)) -> Engineering | D15: =INDEX(Employees!$A:$Z,MATCH(B15,Employees!$A:$A,0),MATCH("gender",Employees!$1:$1,0)) -> M | E15: =INDEX(Employees!$A:$Z,MATCH(B15,Employees!$A:$A,0),MATCH("grade",Employees!$1:$1,0)) -> 7 | F15: =INDEX(Employees!$A:$Z,MATCH(B15,Employees!$A:$A,0),MATCH("rating",Employees!$1:$1,0)) -> 2 | G15: =INDEX(Employees!$A:$Z,MATCH(B15,Employees!$A:$A,0),MATCH("hire_date",Employees!$1:$1,0)) -> 45455 | H15: =INDEX(Employees!$A:$Z,MATCH(B15,Employees!$A:$A,0),MATCH("last_change_date",Employees!$1:$1,0)) -> 46113 | I15: =INDEX(Employees!$A:$Z,MATCH(B15,Employees!$A:$A,0),MATCH("base_salary",Employees!$1:$1,0)) -> 37697.15 | J15: =INDEX(Employees!$A:$Z,MATCH(B15,Employees!$A:$A,0),MATCH("bonus_pct",Employees!$1:$1,0))/100 -> 0.1404 | K15: =INDEX(Employees!$A:$Z,MATCH(B15,Employees!$A:$A,0),MATCH("fte",Employees!$1:$1,0)) -> 1 | L15: =IF(ISNA(MATCH(C15&"|"&E15,Bands!$F:$F,0)),0,1) -> 1 | M15: =INDEX(Bands!$C:$C,MATCH(C15&"|"&E15,Bands!$F:$F,0)) -> 41600 | N15: =INDEX(Bands!$D:$D,MATCH(C15&"|"&E15,Bands!$F:$F,0)) -> 49900 | O15: =INDEX(Bands!$E:$E,MATCH(C15&"|"&E15,Bands!$F:$F,0)) -> 58200 | P15: =(EffDate-G15)/365.25 -> 2.8008214 | Q15: =I15*(1+J15) -> 42989.83 | R15: =E15^2 -> 49 | S15: =P15^2 -> 7.8446003 | T15: =E15*P15 -> 19.605749 | U15: =E15*Q15 -> 300928.81 | V15: =P15*Q15 -> 120406.83 | W15: =ROUND(Q15,2) -> 42989.83 | X15: =COUNTIFS($C:$C,C15,$W:$W,"<"&W15)+COUNTIFS($C:$C,C15,$W:$W,W15,$B:$B,"<"&B15)+1 -> 1 | Y15: =INDEX(Categories!$AH:$AH,MATCH(C15,Categories!$A:$A,0)) -> 71955.394 | Z15: =IF(AND(D15="F",Q15<Y15,INDEX(Categories!$AI:$AI,MATCH(C15,Categories!$A:$A,0))>0),1,0) -> 0 | AA15: =IF(Z15=1,Y15-Q15,0) -> 0 | AB15: =IF(Z15=1,INDEX(Categories!$AI:$AI,MATCH(C15,Categories!$A:$A,0))*AA15/INDEX(Categories!$AJ:$AJ,MATCH(C15,Categories!$A:$A,0)),0) -> 0 | AC15: =AB15/(1+J15) -> 0 | AD15: =I15+AC15 -> 37697.15 | AE15: =IF(AND(AC15>0,AD15>O15),1,0) -> 0 | AF15: =IF(G15>EffDate,-1,DATEDIF(G15,EffDate,"m")) -> 33 | AG15: =IF(H15>EffDate,-1,DATEDIF(H15,EffDate,"m")) -> 12 | AH15: =IF(AND(AF15>=MinMonthsHire,AG15>=MinMonthsChange),1,0) -> 1 | AI15: =AD15/N15 -> 0.75545391 | AJ15: =MATCH(AI15,Inputs!$B$31:$B$34,1) -> 1 | AK15: =INDEX(Inputs!$C$21:$C$25,MATCH(F15,Inputs!$A$21:$A$25,0)) -> 0.95 | AL15: =INDEX(Inputs!$D$21:$D$25,MATCH(F15,Inputs!$A$21:$A$25,0)) -> 0 | AM15: =N15*CompanyTarget*AK15 -> 47405 | AN15: =MAX(0,AM15-AD15) -> 9707.85 | AO15: =IF(AND(ISNUMBER(MaxIncrease),MaxIncrease>0),1,0) -> 1 | AP15: =IF(AO15=1,AD15*MaxIncrease,0) -> 11309.145 | AQ15: =AD15*AL15 -> 0 | AR15: =IF(AK15=0,0,IF(AO15=1,MIN(MAX(AN15,AQ15),AP15),MAX(AN15,AQ15))) -> 9707.85 | AS15: =IF(AD15>=O15,1,0) -> 0 | AT15: =IF(AS15=1,0,AR15) -> 9707.85 | AU15: =MAX(0,O15-AD15) -> 20502.85 | AV15: =IF(ClipAtMax="No",AT15,MIN(AT15,AU15)) -> 9707.85 | AW15: =IF(AH15=1,AV15,0) -> 9707.85 | AX15: =IF(AD15>0,AW15/AD15,0) -> 0.25752212 | AY15: =AD15+AW15 -> 47405 | AZ15: =IF(AY15<M15,1,0) -> 0 | BA15: =Q15*K15 -> 42989.83 | BB15: =RateBelow*MIN(BA15,Ceiling)+AboveCeilingTier1*MIN(MAX(0,BA15-Ceiling),0.1*Ceiling)+AboveCeilingTier2*MIN(MAX(0,BA15-1.1*Ceiling),0.4*Ceiling)+AboveCeilingTier3*MAX(0,BA15-1.5*Ceiling) -> 13821.23 | BC15: =AD15*(1+J15)*K15 -> 42989.83 | BD15: =RateBelow*MIN(BC15,Ceiling)+AboveCeilingTier1*MIN(MAX(0,BC15-Ceiling),0.1*Ceiling)+AboveCeilingTier2*MIN(MAX(0,BC15-1.1*Ceiling),0.4*Ceiling)+AboveCeilingTier3*MAX(0,BC15-1.5*Ceiling) -> 13821.23 | BE15: =AY15*(1+J15)*K15 -> 54060.662 | BF15: =RateBelow*MIN(BE15,Ceiling)+AboveCeilingTier1*MIN(MAX(0,BE15-Ceiling),0.1*Ceiling)+AboveCeilingTier2*MIN(MAX(0,BE15-1.1*Ceiling),0.4*Ceiling)+AboveCeilingTier3*MAX(0,BE15-1.5*Ceiling) -> 17380.503 | BG15: =AC15*K15 -> 0 | BH15: =AC15*J15*K15 -> 0 | BI15: =BD15-BB15 -> 0 | BJ15: =AW15*K15 -> 9707.85 | BK15: =AW15*J15*K15 -> 1362.9821 | BL15: =BF15-BD15 -> 3559.2725 | BM15: =IF(AH15=1,AD15*K15,0) -> 37697.15 | BN15: =IF(AH15=1,AD15*PoolPct,0) -> 1507.886 | BO15: =BN15*K15 -> 1507.886 | BP15: =BN15*J15*K15 -> 211.70719 | BQ15: =(AD15+BN15)*(1+J15)*K15 -> 44709.423 | BR15: =RateBelow*MIN(BQ15,Ceiling)+AboveCeilingTier1*MIN(MAX(0,BQ15-Ceiling),0.1*Ceiling)+AboveCeilingTier2*MIN(MAX(0,BQ15-1.1*Ceiling),0.4*Ceiling)+AboveCeilingTier3*MAX(0,BQ15-1.5*Ceiling) -> 14374.08 | BS15: =BR15-BD15 -> 552.84921 | BT15: =AD15*(1+J15) -> 42989.83 | BU15: =AY15*(1+J15) -> 54060.662 | BV15: =E15*BU15 -> 378424.63 | BW15: =P15*BU15 -> 151414.26
A16: =ROW()-4 -> 12 | B16: =INDEX(Employees!$A:$A,A16+1) -> E012 | C16: =INDEX(Employees!$A:$Z,MATCH(B16,Employees!$A:$A,0),MATCH("category",Employees!$1:$1,0)) -> Engineering | D16: =INDEX(Employees!$A:$Z,MATCH(B16,Employees!$A:$A,0),MATCH("gender",Employees!$1:$1,0)) -> M | E16: =INDEX(Employees!$A:$Z,MATCH(B16,Employees!$A:$A,0),MATCH("grade",Employees!$1:$1,0)) -> 9 | F16: =INDEX(Employees!$A:$Z,MATCH(B16,Employees!$A:$A,0),MATCH("rating",Employees!$1:$1,0)) -> 3 | G16: =INDEX(Employees!$A:$Z,MATCH(B16,Employees!$A:$A,0),MATCH("hire_date",Employees!$1:$1,0)) -> 43666 | H16: =INDEX(Employees!$A:$Z,MATCH(B16,Employees!$A:$A,0),MATCH("last_change_date",Employees!$1:$1,0)) -> 46113 | I16: =INDEX(Employees!$A:$Z,MATCH(B16,Employees!$A:$A,0),MATCH("base_salary",Employees!$1:$1,0)) -> 60920.28 | J16: =INDEX(Employees!$A:$Z,MATCH(B16,Employees!$A:$A,0),MATCH("bonus_pct",Employees!$1:$1,0))/100 -> 0.1228 | K16: =INDEX(Employees!$A:$Z,MATCH(B16,Employees!$A:$A,0),MATCH("fte",Employees!$1:$1,0)) -> 1 | L16: =IF(ISNA(MATCH(C16&"|"&E16,Bands!$F:$F,0)),0,1) -> 1 | M16: =INDEX(Bands!$C:$C,MATCH(C16&"|"&E16,Bands!$F:$F,0)) -> 54500 | N16: =INDEX(Bands!$D:$D,MATCH(C16&"|"&E16,Bands!$F:$F,0)) -> 65400 | O16: =INDEX(Bands!$E:$E,MATCH(C16&"|"&E16,Bands!$F:$F,0)) -> 76300 | P16: =(EffDate-G16)/365.25 -> 7.6988364 | Q16: =I16*(1+J16) -> 68401.29 | R16: =E16^2 -> 81 | S16: =P16^2 -> 59.272082 | T16: =E16*P16 -> 69.289528 | U16: =E16*Q16 -> 615611.61 | V16: =P16*Q16 -> 526610.35 | W16: =ROUND(Q16,2) -> 68401.29 | X16: =COUNTIFS($C:$C,C16,$W:$W,"<"&W16)+COUNTIFS($C:$C,C16,$W:$W,W16,$B:$B,"<"&B16)+1 -> 21 | Y16: =INDEX(Categories!$AH:$AH,MATCH(C16,Categories!$A:$A,0)) -> 71955.394 | Z16: =IF(AND(D16="F",Q16<Y16,INDEX(Categories!$AI:$AI,MATCH(C16,Categories!$A:$A,0))>0),1,0) -> 0 | AA16: =IF(Z16=1,Y16-Q16,0) -> 0 | AB16: =IF(Z16=1,INDEX(Categories!$AI:$AI,MATCH(C16,Categories!$A:$A,0))*AA16/INDEX(Categories!$AJ:$AJ,MATCH(C16,Categories!$A:$A,0)),0) -> 0 | AC16: =AB16/(1+J16) -> 0 | AD16: =I16+AC16 -> 60920.28 | AE16: =IF(AND(AC16>0,AD16>O16),1,0) -> 0 | AF16: =IF(G16>EffDate,-1,DATEDIF(G16,EffDate,"m")) -> 92 | AG16: =IF(H16>EffDate,-1,DATEDIF(H16,EffDate,"m")) -> 12 | AH16: =IF(AND(AF16>=MinMonthsHire,AG16>=MinMonthsChange),1,0) -> 1 | AI16: =AD16/N16 -> 0.93150275 | AJ16: =MATCH(AI16,Inputs!$B$31:$B$34,1) -> 2 | AK16: =INDEX(Inputs!$C$21:$C$25,MATCH(F16,Inputs!$A$21:$A$25,0)) -> 1 | AL16: =INDEX(Inputs!$D$21:$D$25,MATCH(F16,Inputs!$A$21:$A$25,0)) -> 0 | AM16: =N16*CompanyTarget*AK16 -> 65400 | AN16: =MAX(0,AM16-AD16) -> 4479.72 | AO16: =IF(AND(ISNUMBER(MaxIncrease),MaxIncrease>0),1,0) -> 1 | AP16: =IF(AO16=1,AD16*MaxIncrease,0) -> 18276.084 | AQ16: =AD16*AL16 -> 0 | AR16: =IF(AK16=0,0,IF(AO16=1,MIN(MAX(AN16,AQ16),AP16),MAX(AN16,AQ16))) -> 4479.72 | AS16: =IF(AD16>=O16,1,0) -> 0 | AT16: =IF(AS16=1,0,AR16) -> 4479.72 | AU16: =MAX(0,O16-AD16) -> 15379.72 | AV16: =IF(ClipAtMax="No",AT16,MIN(AT16,AU16)) -> 4479.72 | AW16: =IF(AH16=1,AV16,0) -> 4479.72 | AX16: =IF(AD16>0,AW16/AD16,0) -> 0.073534133 | AY16: =AD16+AW16 -> 65400 | AZ16: =IF(AY16<M16,1,0) -> 0 | BA16: =Q16*K16 -> 68401.29 | BB16: =RateBelow*MIN(BA16,Ceiling)+AboveCeilingTier1*MIN(MAX(0,BA16-Ceiling),0.1*Ceiling)+AboveCeilingTier2*MIN(MAX(0,BA16-1.1*Ceiling),0.4*Ceiling)+AboveCeilingTier3*MAX(0,BA16-1.5*Ceiling) -> 19750.276 | BC16: =AD16*(1+J16)*K16 -> 68401.29 | BD16: =RateBelow*MIN(BC16,Ceiling)+AboveCeilingTier1*MIN(MAX(0,BC16-Ceiling),0.1*Ceiling)+AboveCeilingTier2*MIN(MAX(0,BC16-1.1*Ceiling),0.4*Ceiling)+AboveCeilingTier3*MAX(0,BC16-1.5*Ceiling) -> 19750.276 | BE16: =AY16*(1+J16)*K16 -> 73431.12 | BF16: =RateBelow*MIN(BE16,Ceiling)+AboveCeilingTier1*MIN(MAX(0,BE16-Ceiling),0.1*Ceiling)+AboveCeilingTier2*MIN(MAX(0,BE16-1.1*Ceiling),0.4*Ceiling)+AboveCeilingTier3*MAX(0,BE16-1.5*Ceiling) -> 19802.586 | BG16: =AC16*K16 -> 0 | BH16: =AC16*J16*K16 -> 0 | BI16: =BD16-BB16 -> 0 | BJ16: =AW16*K16 -> 4479.72 | BK16: =AW16*J16*K16 -> 550.10962 | BL16: =BF16-BD16 -> 52.310228 | BM16: =IF(AH16=1,AD16*K16,0) -> 60920.28 | BN16: =IF(AH16=1,AD16*PoolPct,0) -> 2436.8112 | BO16: =BN16*K16 -> 2436.8112 | BP16: =BN16*J16*K16 -> 299.24042 | BQ16: =(AD16+BN16)*(1+J16)*K16 -> 71137.342 | BR16: =RateBelow*MIN(BQ16,Ceiling)+AboveCeilingTier1*MIN(MAX(0,BQ16-Ceiling),0.1*Ceiling)+AboveCeilingTier2*MIN(MAX(0,BQ16-1.1*Ceiling),0.4*Ceiling)+AboveCeilingTier3*MAX(0,BQ16-1.5*Ceiling) -> 19778.731 | BS16: =BR16-BD16 -> 28.454937 | BT16: =AD16*(1+J16) -> 68401.29 | BU16: =AY16*(1+J16) -> 73431.12 | BV16: =E16*BU16 -> 660880.08 | BW16: =P16*BU16 -> 565334.18
... A216: =ROW()-4 -> 212 | B216: =INDEX(Employees!$A:$A,A216+1) -> E212 | C216: =INDEX(Employees!$A:$Z,MATCH(B216,Employees!$A:$A,0),MATCH("category",Employees!$1:$1,0)) -> Sales | D216: =INDEX(Employees!$A:$Z,MATCH(B216,Employees!$A:$A,0),MATCH("gender",Employees!$1:$1,0)) -> M | E216: =INDEX(Employees!$A:$Z,MATCH(B216,Employees!$A:$A,0),MATCH("grade",Employees!$1:$1,0)) -> 9 | F216: =INDEX(Employees!$A:$Z,MATCH(B216,Employees!$A:$A,0),MATCH("rating",Employees!$1:$1,0)) -> 3 | G216: =INDEX(Employees!$A:$Z,MATCH(B216,Employees!$A:$A,0),MATCH("hire_date",Employees!$1:$1,0)) -> 45127 | H216: =INDEX(Employees!$A:$Z,MATCH(B216,Employees!$A:$A,0),MATCH("last_change_date",Employees!$1:$1,0)) -> 46113 | I216: =INDEX(Employees!$A:$Z,MATCH(B216,Employees!$A:$A,0),MATCH("base_salary",Employees!$1:$1,0)) -> 54620.08 | J216: =INDEX(Employees!$A:$Z,MATCH(B216,Employees!$A:$A,0),MATCH("bonus_pct",Employees!$1:$1,0))/100 -> 0.26 | K216: =INDEX(Employees!$A:$Z,MATCH(B216,Employees!$A:$A,0),MATCH("fte",Employees!$1:$1,0)) -> 1 | L216: =IF(ISNA(MATCH(C216&"|"&E216,Bands!$F:$F,0)),0,1) -> 1 | M216: =INDEX(Bands!$C:$C,MATCH(C216&"|"&E216,Bands!$F:$F,0)) -> 61100 | N216: =INDEX(Bands!$D:$D,MATCH(C216&"|"&E216,Bands!$F:$F,0)) -> 73300 | O216: =INDEX(Bands!$E:$E,MATCH(C216&"|"&E216,Bands!$F:$F,0)) -> 85500 | P216: =(EffDate-G216)/365.25 -> 3.6988364 | Q216: =I216*(1+J216) -> 68821.301 | R216: =E216^2 -> 81 | S216: =P216^2 -> 13.681391 | T216: =E216*P216 -> 33.289528 | U216: =E216*Q216 -> 619391.71 | V216: =P216*Q216 -> 254558.73 | W216: =ROUND(Q216,2) -> 68821.3 | X216: =COUNTIFS($C:$C,C216,$W:$W,"<"&W216)+COUNTIFS($C:$C,C216,$W:$W,W216,$B:$B,"<"&B216)+1 -> 5 | Y216: =INDEX(Categories!$AH:$AH,MATCH(C216,Categories!$A:$A,0)) -> 85035.918 | Z216: =IF(AND(D216="F",Q216<Y216,INDEX(Categories!$AI:$AI,MATCH(C216,Categories!$A:$A,0))>0),1,0) -> 0 | AA216: =IF(Z216=1,Y216-Q216,0) -> 0 | AB216: =IF(Z216=1,INDEX(Categories!$AI:$AI,MATCH(C216,Categories!$A:$A,0))*AA216/INDEX(Categories!$AJ:$AJ,MATCH(C216,Categories!$A:$A,0)),0) -> 0 | AC216: =AB216/(1+J216) -> 0 | AD216: =I216+AC216 -> 54620.08 | AE216: =IF(AND(AC216>0,AD216>O216),1,0) -> 0 | AF216: =IF(G216>EffDate,-1,DATEDIF(G216,EffDate,"m")) -> 44 | AG216: =IF(H216>EffDate,-1,DATEDIF(H216,EffDate,"m")) -> 12 | AH216: =IF(AND(AF216>=MinMonthsHire,AG216>=MinMonthsChange),1,0) -> 1 | AI216: =AD216/N216 -> 0.74515798 | AJ216: =MATCH(AI216,Inputs!$B$31:$B$34,1) -> 1 | AK216: =INDEX(Inputs!$C$21:$C$25,MATCH(F216,Inputs!$A$21:$A$25,0)) -> 1 | AL216: =INDEX(Inputs!$D$21:$D$25,MATCH(F216,Inputs!$A$21:$A$25,0)) -> 0 | AM216: =N216*CompanyTarget*AK216 -> 73300 | AN216: =MAX(0,AM216-AD216) -> 18679.92 | AO216: =IF(AND(ISNUMBER(MaxIncrease),MaxIncrease>0),1,0) -> 1 | AP216: =IF(AO216=1,AD216*MaxIncrease,0) -> 16386.024 | AQ216: =AD216*AL216 -> 0 | AR216: =IF(AK216=0,0,IF(AO216=1,MIN(MAX(AN216,AQ216),AP216),MAX(AN216,AQ216))) -> 16386.024 | AS216: =IF(AD216>=O216,1,0) -> 0 | AT216: =IF(AS216=1,0,AR216) -> 16386.024 | AU216: =MAX(0,O216-AD216) -> 30879.92 | AV216: =IF(ClipAtMax="No",AT216,MIN(AT216,AU216)) -> 16386.024 | AW216: =IF(AH216=1,AV216,0) -> 16386.024 | AX216: =IF(AD216>0,AW216/AD216,0) -> 0.3 | AY216: =AD216+AW216 -> 71006.104 | AZ216: =IF(AY216<M216,1,0) -> 0 | BA216: =Q216*K216 -> 68821.301 | BB216: =RateBelow*MIN(BA216,Ceiling)+AboveCeilingTier1*MIN(MAX(0,BA216-Ceiling),0.1*Ceiling)+AboveCeilingTier2*MIN(MAX(0,BA216-1.1*Ceiling),0.4*Ceiling)+AboveCeilingTier3*MAX(0,BA216-1.5*Ceiling) -> 19754.644 | BC216: =AD216*(1+J216)*K216 -> 68821.301 | BD216: =RateBelow*MIN(BC216,Ceiling)+AboveCeilingTier1*MIN(MAX(0,BC216-Ceiling),0.1*Ceiling)+AboveCeilingTier2*MIN(MAX(0,BC216-1.1*Ceiling),0.4*Ceiling)+AboveCeilingTier3*MAX(0,BC216-1.5*Ceiling) -> 19754.644 | BE216: =AY216*(1+J216)*K216 -> 89467.691 | BF216: =RateBelow*MIN(BE216,Ceiling)+AboveCeilingTier1*MIN(MAX(0,BE216-Ceiling),0.1*Ceiling)+AboveCeilingTier2*MIN(MAX(0,BE216-1.1*Ceiling),0.4*Ceiling)+AboveCeilingTier3*MAX(0,BE216-1.5*Ceiling) -> 19969.367 | BG216: =AC216*K216 -> 0 | BH216: =AC216*J216*K216 -> 0 | BI216: =BD216-BB216 -> 0 | BJ216: =AW216*K216 -> 16386.024 | BK216: =AW216*J216*K216 -> 4260.3662 | BL216: =BF216-BD216 -> 214.72246 | BM216: =IF(AH216=1,AD216*K216,0) -> 54620.08 | BN216: =IF(AH216=1,AD216*PoolPct,0) -> 2184.8032 | BO216: =BN216*K216 -> 2184.8032 | BP216: =BN216*J216*K216 -> 568.04883 | BQ216: =(AD216+BN216)*(1+J216)*K216 -> 71574.153 | BR216: =RateBelow*MIN(BQ216,Ceiling)+AboveCeilingTier1*MIN(MAX(0,BQ216-Ceiling),0.1*Ceiling)+AboveCeilingTier2*MIN(MAX(0,BQ216-1.1*Ceiling),0.4*Ceiling)+AboveCeilingTier3*MAX(0,BQ216-1.5*Ceiling) -> 19783.274 | BS216: =BR216-BD216 -> 28.629661 | BT216: =AD216*(1+J216) -> 68821.301 | BU216: =AY216*(1+J216) -> 89467.691 | BV216: =E216*BU216 -> 805209.22 | BW216: =P216*BU216 -> 330926.35

Sheet Categories
A1: Pay equity per category: unexplained gap closed in full | H1: Regression of total cash on grade and tenure (explicit sums) | Y1: Explained and unexplained gap | AF1: Who receives it and how much | AK1: Gap after each step | AQ1: Unexplained gap after each step
A2: Type your categories here. | E2: Base + bonus, full time. | G2: (men − women) / men. | H2: Sums over the category. | P2: Centred sums. | U2: Cramer's rule. | AC2: Part of the gap explained by differences in grade and tenure. | AD2: Kept between 0 and the raw gap. | AE2: Closed in full when it is against women (positive). A gap in women's favour is not adjusted. | AF2: The middle place(s) in the category list sorted by total cash. Odd headcount: both ranks are the same person. | AH2: Category median of total cash: the average of the two middle values (one value twice if the headcount is odd). | AI2: Unexplained gap × men's mean total cash × number of women. | AP2: Did the review widen the gap again? | AQ2: Zero where pay equity closed it; otherwise unchanged. | AR2: The same regression, re-run on total cash after merit. | AZ2: Kept between 0 and the raw gap. | BA2: Did the review open an unexplained gap again?
A4: Category | B4: Headcount | C4: Women | D4: Men | E4: Mean total cash, men | F4: Mean total cash, women | G4: Raw gap | H4: Σ grade | I4: Σ tenure | J4: Σ total cash | K4: Σ grade² | L4: Σ tenure² | M4: Σ grade×tenure | N4: Σ grade×cash | O4: Σ tenure×cash | P4: Sgg | Q4: Stt | R4: Sgt | S4: Sgy | T4: Sty | U4: Determinant | V4: Regression usable | W4: € per grade | X4: € per tenure year | Y4: Mean grade, men | Z4: Mean grade, women | AA4: Mean tenure, men | AB4: Mean tenure, women | AC4: Explained, before bounds | AD4: Explained | AE4: Unexplained | AF4: Median rank 1 | AG4: Median rank 2 | AH4: Median total cash | AI4: Amount to close | AJ4: Sum of shortfalls | AK4: Mean men, after equity | AL4: Mean women, after equity | AM4: Raw gap after equity | AN4: Mean men, after merit | AO4: Mean women, after merit | AP4: Raw gap after merit | AQ4: Unexplained after equity | AR4: Σ total cash after merit | AS4: Σ grade×cash after merit | AT4: Σ tenure×cash after merit | AU4: Sgy after merit | AV4: Sty after merit | AW4: € per grade after merit | AX4: € per tenure year after merit | AY4: Explained after merit, before bounds | AZ4: Explained after merit | BA4: Unexplained after merit
A5: Engineering | B5: =COUNTIFS(Calc!$C:$C,$A5) -> 44 | C5: =COUNTIFS(Calc!$C:$C,$A5,Calc!$D:$D,"F") -> 12 | D5: =COUNTIFS(Calc!$C:$C,$A5,Calc!$D:$D,"M") -> 32 | E5: =IF(D5>0,SUMIFS(Calc!$Q:$Q,Calc!$C:$C,$A5,Calc!$D:$D,"M")/D5,0) -> 74136.058 | F5: =IF(C5>0,SUMIFS(Calc!$Q:$Q,Calc!$C:$C,$A5,Calc!$D:$D,"F")/C5,0) -> 65301.371 | G5: =IF(AND(C5>0,D5>0,E5>0),(E5-F5)/E5,0) -> 0.11916856 | H5: =SUMIFS(Calc!$E:$E,Calc!$C:$C,$A5) -> 401 | I5: =SUMIFS(Calc!$P:$P,Calc!$C:$C,$A5) -> 305.00753 | J5: =SUMIFS(Calc!$Q:$Q,Calc!$C:$C,$A5) -> 3155970.3 | K5: =SUMIFS(Calc!$R:$R,Calc!$C:$C,$A5) -> 3745 | L5: =SUMIFS(Calc!$S:$S,Calc!$C:$C,$A5) -> 2444.4562 | M5: =SUMIFS(Calc!$T:$T,Calc!$C:$C,$A5) -> 2917.18 | N5: =SUMIFS(Calc!$U:$U,Calc!$C:$C,$A5) -> 29671258 | O5: =SUMIFS(Calc!$V:$V,Calc!$C:$C,$A5) -> 23394903 | P5: =IF(B5>0,K5-H5^2/B5,0) -> 90.431818 | Q5: =IF(B5>0,L5-I5^2/B5,0) -> 330.14726 | R5: =IF(B5>0,M5-H5*I5/B5,0) -> 137.45231 | S5: =IF(B5>0,N5-H5*J5/B5,0) -> 908891.88 | T5: =IF(B5>0,O5-I5*J5/B5,0) -> 1517750.9 | U5: =P5*Q5-R5^2 -> 10962.681 | V5: =IF(AND(B5>=4,ABS(U5)>0.000000001),1,0) -> 1 | W5: =IF(V5=1,(S5*Q5-T5*R5)/U5,0) -> 8341.9196 | X5: =IF(V5=1,(T5*P5-S5*R5)/U5,0) -> 1124.1494 | Y5: =IF(D5>0,SUMIFS(Calc!$E:$E,Calc!$C:$C,$A5,Calc!$D:$D,"M")/D5,0) -> 9.15625 | Z5: =IF(C5>0,SUMIFS(Calc!$E:$E,Calc!$C:$C,$A5,Calc!$D:$D,"F")/C5,0) -> 9 | AA5: =IF(D5>0,SUMIFS(Calc!$P:$P,Calc!$C:$C,$A5,Calc!$D:$D,"M")/D5,0) -> 7.012577 | AB5: =IF(C5>0,SUMIFS(Calc!$P:$P,Calc!$C:$C,$A5,Calc!$D:$D,"F")/C5,0) -> 6.7170888 | AC5: =IF(AND(V5=1,C5>0,D5>0,E5>0),(W5*(Y5-Z5)+X5*(AA5-AB5))/E5,0) -> 0.02206211 | AD5: =IF(G5>=0,MAX(0,MIN(AC5,G5)),MIN(0,MAX(AC5,G5))) -> 0.02206211 | AE5: =G5-AD5 -> 0.097106451 | AF5: =INT((B5+1)/2) -> 22 | AG5: =INT(B5/2)+1 -> 23 | AH5: =(SUMIFS(Calc!$Q:$Q,Calc!$C:$C,$A5,Calc!$X:$X,AF5)+SUMIFS(Calc!$Q:$Q,Calc!$C:$C,$A5,Calc!$X:$X,AG5))/2 -> 71955.394 | AI5: =IF(AND(G5>=0,AE5>0.000000000001),AE5*E5*C5,0) -> 86389.074 | AJ5: =SUMIFS(Calc!$AA:$AA,Calc!$C:$C,$A5) -> 110188.28 | AK5: =IF(D5>0,SUMIFS(Calc!$BT:$BT,Calc!$C:$C,$A5,Calc!$D:$D,"M")/D5,0) -> 74136.058 | AL5: =IF(C5>0,SUMIFS(Calc!$BT:$BT,Calc!$C:$C,$A5,Calc!$D:$D,"F")/C5,0) -> 72500.46 | AM5: =IF(AK5>0,(AK5-AL5)/AK5,0) -> 0.02206211 | AN5: =IF(D5>0,SUMIFS(Calc!$BU:$BU,Calc!$C:$C,$A5,Calc!$D:$D,"M")/D5,0) -> 77950.866 | AO5: =IF(C5>0,SUMIFS(Calc!$BU:$BU,Calc!$C:$C,$A5,Calc!$D:$D,"F")/C5,0) -> 78644.759 | AP5: =IF(AN5>0,(AN5-AO5)/AN5,0) -> -0.0089016648 | AQ5: =IF(AND(AI5>0,AJ5>0),0,AE5) -> 0 | AR5: =SUMIFS(Calc!$BU:$BU,Calc!$C:$C,$A5) -> 3438164.8 | AS5: =SUMIFS(Calc!$BV:$BV,Calc!$C:$C,$A5) -> 32198699 | AT5: =SUMIFS(Calc!$BW:$BW,Calc!$C:$C,$A5) -> 25165041 | AU5: =IF(B5>0,AS5-H5*AR5/B5,0) -> 864515.41 | AV5: =IF(B5>0,AT5-I5*AR5/B5,0) -> 1331719.3 | AW5: =IF(V5=1,(AU5*Q5-AV5*R5)/U5,0) -> 9337.999 | AX5: =IF(V5=1,(AV5*P5-AU5*R5)/U5,0) -> 145.96464 | AY5: =IF(AND(V5=1,C5>0,D5>0,AN5>0),(AW5*(Y5-Z5)+AX5*(AA5-AB5))/AN5,0) -> 0.019271026 | AZ5: =IF(AP5>=0,MAX(0,MIN(AY5,AP5)),MIN(0,MAX(AY5,AP5))) -> 0 | BA5: =AP5-AZ5 -> -0.0089016648
A6: Operations | B6: =COUNTIFS(Calc!$C:$C,$A6) -> 38 | C6: =COUNTIFS(Calc!$C:$C,$A6,Calc!$D:$D,"F") -> 19 | D6: =COUNTIFS(Calc!$C:$C,$A6,Calc!$D:$D,"M") -> 19 | E6: =IF(D6>0,SUMIFS(Calc!$Q:$Q,Calc!$C:$C,$A6,Calc!$D:$D,"M")/D6,0) -> 57158.66 | F6: =IF(C6>0,SUMIFS(Calc!$Q:$Q,Calc!$C:$C,$A6,Calc!$D:$D,"F")/C6,0) -> 50601.223 | G6: =IF(AND(C6>0,D6>0,E6>0),(E6-F6)/E6,0) -> 0.11472342 | H6: =SUMIFS(Calc!$E:$E,Calc!$C:$C,$A6) -> 253 | I6: =SUMIFS(Calc!$P:$P,Calc!$C:$C,$A6) -> 212.59138 | J6: =SUMIFS(Calc!$Q:$Q,Calc!$C:$C,$A6) -> 2047437.8 | K6: =SUMIFS(Calc!$R:$R,Calc!$C:$C,$A6) -> 1767 | L6: =SUMIFS(Calc!$S:$S,Calc!$C:$C,$A6) -> 1428.4607 | M6: =SUMIFS(Calc!$T:$T,Calc!$C:$C,$A6) -> 1520.4764 | N6: =SUMIFS(Calc!$U:$U,Calc!$C:$C,$A6) -> 14274209 | O6: =SUMIFS(Calc!$V:$V,Calc!$C:$C,$A6) -> 12360230 | P6: =IF(B6>0,K6-H6^2/B6,0) -> 82.552632 | Q6: =IF(B6>0,L6-I6^2/B6,0) -> 239.11615 | R6: =IF(B6>0,M6-H6*I6/B6,0) -> 105.06538 | S6: =IF(B6>0,N6-H6*J6/B6,0) -> 642583.86 | T6: =IF(B6>0,O6-I6*J6/B6,0) -> 905819.33 | U6: =P6*Q6-R6^2 -> 8700.9327 | V6: =IF(AND(B6>=4,ABS(U6)>0.000000001),1,0) -> 1 | W6: =IF(V6=1,(S6*Q6-T6*R6)/U6,0) -> 6721.3398 | X6: =IF(V6=1,(T6*P6-S6*R6)/U6,0) -> 834.90463 | Y6: =IF(D6>0,SUMIFS(Calc!$E:$E,Calc!$C:$C,$A6,Calc!$D:$D,"M")/D6,0) -> 7 | Z6: =IF(C6>0,SUMIFS(Calc!$E:$E,Calc!$C:$C,$A6,Calc!$D:$D,"F")/C6,0) -> 6.3157895 | AA6: =IF(D6>0,SUMIFS(Calc!$P:$P,Calc!$C:$C,$A6,Calc!$D:$D,"M")/D6,0) -> 6.5205519 | AB6: =IF(C6>0,SUMIFS(Calc!$P:$P,Calc!$C:$C,$A6,Calc!$D:$D,"F")/C6,0) -> 4.6684679 | AC6: =IF(AND(V6=1,C6>0,D6>0,E6>0),(W6*(Y6-Z6)+X6*(AA6-AB6))/E6,0) -> 0.10750996 | AD6: =IF(G6>=0,MAX(0,MIN(AC6,G6)),MIN(0,MAX(AC6,G6))) -> 0.10750996 | AE6: =G6-AD6 -> 0.007213465 | AF6: =INT((B6+1)/2) -> 19 | AG6: =INT(B6/2)+1 -> 20 | AH6: =(SUMIFS(Calc!$Q:$Q,Calc!$C:$C,$A6,Calc!$X:$X,AF6)+SUMIFS(Calc!$Q:$Q,Calc!$C:$C,$A6,Calc!$X:$X,AG6))/2 -> 51811.839 | AI6: =IF(AND(G6>=0,AE6>0.000000000001),AE6*E6*C6,0) -> 7833.9278 | AJ6: =SUMIFS(Calc!$AA:$AA,Calc!$C:$C,$A6) -> 99523.989 | AK6: =IF(D6>0,SUMIFS(Calc!$BT:$BT,Calc!$C:$C,$A6,Calc!$D:$D,"M")/D6,0) -> 57158.66 | AL6: =IF(C6>0,SUMIFS(Calc!$BT:$BT,Calc!$C:$C,$A6,Calc!$D:$D,"F")/C6,0) -> 51013.535 | AM6: =IF(AK6>0,(AK6-AL6)/AK6,0) -> 0.10750996 | AN6: =IF(D6>0,SUMIFS(Calc!$BU:$BU,Calc!$C:$C,$A6,Calc!$D:$D,"M")/D6,0) -> 58547.605 | AO6: =IF(C6>0,SUMIFS(Calc!$BU:$BU,Calc!$C:$C,$A6,Calc!$D:$D,"F")/C6,0) -> 52621.372 | AP6: =IF(AN6>0,(AN6-AO6)/AN6,0) -> 0.10122076 | AQ6: =IF(AND(AI6>0,AJ6>0),0,AE6) -> 0 | AR6: =SUMIFS(Calc!$BU:$BU,Calc!$C:$C,$A6) -> 2112210.6 | AS6: =SUMIFS(Calc!$BV:$BV,Calc!$C:$C,$A6) -> 14715813 | AT6: =SUMIFS(Calc!$BW:$BW,Calc!$C:$C,$A6) -> 12691167 | AU6: =IF(B6>0,AS6-H6*AR6/B6,0) -> 652936.85 | AV6: =IF(B6>0,AT6-I6*AR6/B6,0) -> 874383.81 | AW6: =IF(V6=1,(AU6*Q6-AV6*R6)/U6,0) -> 7385.4471 | AX6: =IF(V6=1,(AV6*P6-AU6*R6)/U6,0) -> 411.63666 | AY6: =IF(AND(V6=1,C6>0,D6>0,AN6>0),(AW6*(Y6-Z6)+AX6*(AA6-AB6))/AN6,0) -> 0.099330899 | AZ6: =IF(AP6>=0,MAX(0,MIN(AY6,AP6)),MIN(0,MAX(AY6,AP6))) -> 0.099330899 | BA6: =AP6-AZ6 -> 0.0018898639
A7: Legal | B7: =COUNTIFS(Calc!$C:$C,$A7) -> 8 | C7: =COUNTIFS(Calc!$C:$C,$A7,Calc!$D:$D,"F") -> 3 | D7: =COUNTIFS(Calc!$C:$C,$A7,Calc!$D:$D,"M") -> 5 | E7: =IF(D7>0,SUMIFS(Calc!$Q:$Q,Calc!$C:$C,$A7,Calc!$D:$D,"M")/D7,0) -> 88370.57 | F7: =IF(C7>0,SUMIFS(Calc!$Q:$Q,Calc!$C:$C,$A7,Calc!$D:$D,"F")/C7,0) -> 78581.026 | G7: =IF(AND(C7>0,D7>0,E7>0),(E7-F7)/E7,0) -> 0.11077833 | H7: =SUMIFS(Calc!$E:$E,Calc!$C:$C,$A7) -> 81 | I7: =SUMIFS(Calc!$P:$P,Calc!$C:$C,$A7) -> 44.276523 | J7: =SUMIFS(Calc!$Q:$Q,Calc!$C:$C,$A7) -> 677595.93 | K7: =SUMIFS(Calc!$R:$R,Calc!$C:$C,$A7) -> 827 | L7: =SUMIFS(Calc!$S:$S,Calc!$C:$C,$A7) -> 299.01135 | M7: =SUMIFS(Calc!$T:$T,Calc!$C:$C,$A7) -> 458.29158 | N7: =SUMIFS(Calc!$U:$U,Calc!$C:$C,$A7) -> 6956476.2 | O7: =SUMIFS(Calc!$V:$V,Calc!$C:$C,$A7) -> 3983109.1 | P7: =IF(B7>0,K7-H7^2/B7,0) -> 6.875 | Q7: =IF(B7>0,L7-I7^2/B7,0) -> 53.960044 | R7: =IF(B7>0,M7-H7*I7/B7,0) -> 9.9917864 | S7: =IF(B7>0,N7-H7*J7/B7,0) -> 95817.447 | T7: =IF(B7>0,O7-I7*J7/B7,0) -> 232910.11 | U7: =P7*Q7-R7^2 -> 271.13951 | V7: =IF(AND(B7>=4,ABS(U7)>0.000000001),1,0) -> 1 | W7: =IF(V7=1,(S7*Q7-T7*R7)/U7,0) -> 10485.84 | X7: =IF(V7=1,(T7*P7-S7*R7)/U7,0) -> 2374.68 | Y7: =IF(D7>0,SUMIFS(Calc!$E:$E,Calc!$C:$C,$A7,Calc!$D:$D,"M")/D7,0) -> 10.4 | Z7: =IF(C7>0,SUMIFS(Calc!$E:$E,Calc!$C:$C,$A7,Calc!$D:$D,"F")/C7,0) -> 9.6666667 | AA7: =IF(D7>0,SUMIFS(Calc!$P:$P,Calc!$C:$C,$A7,Calc!$D:$D,"M")/D7,0) -> 5.1953457 | AB7: =IF(C7>0,SUMIFS(Calc!$P:$P,Calc!$C:$C,$A7,Calc!$D:$D,"F")/C7,0) -> 6.0999316 | AC7: =IF(AND(V7=1,C7>0,D7>0,E7>0),(W7*(Y7-Z7)+X7*(AA7-AB7))/E7,0) -> 0.062707689 | AD7: =IF(G7>=0,MAX(0,MIN(AC7,G7)),MIN(0,MAX(AC7,G7))) -> 0.062707689 | AE7: =G7-AD7 -> 0.048070638 | AF7: =INT((B7+1)/2) -> 4 | AG7: =INT(B7/2)+1 -> 5 | AH7: =(SUMIFS(Calc!$Q:$Q,Calc!$C:$C,$A7,Calc!$X:$X,AF7)+SUMIFS(Calc!$Q:$Q,Calc!$C:$C,$A7,Calc!$X:$X,AG7))/2 -> 80332.662 | AI7: =IF(AND(G7>=0,AE7>0.000000000001),AE7*E7*C7,0) -> 12744.089 | AJ7: =SUMIFS(Calc!$AA:$AA,Calc!$C:$C,$A7) -> 6404.207 | AK7: =IF(D7>0,SUMIFS(Calc!$BT:$BT,Calc!$C:$C,$A7,Calc!$D:$D,"M")/D7,0) -> 88370.57 | AL7: =IF(C7>0,SUMIFS(Calc!$BT:$BT,Calc!$C:$C,$A7,Calc!$D:$D,"F")/C7,0) -> 82829.056 | AM7: =IF(AK7>0,(AK7-AL7)/AK7,0) -> 0.062707689 | AN7: =IF(D7>0,SUMIFS(Calc!$BU:$BU,Calc!$C:$C,$A7,Calc!$D:$D,"M")/D7,0) -> 92652.76 | AO7: =IF(C7>0,SUMIFS(Calc!$BU:$BU,Calc!$C:$C,$A7,Calc!$D:$D,"F")/C7,0) -> 89540.367 | AP7: =IF(AN7>0,(AN7-AO7)/AN7,0) -> 0.033592008 | AQ7: =IF(AND(AI7>0,AJ7>0),0,AE7) -> 0 | AR7: =SUMIFS(Calc!$BU:$BU,Calc!$C:$C,$A7) -> 731884.9 | AS7: =SUMIFS(Calc!$BV:$BV,Calc!$C:$C,$A7) -> 7490546.7 | AT7: =SUMIFS(Calc!$BW:$BW,Calc!$C:$C,$A7) -> 4248745.9 | AU7: =IF(B7>0,AS7-H7*AR7/B7,0) -> 80212.116 | AV7: =IF(B7>0,AT7-I7*AR7/B7,0) -> 198081.11 | AW7: =IF(V7=1,(AU7*Q7-AV7*R7)/U7,0) -> 8663.6771 | AX7: =IF(V7=1,(AV7*P7-AU7*R7)/U7,0) -> 2066.631 | AY7: =IF(AND(V7=1,C7>0,D7>0,AN7>0),(AW7*(Y7-Z7)+AX7*(AA7-AB7))/AN7,0) -> 0.048394866 | AZ7: =IF(AP7>=0,MAX(0,MIN(AY7,AP7)),MIN(0,MAX(AY7,AP7))) -> 0.033592008 | BA7: =AP7-AZ7 -> 0
A8: Marketing | B8: =COUNTIFS(Calc!$C:$C,$A8) -> 26 | C8: =COUNTIFS(Calc!$C:$C,$A8,Calc!$D:$D,"F") -> 12 | D8: =COUNTIFS(Calc!$C:$C,$A8,Calc!$D:$D,"M") -> 14 | E8: =IF(D8>0,SUMIFS(Calc!$Q:$Q,Calc!$C:$C,$A8,Calc!$D:$D,"M")/D8,0) -> 68396.187 | F8: =IF(C8>0,SUMIFS(Calc!$Q:$Q,Calc!$C:$C,$A8,Calc!$D:$D,"F")/C8,0) -> 77723.673 | G8: =IF(AND(C8>0,D8>0,E8>0),(E8-F8)/E8,0) -> -0.13637435 | H8: =SUMIFS(Calc!$E:$E,Calc!$C:$C,$A8) -> 223 | I8: =SUMIFS(Calc!$P:$P,Calc!$C:$C,$A8) -> 204.30664 | J8: =SUMIFS(Calc!$Q:$Q,Calc!$C:$C,$A8) -> 1890230.7 | K8: =SUMIFS(Calc!$R:$R,Calc!$C:$C,$A8) -> 1957 | L8: =SUMIFS(Calc!$S:$S,Calc!$C:$C,$A8) -> 1795.2459 | M8: =SUMIFS(Calc!$T:$T,Calc!$C:$C,$A8) -> 1821.7522 | N8: =SUMIFS(Calc!$U:$U,Calc!$C:$C,$A8) -> 16567959 | O8: =SUMIFS(Calc!$V:$V,Calc!$C:$C,$A8) -> 15479768 | P8: =IF(B8>0,K8-H8^2/B8,0) -> 44.346154 | Q8: =IF(B8>0,L8-I8^2/B8,0) -> 189.81502 | R8: =IF(B8>0,M8-H8*I8/B8,0) -> 69.429895 | S8: =IF(B8>0,N8-H8*J8/B8,0) -> 355595.86 | T8: =IF(B8>0,O8-I8*J8/B8,0) -> 626434.5 | U8: =P8*Q8-R8^2 -> 3597.0556 | V8: =IF(AND(B8>=4,ABS(U8)>0.000000001),1,0) -> 1 | W8: =IF(V8=1,(S8*Q8-T8*R8)/U8,0) -> 6673.2784 | X8: =IF(V8=1,(T8*P8-S8*R8)/U8,0) -> 859.30756 | Y8: =IF(D8>0,SUMIFS(Calc!$E:$E,Calc!$C:$C,$A8,Calc!$D:$D,"M")/D8,0) -> 8.3571429 | Z8: =IF(C8>0,SUMIFS(Calc!$E:$E,Calc!$C:$C,$A8,Calc!$D:$D,"F")/C8,0) -> 8.8333333 | AA8: =IF(D8>0,SUMIFS(Calc!$P:$P,Calc!$C:$C,$A8,Calc!$D:$D,"M")/D8,0) -> 7.2359441 | AB8: =IF(C8>0,SUMIFS(Calc!$P:$P,Calc!$C:$C,$A8,Calc!$D:$D,"F")/C8,0) -> 8.5836185 | AC8: =IF(AND(V8=1,C8>0,D8>0,E8>0),(W8*(Y8-Z8)+X8*(AA8-AB8))/E8,0) -> -0.063392692 | AD8: =IF(G8>=0,MAX(0,MIN(AC8,G8)),MIN(0,MAX(AC8,G8))) -> -0.063392692 | AE8: =G8-AD8 -> -0.072981661 | AF8: =INT((B8+1)/2) -> 13 | AG8: =INT(B8/2)+1 -> 14 | AH8: =(SUMIFS(Calc!$Q:$Q,Calc!$C:$C,$A8,Calc!$X:$X,AF8)+SUMIFS(Calc!$Q:$Q,Calc!$C:$C,$A8,Calc!$X:$X,AG8))/2 -> 75605.018 | AI8: =IF(AND(G8>=0,AE8>0.000000000001),AE8*E8*C8,0) -> 0 | AJ8: =SUMIFS(Calc!$AA:$AA,Calc!$C:$C,$A8) -> 0 | AK8: =IF(D8>0,SUMIFS(Calc!$BT:$BT,Calc!$C:$C,$A8,Calc!$D:$D,"M")/D8,0) -> 68396.187 | AL8: =IF(C8>0,SUMIFS(Calc!$BT:$BT,Calc!$C:$C,$A8,Calc!$D:$D,"F")/C8,0) -> 77723.673 | AM8: =IF(AK8>0,(AK8-AL8)/AK8,0) -> -0.13637435 | AN8: =IF(D8>0,SUMIFS(Calc!$BU:$BU,Calc!$C:$C,$A8,Calc!$D:$D,"M")/D8,0) -> 74102.994 | AO8: =IF(C8>0,SUMIFS(Calc!$BU:$BU,Calc!$C:$C,$A8,Calc!$D:$D,"F")/C8,0) -> 80239.983 | AP8: =IF(AN8>0,(AN8-AO8)/AN8,0) -> -0.082817019 | AQ8: =IF(AND(AI8>0,AJ8>0),0,AE8) -> -0.072981661 | AR8: =SUMIFS(Calc!$BU:$BU,Calc!$C:$C,$A8) -> 2000321.7 | AS8: =SUMIFS(Calc!$BV:$BV,Calc!$C:$C,$A8) -> 17586574 | AT8: =SUMIFS(Calc!$BW:$BW,Calc!$C:$C,$A8) -> 16398310 | AU8: =IF(B8>0,AS8-H8*AR8/B8,0) -> 429968.89 | AV8: =IF(B8>0,AT8-I8*AR8/B8,0) -> 679886.64 | AW8: =IF(V8=1,(AU8*Q8-AV8*R8)/U8,0) -> 9566.1836 | AX8: =IF(V8=1,(AV8*P8-AU8*R8)/U8,0) -> 82.751679 | AY8: =IF(AND(V8=1,C8>0,D8>0,AN8>0),(AW8*(Y8-Z8)+AX8*(AA8-AB8))/AN8,0) -> -0.062977858 | AZ8: =IF(AP8>=0,MAX(0,MIN(AY8,AP8)),MIN(0,MAX(AY8,AP8))) -> -0.062977858 | BA8: =AP8-AZ8 -> -0.019839161
A9: Manufacturing | B9: =COUNTIFS(Calc!$C:$C,$A9) -> 40 | C9: =COUNTIFS(Calc!$C:$C,$A9,Calc!$D:$D,"F") -> 19 | D9: =COUNTIFS(Calc!$C:$C,$A9,Calc!$D:$D,"M") -> 21 | E9: =IF(D9>0,SUMIFS(Calc!$Q:$Q,Calc!$C:$C,$A9,Calc!$D:$D,"M")/D9,0) -> 54294.289 | F9: =IF(C9>0,SUMIFS(Calc!$Q:$Q,Calc!$C:$C,$A9,Calc!$D:$D,"F")/C9,0) -> 45818.939 | G9: =IF(AND(C9>0,D9>0,E9>0),(E9-F9)/E9,0) -> 0.1561002 | H9: =SUMIFS(Calc!$E:$E,Calc!$C:$C,$A9) -> 230 | I9: =SUMIFS(Calc!$P:$P,Calc!$C:$C,$A9) -> 411.10198 | J9: =SUMIFS(Calc!$Q:$Q,Calc!$C:$C,$A9) -> 2010739.9 | K9: =SUMIFS(Calc!$R:$R,Calc!$C:$C,$A9) -> 1386 | L9: =SUMIFS(Calc!$S:$S,Calc!$C:$C,$A9) -> 5002.5323 | M9: =SUMIFS(Calc!$T:$T,Calc!$C:$C,$A9) -> 2527.0062 | N9: =SUMIFS(Calc!$U:$U,Calc!$C:$C,$A9) -> 12046070 | O9: =SUMIFS(Calc!$V:$V,Calc!$C:$C,$A9) -> 22170648 | P9: =IF(B9>0,K9-H9^2/B9,0) -> 63.5 | Q9: =IF(B9>0,L9-I9^2/B9,0) -> 777.41125 | R9: =IF(B9>0,M9-H9*I9/B9,0) -> 163.16975 | S9: =IF(B9>0,N9-H9*J9/B9,0) -> 484315.98 | T9: =IF(B9>0,O9-I9*J9/B9,0) -> 1505169 | U9: =P9*Q9-R9^2 -> 22741.248 | V9: =IF(AND(B9>=4,ABS(U9)>0.000000001),1,0) -> 1 | W9: =IF(V9=1,(S9*Q9-T9*R9)/U9,0) -> 5756.705 | X9: =IF(V9=1,(T9*P9-S9*R9)/U9,0) -> 727.86296 | Y9: =IF(D9>0,SUMIFS(Calc!$E:$E,Calc!$C:$C,$A9,Calc!$D:$D,"M")/D9,0) -> 6 | Z9: =IF(C9>0,SUMIFS(Calc!$E:$E,Calc!$C:$C,$A9,Calc!$D:$D,"F")/C9,0) -> 5.4736842 | AA9: =IF(D9>0,SUMIFS(Calc!$P:$P,Calc!$C:$C,$A9,Calc!$D:$D,"M")/D9,0) -> 11.471464 | AB9: =IF(C9>0,SUMIFS(Calc!$P:$P,Calc!$C:$C,$A9,Calc!$D:$D,"F")/C9,0) -> 8.9579596 | AC9: =IF(AND(V9=1,C9>0,D9>0,E9>0),(W9*(Y9-Z9)+X9*(AA9-AB9))/E9,0) -> 0.089499871 | AD9: =IF(G9>=0,MAX(0,MIN(AC9,G9)),MIN(0,MAX(AC9,G9))) -> 0.089499871 | AE9: =G9-AD9 -> 0.066600326 | AF9: =INT((B9+1)/2) -> 20 | AG9: =INT(B9/2)+1 -> 21 | AH9: =(SUMIFS(Calc!$Q:$Q,Calc!$C:$C,$A9,Calc!$X:$X,AF9)+SUMIFS(Calc!$Q:$Q,Calc!$C:$C,$A9,Calc!$X:$X,AG9))/2 -> 48803.731 | AI9: =IF(AND(G9>=0,AE9>0.000000000001),AE9*E9*C9,0) -> 68704.329 | AJ9: =SUMIFS(Calc!$AA:$AA,Calc!$C:$C,$A9) -> 105697.83 | AK9: =IF(D9>0,SUMIFS(Calc!$BT:$BT,Calc!$C:$C,$A9,Calc!$D:$D,"M")/D9,0) -> 54294.289 | AL9: =IF(C9>0,SUMIFS(Calc!$BT:$BT,Calc!$C:$C,$A9,Calc!$D:$D,"F")/C9,0) -> 49434.957 | AM9: =IF(AK9>0,(AK9-AL9)/AK9,0) -> 0.089499871 | AN9: =IF(D9>0,SUMIFS(Calc!$BU:$BU,Calc!$C:$C,$A9,Calc!$D:$D,"M")/D9,0) -> 54445.174 | AO9: =IF(C9>0,SUMIFS(Calc!$BU:$BU,Calc!$C:$C,$A9,Calc!$D:$D,"F")/C9,0) -> 50691.717 | AP9: =IF(AN9>0,(AN9-AO9)/AN9,0) -> 0.068940134 | AQ9: =IF(AND(AI9>0,AJ9>0),0,AE9) -> 0 | AR9: =SUMIFS(Calc!$BU:$BU,Calc!$C:$C,$A9) -> 2106491.3 | AS9: =SUMIFS(Calc!$BV:$BV,Calc!$C:$C,$A9) -> 12531895 | AT9: =SUMIFS(Calc!$BW:$BW,Calc!$C:$C,$A9) -> 22938437 | AU9: =IF(B9>0,AS9-H9*AR9/B9,0) -> 419569.74 | AV9: =IF(B9>0,AT9-I9*AR9/B9,0) -> 1288868.6 | AW9: =IF(V9=1,(AU9*Q9-AV9*R9)/U9,0) -> 5095.3172 | AX9: =IF(V9=1,(AV9*P9-AU9*R9)/U9,0) -> 588.44918 | AY9: =IF(AND(V9=1,C9>0,D9>0,AN9>0),(AW9*(Y9-Z9)+AX9*(AA9-AB9))/AN9,0) -> 0.076422122 | AZ9: =IF(AP9>=0,MAX(0,MIN(AY9,AP9)),MIN(0,MAX(AY9,AP9))) -> 0.068940134 | BA9: =AP9-AZ9 -> 0
A10: Customer Support | B10: =COUNTIFS(Calc!$C:$C,$A10) -> 30 | C10: =COUNTIFS(Calc!$C:$C,$A10,Calc!$D:$D,"F") -> 13 | D10: =COUNTIFS(Calc!$C:$C,$A10,Calc!$D:$D,"M") -> 17 | E10: =IF(D10>0,SUMIFS(Calc!$Q:$Q,Calc!$C:$C,$A10,Calc!$D:$D,"M")/D10,0) -> 40975.545 | F10: =IF(C10>0,SUMIFS(Calc!$Q:$Q,Calc!$C:$C,$A10,Calc!$D:$D,"F")/C10,0) -> 34745.224 | G10: =IF(AND(C10>0,D10>0,E10>0),(E10-F10)/E10,0) -> 0.15204975 | H10: =SUMIFS(Calc!$E:$E,Calc!$C:$C,$A10) -> 129 | I10: =SUMIFS(Calc!$P:$P,Calc!$C:$C,$A10) -> 190.04244 | J10: =SUMIFS(Calc!$Q:$Q,Calc!$C:$C,$A10) -> 1148272.2 | K10: =SUMIFS(Calc!$R:$R,Calc!$C:$C,$A10) -> 589 | L10: =SUMIFS(Calc!$S:$S,Calc!$C:$C,$A10) -> 1474.0321 | M10: =SUMIFS(Calc!$T:$T,Calc!$C:$C,$A10) -> 889.92745 | N10: =SUMIFS(Calc!$U:$U,Calc!$C:$C,$A10) -> 5166324.9 | O10: =SUMIFS(Calc!$V:$V,Calc!$C:$C,$A10) -> 7877652.6 | P10: =IF(B10>0,K10-H10^2/B10,0) -> 34.3 | Q10: =IF(B10>0,L10-I10^2/B10,0) -> 270.16119 | R10: =IF(B10>0,M10-H10*I10/B10,0) -> 72.744969 | S10: =IF(B10>0,N10-H10*J10/B10,0) -> 228754.58 | T10: =IF(B10>0,O10-I10*J10/B10,0) -> 603637.9 | U10: =P10*Q10-R10^2 -> 3974.6982 | V10: =IF(AND(B10>=4,ABS(U10)>0.000000001),1,0) -> 1 | W10: =IF(V10=1,(S10*Q10-T10*R10)/U10,0) -> 4500.7161 | X10: =IF(V10=1,(T10*P10-S10*R10)/U10,0) -> 1022.4764 | Y10: =IF(D10>0,SUMIFS(Calc!$E:$E,Calc!$C:$C,$A10,Calc!$D:$D,"M")/D10,0) -> 4.6470588 | Z10: =IF(C10>0,SUMIFS(Calc!$E:$E,Calc!$C:$C,$A10,Calc!$D:$D,"F")/C10,0) -> 3.8461538 | AA10: =IF(D10>0,SUMIFS(Calc!$P:$P,Calc!$C:$C,$A10,Calc!$D:$D,"M")/D10,0) -> 6.9998792 | AB10: =IF(C10>0,SUMIFS(Calc!$P:$P,Calc!$C:$C,$A10,Calc!$D:$D,"F")/C10,0) -> 5.4649608 | AC10: =IF(AND(V10=1,C10>0,D10>0,E10>0),(W10*(Y10-Z10)+X10*(AA10-AB10))/E10,0) -> 0.126272 | AD10: =IF(G10>=0,MAX(0,MIN(AC10,G10)),MIN(0,MAX(AC10,G10))) -> 0.126272 | AE10: =G10-AD10 -> 0.025777752 | AF10: =INT((B10+1)/2) -> 15 | AG10: =INT(B10/2)+1 -> 16 | AH10: =(SUMIFS(Calc!$Q:$Q,Calc!$C:$C,$A10,Calc!$X:$X,AF10)+SUMIFS(Calc!$Q:$Q,Calc!$C:$C,$A10,Calc!$X:$X,AG10))/2 -> 37853.452 | AI10: =IF(AND(G10>=0,AE10>0.000000000001),AE10*E10*C10,0) -> 13731.346 | AJ10: =SUMIFS(Calc!$AA:$AA,Calc!$C:$C,$A10) -> 57617.545 | AK10: =IF(D10>0,SUMIFS(Calc!$BT:$BT,Calc!$C:$C,$A10,Calc!$D:$D,"M")/D10,0) -> 40975.545 | AL10: =IF(C10>0,SUMIFS(Calc!$BT:$BT,Calc!$C:$C,$A10,Calc!$D:$D,"F")/C10,0) -> 35801.481 | AM10: =IF(AK10>0,(AK10-AL10)/AK10,0) -> 0.126272 | AN10: =IF(D10>0,SUMIFS(Calc!$BU:$BU,Calc!$C:$C,$A10,Calc!$D:$D,"M")/D10,0) -> 42382.121 | AO10: =IF(C10>0,SUMIFS(Calc!$BU:$BU,Calc!$C:$C,$A10,Calc!$D:$D,"F")/C10,0) -> 37590.237 | AP10: =IF(AN10>0,(AN10-AO10)/AN10,0) -> 0.11306382 | AQ10: =IF(AND(AI10>0,AJ10>0),0,AE10) -> 0 | AR10: =SUMIFS(Calc!$BU:$BU,Calc!$C:$C,$A10) -> 1209169.1 | AS10: =SUMIFS(Calc!$BV:$BV,Calc!$C:$C,$A10) -> 5415853.8 | AT10: =SUMIFS(Calc!$BW:$BW,Calc!$C:$C,$A10) -> 8186338.2 | AU10: =IF(B10>0,AS10-H10*AR10/B10,0) -> 216426.46 | AV10: =IF(B10>0,AT10-I10*AR10/B10,0) -> 526556.5 | AW10: =IF(V10=1,(AU10*Q10-AV10*R10)/U10,0) -> 5073.5158 | AX10: =IF(V10=1,(AV10*P10-AU10*R10)/U10,0) -> 582.92515 | AY10: =IF(AND(V10=1,C10>0,D10>0,AN10>0),(AW10*(Y10-Z10)+AX10*(AA10-AB10))/AN10,0) -> 0.11698675 | AZ10: =IF(AP10>=0,MAX(0,MIN(AY10,AP10)),MIN(0,MAX(AY10,AP10))) -> 0.11306382 | BA10: =AP10-AZ10 -> 0
A11: Sales | B11: =COUNTIFS(Calc!$C:$C,$A11) -> 26 | C11: =COUNTIFS(Calc!$C:$C,$A11,Calc!$D:$D,"F") -> 13 | D11: =COUNTIFS(Calc!$C:$C,$A11,Calc!$D:$D,"M") -> 13 | E11: =IF(D11>0,SUMIFS(Calc!$Q:$Q,Calc!$C:$C,$A11,Calc!$D:$D,"M")/D11,0) -> 90492.929 | F11: =IF(C11>0,SUMIFS(Calc!$Q:$Q,Calc!$C:$C,$A11,Calc!$D:$D,"F")/C11,0) -> 82623.244 | G11: =IF(AND(C11>0,D11>0,E11>0),(E11-F11)/E11,0) -> 0.086964632 | H11: =SUMIFS(Calc!$E:$E,Calc!$C:$C,$A11) -> 252 | I11: =SUMIFS(Calc!$P:$P,Calc!$C:$C,$A11) -> 160.19165 | J11: =SUMIFS(Calc!$Q:$Q,Calc!$C:$C,$A11) -> 2250510.2 | K11: =SUMIFS(Calc!$R:$R,Calc!$C:$C,$A11) -> 2484 | L11: =SUMIFS(Calc!$S:$S,Calc!$C:$C,$A11) -> 1269.4043 | M11: =SUMIFS(Calc!$T:$T,Calc!$C:$C,$A11) -> 1647.3101 | N11: =SUMIFS(Calc!$U:$U,Calc!$C:$C,$A11) -> 22402660 | O11: =SUMIFS(Calc!$V:$V,Calc!$C:$C,$A11) -> 15303025 | P11: =IF(B11>0,K11-H11^2/B11,0) -> 41.538462 | Q11: =IF(B11>0,L11-I11^2/B11,0) -> 282.42871 | R11: =IF(B11>0,M11-H11*I11/B11,0) -> 94.683304 | S11: =IF(B11>0,N11-H11*J11/B11,0) -> 590022.16 | T11: =IF(B11>0,O11-I11*J11/B11,0) -> 1437142.2 | U11: =P11*Q11-R11^2 -> 2766.7261 | V11: =IF(AND(B11>=4,ABS(U11)>0.000000001),1,0) -> 1 | W11: =IF(V11=1,(S11*Q11-T11*R11)/U11,0) -> 11047.653 | X11: =IF(V11=1,(T11*P11-S11*R11)/U11,0) -> 1384.8235 | Y11: =IF(D11>0,SUMIFS(Calc!$E:$E,Calc!$C:$C,$A11,Calc!$D:$D,"M")/D11,0) -> 9.6923077 | Z11: =IF(C11>0,SUMIFS(Calc!$E:$E,Calc!$C:$C,$A11,Calc!$D:$D,"F")/C11,0) -> 9.6923077 | AA11: =IF(D11>0,SUMIFS(Calc!$P:$P,Calc!$C:$C,$A11,Calc!$D:$D,"M")/D11,0) -> 6.1612173 | AB11: =IF(C11>0,SUMIFS(Calc!$P:$P,Calc!$C:$C,$A11,Calc!$D:$D,"F")/C11,0) -> 6.1612173 | AC11: =IF(AND(V11=1,C11>0,D11>0,E11>0),(W11*(Y11-Z11)+X11*(AA11-AB11))/E11,0) -> 0 | AD11: =IF(G11>=0,MAX(0,MIN(AC11,G11)),MIN(0,MAX(AC11,G11))) -> 0 | AE11: =G11-AD11 -> 0.086964632 | AF11: =INT((B11+1)/2) -> 13 | AG11: =INT(B11/2)+1 -> 14 | AH11: =(SUMIFS(Calc!$Q:$Q,Calc!$C:$C,$A11,Calc!$X:$X,AF11)+SUMIFS(Calc!$Q:$Q,Calc!$C:$C,$A11,Calc!$X:$X,AG11))/2 -> 85035.918 | AI11: =IF(AND(G11>=0,AE11>0.000000000001),AE11*E11*C11,0) -> 102305.9 | AJ11: =SUMIFS(Calc!$AA:$AA,Calc!$C:$C,$A11) -> 109270.76 | AK11: =IF(D11>0,SUMIFS(Calc!$BT:$BT,Calc!$C:$C,$A11,Calc!$D:$D,"M")/D11,0) -> 90492.929 | AL11: =IF(C11>0,SUMIFS(Calc!$BT:$BT,Calc!$C:$C,$A11,Calc!$D:$D,"F")/C11,0) -> 90492.929 | AM11: =IF(AK11>0,(AK11-AL11)/AK11,0) -> 0 | AN11: =IF(D11>0,SUMIFS(Calc!$BU:$BU,Calc!$C:$C,$A11,Calc!$D:$D,"M")/D11,0) -> 104399.12 | AO11: =IF(C11>0,SUMIFS(Calc!$BU:$BU,Calc!$C:$C,$A11,Calc!$D:$D,"F")/C11,0) -> 96182.02 | AP11: =IF(AN11>0,(AN11-AO11)/AN11,0) -> 0.078708557 | AQ11: =IF(AND(AI11>0,AJ11>0),0,AE11) -> 0 | AR11: =SUMIFS(Calc!$BU:$BU,Calc!$C:$C,$A11) -> 2607554.9 | AS11: =SUMIFS(Calc!$BV:$BV,Calc!$C:$C,$A11) -> 25858042 | AT11: =SUMIFS(Calc!$BW:$BW,Calc!$C:$C,$A11) -> 17454661 | AU11: =IF(B11>0,AS11-H11*AR11/B11,0) -> 584817.9 | AV11: =IF(B11>0,AT11-I11*AR11/B11,0) -> 1388949.1 | AW11: =IF(V11=1,(AU11*Q11-AV11*R11)/U11,0) -> 12165.668 | AX11: =IF(V11=1,(AV11*P11-AU11*R11)/U11,0) -> 839.37455 | AY11: =IF(AND(V11=1,C11>0,D11>0,AN11>0),(AW11*(Y11-Z11)+AX11*(AA11-AB11))/AN11,0) -> 0 | AZ11: =IF(AP11>=0,MAX(0,MIN(AY11,AP11)),MIN(0,MAX(AY11,AP11))) -> 0 | BA11: =AP11-AZ11 -> 0.078708557

Sheet Matrix
A1: Merit matrix: the result, computed person by person
A2: Rows: rating. Columns: compa-ratio (CR) zone after equity. Eligible staff only.
A5: Merit increase, % of eligible base payroll
B6: ="CR < "&TEXT(INDEX(Inputs!$B$31:$B$34,2),"0%") -> CR < 90% | C6: ="CR "&TEXT(INDEX(Inputs!$B$31:$B$34,2),"0%")&" to "&TEXT(INDEX(Inputs!$B$31:$B$34,3),"0%") -> CR 90% to 100% | D6: ="CR "&TEXT(INDEX(Inputs!$B$31:$B$34,3),"0%")&" to "&TEXT(INDEX(Inputs!$B$31:$B$34,4),"0%") -> CR 100% to 110% | E6: ="CR ≥ "&TEXT(INDEX(Inputs!$B$31:$B$34,4),"0%") -> CR ≥ 110%
A7: =INDEX(Inputs!$A$21:$A$25,1)&" "&INDEX(Inputs!$B$21:$B$25,1) -> 1 Unsatisfactory | B7: =IF(SUMIFS(Calc!$BM:$BM,Calc!$F:$F,INDEX(Inputs!$A$21:$A$25,1),Calc!$AJ:$AJ,1,Calc!$AH:$AH,1)>0,SUMIFS(Calc!$BJ:$BJ,Calc!$F:$F,INDEX(Inputs!$A$21:$A$25,1),Calc!$AJ:$AJ,1,Calc!$AH:$AH,1)/SUMIFS(Calc!$BM:$BM,Calc!$F:$F,INDEX(Inputs!$A$21:$A$25,1),Calc!$AJ:$AJ,1,Calc!$AH:$AH,1),0) -> 0 | C7: =IF(SUMIFS(Calc!$BM:$BM,Calc!$F:$F,INDEX(Inputs!$A$21:$A$25,1),Calc!$AJ:$AJ,2,Calc!$AH:$AH,1)>0,SUMIFS(Calc!$BJ:$BJ,Calc!$F:$F,INDEX(Inputs!$A$21:$A$25,1),Calc!$AJ:$AJ,2,Calc!$AH:$AH,1)/SUMIFS(Calc!$BM:$BM,Calc!$F:$F,INDEX(Inputs!$A$21:$A$25,1),Calc!$AJ:$AJ,2,Calc!$AH:$AH,1),0) -> 0 | D7: =IF(SUMIFS(Calc!$BM:$BM,Calc!$F:$F,INDEX(Inputs!$A$21:$A$25,1),Calc!$AJ:$AJ,3,Calc!$AH:$AH,1)>0,SUMIFS(Calc!$BJ:$BJ,Calc!$F:$F,INDEX(Inputs!$A$21:$A$25,1),Calc!$AJ:$AJ,3,Calc!$AH:$AH,1)/SUMIFS(Calc!$BM:$BM,Calc!$F:$F,INDEX(Inputs!$A$21:$A$25,1),Calc!$AJ:$AJ,3,Calc!$AH:$AH,1),0) -> 0 | E7: =IF(SUMIFS(Calc!$BM:$BM,Calc!$F:$F,INDEX(Inputs!$A$21:$A$25,1),Calc!$AJ:$AJ,4,Calc!$AH:$AH,1)>0,SUMIFS(Calc!$BJ:$BJ,Calc!$F:$F,INDEX(Inputs!$A$21:$A$25,1),Calc!$AJ:$AJ,4,Calc!$AH:$AH,1)/SUMIFS(Calc!$BM:$BM,Calc!$F:$F,INDEX(Inputs!$A$21:$A$25,1),Calc!$AJ:$AJ,4,Calc!$AH:$AH,1),0) -> 0
A8: =INDEX(Inputs!$A$21:$A$25,2)&" "&INDEX(Inputs!$B$21:$B$25,2) -> 2 Partially meets | B8: =IF(SUMIFS(Calc!$BM:$BM,Calc!$F:$F,INDEX(Inputs!$A$21:$A$25,2),Calc!$AJ:$AJ,1,Calc!$AH:$AH,1)>0,SUMIFS(Calc!$BJ:$BJ,Calc!$F:$F,INDEX(Inputs!$A$21:$A$25,2),Calc!$AJ:$AJ,1,Calc!$AH:$AH,1)/SUMIFS(Calc!$BM:$BM,Calc!$F:$F,INDEX(Inputs!$A$21:$A$25,2),Calc!$AJ:$AJ,1,Calc!$AH:$AH,1),0) -> 0.14889929 | C8: =IF(SUMIFS(Calc!$BM:$BM,Calc!$F:$F,INDEX(Inputs!$A$21:$A$25,2),Calc!$AJ:$AJ,2,Calc!$AH:$AH,1)>0,SUMIFS(Calc!$BJ:$BJ,Calc!$F:$F,INDEX(Inputs!$A$21:$A$25,2),Calc!$AJ:$AJ,2,Calc!$AH:$AH,1)/SUMIFS(Calc!$BM:$BM,Calc!$F:$F,INDEX(Inputs!$A$21:$A$25,2),Calc!$AJ:$AJ,2,Calc!$AH:$AH,1),0) -> 0.015002762 | D8: =IF(SUMIFS(Calc!$BM:$BM,Calc!$F:$F,INDEX(Inputs!$A$21:$A$25,2),Calc!$AJ:$AJ,3,Calc!$AH:$AH,1)>0,SUMIFS(Calc!$BJ:$BJ,Calc!$F:$F,INDEX(Inputs!$A$21:$A$25,2),Calc!$AJ:$AJ,3,Calc!$AH:$AH,1)/SUMIFS(Calc!$BM:$BM,Calc!$F:$F,INDEX(Inputs!$A$21:$A$25,2),Calc!$AJ:$AJ,3,Calc!$AH:$AH,1),0) -> 0 | E8: =IF(SUMIFS(Calc!$BM:$BM,Calc!$F:$F,INDEX(Inputs!$A$21:$A$25,2),Calc!$AJ:$AJ,4,Calc!$AH:$AH,1)>0,SUMIFS(Calc!$BJ:$BJ,Calc!$F:$F,INDEX(Inputs!$A$21:$A$25,2),Calc!$AJ:$AJ,4,Calc!$AH:$AH,1)/SUMIFS(Calc!$BM:$BM,Calc!$F:$F,INDEX(Inputs!$A$21:$A$25,2),Calc!$AJ:$AJ,4,Calc!$AH:$AH,1),0) -> 0
A9: =INDEX(Inputs!$A$21:$A$25,3)&" "&INDEX(Inputs!$B$21:$B$25,3) -> 3 Meets | B9: =IF(SUMIFS(Calc!$BM:$BM,Calc!$F:$F,INDEX(Inputs!$A$21:$A$25,3),Calc!$AJ:$AJ,1,Calc!$AH:$AH,1)>0,SUMIFS(Calc!$BJ:$BJ,Calc!$F:$F,INDEX(Inputs!$A$21:$A$25,3),Calc!$AJ:$AJ,1,Calc!$AH:$AH,1)/SUMIFS(Calc!$BM:$BM,Calc!$F:$F,INDEX(Inputs!$A$21:$A$25,3),Calc!$AJ:$AJ,1,Calc!$AH:$AH,1),0) -> 0.19074459 | C9: =IF(SUMIFS(Calc!$BM:$BM,Calc!$F:$F,INDEX(Inputs!$A$21:$A$25,3),Calc!$AJ:$AJ,2,Calc!$AH:$AH,1)>0,SUMIFS(Calc!$BJ:$BJ,Calc!$F:$F,INDEX(Inputs!$A$21:$A$25,3),Calc!$AJ:$AJ,2,Calc!$AH:$AH,1)/SUMIFS(Calc!$BM:$BM,Calc!$F:$F,INDEX(Inputs!$A$21:$A$25,3),Calc!$AJ:$AJ,2,Calc!$AH:$AH,1),0) -> 0.043052849 | D9: =IF(SUMIFS(Calc!$BM:$BM,Calc!$F:$F,INDEX(Inputs!$A$21:$A$25,3),Calc!$AJ:$AJ,3,Calc!$AH:$AH,1)>0,SUMIFS(Calc!$BJ:$BJ,Calc!$F:$F,INDEX(Inputs!$A$21:$A$25,3),Calc!$AJ:$AJ,3,Calc!$AH:$AH,1)/SUMIFS(Calc!$BM:$BM,Calc!$F:$F,INDEX(Inputs!$A$21:$A$25,3),Calc!$AJ:$AJ,3,Calc!$AH:$AH,1),0) -> 0 | E9: =IF(SUMIFS(Calc!$BM:$BM,Calc!$F:$F,INDEX(Inputs!$A$21:$A$25,3),Calc!$AJ:$AJ,4,Calc!$AH:$AH,1)>0,SUMIFS(Calc!$BJ:$BJ,Calc!$F:$F,INDEX(Inputs!$A$21:$A$25,3),Calc!$AJ:$AJ,4,Calc!$AH:$AH,1)/SUMIFS(Calc!$BM:$BM,Calc!$F:$F,INDEX(Inputs!$A$21:$A$25,3),Calc!$AJ:$AJ,4,Calc!$AH:$AH,1),0) -> 0
A10: =INDEX(Inputs!$A$21:$A$25,4)&" "&INDEX(Inputs!$B$21:$B$25,4) -> 4 Exceeds | B10: =IF(SUMIFS(Calc!$BM:$BM,Calc!$F:$F,INDEX(Inputs!$A$21:$A$25,4),Calc!$AJ:$AJ,1,Calc!$AH:$AH,1)>0,SUMIFS(Calc!$BJ:$BJ,Calc!$F:$F,INDEX(Inputs!$A$21:$A$25,4),Calc!$AJ:$AJ,1,Calc!$AH:$AH,1)/SUMIFS(Calc!$BM:$BM,Calc!$F:$F,INDEX(Inputs!$A$21:$A$25,4),Calc!$AJ:$AJ,1,Calc!$AH:$AH,1),0) -> 0.20824508 | C10: =IF(SUMIFS(Calc!$BM:$BM,Calc!$F:$F,INDEX(Inputs!$A$21:$A$25,4),Calc!$AJ:$AJ,2,Calc!$AH:$AH,1)>0,SUMIFS(Calc!$BJ:$BJ,Calc!$F:$F,INDEX(Inputs!$A$21:$A$25,4),Calc!$AJ:$AJ,2,Calc!$AH:$AH,1)/SUMIFS(Calc!$BM:$BM,Calc!$F:$F,INDEX(Inputs!$A$21:$A$25,4),Calc!$AJ:$AJ,2,Calc!$AH:$AH,1),0) -> 0.11082304 | D10: =IF(SUMIFS(Calc!$BM:$BM,Calc!$F:$F,INDEX(Inputs!$A$21:$A$25,4),Calc!$AJ:$AJ,3,Calc!$AH:$AH,1)>0,SUMIFS(Calc!$BJ:$BJ,Calc!$F:$F,INDEX(Inputs!$A$21:$A$25,4),Calc!$AJ:$AJ,3,Calc!$AH:$AH,1)/SUMIFS(Calc!$BM:$BM,Calc!$F:$F,INDEX(Inputs!$A$21:$A$25,4),Calc!$AJ:$AJ,3,Calc!$AH:$AH,1),0) -> 0.020195059 | E10: =IF(SUMIFS(Calc!$BM:$BM,Calc!$F:$F,INDEX(Inputs!$A$21:$A$25,4),Calc!$AJ:$AJ,4,Calc!$AH:$AH,1)>0,SUMIFS(Calc!$BJ:$BJ,Calc!$F:$F,INDEX(Inputs!$A$21:$A$25,4),Calc!$AJ:$AJ,4,Calc!$AH:$AH,1)/SUMIFS(Calc!$BM:$BM,Calc!$F:$F,INDEX(Inputs!$A$21:$A$25,4),Calc!$AJ:$AJ,4,Calc!$AH:$AH,1),0) -> 0.0073102513
A11: =INDEX(Inputs!$A$21:$A$25,5)&" "&INDEX(Inputs!$B$21:$B$25,5) -> 5 Outstanding | B11: =IF(SUMIFS(Calc!$BM:$BM,Calc!$F:$F,INDEX(Inputs!$A$21:$A$25,5),Calc!$AJ:$AJ,1,Calc!$AH:$AH,1)>0,SUMIFS(Calc!$BJ:$BJ,Calc!$F:$F,INDEX(Inputs!$A$21:$A$25,5),Calc!$AJ:$AJ,1,Calc!$AH:$AH,1)/SUMIFS(Calc!$BM:$BM,Calc!$F:$F,INDEX(Inputs!$A$21:$A$25,5),Calc!$AJ:$AJ,1,Calc!$AH:$AH,1),0) -> 0.24960821 | C11: =IF(SUMIFS(Calc!$BM:$BM,Calc!$F:$F,INDEX(Inputs!$A$21:$A$25,5),Calc!$AJ:$AJ,2,Calc!$AH:$AH,1)>0,SUMIFS(Calc!$BJ:$BJ,Calc!$F:$F,INDEX(Inputs!$A$21:$A$25,5),Calc!$AJ:$AJ,2,Calc!$AH:$AH,1)/SUMIFS(Calc!$BM:$BM,Calc!$F:$F,INDEX(Inputs!$A$21:$A$25,5),Calc!$AJ:$AJ,2,Calc!$AH:$AH,1),0) -> 0.15197853 | D11: =IF(SUMIFS(Calc!$BM:$BM,Calc!$F:$F,INDEX(Inputs!$A$21:$A$25,5),Calc!$AJ:$AJ,3,Calc!$AH:$AH,1)>0,SUMIFS(Calc!$BJ:$BJ,Calc!$F:$F,INDEX(Inputs!$A$21:$A$25,5),Calc!$AJ:$AJ,3,Calc!$AH:$AH,1)/SUMIFS(Calc!$BM:$BM,Calc!$F:$F,INDEX(Inputs!$A$21:$A$25,5),Calc!$AJ:$AJ,3,Calc!$AH:$AH,1),0) -> 0.051768804 | E11: =IF(SUMIFS(Calc!$BM:$BM,Calc!$F:$F,INDEX(Inputs!$A$21:$A$25,5),Calc!$AJ:$AJ,4,Calc!$AH:$AH,1)>0,SUMIFS(Calc!$BJ:$BJ,Calc!$F:$F,INDEX(Inputs!$A$21:$A$25,5),Calc!$AJ:$AJ,4,Calc!$AH:$AH,1)/SUMIFS(Calc!$BM:$BM,Calc!$F:$F,INDEX(Inputs!$A$21:$A$25,5),Calc!$AJ:$AJ,4,Calc!$AH:$AH,1),0) -> 0
A14: Headcount
B15: ="CR < "&TEXT(INDEX(Inputs!$B$31:$B$34,2),"0%") -> CR < 90% | C15: ="CR "&TEXT(INDEX(Inputs!$B$31:$B$34,2),"0%")&" to "&TEXT(INDEX(Inputs!$B$31:$B$34,3),"0%") -> CR 90% to 100% | D15: ="CR "&TEXT(INDEX(Inputs!$B$31:$B$34,3),"0%")&" to "&TEXT(INDEX(Inputs!$B$31:$B$34,4),"0%") -> CR 100% to 110% | E15: ="CR ≥ "&TEXT(INDEX(Inputs!$B$31:$B$34,4),"0%") -> CR ≥ 110%
A16: =INDEX(Inputs!$A$21:$A$25,1)&" "&INDEX(Inputs!$B$21:$B$25,1) -> 1 Unsatisfactory | B16: =COUNTIFS(Calc!$F:$F,INDEX(Inputs!$A$21:$A$25,1),Calc!$AJ:$AJ,1,Calc!$AH:$AH,1) -> 1 | C16: =COUNTIFS(Calc!$F:$F,INDEX(Inputs!$A$21:$A$25,1),Calc!$AJ:$AJ,2,Calc!$AH:$AH,1) -> 0 | D16: =COUNTIFS(Calc!$F:$F,INDEX(Inputs!$A$21:$A$25,1),Calc!$AJ:$AJ,3,Calc!$AH:$AH,1) -> 1 | E16: =COUNTIFS(Calc!$F:$F,INDEX(Inputs!$A$21:$A$25,1),Calc!$AJ:$AJ,4,Calc!$AH:$AH,1) -> 1
A17: =INDEX(Inputs!$A$21:$A$25,2)&" "&INDEX(Inputs!$B$21:$B$25,2) -> 2 Partially meets | B17: =COUNTIFS(Calc!$F:$F,INDEX(Inputs!$A$21:$A$25,2),Calc!$AJ:$AJ,1,Calc!$AH:$AH,1) -> 7 | C17: =COUNTIFS(Calc!$F:$F,INDEX(Inputs!$A$21:$A$25,2),Calc!$AJ:$AJ,2,Calc!$AH:$AH,1) -> 13 | D17: =COUNTIFS(Calc!$F:$F,INDEX(Inputs!$A$21:$A$25,2),Calc!$AJ:$AJ,3,Calc!$AH:$AH,1) -> 16 | E17: =COUNTIFS(Calc!$F:$F,INDEX(Inputs!$A$21:$A$25,2),Calc!$AJ:$AJ,4,Calc!$AH:$AH,1) -> 3
A18: =INDEX(Inputs!$A$21:$A$25,3)&" "&INDEX(Inputs!$B$21:$B$25,3) -> 3 Meets | B18: =COUNTIFS(Calc!$F:$F,INDEX(Inputs!$A$21:$A$25,3),Calc!$AJ:$AJ,1,Calc!$AH:$AH,1) -> 13 | C18: =COUNTIFS(Calc!$F:$F,INDEX(Inputs!$A$21:$A$25,3),Calc!$AJ:$AJ,2,Calc!$AH:$AH,1) -> 31 | D18: =COUNTIFS(Calc!$F:$F,INDEX(Inputs!$A$21:$A$25,3),Calc!$AJ:$AJ,3,Calc!$AH:$AH,1) -> 45 | E18: =COUNTIFS(Calc!$F:$F,INDEX(Inputs!$A$21:$A$25,3),Calc!$AJ:$AJ,4,Calc!$AH:$AH,1) -> 14
A19: =INDEX(Inputs!$A$21:$A$25,4)&" "&INDEX(Inputs!$B$21:$B$25,4) -> 4 Exceeds | B19: =COUNTIFS(Calc!$F:$F,INDEX(Inputs!$A$21:$A$25,4),Calc!$AJ:$AJ,1,Calc!$AH:$AH,1) -> 5 | C19: =COUNTIFS(Calc!$F:$F,INDEX(Inputs!$A$21:$A$25,4),Calc!$AJ:$AJ,2,Calc!$AH:$AH,1) -> 20 | D19: =COUNTIFS(Calc!$F:$F,INDEX(Inputs!$A$21:$A$25,4),Calc!$AJ:$AJ,3,Calc!$AH:$AH,1) -> 15 | E19: =COUNTIFS(Calc!$F:$F,INDEX(Inputs!$A$21:$A$25,4),Calc!$AJ:$AJ,4,Calc!$AH:$AH,1) -> 7
A20: =INDEX(Inputs!$A$21:$A$25,5)&" "&INDEX(Inputs!$B$21:$B$25,5) -> 5 Outstanding | B20: =COUNTIFS(Calc!$F:$F,INDEX(Inputs!$A$21:$A$25,5),Calc!$AJ:$AJ,1,Calc!$AH:$AH,1) -> 2 | C20: =COUNTIFS(Calc!$F:$F,INDEX(Inputs!$A$21:$A$25,5),Calc!$AJ:$AJ,2,Calc!$AH:$AH,1) -> 8 | D20: =COUNTIFS(Calc!$F:$F,INDEX(Inputs!$A$21:$A$25,5),Calc!$AJ:$AJ,3,Calc!$AH:$AH,1) -> 5 | E20: =COUNTIFS(Calc!$F:$F,INDEX(Inputs!$A$21:$A$25,5),Calc!$AJ:$AJ,4,Calc!$AH:$AH,1) -> 2
A23: Merit increase, € (annual, FTE-weighted)
B24: ="CR < "&TEXT(INDEX(Inputs!$B$31:$B$34,2),"0%") -> CR < 90% | C24: ="CR "&TEXT(INDEX(Inputs!$B$31:$B$34,2),"0%")&" to "&TEXT(INDEX(Inputs!$B$31:$B$34,3),"0%") -> CR 90% to 100% | D24: ="CR "&TEXT(INDEX(Inputs!$B$31:$B$34,3),"0%")&" to "&TEXT(INDEX(Inputs!$B$31:$B$34,4),"0%") -> CR 100% to 110% | E24: ="CR ≥ "&TEXT(INDEX(Inputs!$B$31:$B$34,4),"0%") -> CR ≥ 110%
A25: =INDEX(Inputs!$A$21:$A$25,1)&" "&INDEX(Inputs!$B$21:$B$25,1) -> 1 Unsatisfactory | B25: =SUMIFS(Calc!$BJ:$BJ,Calc!$F:$F,INDEX(Inputs!$A$21:$A$25,1),Calc!$AJ:$AJ,1,Calc!$AH:$AH,1) -> 0 | C25: =SUMIFS(Calc!$BJ:$BJ,Calc!$F:$F,INDEX(Inputs!$A$21:$A$25,1),Calc!$AJ:$AJ,2,Calc!$AH:$AH,1) -> 0 | D25: =SUMIFS(Calc!$BJ:$BJ,Calc!$F:$F,INDEX(Inputs!$A$21:$A$25,1),Calc!$AJ:$AJ,3,Calc!$AH:$AH,1) -> 0 | E25: =SUMIFS(Calc!$BJ:$BJ,Calc!$F:$F,INDEX(Inputs!$A$21:$A$25,1),Calc!$AJ:$AJ,4,Calc!$AH:$AH,1) -> 0
A26: =INDEX(Inputs!$A$21:$A$25,2)&" "&INDEX(Inputs!$B$21:$B$25,2) -> 2 Partially meets | B26: =SUMIFS(Calc!$BJ:$BJ,Calc!$F:$F,INDEX(Inputs!$A$21:$A$25,2),Calc!$AJ:$AJ,1,Calc!$AH:$AH,1) -> 60354.211 | C26: =SUMIFS(Calc!$BJ:$BJ,Calc!$F:$F,INDEX(Inputs!$A$21:$A$25,2),Calc!$AJ:$AJ,2,Calc!$AH:$AH,1) -> 11557.84 | D26: =SUMIFS(Calc!$BJ:$BJ,Calc!$F:$F,INDEX(Inputs!$A$21:$A$25,2),Calc!$AJ:$AJ,3,Calc!$AH:$AH,1) -> 0 | E26: =SUMIFS(Calc!$BJ:$BJ,Calc!$F:$F,INDEX(Inputs!$A$21:$A$25,2),Calc!$AJ:$AJ,4,Calc!$AH:$AH,1) -> 0
A27: =INDEX(Inputs!$A$21:$A$25,3)&" "&INDEX(Inputs!$B$21:$B$25,3) -> 3 Meets | B27: =SUMIFS(Calc!$BJ:$BJ,Calc!$F:$F,INDEX(Inputs!$A$21:$A$25,3),Calc!$AJ:$AJ,1,Calc!$AH:$AH,1) -> 140549.01 | C27: =SUMIFS(Calc!$BJ:$BJ,Calc!$F:$F,INDEX(Inputs!$A$21:$A$25,3),Calc!$AJ:$AJ,2,Calc!$AH:$AH,1) -> 81776.456 | D27: =SUMIFS(Calc!$BJ:$BJ,Calc!$F:$F,INDEX(Inputs!$A$21:$A$25,3),Calc!$AJ:$AJ,3,Calc!$AH:$AH,1) -> 0 | E27: =SUMIFS(Calc!$BJ:$BJ,Calc!$F:$F,INDEX(Inputs!$A$21:$A$25,3),Calc!$AJ:$AJ,4,Calc!$AH:$AH,1) -> 0
A28: =INDEX(Inputs!$A$21:$A$25,4)&" "&INDEX(Inputs!$B$21:$B$25,4) -> 4 Exceeds | B28: =SUMIFS(Calc!$BJ:$BJ,Calc!$F:$F,INDEX(Inputs!$A$21:$A$25,4),Calc!$AJ:$AJ,1,Calc!$AH:$AH,1) -> 75567.212 | C28: =SUMIFS(Calc!$BJ:$BJ,Calc!$F:$F,INDEX(Inputs!$A$21:$A$25,4),Calc!$AJ:$AJ,2,Calc!$AH:$AH,1) -> 144831.56 | D28: =SUMIFS(Calc!$BJ:$BJ,Calc!$F:$F,INDEX(Inputs!$A$21:$A$25,4),Calc!$AJ:$AJ,3,Calc!$AH:$AH,1) -> 14400.905 | E28: =SUMIFS(Calc!$BJ:$BJ,Calc!$F:$F,INDEX(Inputs!$A$21:$A$25,4),Calc!$AJ:$AJ,4,Calc!$AH:$AH,1) -> 3207.8434
A29: =INDEX(Inputs!$A$21:$A$25,5)&" "&INDEX(Inputs!$B$21:$B$25,5) -> 5 Outstanding | B29: =SUMIFS(Calc!$BJ:$BJ,Calc!$F:$F,INDEX(Inputs!$A$21:$A$25,5),Calc!$AJ:$AJ,1,Calc!$AH:$AH,1) -> 25948.004 | C29: =SUMIFS(Calc!$BJ:$BJ,Calc!$F:$F,INDEX(Inputs!$A$21:$A$25,5),Calc!$AJ:$AJ,2,Calc!$AH:$AH,1) -> 70166.05 | D29: =SUMIFS(Calc!$BJ:$BJ,Calc!$F:$F,INDEX(Inputs!$A$21:$A$25,5),Calc!$AJ:$AJ,3,Calc!$AH:$AH,1) -> 9210.626 | E29: =SUMIFS(Calc!$BJ:$BJ,Calc!$F:$F,INDEX(Inputs!$A$21:$A$25,5),Calc!$AJ:$AJ,4,Calc!$AH:$AH,1) -> 0
