Workbook
Name AboveCeilingTier1: Inputs!$B$15
Name AboveCeilingTier2: Inputs!$B$16
Name AboveCeilingTier3: Inputs!$B$17
Name Ceiling: Inputs!$B$14
Name ClipAtMax: Inputs!$B$11
Name CompanyTarget: Inputs!$B$12
Name EffDate: Inputs!$B$4
Name EffMonth: Inputs!$B$5
Name InYearFactor: Inputs!$B$6
Name MaxIncrease: Inputs!$B$10
Name MinMonthsChange: Inputs!$B$9
Name MinMonthsHire: Inputs!$B$8
Name PoolPct: Inputs!$B$7
Name RateBelow: Inputs!$B$13

Sheet Summary
A1: Summary: what the review costs
B3: Value
A4: Headcount | B4: =COUNT(Calc!$I:$I) -> 212
A5: Eligible for merit | B5: =SUM(Calc!$AH:$AH) -> 209
A7: PAYROLL COST: full year, incl. employer contributions
A8: Current payroll cost | B8: =SUM(Calc!$BA:$BA)+SUM(Calc!$BB:$BB) -> 16557322
A9: of which total cash (base + bonus) | B9: =SUM(Calc!$BA:$BA) -> 12970151
A10: of which employer contributions | B10: =SUM(Calc!$BB:$BB) -> 3587171
A11: Payroll cost after pay equity | B11: =SUM(Calc!$BC:$BC)+SUM(Calc!$BD:$BD) -> 16890080
A12: Payroll cost after merit review | B12: =SUM(Calc!$BE:$BE)+SUM(Calc!$BF:$BF) -> 17676509
A13: Change: pay equity | B13: =B11-B8 -> 332757.14
A14: Change: merit review | B14: =B12-B11 -> 786429.76
A15: Change: total | B15: =B12-B8 -> 1119186.9
A16: Change: total, % of current payroll cost | B16: =IF(B8>0,B15/B8,0) -> 0.067594679
A18: THIS YEAR: from the effective month
A19: Change this year: pay equity | B19: =B13*InYearFactor -> 249567.85
A20: Change this year: merit review | B20: =B14*InYearFactor -> 589822.32
A21: Change this year: total | B21: =B19+B20 -> 839390.17
A22: Change this year, % of current payroll cost | B22: =IF(B8>0,B21/B8,0) -> 0.050696009
A24: PAY EQUITY ADJUSTMENT (Calc step 2), breakdown
A25: Base adjustment | B25: =SUM(Calc!$BG:$BG) -> 257991.67
A26: Bonus effect | B26: =SUM(Calc!$BH:$BH) -> 27282.115
A27: Employer contributions | B27: =SUM(Calc!$BI:$BI) -> 47483.359
A28: Total, full year | B28: =B25+B26+B27 -> 332757.14
A29: Total, this year | B29: =B28*InYearFactor -> 249567.85
A31: MERIT INCREASE from the aligned base (Calc step 5), breakdown
A32: Merit increase (base) | B32: =SUM(Calc!$BJ:$BJ) -> 637569.71
A33: Bonus effect | B33: =SUM(Calc!$BK:$BK) -> 90440.597
A34: Employer contributions | B34: =SUM(Calc!$BL:$BL) -> 58419.452
A35: Total, full year | B35: =B32+B33+B34 -> 786429.76
A36: Total, this year | B36: =B35*InYearFactor -> 589822.32
A38: MERIT REVIEW VS TARGET BUDGET, incl. bonus and employer contributions
A39: Eligible base payroll | B39: =SUM(Calc!$BM:$BM) -> 11819694
A40: Target merit increase, % of eligible base payroll (change on Inputs) | B40: =PoolPct -> 0.04
A41: Merit increase as calculated, % of eligible base payroll | B41: =IF(B39>0,B32/B39,0) -> 0.053941305
A42: Variance vs target, pp (+ over, − under) | B42: =(B41-B40)*100 -> 1.3941305
A43: Target budget, full year | B43: =B44+B45+B46 -> 586858.83
A44: of which base | B44: =SUM(Calc!$BO:$BO) -> 472787.75
A45: of which bonus | B45: =SUM(Calc!$BP:$BP) -> 51551.713
A46: of which employer contributions | B46: =SUM(Calc!$BS:$BS) -> 62519.368
A47: Variance vs target budget, € full year (+ over) | B47: =B35-B43 -> 199570.92
A48: Target budget, this year | B48: =B43*InYearFactor -> 440144.13
A49: Variance vs target budget, € this year (+ over) | B49: =B36-B48 -> 149678.19
A51: FLAGS
A52: Above range max after equity adjustment (amber: check, not an error) | B52: =SUM(Calc!$AE:$AE) -> 7
A53: At or above range max: no merit increase (red-circled if above) | B53: =SUM(Calc!$AS:$AS) -> 10
A54: Below range min after review | B54: =SUM(Calc!$AZ:$AZ) -> 1
A56: DATA CHECKS: all should be 0
A57: Employee rows not in the calculation | B57: =COUNTA(Employees!$A:$A)-1-B4 -> 0
A58: Employees without a range on Bands | B58: =B4-SUM(Calc!$L:$L) -> 0
A59: Employees in categories missing from Categories | B59: =B4-SUM(Categories!$B:$B) -> 0
A60: Employees with a rating missing from the rating table | B60: =B4-SUMPRODUCT(COUNTIFS(Calc!$F:$F,Inputs!$A$21:$A$25)) -> 0

Sheet Inputs
A1: Inputs: change the yellow cells
A3: Setting | B3: Value | C3: Note
A4: Effective from (pick a month) | B4: 46478 | C4: Increases take effect on the 1st of this month. Eligibility is counted up to it. Pick from the list.
A5: Effective month | B5: =MONTH(EffDate) -> 4 | C5: Month number of the effective date.
A6: In-year proration factor | B6: =(13-EffMonth)/12 -> 0.75 | C6: Months from the effective month to December inclusive, ÷ 12; the increase is assumed to start on the 1st of that month.
A7: Target merit increase, % of eligible base payroll | B7: 0.04 | C7: The planned average increase, as % of eligible staff's annual base after the pay equity step, FTE-weighted. The target budget on Summary is this % given to every eligible person, with bonus and employer contributions.
A8: Minimum tenure, months | B8: 6 | C8: Hired fewer months before the effective date than this: not in the review. Hired after the effective date: never in it.
A9: No individual pay change in the last, months | B9: 3 | C9: Individual pay change fewer months before the effective date than this: not in the review.
A10: Increase cap per person, % of aligned base | B10: 0.3 | C10: A safety limit. The increase is each person's gap to target, or the rating minimum if higher; the cap only cuts it if it is larger. 'No cap' (or an empty cell, or 0%) = no limit.
A11: Clip increases at range maximum | B11: Yes | C11: Yes: a merit increase never takes base pay above the range maximum. The pay equity adjustment is not clipped.
A12: Pay policy position, % of range midpoint | B12: 1 | C12: Leave at 100% if your range midpoints already reflect your pay policy.
A13: Employer contribution rate up to the ceiling | B13: 0.3215 | C13: Default: Spain 2026, 30.65% (permanent contracts; fixed-term 31.85%) + AT/EP occupational accident and disease premium, office-work rate 1.50% (RDL 3/2026, Cuadro II a) = 32.15%. Use your activity's AT/EP rate. These are 2026 rates. Rates for 2027 are already set and slightly higher (MEI employer share 0.83%, higher solidarity rates); 2026 rates are kept, so the contribution cost of a 2027 review is slightly understated.
A14: Annual contribution ceiling | B14: 61214.4 | C14: Default: Spain 2026, €5,101.20 a month × 12 (Orden PJC/297/2026). 2027 not yet published: 2026 assumed.
A15: Rate above the ceiling, tier 1: up to 10% over the ceiling | B15: 0.0096 | C15: Employer rate on the part of pay above the ceiling. Set 0% in all three tiers if your country charges nothing above it. Default: Spain 2026 (cuota de solidaridad), employer share, 0.96%.
A16: Rate above the ceiling, tier 2: 10% to 50% over the ceiling | B16: 0.0104 | C16: Default: Spain 2026, employer share, 1.04%.
A17: Rate above the ceiling, tier 3: more than 50% over the ceiling | B17: 0.0122 | C17: Default: Spain 2026, employer share, 1.22%.
A19: Targets by performance rating (illustrative assumption: set your own)
A20: Rating | B20: Label | C20: Target compa-ratio | D20: Minimum increase, % of aligned base
A21: 1 | B21: Unsatisfactory | C21: 0 | D21: 0
A22: 2 | B22: Partially meets | C22: 0.95 | D22: 0
A23: 3 | B23: Meets | C23: 1 | D23: 0
A24: 4 | B24: Exceeds | C24: 1.05 | D24: 0.01
A25: 5 | B25: Outstanding | C25: 1.1 | D25: 0.02
A26: Target compa-ratio: the compa-ratio each rating is raised to. The increase is the gap from aligned base to mid × pay policy position × this target. Set 0% to give a rating no increase at all. A target above a grade's range max (max / mid) is cut at the max when 'Clip increases at range maximum' = Yes.
A27: Minimum increase: a floor for a rating, paid even when the person is already at or above the target. 0% = no floor. It does not apply at or above the range maximum or to ineligible staff, and it is limited by the per-person cap and, when the clip at max is on, by the headroom to the max.
A29: Compa-ratio zones: only for the Matrix sheet view | C29: Increases do not depend on zones. Zones only group people into the classic rating × compa-ratio grid on the Matrix sheet.
A30: Zone | B30: Lower bound (CR from)
A31: 1 | B31: 0
A32: 2 | B32: 0.9
A33: 3 | B33: 1
A34: 4 | B34: 1.1

Sheet Lists
A1: Effective from | B1: Minimum tenure, months | C1: No pay change in the last, months | D1: Increase cap | E1: Clip at range max
A2: 46327 | B2: 0 | C2: 0 | D2: No cap | E2: Yes
A3: 46357 | B3: 1 | C3: 1 | D3: 0.1 | E3: No
A4: 46388 | B4: 2 | C4: 2 | D4: 0.15
A5: 46419 | B5: 3 | C5: 3 | D5: 0.2
A6: 46447 | B6: 6 | C6: 6 | D6: 0.25
A7: 46478 | B7: 9 | C7: 9 | D7: 0.3
A8: 46508 | B8: 12 | C8: 12 | D8: 0.4
A9: 46539 | D9: 0.5
A10: 46569 | D10: 0.75
A11: 46600 | D11: 1
A12: 46631
A13: 46661
A14: 46692
A15: 46722
A16: 46753
A17: 46784
A18: 46813
A19: 46844
A20: 46874
A21: 46905
A22: 46935
A23: 46966
... A27: 47088

Sheet Bands
A1: Category | B1: Grade | C1: Range min | D1: Range mid | E1: Range max | F1: Lookup key
A2: Customer Support | B2: 3 | C2: 25700 | D2: 29500 | E2: 33400 | F2: =A2&"|"&B2 -> Customer Support|3
A3: Customer Support | B3: 4 | C3: 29800 | D3: 34300 | E3: 38700 | F3: =A3&"|"&B3 -> Customer Support|4
A4: Customer Support | B4: 5 | C4: 34500 | D4: 39700 | E4: 44900 | F4: =A4&"|"&B4 -> Customer Support|5
A5: Customer Support | B5: 6 | C5: 38300 | D5: 46000 | E5: 53600 | F5: =A5&"|"&B5 -> Customer Support|6
A6: Manufacturing | B6: 4 | C6: 30400 | D6: 35000 | E6: 39500 | F6: =A6&"|"&B6 -> Manufacturing|4
A7: Manufacturing | B7: 5 | C7: 35600 | D7: 40900 | E7: 46300 | F7: =A7&"|"&B7 -> Manufacturing|5
A8: Manufacturing | B8: 6 | C8: 39700 | D8: 47600 | E8: 55600 | F8: =A8&"|"&B8 -> Manufacturing|6
A9: Manufacturing | B9: 7 | C9: 46200 | D9: 55400 | E9: 64700 | F9: =A9&"|"&B9 -> Manufacturing|7
A10: Manufacturing | B10: 8 | C10: 53700 | D10: 64400 | E10: 75200 | F10: =A10&"|"&B10 -> Manufacturing|8
A11: Operations | B11: 5 | C11: 33700 | D11: 38800 | E11: 43800 | F11: =A11&"|"&B11 -> Operations|5
A12: Operations | B12: 6 | C12: 37000 | D12: 44400 | E12: 51800 | F12: =A12&"|"&B12 -> Operations|6
A13: Operations | B13: 7 | C13: 42300 | D13: 50800 | E13: 59200 | F13: =A13&"|"&B13 -> Operations|7
... A36: Legal | B36: 12 | C36: 76700 | D36: 99700 | E36: 122700 | F36: =A36&"|"&B36 -> Legal|12
F37: =IF(A37="","",A37&"|"&B37)
F38: =IF(A38="","",A38&"|"&B38)
F39: =IF(A39="","",A39&"|"&B39)
F40: =IF(A40="","",A40&"|"&B40)
F41: =IF(A41="","",A41&"|"&B41)
F42: =IF(A42="","",A42&"|"&B42)
F43: =IF(A43="","",A43&"|"&B43)
F44: =IF(A44="","",A44&"|"&B44)
F45: =IF(A45="","",A45&"|"&B45)
F46: =IF(A46="","",A46&"|"&B46)
F47: =IF(A47="","",A47&"|"&B47)
F48: =IF(A48="","",A48&"|"&B48)
... F501: =IF(A501="","",A501&"|"&B501)

Sheet Employees
A1: id | B1: category | C1: gender | D1: grade | E1: rating | F1: hire_date | G1: last_change_date | H1: base_salary | I1: bonus_pct | J1: fte
A2: E001 | B2: Engineering | C2: M | D2: 8 | E2: 4 | F2: 44433 | G2: 46270 | H2: 56987.18 | I2: 14.33 | J2: 1
A3: E002 | B3: Engineering | C3: M | D3: 9 | E3: 2 | F3: 43227 | G3: 46113 | H3: 65996.64 | I3: 13.38 | J3: 1
A4: E003 | B4: Engineering | C4: M | D4: 11 | E4: 3 | F4: 42168 | G4: 46113 | H4: 79747.78 | I4: 14.12 | J4: 1
A5: E004 | B5: Engineering | C5: M | D5: 10 | E5: 2 | F5: 43775 | G5: 46113 | H5: 73284.69 | I5: 11.99 | J5: 1
A6: E005 | B6: Engineering | C6: F | D6: 10 | E6: 4 | F6: 44067 | G6: 46113 | H6: 69538.46 | I6: 9.57 | J6: 1
A7: E006 | B7: Engineering | C7: M | D7: 9 | E7: 5 | F7: 44469 | G7: 46113 | H7: 60248.19 | I7: 10.4 | J7: 1
A8: E007 | B8: Engineering | C8: M | D8: 7 | E8: 5 | F8: 44725 | G8: 46113 | H8: 47983.14 | I8: 11.81 | J8: 1
A9: E008 | B9: Engineering | C9: M | D9: 11 | E9: 2 | F9: 44067 | G9: 46113 | H9: 79273.59 | I9: 9.24 | J9: 1
A10: E009 | B10: Engineering | C10: M | D10: 8 | E10: 3 | F10: 44323 | G10: 46113 | H10: 56597.91 | I10: 10.73 | J10: 1
A11: E010 | B11: Engineering | C11: M | D11: 10 | E11: 3 | F11: 42935 | G11: 46113 | H11: 75607.45 | I11: 11.99 | J11: 1
A12: E011 | B12: Engineering | C12: M | D12: 7 | E12: 2 | F12: 45455 | G12: 46113 | H12: 37697.15 | I12: 14.04 | J12: 1
A13: E012 | B13: Engineering | C13: M | D13: 9 | E13: 3 | F13: 43666 | G13: 46113 | H13: 60920.28 | I13: 12.28 | J13: 1
... A213: E212 | B213: Sales | C213: M | D213: 9 | E213: 3 | F213: 45127 | G213: 46113 | H213: 54620.08 | I213: 26 | J213: 1

Sheet Calc
A1: Step 0: Input | L1: Step 1: Range and total cash | R1: Step 2: Pay equity adjustment (unexplained gap closed in full) | AF1: Step 3: Eligibility | AI1: Step 4: Target salary | AO1: Step 5: Merit increase | BA1: Step 6: Cost (annual, FTE-weighted) | BN1: Step 6a: Target budget, the target % to every eligible person | BT1: Step 7: Total cash for the gap check | BX1: Helper: list of categories
A2: Row number in the list. | B2: The n-th ID on Employees. Blank when the list is shorter: the whole row then stays blank. | C2: Category of workers (same work or work of equal value); looked up by ID. | D2: F or M. | F2: 1 to 5. | H2: Last individual change. | I2: Annual gross base, full time; in Spain including the extra payments (pagas extra). | J2: Bonus as a share of base. | K2: 1 = full time. | L2: 0: no row for this category and grade on Bands; totals show #N/A until it is added. | M2: From Bands by category and grade. | P2: Years from hire to effective date. | Q2: Base plus bonus, full time. | R2: Helper sums for the regression on Categories. | W2: Rounded to the cent so that ranking compares exact values. | X2: Order by total cash within the category, for the median. | Y2: From Categories. | Z2: 1: woman below the category median, and the category has an unexplained gap against women. | AB2: Category amount shared in proportion to each shortfall. | AC2: Paid through base; the bonus follows the base. | AD2: Merit is computed from this base. | AE2: Amber flag, not an error. The adjustment is paid in full. The category's amount is shared in proportion to each woman's shortfall to the category median, and a category spans several grades, so her new pay can sit above her grade's range maximum. Worth a look: her grade, the range, or how the category is defined. | AF2: Complete months up to the effective date; −1 if hired after it. | AG2: −1 if the change is after the effective date. | AH2: 1: in the review. | AI2: Aligned base / range mid. | AJ2: Not used in the increase. Only places the person in a column of the Matrix sheet grid (rating × compa-ratio). | AK2: From the rating table. | AL2: Floor for the rating, paid even at or above target; see Inputs. | AM2: Mid × pay policy position × target compa-ratio. | AN2: 0 if already at or above target. | AO2: 0: 'No cap', empty or 0% on Inputs. | AP2: Largest increase for this person: the cap × their aligned base; 0 when there is no cap. | AR2: Gap to target, at least the minimum, never above the cap (if there is one). | AS2: At or above range max: no merit increase. | AT2: Already at or above max: increase set to 0, whatever the rule gave. | AU2: Range max − aligned base: the most an increase can add without leaving the range. | AV2: If 'Clip increases at range maximum' = Yes, an increase larger than the headroom is cut to the headroom, so new base = range max. | AW2: Annual full-time base increase. | AZ2: Flag. | BA2: (Annual base + bonus) × FTE. | BB2: Full rate up to the contribution ceiling, tiered rates above it (Inputs). | BH2: Bonus grows with base. | BI2: Extra employer contributions on the increase. | BM2: Aligned base of eligible staff, FTE-weighted: the denominator for the target %. | BN2: Aligned base × target %, full time. A benchmark, not a payout. | BP2: Each person's own bonus %. | BS2: Depends on where each person sits against the ceiling, so it is not a flat rate on the target base. | BV2: Helper sums for the regression after merit on Categories. | BX2: Numbers each category where it first appears; the Categories sheet lists them in this order.
A4: No. | B4: ID | C4: Category | D4: Gender | E4: Grade | F4: Rating | G4: Hire date | H4: Last pay change | I4: Base salary | J4: Bonus % of base | K4: FTE | L4: Range found | M4: Range min | N4: Range mid | O4: Range max | P4: Tenure, years | Q4: Total cash | R4: grade² | S4: tenure² | T4: grade×tenure | U4: grade×cash | V4: tenure×cash | W4: Total cash, rounded | X4: Rank in category | Y4: Category median total cash | Z4: Receives adjustment | AA4: Shortfall to median | AB4: Adjustment, total cash | AC4: Adjustment, base | AD4: Aligned base | AE4: Above range max after equity adjustment | AF4: Months since hire | AG4: Months since change | AH4: Eligible | AI4: Compa-ratio | AJ4: Compa-ratio zone | AK4: Target compa-ratio for rating | AL4: Minimum increase | AM4: Target salary | AN4: Gap to target | AO4: Cap applies | AP4: Increase cap, € | AQ4: Minimum increase, € | AR4: Increase before range limits | AS4: At or above range max (red-circled) | AT4: After red-circle rule | AU4: Headroom to range max | AV4: After clip at max | AW4: Merit increase | AX4: Increase % | AY4: New base | AZ4: Below range min after review | BA4: Total cash before equity, at actual FTE | BB4: Employer contributions before equity | BC4: Total cash after equity, at actual FTE | BD4: Employer contributions after equity | BE4: Total cash after merit, at actual FTE | BF4: Employer contributions after merit | BG4: Equity: base | BH4: Equity: bonus | BI4: Equity: employer contributions | BJ4: Merit: base | BK4: Merit: bonus | BL4: Merit: employer contributions | BM4: Eligible base | BN4: Target increase | BO4: Target: base | BP4: Target: bonus | BQ4: Total cash at target, at actual FTE | BR4: Employer contributions at target | BS4: Target: employer contributions | BT4: Total cash after equity, full time | BU4: Total cash after merit, full time | BV4: grade×cash after merit | BW4: tenure×cash after merit | BX4: Category list no.
A5: =ROW()-4 -> 1 | B5: =IF(INDEX(Employees!$A:$A,A5+1)="","",INDEX(Employees!$A:$A,A5+1)) -> E001 | C5: =IF(B5="","",INDEX(Employees!$A:$Z,MATCH(B5,Employees!$A:$A,0),MATCH("category",Employees!$1:$1,0))) -> Engineering | D5: =IF(B5="","",INDEX(Employees!$A:$Z,MATCH(B5,Employees!$A:$A,0),MATCH("gender",Employees!$1:$1,0))) -> M | E5: =IF(B5="","",INDEX(Employees!$A:$Z,MATCH(B5,Employees!$A:$A,0),MATCH("grade",Employees!$1:$1,0))) -> 8 | F5: =IF(B5="","",INDEX(Employees!$A:$Z,MATCH(B5,Employees!$A:$A,0),MATCH("rating",Employees!$1:$1,0))) -> 4 | G5: =IF(B5="","",INDEX(Employees!$A:$Z,MATCH(B5,Employees!$A:$A,0),MATCH("hire_date",Employees!$1:$1,0))) -> 44433 | H5: =IF(B5="","",INDEX(Employees!$A:$Z,MATCH(B5,Employees!$A:$A,0),MATCH("last_change_date",Employees!$1:$1,0))) -> 46270 | I5: =IF(B5="","",INDEX(Employees!$A:$Z,MATCH(B5,Employees!$A:$A,0),MATCH("base_salary",Employees!$1:$1,0))) -> 56987.18 | J5: =IF(B5="","",INDEX(Employees!$A:$Z,MATCH(B5,Employees!$A:$A,0),MATCH("bonus_pct",Employees!$1:$1,0))/100) -> 0.1433 | K5: =IF(B5="","",INDEX(Employees!$A:$Z,MATCH(B5,Employees!$A:$A,0),MATCH("fte",Employees!$1:$1,0))) -> 1 | L5: =IF(B5="","",IF(ISNA(MATCH(C5&"|"&E5,Bands!$F:$F,0)),0,1)) -> 1 | M5: =IF(B5="","",INDEX(Bands!$C:$C,MATCH(C5&"|"&E5,Bands!$F:$F,0))) -> 47700 | N5: =IF(B5="","",INDEX(Bands!$D:$D,MATCH(C5&"|"&E5,Bands!$F:$F,0))) -> 57200 | O5: =IF(B5="","",INDEX(Bands!$E:$E,MATCH(C5&"|"&E5,Bands!$F:$F,0))) -> 66800 | P5: =IF(B5="","",(EffDate-G5)/365.25) -> 5.5989049 | Q5: =IF(B5="","",I5*(1+J5)) -> 65153.443 | R5: =IF(B5="","",E5^2) -> 64 | S5: =IF(B5="","",P5^2) -> 31.347736 | T5: =IF(B5="","",E5*P5) -> 44.791239 | U5: =IF(B5="","",E5*Q5) -> 521227.54 | V5: =IF(B5="","",P5*Q5) -> 364787.93 | W5: =IF(B5="","",ROUND(Q5,2)) -> 65153.44 | X5: =IF(B5="","",COUNTIFS($C:$C,C5,$W:$W,"<"&W5)+COUNTIFS($C:$C,C5,$W:$W,W5,$B:$B,"<"&B5)+1) -> 17 | Y5: =IF(B5="","",INDEX(Categories!$AH:$AH,MATCH(C5,Categories!$A:$A,0))) -> 71955.394 | Z5: =IF(B5="","",IF(AND(D5="F",Q5<Y5,INDEX(Categories!$AI:$AI,MATCH(C5,Categories!$A:$A,0))>0),1,0)) -> 0 | AA5: =IF(B5="","",IF(Z5=1,Y5-Q5,0)) -> 0 | AB5: =IF(B5="","",IF(Z5=1,INDEX(Categories!$AI:$AI,MATCH(C5,Categories!$A:$A,0))*AA5/INDEX(Categories!$AJ:$AJ,MATCH(C5,Categories!$A:$A,0)),0)) -> 0 | AC5: =IF(B5="","",AB5/(1+J5)) -> 0 | AD5: =IF(B5="","",I5+AC5) -> 56987.18 | AE5: =IF(B5="","",IF(AND(AC5>0,AD5>O5),1,0)) -> 0 | AF5: =IF(B5="","",IF(G5>EffDate,-1,DATEDIF(G5,EffDate,"m"))) -> 67 | AG5: =IF(B5="","",IF(H5>EffDate,-1,DATEDIF(H5,EffDate,"m"))) -> 6 | AH5: =IF(B5="","",IF(AND(AF5>=MinMonthsHire,AG5>=MinMonthsChange),1,0)) -> 1 | AI5: =IF(B5="","",AD5/N5) -> 0.99627937 | AJ5: =IF(B5="","",MATCH(AI5,Inputs!$B$31:$B$34,1)) -> 2 | AK5: =IF(B5="","",INDEX(Inputs!$C$21:$C$25,MATCH(F5,Inputs!$A$21:$A$25,0))) -> 1.05 | AL5: =IF(B5="","",INDEX(Inputs!$D$21:$D$25,MATCH(F5,Inputs!$A$21:$A$25,0))) -> 0.01 | AM5: =IF(B5="","",N5*CompanyTarget*AK5) -> 60060 | AN5: =IF(B5="","",MAX(0,AM5-AD5)) -> 3072.82 | AO5: =IF(B5="","",IF(AND(ISNUMBER(MaxIncrease),MaxIncrease>0),1,0)) -> 1 | AP5: =IF(B5="","",IF(AO5=1,AD5*MaxIncrease,0)) -> 17096.154 | AQ5: =IF(B5="","",AD5*AL5) -> 569.8718 | AR5: =IF(B5="","",IF(AK5=0,0,IF(AO5=1,MIN(MAX(AN5,AQ5),AP5),MAX(AN5,AQ5)))) -> 3072.82 | AS5: =IF(B5="","",IF(AD5>=O5,1,0)) -> 0 | AT5: =IF(B5="","",IF(AS5=1,0,AR5)) -> 3072.82 | AU5: =IF(B5="","",MAX(0,O5-AD5)) -> 9812.82 | AV5: =IF(B5="","",IF(ClipAtMax="No",AT5,MIN(AT5,AU5))) -> 3072.82 | AW5: =IF(B5="","",IF(AH5=1,AV5,0)) -> 3072.82 | AX5: =IF(B5="","",IF(AD5>0,AW5/AD5,0)) -> 0.05392125 | AY5: =IF(B5="","",AD5+AW5) -> 60060 | AZ5: =IF(B5="","",IF(AY5<M5,1,0)) -> 0 | BA5: =IF(B5="","",Q5*K5) -> 65153.443 | BB5: =IF(B5="","",RateBelow*MIN(BA5,Ceiling)+AboveCeilingTier1*MIN(MAX(0,BA5-Ceiling),0.1*Ceiling)+AboveCeilingTier2*MIN(MAX(0,BA5-1.1*Ceiling),0.4*Ceiling)+AboveCeilingTier3*MAX(0,BA5-1.5*Ceiling)) -> 19718.244 | BC5: =IF(B5="","",AD5*(1+J5)*K5) -> 65153.443 | BD5: =IF(B5="","",RateBelow*MIN(BC5,Ceiling)+AboveCeilingTier1*MIN(MAX(0,BC5-Ceiling),0.1*Ceiling)+AboveCeilingTier2*MIN(MAX(0,BC5-1.1*Ceiling),0.4*Ceiling)+AboveCeilingTier3*MAX(0,BC5-1.5*Ceiling)) -> 19718.244 | BE5: =IF(B5="","",AY5*(1+J5)*K5) -> 68666.598 | BF5: =IF(B5="","",RateBelow*MIN(BE5,Ceiling)+AboveCeilingTier1*MIN(MAX(0,BE5-Ceiling),0.1*Ceiling)+AboveCeilingTier2*MIN(MAX(0,BE5-1.1*Ceiling),0.4*Ceiling)+AboveCeilingTier3*MAX(0,BE5-1.5*Ceiling)) -> 19753.035 | BG5: =IF(B5="","",AC5*K5) -> 0 | BH5: =IF(B5="","",AC5*J5*K5) -> 0 | BI5: =IF(B5="","",BD5-BB5) -> 0 | BJ5: =IF(B5="","",AW5*K5) -> 3072.82 | BK5: =IF(B5="","",AW5*J5*K5) -> 440.33511 | BL5: =IF(B5="","",BF5-BD5) -> 34.790895 | BM5: =IF(B5="","",IF(AH5=1,AD5*K5,0)) -> 56987.18 | BN5: =IF(B5="","",IF(AH5=1,AD5*PoolPct,0)) -> 2279.4872 | BO5: =IF(B5="","",BN5*K5) -> 2279.4872 | BP5: =IF(B5="","",BN5*J5*K5) -> 326.65052 | BQ5: =IF(B5="","",(AD5+BN5)*(1+J5)*K5) -> 67759.581 | BR5: =IF(B5="","",RateBelow*MIN(BQ5,Ceiling)+AboveCeilingTier1*MIN(MAX(0,BQ5-Ceiling),0.1*Ceiling)+AboveCeilingTier2*MIN(MAX(0,BQ5-1.1*Ceiling),0.4*Ceiling)+AboveCeilingTier3*MAX(0,BQ5-1.5*Ceiling)) -> 19743.602 | BS5: =IF(B5="","",BR5-BD5) -> 25.357915 | BT5: =IF(B5="","",AD5*(1+J5)) -> 65153.443 | BU5: =IF(B5="","",AY5*(1+J5)) -> 68666.598 | BV5: =IF(B5="","",E5*BU5) -> 549332.78 | BW5: =IF(B5="","",P5*BU5) -> 384457.75 | BX5: =IF(B5="","",IF(COUNTIF($C$5:C5,C5)=1,MAX($BX$4:BX4)+1,"")) -> 1
A6: =ROW()-4 -> 2 | B6: =IF(INDEX(Employees!$A:$A,A6+1)="","",INDEX(Employees!$A:$A,A6+1)) -> E002 | C6: =IF(B6="","",INDEX(Employees!$A:$Z,MATCH(B6,Employees!$A:$A,0),MATCH("category",Employees!$1:$1,0))) -> Engineering | D6: =IF(B6="","",INDEX(Employees!$A:$Z,MATCH(B6,Employees!$A:$A,0),MATCH("gender",Employees!$1:$1,0))) -> M | E6: =IF(B6="","",INDEX(Employees!$A:$Z,MATCH(B6,Employees!$A:$A,0),MATCH("grade",Employees!$1:$1,0))) -> 9 | F6: =IF(B6="","",INDEX(Employees!$A:$Z,MATCH(B6,Employees!$A:$A,0),MATCH("rating",Employees!$1:$1,0))) -> 2 | G6: =IF(B6="","",INDEX(Employees!$A:$Z,MATCH(B6,Employees!$A:$A,0),MATCH("hire_date",Employees!$1:$1,0))) -> 43227 | H6: =IF(B6="","",INDEX(Employees!$A:$Z,MATCH(B6,Employees!$A:$A,0),MATCH("last_change_date",Employees!$1:$1,0))) -> 46113 | I6: =IF(B6="","",INDEX(Employees!$A:$Z,MATCH(B6,Employees!$A:$A,0),MATCH("base_salary",Employees!$1:$1,0))) -> 65996.64 | J6: =IF(B6="","",INDEX(Employees!$A:$Z,MATCH(B6,Employees!$A:$A,0),MATCH("bonus_pct",Employees!$1:$1,0))/100) -> 0.1338 | K6: =IF(B6="","",INDEX(Employees!$A:$Z,MATCH(B6,Employees!$A:$A,0),MATCH("fte",Employees!$1:$1,0))) -> 1 | L6: =IF(B6="","",IF(ISNA(MATCH(C6&"|"&E6,Bands!$F:$F,0)),0,1)) -> 1 | M6: =IF(B6="","",INDEX(Bands!$C:$C,MATCH(C6&"|"&E6,Bands!$F:$F,0))) -> 54500 | N6: =IF(B6="","",INDEX(Bands!$D:$D,MATCH(C6&"|"&E6,Bands!$F:$F,0))) -> 65400 | O6: =IF(B6="","",INDEX(Bands!$E:$E,MATCH(C6&"|"&E6,Bands!$F:$F,0))) -> 76300 | P6: =IF(B6="","",(EffDate-G6)/365.25) -> 8.9007529 | Q6: =IF(B6="","",I6*(1+J6)) -> 74826.99 | R6: =IF(B6="","",E6^2) -> 81 | S6: =IF(B6="","",P6^2) -> 79.223402 | T6: =IF(B6="","",E6*P6) -> 80.106776 | U6: =IF(B6="","",E6*Q6) -> 673442.91 | V6: =IF(B6="","",P6*Q6) -> 666016.55 | W6: =IF(B6="","",ROUND(Q6,2)) -> 74826.99 | X6: =IF(B6="","",COUNTIFS($C:$C,C6,$W:$W,"<"&W6)+COUNTIFS($C:$C,C6,$W:$W,W6,$B:$B,"<"&B6)+1) -> 25 | Y6: =IF(B6="","",INDEX(Categories!$AH:$AH,MATCH(C6,Categories!$A:$A,0))) -> 71955.394 | Z6: =IF(B6="","",IF(AND(D6="F",Q6<Y6,INDEX(Categories!$AI:$AI,MATCH(C6,Categories!$A:$A,0))>0),1,0)) -> 0 | AA6: =IF(B6="","",IF(Z6=1,Y6-Q6,0)) -> 0 | AB6: =IF(B6="","",IF(Z6=1,INDEX(Categories!$AI:$AI,MATCH(C6,Categories!$A:$A,0))*AA6/INDEX(Categories!$AJ:$AJ,MATCH(C6,Categories!$A:$A,0)),0)) -> 0 | AC6: =IF(B6="","",AB6/(1+J6)) -> 0 | AD6: =IF(B6="","",I6+AC6) -> 65996.64 | AE6: =IF(B6="","",IF(AND(AC6>0,AD6>O6),1,0)) -> 0 | AF6: =IF(B6="","",IF(G6>EffDate,-1,DATEDIF(G6,EffDate,"m"))) -> 106 | AG6: =IF(B6="","",IF(H6>EffDate,-1,DATEDIF(H6,EffDate,"m"))) -> 12 | AH6: =IF(B6="","",IF(AND(AF6>=MinMonthsHire,AG6>=MinMonthsChange),1,0)) -> 1 | AI6: =IF(B6="","",AD6/N6) -> 1.0091229 | AJ6: =IF(B6="","",MATCH(AI6,Inputs!$B$31:$B$34,1)) -> 3 | AK6: =IF(B6="","",INDEX(Inputs!$C$21:$C$25,MATCH(F6,Inputs!$A$21:$A$25,0))) -> 0.95 | AL6: =IF(B6="","",INDEX(Inputs!$D$21:$D$25,MATCH(F6,Inputs!$A$21:$A$25,0))) -> 0 | AM6: =IF(B6="","",N6*CompanyTarget*AK6) -> 62130 | AN6: =IF(B6="","",MAX(0,AM6-AD6)) -> 0 | AO6: =IF(B6="","",IF(AND(ISNUMBER(MaxIncrease),MaxIncrease>0),1,0)) -> 1 | AP6: =IF(B6="","",IF(AO6=1,AD6*MaxIncrease,0)) -> 19798.992 | AQ6: =IF(B6="","",AD6*AL6) -> 0 | AR6: =IF(B6="","",IF(AK6=0,0,IF(AO6=1,MIN(MAX(AN6,AQ6),AP6),MAX(AN6,AQ6)))) -> 0 | AS6: =IF(B6="","",IF(AD6>=O6,1,0)) -> 0 | AT6: =IF(B6="","",IF(AS6=1,0,AR6)) -> 0 | AU6: =IF(B6="","",MAX(0,O6-AD6)) -> 10303.36 | AV6: =IF(B6="","",IF(ClipAtMax="No",AT6,MIN(AT6,AU6))) -> 0 | AW6: =IF(B6="","",IF(AH6=1,AV6,0)) -> 0 | AX6: =IF(B6="","",IF(AD6>0,AW6/AD6,0)) -> 0 | AY6: =IF(B6="","",AD6+AW6) -> 65996.64 | AZ6: =IF(B6="","",IF(AY6<M6,1,0)) -> 0 | BA6: =IF(B6="","",Q6*K6) -> 74826.99 | BB6: =IF(B6="","",RateBelow*MIN(BA6,Ceiling)+AboveCeilingTier1*MIN(MAX(0,BA6-Ceiling),0.1*Ceiling)+AboveCeilingTier2*MIN(MAX(0,BA6-1.1*Ceiling),0.4*Ceiling)+AboveCeilingTier3*MAX(0,BA6-1.5*Ceiling)) -> 19817.103 | BC6: =IF(B6="","",AD6*(1+J6)*K6) -> 74826.99 | BD6: =IF(B6="","",RateBelow*MIN(BC6,Ceiling)+AboveCeilingTier1*MIN(MAX(0,BC6-Ceiling),0.1*Ceiling)+AboveCeilingTier2*MIN(MAX(0,BC6-1.1*Ceiling),0.4*Ceiling)+AboveCeilingTier3*MAX(0,BC6-1.5*Ceiling)) -> 19817.103 | BE6: =IF(B6="","",AY6*(1+J6)*K6) -> 74826.99 | BF6: =IF(B6="","",RateBelow*MIN(BE6,Ceiling)+AboveCeilingTier1*MIN(MAX(0,BE6-Ceiling),0.1*Ceiling)+AboveCeilingTier2*MIN(MAX(0,BE6-1.1*Ceiling),0.4*Ceiling)+AboveCeilingTier3*MAX(0,BE6-1.5*Ceiling)) -> 19817.103 | BG6: =IF(B6="","",AC6*K6) -> 0 | BH6: =IF(B6="","",AC6*J6*K6) -> 0 | BI6: =IF(B6="","",BD6-BB6) -> 0 | BJ6: =IF(B6="","",AW6*K6) -> 0 | BK6: =IF(B6="","",AW6*J6*K6) -> 0 | BL6: =IF(B6="","",BF6-BD6) -> 0 | BM6: =IF(B6="","",IF(AH6=1,AD6*K6,0)) -> 65996.64 | BN6: =IF(B6="","",IF(AH6=1,AD6*PoolPct,0)) -> 2639.8656 | BO6: =IF(B6="","",BN6*K6) -> 2639.8656 | BP6: =IF(B6="","",BN6*J6*K6) -> 353.21402 | BQ6: =IF(B6="","",(AD6+BN6)*(1+J6)*K6) -> 77820.07 | BR6: =IF(B6="","",RateBelow*MIN(BQ6,Ceiling)+AboveCeilingTier1*MIN(MAX(0,BQ6-Ceiling),0.1*Ceiling)+AboveCeilingTier2*MIN(MAX(0,BQ6-1.1*Ceiling),0.4*Ceiling)+AboveCeilingTier3*MAX(0,BQ6-1.5*Ceiling)) -> 19848.231 | BS6: =IF(B6="","",BR6-BD6) -> 31.128028 | BT6: =IF(B6="","",AD6*(1+J6)) -> 74826.99 | BU6: =IF(B6="","",AY6*(1+J6)) -> 74826.99 | BV6: =IF(B6="","",E6*BU6) -> 673442.91 | BW6: =IF(B6="","",P6*BU6) -> 666016.55 | BX6: =IF(B6="","",IF(COUNTIF($C$5:C6,C6)=1,MAX($BX$4:BX5)+1,""))
A7: =ROW()-4 -> 3 | B7: =IF(INDEX(Employees!$A:$A,A7+1)="","",INDEX(Employees!$A:$A,A7+1)) -> E003 | C7: =IF(B7="","",INDEX(Employees!$A:$Z,MATCH(B7,Employees!$A:$A,0),MATCH("category",Employees!$1:$1,0))) -> Engineering | D7: =IF(B7="","",INDEX(Employees!$A:$Z,MATCH(B7,Employees!$A:$A,0),MATCH("gender",Employees!$1:$1,0))) -> M | E7: =IF(B7="","",INDEX(Employees!$A:$Z,MATCH(B7,Employees!$A:$A,0),MATCH("grade",Employees!$1:$1,0))) -> 11 | F7: =IF(B7="","",INDEX(Employees!$A:$Z,MATCH(B7,Employees!$A:$A,0),MATCH("rating",Employees!$1:$1,0))) -> 3 | G7: =IF(B7="","",INDEX(Employees!$A:$Z,MATCH(B7,Employees!$A:$A,0),MATCH("hire_date",Employees!$1:$1,0))) -> 42168 | H7: =IF(B7="","",INDEX(Employees!$A:$Z,MATCH(B7,Employees!$A:$A,0),MATCH("last_change_date",Employees!$1:$1,0))) -> 46113 | I7: =IF(B7="","",INDEX(Employees!$A:$Z,MATCH(B7,Employees!$A:$A,0),MATCH("base_salary",Employees!$1:$1,0))) -> 79747.78 | J7: =IF(B7="","",INDEX(Employees!$A:$Z,MATCH(B7,Employees!$A:$A,0),MATCH("bonus_pct",Employees!$1:$1,0))/100) -> 0.1412 | K7: =IF(B7="","",INDEX(Employees!$A:$Z,MATCH(B7,Employees!$A:$A,0),MATCH("fte",Employees!$1:$1,0))) -> 1 | L7: =IF(B7="","",IF(ISNA(MATCH(C7&"|"&E7,Bands!$F:$F,0)),0,1)) -> 1 | M7: =IF(B7="","",INDEX(Bands!$C:$C,MATCH(C7&"|"&E7,Bands!$F:$F,0))) -> 68400 | N7: =IF(B7="","",INDEX(Bands!$D:$D,MATCH(C7&"|"&E7,Bands!$F:$F,0))) -> 85500 | O7: =IF(B7="","",INDEX(Bands!$E:$E,MATCH(C7&"|"&E7,Bands!$F:$F,0))) -> 102600 | P7: =IF(B7="","",(EffDate-G7)/365.25) -> 11.800137 | Q7: =IF(B7="","",I7*(1+J7)) -> 91008.167 | R7: =IF(B7="","",E7^2) -> 121 | S7: =IF(B7="","",P7^2) -> 139.24323 | T7: =IF(B7="","",E7*P7) -> 129.80151 | U7: =IF(B7="","",E7*Q7) -> 1001089.8 | V7: =IF(B7="","",P7*Q7) -> 1073908.8 | W7: =IF(B7="","",ROUND(Q7,2)) -> 91008.17 | X7: =IF(B7="","",COUNTIFS($C:$C,C7,$W:$W,"<"&W7)+COUNTIFS($C:$C,C7,$W:$W,W7,$B:$B,"<"&B7)+1) -> 40 | Y7: =IF(B7="","",INDEX(Categories!$AH:$AH,MATCH(C7,Categories!$A:$A,0))) -> 71955.394 | Z7: =IF(B7="","",IF(AND(D7="F",Q7<Y7,INDEX(Categories!$AI:$AI,MATCH(C7,Categories!$A:$A,0))>0),1,0)) -> 0 | AA7: =IF(B7="","",IF(Z7=1,Y7-Q7,0)) -> 0 | AB7: =IF(B7="","",IF(Z7=1,INDEX(Categories!$AI:$AI,MATCH(C7,Categories!$A:$A,0))*AA7/INDEX(Categories!$AJ:$AJ,MATCH(C7,Categories!$A:$A,0)),0)) -> 0 | AC7: =IF(B7="","",AB7/(1+J7)) -> 0 | AD7: =IF(B7="","",I7+AC7) -> 79747.78 | AE7: =IF(B7="","",IF(AND(AC7>0,AD7>O7),1,0)) -> 0 | AF7: =IF(B7="","",IF(G7>EffDate,-1,DATEDIF(G7,EffDate,"m"))) -> 141 | AG7: =IF(B7="","",IF(H7>EffDate,-1,DATEDIF(H7,EffDate,"m"))) -> 12 | AH7: =IF(B7="","",IF(AND(AF7>=MinMonthsHire,AG7>=MinMonthsChange),1,0)) -> 1 | AI7: =IF(B7="","",AD7/N7) -> 0.93272257 | AJ7: =IF(B7="","",MATCH(AI7,Inputs!$B$31:$B$34,1)) -> 2 | AK7: =IF(B7="","",INDEX(Inputs!$C$21:$C$25,MATCH(F7,Inputs!$A$21:$A$25,0))) -> 1 | AL7: =IF(B7="","",INDEX(Inputs!$D$21:$D$25,MATCH(F7,Inputs!$A$21:$A$25,0))) -> 0 | AM7: =IF(B7="","",N7*CompanyTarget*AK7) -> 85500 | AN7: =IF(B7="","",MAX(0,AM7-AD7)) -> 5752.22 | AO7: =IF(B7="","",IF(AND(ISNUMBER(MaxIncrease),MaxIncrease>0),1,0)) -> 1 | AP7: =IF(B7="","",IF(AO7=1,AD7*MaxIncrease,0)) -> 23924.334 | AQ7: =IF(B7="","",AD7*AL7) -> 0 | AR7: =IF(B7="","",IF(AK7=0,0,IF(AO7=1,MIN(MAX(AN7,AQ7),AP7),MAX(AN7,AQ7)))) -> 5752.22 | AS7: =IF(B7="","",IF(AD7>=O7,1,0)) -> 0 | AT7: =IF(B7="","",IF(AS7=1,0,AR7)) -> 5752.22 | AU7: =IF(B7="","",MAX(0,O7-AD7)) -> 22852.22 | AV7: =IF(B7="","",IF(ClipAtMax="No",AT7,MIN(AT7,AU7))) -> 5752.22 | AW7: =IF(B7="","",IF(AH7=1,AV7,0)) -> 5752.22 | AX7: =IF(B7="","",IF(AD7>0,AW7/AD7,0)) -> 0.072130158 | AY7: =IF(B7="","",AD7+AW7) -> 85500 | AZ7: =IF(B7="","",IF(AY7<M7,1,0)) -> 0 | BA7: =IF(B7="","",Q7*K7) -> 91008.167 | BB7: =IF(B7="","",RateBelow*MIN(BA7,Ceiling)+AboveCeilingTier1*MIN(MAX(0,BA7-Ceiling),0.1*Ceiling)+AboveCeilingTier2*MIN(MAX(0,BA7-1.1*Ceiling),0.4*Ceiling)+AboveCeilingTier3*MAX(0,BA7-1.5*Ceiling)) -> 19985.388 | BC7: =IF(B7="","",AD7*(1+J7)*K7) -> 91008.167 | BD7: =IF(B7="","",RateBelow*MIN(BC7,Ceiling)+AboveCeilingTier1*MIN(MAX(0,BC7-Ceiling),0.1*Ceiling)+AboveCeilingTier2*MIN(MAX(0,BC7-1.1*Ceiling),0.4*Ceiling)+AboveCeilingTier3*MAX(0,BC7-1.5*Ceiling)) -> 19985.388 | BE7: =IF(B7="","",AY7*(1+J7)*K7) -> 97572.6 | BF7: =IF(B7="","",RateBelow*MIN(BE7,Ceiling)+AboveCeilingTier1*MIN(MAX(0,BE7-Ceiling),0.1*Ceiling)+AboveCeilingTier2*MIN(MAX(0,BE7-1.1*Ceiling),0.4*Ceiling)+AboveCeilingTier3*MAX(0,BE7-1.5*Ceiling)) -> 20064.01 | BG7: =IF(B7="","",AC7*K7) -> 0 | BH7: =IF(B7="","",AC7*J7*K7) -> 0 | BI7: =IF(B7="","",BD7-BB7) -> 0 | BJ7: =IF(B7="","",AW7*K7) -> 5752.22 | BK7: =IF(B7="","",AW7*J7*K7) -> 812.21346 | BL7: =IF(B7="","",BF7-BD7) -> 78.621908 | BM7: =IF(B7="","",IF(AH7=1,AD7*K7,0)) -> 79747.78 | BN7: =IF(B7="","",IF(AH7=1,AD7*PoolPct,0)) -> 3189.9112 | BO7: =IF(B7="","",BN7*K7) -> 3189.9112 | BP7: =IF(B7="","",BN7*J7*K7) -> 450.41546 | BQ7: =IF(B7="","",(AD7+BN7)*(1+J7)*K7) -> 94648.493 | BR7: =IF(B7="","",RateBelow*MIN(BQ7,Ceiling)+AboveCeilingTier1*MIN(MAX(0,BQ7-Ceiling),0.1*Ceiling)+AboveCeilingTier2*MIN(MAX(0,BQ7-1.1*Ceiling),0.4*Ceiling)+AboveCeilingTier3*MAX(0,BQ7-1.5*Ceiling)) -> 20028.335 | BS7: =IF(B7="","",BR7-BD7) -> 42.947805 | BT7: =IF(B7="","",AD7*(1+J7)) -> 91008.167 | BU7: =IF(B7="","",AY7*(1+J7)) -> 97572.6 | BV7: =IF(B7="","",E7*BU7) -> 1073298.6 | BW7: =IF(B7="","",P7*BU7) -> 1151370 | BX7: =IF(B7="","",IF(COUNTIF($C$5:C7,C7)=1,MAX($BX$4:BX6)+1,""))
A8: =ROW()-4 -> 4 | B8: =IF(INDEX(Employees!$A:$A,A8+1)="","",INDEX(Employees!$A:$A,A8+1)) -> E004 | C8: =IF(B8="","",INDEX(Employees!$A:$Z,MATCH(B8,Employees!$A:$A,0),MATCH("category",Employees!$1:$1,0))) -> Engineering | D8: =IF(B8="","",INDEX(Employees!$A:$Z,MATCH(B8,Employees!$A:$A,0),MATCH("gender",Employees!$1:$1,0))) -> M | E8: =IF(B8="","",INDEX(Employees!$A:$Z,MATCH(B8,Employees!$A:$A,0),MATCH("grade",Employees!$1:$1,0))) -> 10 | F8: =IF(B8="","",INDEX(Employees!$A:$Z,MATCH(B8,Employees!$A:$A,0),MATCH("rating",Employees!$1:$1,0))) -> 2 | G8: =IF(B8="","",INDEX(Employees!$A:$Z,MATCH(B8,Employees!$A:$A,0),MATCH("hire_date",Employees!$1:$1,0))) -> 43775 | H8: =IF(B8="","",INDEX(Employees!$A:$Z,MATCH(B8,Employees!$A:$A,0),MATCH("last_change_date",Employees!$1:$1,0))) -> 46113 | I8: =IF(B8="","",INDEX(Employees!$A:$Z,MATCH(B8,Employees!$A:$A,0),MATCH("base_salary",Employees!$1:$1,0))) -> 73284.69 | J8: =IF(B8="","",INDEX(Employees!$A:$Z,MATCH(B8,Employees!$A:$A,0),MATCH("bonus_pct",Employees!$1:$1,0))/100) -> 0.1199 | K8: =IF(B8="","",INDEX(Employees!$A:$Z,MATCH(B8,Employees!$A:$A,0),MATCH("fte",Employees!$1:$1,0))) -> 1 | L8: =IF(B8="","",IF(ISNA(MATCH(C8&"|"&E8,Bands!$F:$F,0)),0,1)) -> 1 | M8: =IF(B8="","",INDEX(Bands!$C:$C,MATCH(C8&"|"&E8,Bands!$F:$F,0))) -> 59800 | N8: =IF(B8="","",INDEX(Bands!$D:$D,MATCH(C8&"|"&E8,Bands!$F:$F,0))) -> 74800 | O8: =IF(B8="","",INDEX(Bands!$E:$E,MATCH(C8&"|"&E8,Bands!$F:$F,0))) -> 89700 | P8: =IF(B8="","",(EffDate-G8)/365.25) -> 7.4004107 | Q8: =IF(B8="","",I8*(1+J8)) -> 82071.524 | R8: =IF(B8="","",E8^2) -> 100 | S8: =IF(B8="","",P8^2) -> 54.766078 | T8: =IF(B8="","",E8*P8) -> 74.004107 | U8: =IF(B8="","",E8*Q8) -> 820715.24 | V8: =IF(B8="","",P8*Q8) -> 607362.98 | W8: =IF(B8="","",ROUND(Q8,2)) -> 82071.52 | X8: =IF(B8="","",COUNTIFS($C:$C,C8,$W:$W,"<"&W8)+COUNTIFS($C:$C,C8,$W:$W,W8,$B:$B,"<"&B8)+1) -> 33 | Y8: =IF(B8="","",INDEX(Categories!$AH:$AH,MATCH(C8,Categories!$A:$A,0))) -> 71955.394 | Z8: =IF(B8="","",IF(AND(D8="F",Q8<Y8,INDEX(Categories!$AI:$AI,MATCH(C8,Categories!$A:$A,0))>0),1,0)) -> 0 | AA8: =IF(B8="","",IF(Z8=1,Y8-Q8,0)) -> 0 | AB8: =IF(B8="","",IF(Z8=1,INDEX(Categories!$AI:$AI,MATCH(C8,Categories!$A:$A,0))*AA8/INDEX(Categories!$AJ:$AJ,MATCH(C8,Categories!$A:$A,0)),0)) -> 0 | AC8: =IF(B8="","",AB8/(1+J8)) -> 0 | AD8: =IF(B8="","",I8+AC8) -> 73284.69 | AE8: =IF(B8="","",IF(AND(AC8>0,AD8>O8),1,0)) -> 0 | AF8: =IF(B8="","",IF(G8>EffDate,-1,DATEDIF(G8,EffDate,"m"))) -> 88 | AG8: =IF(B8="","",IF(H8>EffDate,-1,DATEDIF(H8,EffDate,"m"))) -> 12 | AH8: =IF(B8="","",IF(AND(AF8>=MinMonthsHire,AG8>=MinMonthsChange),1,0)) -> 1 | AI8: =IF(B8="","",AD8/N8) -> 0.97974184 | AJ8: =IF(B8="","",MATCH(AI8,Inputs!$B$31:$B$34,1)) -> 2 | AK8: =IF(B8="","",INDEX(Inputs!$C$21:$C$25,MATCH(F8,Inputs!$A$21:$A$25,0))) -> 0.95 | AL8: =IF(B8="","",INDEX(Inputs!$D$21:$D$25,MATCH(F8,Inputs!$A$21:$A$25,0))) -> 0 | AM8: =IF(B8="","",N8*CompanyTarget*AK8) -> 71060 | AN8: =IF(B8="","",MAX(0,AM8-AD8)) -> 0 | AO8: =IF(B8="","",IF(AND(ISNUMBER(MaxIncrease),MaxIncrease>0),1,0)) -> 1 | AP8: =IF(B8="","",IF(AO8=1,AD8*MaxIncrease,0)) -> 21985.407 | AQ8: =IF(B8="","",AD8*AL8) -> 0 | AR8: =IF(B8="","",IF(AK8=0,0,IF(AO8=1,MIN(MAX(AN8,AQ8),AP8),MAX(AN8,AQ8)))) -> 0 | AS8: =IF(B8="","",IF(AD8>=O8,1,0)) -> 0 | AT8: =IF(B8="","",IF(AS8=1,0,AR8)) -> 0 | AU8: =IF(B8="","",MAX(0,O8-AD8)) -> 16415.31 | AV8: =IF(B8="","",IF(ClipAtMax="No",AT8,MIN(AT8,AU8))) -> 0 | AW8: =IF(B8="","",IF(AH8=1,AV8,0)) -> 0 | AX8: =IF(B8="","",IF(AD8>0,AW8/AD8,0)) -> 0 | AY8: =IF(B8="","",AD8+AW8) -> 73284.69 | AZ8: =IF(B8="","",IF(AY8<M8,1,0)) -> 0 | BA8: =IF(B8="","",Q8*K8) -> 82071.524 | BB8: =IF(B8="","",RateBelow*MIN(BA8,Ceiling)+AboveCeilingTier1*MIN(MAX(0,BA8-Ceiling),0.1*Ceiling)+AboveCeilingTier2*MIN(MAX(0,BA8-1.1*Ceiling),0.4*Ceiling)+AboveCeilingTier3*MAX(0,BA8-1.5*Ceiling)) -> 19892.447 | BC8: =IF(B8="","",AD8*(1+J8)*K8) -> 82071.524 | BD8: =IF(B8="","",RateBelow*MIN(BC8,Ceiling)+AboveCeilingTier1*MIN(MAX(0,BC8-Ceiling),0.1*Ceiling)+AboveCeilingTier2*MIN(MAX(0,BC8-1.1*Ceiling),0.4*Ceiling)+AboveCeilingTier3*MAX(0,BC8-1.5*Ceiling)) -> 19892.447 | BE8: =IF(B8="","",AY8*(1+J8)*K8) -> 82071.524 | BF8: =IF(B8="","",RateBelow*MIN(BE8,Ceiling)+AboveCeilingTier1*MIN(MAX(0,BE8-Ceiling),0.1*Ceiling)+AboveCeilingTier2*MIN(MAX(0,BE8-1.1*Ceiling),0.4*Ceiling)+AboveCeilingTier3*MAX(0,BE8-1.5*Ceiling)) -> 19892.447 | BG8: =IF(B8="","",AC8*K8) -> 0 | BH8: =IF(B8="","",AC8*J8*K8) -> 0 | BI8: =IF(B8="","",BD8-BB8) -> 0 | BJ8: =IF(B8="","",AW8*K8) -> 0 | BK8: =IF(B8="","",AW8*J8*K8) -> 0 | BL8: =IF(B8="","",BF8-BD8) -> 0 | BM8: =IF(B8="","",IF(AH8=1,AD8*K8,0)) -> 73284.69 | BN8: =IF(B8="","",IF(AH8=1,AD8*PoolPct,0)) -> 2931.3876 | BO8: =IF(B8="","",BN8*K8) -> 2931.3876 | BP8: =IF(B8="","",BN8*J8*K8) -> 351.47337 | BQ8: =IF(B8="","",(AD8+BN8)*(1+J8)*K8) -> 85354.385 | BR8: =IF(B8="","",RateBelow*MIN(BQ8,Ceiling)+AboveCeilingTier1*MIN(MAX(0,BQ8-Ceiling),0.1*Ceiling)+AboveCeilingTier2*MIN(MAX(0,BQ8-1.1*Ceiling),0.4*Ceiling)+AboveCeilingTier3*MAX(0,BQ8-1.5*Ceiling)) -> 19926.588 | BS8: =IF(B8="","",BR8-BD8) -> 34.141754 | BT8: =IF(B8="","",AD8*(1+J8)) -> 82071.524 | BU8: =IF(B8="","",AY8*(1+J8)) -> 82071.524 | BV8: =IF(B8="","",E8*BU8) -> 820715.24 | BW8: =IF(B8="","",P8*BU8) -> 607362.98 | BX8: =IF(B8="","",IF(COUNTIF($C$5:C8,C8)=1,MAX($BX$4:BX7)+1,""))
A9: =ROW()-4 -> 5 | B9: =IF(INDEX(Employees!$A:$A,A9+1)="","",INDEX(Employees!$A:$A,A9+1)) -> E005 | C9: =IF(B9="","",INDEX(Employees!$A:$Z,MATCH(B9,Employees!$A:$A,0),MATCH("category",Employees!$1:$1,0))) -> Engineering | D9: =IF(B9="","",INDEX(Employees!$A:$Z,MATCH(B9,Employees!$A:$A,0),MATCH("gender",Employees!$1:$1,0))) -> F | E9: =IF(B9="","",INDEX(Employees!$A:$Z,MATCH(B9,Employees!$A:$A,0),MATCH("grade",Employees!$1:$1,0))) -> 10 | F9: =IF(B9="","",INDEX(Employees!$A:$Z,MATCH(B9,Employees!$A:$A,0),MATCH("rating",Employees!$1:$1,0))) -> 4 | G9: =IF(B9="","",INDEX(Employees!$A:$Z,MATCH(B9,Employees!$A:$A,0),MATCH("hire_date",Employees!$1:$1,0))) -> 44067 | H9: =IF(B9="","",INDEX(Employees!$A:$Z,MATCH(B9,Employees!$A:$A,0),MATCH("last_change_date",Employees!$1:$1,0))) -> 46113 | I9: =IF(B9="","",INDEX(Employees!$A:$Z,MATCH(B9,Employees!$A:$A,0),MATCH("base_salary",Employees!$1:$1,0))) -> 69538.46 | J9: =IF(B9="","",INDEX(Employees!$A:$Z,MATCH(B9,Employees!$A:$A,0),MATCH("bonus_pct",Employees!$1:$1,0))/100) -> 0.0957 | K9: =IF(B9="","",INDEX(Employees!$A:$Z,MATCH(B9,Employees!$A:$A,0),MATCH("fte",Employees!$1:$1,0))) -> 1 | L9: =IF(B9="","",IF(ISNA(MATCH(C9&"|"&E9,Bands!$F:$F,0)),0,1)) -> 1 | M9: =IF(B9="","",INDEX(Bands!$C:$C,MATCH(C9&"|"&E9,Bands!$F:$F,0))) -> 59800 | N9: =IF(B9="","",INDEX(Bands!$D:$D,MATCH(C9&"|"&E9,Bands!$F:$F,0))) -> 74800 | O9: =IF(B9="","",INDEX(Bands!$E:$E,MATCH(C9&"|"&E9,Bands!$F:$F,0))) -> 89700 | P9: =IF(B9="","",(EffDate-G9)/365.25) -> 6.6009582 | Q9: =IF(B9="","",I9*(1+J9)) -> 76193.291 | R9: =IF(B9="","",E9^2) -> 100 | S9: =IF(B9="","",P9^2) -> 43.57265 | T9: =IF(B9="","",E9*P9) -> 66.009582 | U9: =IF(B9="","",E9*Q9) -> 761932.91 | V9: =IF(B9="","",P9*Q9) -> 502948.73 | W9: =IF(B9="","",ROUND(Q9,2)) -> 76193.29 | X9: =IF(B9="","",COUNTIFS($C:$C,C9,$W:$W,"<"&W9)+COUNTIFS($C:$C,C9,$W:$W,W9,$B:$B,"<"&B9)+1) -> 26 | Y9: =IF(B9="","",INDEX(Categories!$AH:$AH,MATCH(C9,Categories!$A:$A,0))) -> 71955.394 | Z9: =IF(B9="","",IF(AND(D9="F",Q9<Y9,INDEX(Categories!$AI:$AI,MATCH(C9,Categories!$A:$A,0))>0),1,0)) -> 0 | AA9: =IF(B9="","",IF(Z9=1,Y9-Q9,0)) -> 0 | AB9: =IF(B9="","",IF(Z9=1,INDEX(Categories!$AI:$AI,MATCH(C9,Categories!$A:$A,0))*AA9/INDEX(Categories!$AJ:$AJ,MATCH(C9,Categories!$A:$A,0)),0)) -> 0 | AC9: =IF(B9="","",AB9/(1+J9)) -> 0 | AD9: =IF(B9="","",I9+AC9) -> 69538.46 | AE9: =IF(B9="","",IF(AND(AC9>0,AD9>O9),1,0)) -> 0 | AF9: =IF(B9="","",IF(G9>EffDate,-1,DATEDIF(G9,EffDate,"m"))) -> 79 | AG9: =IF(B9="","",IF(H9>EffDate,-1,DATEDIF(H9,EffDate,"m"))) -> 12 | AH9: =IF(B9="","",IF(AND(AF9>=MinMonthsHire,AG9>=MinMonthsChange),1,0)) -> 1 | AI9: =IF(B9="","",AD9/N9) -> 0.92965856 | AJ9: =IF(B9="","",MATCH(AI9,Inputs!$B$31:$B$34,1)) -> 2 | AK9: =IF(B9="","",INDEX(Inputs!$C$21:$C$25,MATCH(F9,Inputs!$A$21:$A$25,0))) -> 1.05 | AL9: =IF(B9="","",INDEX(Inputs!$D$21:$D$25,MATCH(F9,Inputs!$A$21:$A$25,0))) -> 0.01 | AM9: =IF(B9="","",N9*CompanyTarget*AK9) -> 78540 | AN9: =IF(B9="","",MAX(0,AM9-AD9)) -> 9001.54 | AO9: =IF(B9="","",IF(AND(ISNUMBER(MaxIncrease),MaxIncrease>0),1,0)) -> 1 | AP9: =IF(B9="","",IF(AO9=1,AD9*MaxIncrease,0)) -> 20861.538 | AQ9: =IF(B9="","",AD9*AL9) -> 695.3846 | AR9: =IF(B9="","",IF(AK9=0,0,IF(AO9=1,MIN(MAX(AN9,AQ9),AP9),MAX(AN9,AQ9)))) -> 9001.54 | AS9: =IF(B9="","",IF(AD9>=O9,1,0)) -> 0 | AT9: =IF(B9="","",IF(AS9=1,0,AR9)) -> 9001.54 | AU9: =IF(B9="","",MAX(0,O9-AD9)) -> 20161.54 | AV9: =IF(B9="","",IF(ClipAtMax="No",AT9,MIN(AT9,AU9))) -> 9001.54 | AW9: =IF(B9="","",IF(AH9=1,AV9,0)) -> 9001.54 | AX9: =IF(B9="","",IF(AD9>0,AW9/AD9,0)) -> 0.12944693 | AY9: =IF(B9="","",AD9+AW9) -> 78540 | AZ9: =IF(B9="","",IF(AY9<M9,1,0)) -> 0 | BA9: =IF(B9="","",Q9*K9) -> 76193.291 | BB9: =IF(B9="","",RateBelow*MIN(BA9,Ceiling)+AboveCeilingTier1*MIN(MAX(0,BA9-Ceiling),0.1*Ceiling)+AboveCeilingTier2*MIN(MAX(0,BA9-1.1*Ceiling),0.4*Ceiling)+AboveCeilingTier3*MAX(0,BA9-1.5*Ceiling)) -> 19831.313 | BC9: =IF(B9="","",AD9*(1+J9)*K9) -> 76193.291 | BD9: =IF(B9="","",RateBelow*MIN(BC9,Ceiling)+AboveCeilingTier1*MIN(MAX(0,BC9-Ceiling),0.1*Ceiling)+AboveCeilingTier2*MIN(MAX(0,BC9-1.1*Ceiling),0.4*Ceiling)+AboveCeilingTier3*MAX(0,BC9-1.5*Ceiling)) -> 19831.313 | BE9: =IF(B9="","",AY9*(1+J9)*K9) -> 86056.278 | BF9: =IF(B9="","",RateBelow*MIN(BE9,Ceiling)+AboveCeilingTier1*MIN(MAX(0,BE9-Ceiling),0.1*Ceiling)+AboveCeilingTier2*MIN(MAX(0,BE9-1.1*Ceiling),0.4*Ceiling)+AboveCeilingTier3*MAX(0,BE9-1.5*Ceiling)) -> 19933.888 | BG9: =IF(B9="","",AC9*K9) -> 0 | BH9: =IF(B9="","",AC9*J9*K9) -> 0 | BI9: =IF(B9="","",BD9-BB9) -> 0 | BJ9: =IF(B9="","",AW9*K9) -> 9001.54 | BK9: =IF(B9="","",AW9*J9*K9) -> 861.44738 | BL9: =IF(B9="","",BF9-BD9) -> 102.57507 | BM9: =IF(B9="","",IF(AH9=1,AD9*K9,0)) -> 69538.46 | BN9: =IF(B9="","",IF(AH9=1,AD9*PoolPct,0)) -> 2781.5384 | BO9: =IF(B9="","",BN9*K9) -> 2781.5384 | BP9: =IF(B9="","",BN9*J9*K9) -> 266.19322 | BQ9: =IF(B9="","",(AD9+BN9)*(1+J9)*K9) -> 79241.022 | BR9: =IF(B9="","",RateBelow*MIN(BQ9,Ceiling)+AboveCeilingTier1*MIN(MAX(0,BQ9-Ceiling),0.1*Ceiling)+AboveCeilingTier2*MIN(MAX(0,BQ9-1.1*Ceiling),0.4*Ceiling)+AboveCeilingTier3*MAX(0,BQ9-1.5*Ceiling)) -> 19863.009 | BS9: =IF(B9="","",BR9-BD9) -> 31.696409 | BT9: =IF(B9="","",AD9*(1+J9)) -> 76193.291 | BU9: =IF(B9="","",AY9*(1+J9)) -> 86056.278 | BV9: =IF(B9="","",E9*BU9) -> 860562.78 | BW9: =IF(B9="","",P9*BU9) -> 568053.9 | BX9: =IF(B9="","",IF(COUNTIF($C$5:C9,C9)=1,MAX($BX$4:BX8)+1,""))
A10: =ROW()-4 -> 6 | B10: =IF(INDEX(Employees!$A:$A,A10+1)="","",INDEX(Employees!$A:$A,A10+1)) -> E006 | C10: =IF(B10="","",INDEX(Employees!$A:$Z,MATCH(B10,Employees!$A:$A,0),MATCH("category",Employees!$1:$1,0))) -> Engineering | D10: =IF(B10="","",INDEX(Employees!$A:$Z,MATCH(B10,Employees!$A:$A,0),MATCH("gender",Employees!$1:$1,0))) -> M | E10: =IF(B10="","",INDEX(Employees!$A:$Z,MATCH(B10,Employees!$A:$A,0),MATCH("grade",Employees!$1:$1,0))) -> 9 | F10: =IF(B10="","",INDEX(Employees!$A:$Z,MATCH(B10,Employees!$A:$A,0),MATCH("rating",Employees!$1:$1,0))) -> 5 | G10: =IF(B10="","",INDEX(Employees!$A:$Z,MATCH(B10,Employees!$A:$A,0),MATCH("hire_date",Employees!$1:$1,0))) -> 44469 | H10: =IF(B10="","",INDEX(Employees!$A:$Z,MATCH(B10,Employees!$A:$A,0),MATCH("last_change_date",Employees!$1:$1,0))) -> 46113 | I10: =IF(B10="","",INDEX(Employees!$A:$Z,MATCH(B10,Employees!$A:$A,0),MATCH("base_salary",Employees!$1:$1,0))) -> 60248.19 | J10: =IF(B10="","",INDEX(Employees!$A:$Z,MATCH(B10,Employees!$A:$A,0),MATCH("bonus_pct",Employees!$1:$1,0))/100) -> 0.104 | K10: =IF(B10="","",INDEX(Employees!$A:$Z,MATCH(B10,Employees!$A:$A,0),MATCH("fte",Employees!$1:$1,0))) -> 1 | L10: =IF(B10="","",IF(ISNA(MATCH(C10&"|"&E10,Bands!$F:$F,0)),0,1)) -> 1 | M10: =IF(B10="","",INDEX(Bands!$C:$C,MATCH(C10&"|"&E10,Bands!$F:$F,0))) -> 54500 | N10: =IF(B10="","",INDEX(Bands!$D:$D,MATCH(C10&"|"&E10,Bands!$F:$F,0))) -> 65400 | O10: =IF(B10="","",INDEX(Bands!$E:$E,MATCH(C10&"|"&E10,Bands!$F:$F,0))) -> 76300 | P10: =IF(B10="","",(EffDate-G10)/365.25) -> 5.5003422 | Q10: =IF(B10="","",I10*(1+J10)) -> 66514.002 | R10: =IF(B10="","",E10^2) -> 81 | S10: =IF(B10="","",P10^2) -> 30.253765 | T10: =IF(B10="","",E10*P10) -> 49.50308 | U10: =IF(B10="","",E10*Q10) -> 598626.02 | V10: =IF(B10="","",P10*Q10) -> 365849.77 | W10: =IF(B10="","",ROUND(Q10,2)) -> 66514 | X10: =IF(B10="","",COUNTIFS($C:$C,C10,$W:$W,"<"&W10)+COUNTIFS($C:$C,C10,$W:$W,W10,$B:$B,"<"&B10)+1) -> 18 | Y10: =IF(B10="","",INDEX(Categories!$AH:$AH,MATCH(C10,Categories!$A:$A,0))) -> 71955.394 | Z10: =IF(B10="","",IF(AND(D10="F",Q10<Y10,INDEX(Categories!$AI:$AI,MATCH(C10,Categories!$A:$A,0))>0),1,0)) -> 0 | AA10: =IF(B10="","",IF(Z10=1,Y10-Q10,0)) -> 0 | AB10: =IF(B10="","",IF(Z10=1,INDEX(Categories!$AI:$AI,MATCH(C10,Categories!$A:$A,0))*AA10/INDEX(Categories!$AJ:$AJ,MATCH(C10,Categories!$A:$A,0)),0)) -> 0 | AC10: =IF(B10="","",AB10/(1+J10)) -> 0 | AD10: =IF(B10="","",I10+AC10) -> 60248.19 | AE10: =IF(B10="","",IF(AND(AC10>0,AD10>O10),1,0)) -> 0 | AF10: =IF(B10="","",IF(G10>EffDate,-1,DATEDIF(G10,EffDate,"m"))) -> 66 | AG10: =IF(B10="","",IF(H10>EffDate,-1,DATEDIF(H10,EffDate,"m"))) -> 12 | AH10: =IF(B10="","",IF(AND(AF10>=MinMonthsHire,AG10>=MinMonthsChange),1,0)) -> 1 | AI10: =IF(B10="","",AD10/N10) -> 0.92122615 | AJ10: =IF(B10="","",MATCH(AI10,Inputs!$B$31:$B$34,1)) -> 2 | AK10: =IF(B10="","",INDEX(Inputs!$C$21:$C$25,MATCH(F10,Inputs!$A$21:$A$25,0))) -> 1.1 | AL10: =IF(B10="","",INDEX(Inputs!$D$21:$D$25,MATCH(F10,Inputs!$A$21:$A$25,0))) -> 0.02 | AM10: =IF(B10="","",N10*CompanyTarget*AK10) -> 71940 | AN10: =IF(B10="","",MAX(0,AM10-AD10)) -> 11691.81 | AO10: =IF(B10="","",IF(AND(ISNUMBER(MaxIncrease),MaxIncrease>0),1,0)) -> 1 | AP10: =IF(B10="","",IF(AO10=1,AD10*MaxIncrease,0)) -> 18074.457 | AQ10: =IF(B10="","",AD10*AL10) -> 1204.9638 | AR10: =IF(B10="","",IF(AK10=0,0,IF(AO10=1,MIN(MAX(AN10,AQ10),AP10),MAX(AN10,AQ10)))) -> 11691.81 | AS10: =IF(B10="","",IF(AD10>=O10,1,0)) -> 0 | AT10: =IF(B10="","",IF(AS10=1,0,AR10)) -> 11691.81 | AU10: =IF(B10="","",MAX(0,O10-AD10)) -> 16051.81 | AV10: =IF(B10="","",IF(ClipAtMax="No",AT10,MIN(AT10,AU10))) -> 11691.81 | AW10: =IF(B10="","",IF(AH10=1,AV10,0)) -> 11691.81 | AX10: =IF(B10="","",IF(AD10>0,AW10/AD10,0)) -> 0.19406077 | AY10: =IF(B10="","",AD10+AW10) -> 71940 | AZ10: =IF(B10="","",IF(AY10<M10,1,0)) -> 0 | BA10: =IF(B10="","",Q10*K10) -> 66514.002 | BB10: =IF(B10="","",RateBelow*MIN(BA10,Ceiling)+AboveCeilingTier1*MIN(MAX(0,BA10-Ceiling),0.1*Ceiling)+AboveCeilingTier2*MIN(MAX(0,BA10-1.1*Ceiling),0.4*Ceiling)+AboveCeilingTier3*MAX(0,BA10-1.5*Ceiling)) -> 19731.306 | BC10: =IF(B10="","",AD10*(1+J10)*K10) -> 66514.002 | BD10: =IF(B10="","",RateBelow*MIN(BC10,Ceiling)+AboveCeilingTier1*MIN(MAX(0,BC10-Ceiling),0.1*Ceiling)+AboveCeilingTier2*MIN(MAX(0,BC10-1.1*Ceiling),0.4*Ceiling)+AboveCeilingTier3*MAX(0,BC10-1.5*Ceiling)) -> 19731.306 | BE10: =IF(B10="","",AY10*(1+J10)*K10) -> 79421.76 | BF10: =IF(B10="","",RateBelow*MIN(BE10,Ceiling)+AboveCeilingTier1*MIN(MAX(0,BE10-Ceiling),0.1*Ceiling)+AboveCeilingTier2*MIN(MAX(0,BE10-1.1*Ceiling),0.4*Ceiling)+AboveCeilingTier3*MAX(0,BE10-1.5*Ceiling)) -> 19864.889 | BG10: =IF(B10="","",AC10*K10) -> 0 | BH10: =IF(B10="","",AC10*J10*K10) -> 0 | BI10: =IF(B10="","",BD10-BB10) -> 0 | BJ10: =IF(B10="","",AW10*K10) -> 11691.81 | BK10: =IF(B10="","",AW10*J10*K10) -> 1215.9482 | BL10: =IF(B10="","",BF10-BD10) -> 133.58322 | BM10: =IF(B10="","",IF(AH10=1,AD10*K10,0)) -> 60248.19 | BN10: =IF(B10="","",IF(AH10=1,AD10*PoolPct,0)) -> 2409.9276 | BO10: =IF(B10="","",BN10*K10) -> 2409.9276 | BP10: =IF(B10="","",BN10*J10*K10) -> 250.63247 | BQ10: =IF(B10="","",(AD10+BN10)*(1+J10)*K10) -> 69174.562 | BR10: =IF(B10="","",RateBelow*MIN(BQ10,Ceiling)+AboveCeilingTier1*MIN(MAX(0,BQ10-Ceiling),0.1*Ceiling)+AboveCeilingTier2*MIN(MAX(0,BQ10-1.1*Ceiling),0.4*Ceiling)+AboveCeilingTier3*MAX(0,BQ10-1.5*Ceiling)) -> 19758.318 | BS10: =IF(B10="","",BR10-BD10) -> 27.012354 | BT10: =IF(B10="","",AD10*(1+J10)) -> 66514.002 | BU10: =IF(B10="","",AY10*(1+J10)) -> 79421.76 | BV10: =IF(B10="","",E10*BU10) -> 714795.84 | BW10: =IF(B10="","",P10*BU10) -> 436846.86 | BX10: =IF(B10="","",IF(COUNTIF($C$5:C10,C10)=1,MAX($BX$4:BX9)+1,""))
A11: =ROW()-4 -> 7 | B11: =IF(INDEX(Employees!$A:$A,A11+1)="","",INDEX(Employees!$A:$A,A11+1)) -> E007 | C11: =IF(B11="","",INDEX(Employees!$A:$Z,MATCH(B11,Employees!$A:$A,0),MATCH("category",Employees!$1:$1,0))) -> Engineering | D11: =IF(B11="","",INDEX(Employees!$A:$Z,MATCH(B11,Employees!$A:$A,0),MATCH("gender",Employees!$1:$1,0))) -> M | E11: =IF(B11="","",INDEX(Employees!$A:$Z,MATCH(B11,Employees!$A:$A,0),MATCH("grade",Employees!$1:$1,0))) -> 7 | F11: =IF(B11="","",INDEX(Employees!$A:$Z,MATCH(B11,Employees!$A:$A,0),MATCH("rating",Employees!$1:$1,0))) -> 5 | G11: =IF(B11="","",INDEX(Employees!$A:$Z,MATCH(B11,Employees!$A:$A,0),MATCH("hire_date",Employees!$1:$1,0))) -> 44725 | H11: =IF(B11="","",INDEX(Employees!$A:$Z,MATCH(B11,Employees!$A:$A,0),MATCH("last_change_date",Employees!$1:$1,0))) -> 46113 | I11: =IF(B11="","",INDEX(Employees!$A:$Z,MATCH(B11,Employees!$A:$A,0),MATCH("base_salary",Employees!$1:$1,0))) -> 47983.14 | J11: =IF(B11="","",INDEX(Employees!$A:$Z,MATCH(B11,Employees!$A:$A,0),MATCH("bonus_pct",Employees!$1:$1,0))/100) -> 0.1181 | K11: =IF(B11="","",INDEX(Employees!$A:$Z,MATCH(B11,Employees!$A:$A,0),MATCH("fte",Employees!$1:$1,0))) -> 1 | L11: =IF(B11="","",IF(ISNA(MATCH(C11&"|"&E11,Bands!$F:$F,0)),0,1)) -> 1 | M11: =IF(B11="","",INDEX(Bands!$C:$C,MATCH(C11&"|"&E11,Bands!$F:$F,0))) -> 41600 | N11: =IF(B11="","",INDEX(Bands!$D:$D,MATCH(C11&"|"&E11,Bands!$F:$F,0))) -> 49900 | O11: =IF(B11="","",INDEX(Bands!$E:$E,MATCH(C11&"|"&E11,Bands!$F:$F,0))) -> 58200 | P11: =IF(B11="","",(EffDate-G11)/365.25) -> 4.7994524 | Q11: =IF(B11="","",I11*(1+J11)) -> 53649.949 | R11: =IF(B11="","",E11^2) -> 49 | S11: =IF(B11="","",P11^2) -> 23.034744 | T11: =IF(B11="","",E11*P11) -> 33.596167 | U11: =IF(B11="","",E11*Q11) -> 375549.64 | V11: =IF(B11="","",P11*Q11) -> 257490.38 | W11: =IF(B11="","",ROUND(Q11,2)) -> 53649.95 | X11: =IF(B11="","",COUNTIFS($C:$C,C11,$W:$W,"<"&W11)+COUNTIFS($C:$C,C11,$W:$W,W11,$B:$B,"<"&B11)+1) -> 7 | Y11: =IF(B11="","",INDEX(Categories!$AH:$AH,MATCH(C11,Categories!$A:$A,0))) -> 71955.394 | Z11: =IF(B11="","",IF(AND(D11="F",Q11<Y11,INDEX(Categories!$AI:$AI,MATCH(C11,Categories!$A:$A,0))>0),1,0)) -> 0 | AA11: =IF(B11="","",IF(Z11=1,Y11-Q11,0)) -> 0 | AB11: =IF(B11="","",IF(Z11=1,INDEX(Categories!$AI:$AI,MATCH(C11,Categories!$A:$A,0))*AA11/INDEX(Categories!$AJ:$AJ,MATCH(C11,Categories!$A:$A,0)),0)) -> 0 | AC11: =IF(B11="","",AB11/(1+J11)) -> 0 | AD11: =IF(B11="","",I11+AC11) -> 47983.14 | AE11: =IF(B11="","",IF(AND(AC11>0,AD11>O11),1,0)) -> 0 | AF11: =IF(B11="","",IF(G11>EffDate,-1,DATEDIF(G11,EffDate,"m"))) -> 57 | AG11: =IF(B11="","",IF(H11>EffDate,-1,DATEDIF(H11,EffDate,"m"))) -> 12 | AH11: =IF(B11="","",IF(AND(AF11>=MinMonthsHire,AG11>=MinMonthsChange),1,0)) -> 1 | AI11: =IF(B11="","",AD11/N11) -> 0.96158597 | AJ11: =IF(B11="","",MATCH(AI11,Inputs!$B$31:$B$34,1)) -> 2 | AK11: =IF(B11="","",INDEX(Inputs!$C$21:$C$25,MATCH(F11,Inputs!$A$21:$A$25,0))) -> 1.1 | AL11: =IF(B11="","",INDEX(Inputs!$D$21:$D$25,MATCH(F11,Inputs!$A$21:$A$25,0))) -> 0.02 | AM11: =IF(B11="","",N11*CompanyTarget*AK11) -> 54890 | AN11: =IF(B11="","",MAX(0,AM11-AD11)) -> 6906.86 | AO11: =IF(B11="","",IF(AND(ISNUMBER(MaxIncrease),MaxIncrease>0),1,0)) -> 1 | AP11: =IF(B11="","",IF(AO11=1,AD11*MaxIncrease,0)) -> 14394.942 | AQ11: =IF(B11="","",AD11*AL11) -> 959.6628 | AR11: =IF(B11="","",IF(AK11=0,0,IF(AO11=1,MIN(MAX(AN11,AQ11),AP11),MAX(AN11,AQ11)))) -> 6906.86 | AS11: =IF(B11="","",IF(AD11>=O11,1,0)) -> 0 | AT11: =IF(B11="","",IF(AS11=1,0,AR11)) -> 6906.86 | AU11: =IF(B11="","",MAX(0,O11-AD11)) -> 10216.86 | AV11: =IF(B11="","",IF(ClipAtMax="No",AT11,MIN(AT11,AU11))) -> 6906.86 | AW11: =IF(B11="","",IF(AH11=1,AV11,0)) -> 6906.86 | AX11: =IF(B11="","",IF(AD11>0,AW11/AD11,0)) -> 0.14394348 | AY11: =IF(B11="","",AD11+AW11) -> 54890 | AZ11: =IF(B11="","",IF(AY11<M11,1,0)) -> 0 | BA11: =IF(B11="","",Q11*K11) -> 53649.949 | BB11: =IF(B11="","",RateBelow*MIN(BA11,Ceiling)+AboveCeilingTier1*MIN(MAX(0,BA11-Ceiling),0.1*Ceiling)+AboveCeilingTier2*MIN(MAX(0,BA11-1.1*Ceiling),0.4*Ceiling)+AboveCeilingTier3*MAX(0,BA11-1.5*Ceiling)) -> 17248.459 | BC11: =IF(B11="","",AD11*(1+J11)*K11) -> 53649.949 | BD11: =IF(B11="","",RateBelow*MIN(BC11,Ceiling)+AboveCeilingTier1*MIN(MAX(0,BC11-Ceiling),0.1*Ceiling)+AboveCeilingTier2*MIN(MAX(0,BC11-1.1*Ceiling),0.4*Ceiling)+AboveCeilingTier3*MAX(0,BC11-1.5*Ceiling)) -> 17248.459 | BE11: =IF(B11="","",AY11*(1+J11)*K11) -> 61372.509 | BF11: =IF(B11="","",RateBelow*MIN(BE11,Ceiling)+AboveCeilingTier1*MIN(MAX(0,BE11-Ceiling),0.1*Ceiling)+AboveCeilingTier2*MIN(MAX(0,BE11-1.1*Ceiling),0.4*Ceiling)+AboveCeilingTier3*MAX(0,BE11-1.5*Ceiling)) -> 19681.947 | BG11: =IF(B11="","",AC11*K11) -> 0 | BH11: =IF(B11="","",AC11*J11*K11) -> 0 | BI11: =IF(B11="","",BD11-BB11) -> 0 | BJ11: =IF(B11="","",AW11*K11) -> 6906.86 | BK11: =IF(B11="","",AW11*J11*K11) -> 815.70017 | BL11: =IF(B11="","",BF11-BD11) -> 2433.4889 | BM11: =IF(B11="","",IF(AH11=1,AD11*K11,0)) -> 47983.14 | BN11: =IF(B11="","",IF(AH11=1,AD11*PoolPct,0)) -> 1919.3256 | BO11: =IF(B11="","",BN11*K11) -> 1919.3256 | BP11: =IF(B11="","",BN11*J11*K11) -> 226.67235 | BQ11: =IF(B11="","",(AD11+BN11)*(1+J11)*K11) -> 55795.947 | BR11: =IF(B11="","",RateBelow*MIN(BQ11,Ceiling)+AboveCeilingTier1*MIN(MAX(0,BQ11-Ceiling),0.1*Ceiling)+AboveCeilingTier2*MIN(MAX(0,BQ11-1.1*Ceiling),0.4*Ceiling)+AboveCeilingTier3*MAX(0,BQ11-1.5*Ceiling)) -> 17938.397 | BS11: =IF(B11="","",BR11-BD11) -> 689.93834 | BT11: =IF(B11="","",AD11*(1+J11)) -> 53649.949 | BU11: =IF(B11="","",AY11*(1+J11)) -> 61372.509 | BV11: =IF(B11="","",E11*BU11) -> 429607.56 | BW11: =IF(B11="","",P11*BU11) -> 294554.44 | BX11: =IF(B11="","",IF(COUNTIF($C$5:C11,C11)=1,MAX($BX$4:BX10)+1,""))
A12: =ROW()-4 -> 8 | B12: =IF(INDEX(Employees!$A:$A,A12+1)="","",INDEX(Employees!$A:$A,A12+1)) -> E008 | C12: =IF(B12="","",INDEX(Employees!$A:$Z,MATCH(B12,Employees!$A:$A,0),MATCH("category",Employees!$1:$1,0))) -> Engineering | D12: =IF(B12="","",INDEX(Employees!$A:$Z,MATCH(B12,Employees!$A:$A,0),MATCH("gender",Employees!$1:$1,0))) -> M | E12: =IF(B12="","",INDEX(Employees!$A:$Z,MATCH(B12,Employees!$A:$A,0),MATCH("grade",Employees!$1:$1,0))) -> 11 | F12: =IF(B12="","",INDEX(Employees!$A:$Z,MATCH(B12,Employees!$A:$A,0),MATCH("rating",Employees!$1:$1,0))) -> 2 | G12: =IF(B12="","",INDEX(Employees!$A:$Z,MATCH(B12,Employees!$A:$A,0),MATCH("hire_date",Employees!$1:$1,0))) -> 44067 | H12: =IF(B12="","",INDEX(Employees!$A:$Z,MATCH(B12,Employees!$A:$A,0),MATCH("last_change_date",Employees!$1:$1,0))) -> 46113 | I12: =IF(B12="","",INDEX(Employees!$A:$Z,MATCH(B12,Employees!$A:$A,0),MATCH("base_salary",Employees!$1:$1,0))) -> 79273.59 | J12: =IF(B12="","",INDEX(Employees!$A:$Z,MATCH(B12,Employees!$A:$A,0),MATCH("bonus_pct",Employees!$1:$1,0))/100) -> 0.0924 | K12: =IF(B12="","",INDEX(Employees!$A:$Z,MATCH(B12,Employees!$A:$A,0),MATCH("fte",Employees!$1:$1,0))) -> 1 | L12: =IF(B12="","",IF(ISNA(MATCH(C12&"|"&E12,Bands!$F:$F,0)),0,1)) -> 1 | M12: =IF(B12="","",INDEX(Bands!$C:$C,MATCH(C12&"|"&E12,Bands!$F:$F,0))) -> 68400 | N12: =IF(B12="","",INDEX(Bands!$D:$D,MATCH(C12&"|"&E12,Bands!$F:$F,0))) -> 85500 | O12: =IF(B12="","",INDEX(Bands!$E:$E,MATCH(C12&"|"&E12,Bands!$F:$F,0))) -> 102600 | P12: =IF(B12="","",(EffDate-G12)/365.25) -> 6.6009582 | Q12: =IF(B12="","",I12*(1+J12)) -> 86598.47 | R12: =IF(B12="","",E12^2) -> 121 | S12: =IF(B12="","",P12^2) -> 43.57265 | T12: =IF(B12="","",E12*P12) -> 72.610541 | U12: =IF(B12="","",E12*Q12) -> 952583.17 | V12: =IF(B12="","",P12*Q12) -> 571632.88 | W12: =IF(B12="","",ROUND(Q12,2)) -> 86598.47 | X12: =IF(B12="","",COUNTIFS($C:$C,C12,$W:$W,"<"&W12)+COUNTIFS($C:$C,C12,$W:$W,W12,$B:$B,"<"&B12)+1) -> 37 | Y12: =IF(B12="","",INDEX(Categories!$AH:$AH,MATCH(C12,Categories!$A:$A,0))) -> 71955.394 | Z12: =IF(B12="","",IF(AND(D12="F",Q12<Y12,INDEX(Categories!$AI:$AI,MATCH(C12,Categories!$A:$A,0))>0),1,0)) -> 0 | AA12: =IF(B12="","",IF(Z12=1,Y12-Q12,0)) -> 0 | AB12: =IF(B12="","",IF(Z12=1,INDEX(Categories!$AI:$AI,MATCH(C12,Categories!$A:$A,0))*AA12/INDEX(Categories!$AJ:$AJ,MATCH(C12,Categories!$A:$A,0)),0)) -> 0 | AC12: =IF(B12="","",AB12/(1+J12)) -> 0 | AD12: =IF(B12="","",I12+AC12) -> 79273.59 | AE12: =IF(B12="","",IF(AND(AC12>0,AD12>O12),1,0)) -> 0 | AF12: =IF(B12="","",IF(G12>EffDate,-1,DATEDIF(G12,EffDate,"m"))) -> 79 | AG12: =IF(B12="","",IF(H12>EffDate,-1,DATEDIF(H12,EffDate,"m"))) -> 12 | AH12: =IF(B12="","",IF(AND(AF12>=MinMonthsHire,AG12>=MinMonthsChange),1,0)) -> 1 | AI12: =IF(B12="","",AD12/N12) -> 0.92717649 | AJ12: =IF(B12="","",MATCH(AI12,Inputs!$B$31:$B$34,1)) -> 2 | AK12: =IF(B12="","",INDEX(Inputs!$C$21:$C$25,MATCH(F12,Inputs!$A$21:$A$25,0))) -> 0.95 | AL12: =IF(B12="","",INDEX(Inputs!$D$21:$D$25,MATCH(F12,Inputs!$A$21:$A$25,0))) -> 0 | AM12: =IF(B12="","",N12*CompanyTarget*AK12) -> 81225 | AN12: =IF(B12="","",MAX(0,AM12-AD12)) -> 1951.41 | AO12: =IF(B12="","",IF(AND(ISNUMBER(MaxIncrease),MaxIncrease>0),1,0)) -> 1 | AP12: =IF(B12="","",IF(AO12=1,AD12*MaxIncrease,0)) -> 23782.077 | AQ12: =IF(B12="","",AD12*AL12) -> 0 | AR12: =IF(B12="","",IF(AK12=0,0,IF(AO12=1,MIN(MAX(AN12,AQ12),AP12),MAX(AN12,AQ12)))) -> 1951.41 | AS12: =IF(B12="","",IF(AD12>=O12,1,0)) -> 0 | AT12: =IF(B12="","",IF(AS12=1,0,AR12)) -> 1951.41 | AU12: =IF(B12="","",MAX(0,O12-AD12)) -> 23326.41 | AV12: =IF(B12="","",IF(ClipAtMax="No",AT12,MIN(AT12,AU12))) -> 1951.41 | AW12: =IF(B12="","",IF(AH12=1,AV12,0)) -> 1951.41 | AX12: =IF(B12="","",IF(AD12>0,AW12/AD12,0)) -> 0.024616143 | AY12: =IF(B12="","",AD12+AW12) -> 81225 | AZ12: =IF(B12="","",IF(AY12<M12,1,0)) -> 0 | BA12: =IF(B12="","",Q12*K12) -> 86598.47 | BB12: =IF(B12="","",RateBelow*MIN(BA12,Ceiling)+AboveCeilingTier1*MIN(MAX(0,BA12-Ceiling),0.1*Ceiling)+AboveCeilingTier2*MIN(MAX(0,BA12-1.1*Ceiling),0.4*Ceiling)+AboveCeilingTier3*MAX(0,BA12-1.5*Ceiling)) -> 19939.527 | BC12: =IF(B12="","",AD12*(1+J12)*K12) -> 86598.47 | BD12: =IF(B12="","",RateBelow*MIN(BC12,Ceiling)+AboveCeilingTier1*MIN(MAX(0,BC12-Ceiling),0.1*Ceiling)+AboveCeilingTier2*MIN(MAX(0,BC12-1.1*Ceiling),0.4*Ceiling)+AboveCeilingTier3*MAX(0,BC12-1.5*Ceiling)) -> 19939.527 | BE12: =IF(B12="","",AY12*(1+J12)*K12) -> 88730.19 | BF12: =IF(B12="","",RateBelow*MIN(BE12,Ceiling)+AboveCeilingTier1*MIN(MAX(0,BE12-Ceiling),0.1*Ceiling)+AboveCeilingTier2*MIN(MAX(0,BE12-1.1*Ceiling),0.4*Ceiling)+AboveCeilingTier3*MAX(0,BE12-1.5*Ceiling)) -> 19961.697 | BG12: =IF(B12="","",AC12*K12) -> 0 | BH12: =IF(B12="","",AC12*J12*K12) -> 0 | BI12: =IF(B12="","",BD12-BB12) -> 0 | BJ12: =IF(B12="","",AW12*K12) -> 1951.41 | BK12: =IF(B12="","",AW12*J12*K12) -> 180.31028 | BL12: =IF(B12="","",BF12-BD12) -> 22.169891 | BM12: =IF(B12="","",IF(AH12=1,AD12*K12,0)) -> 79273.59 | BN12: =IF(B12="","",IF(AH12=1,AD12*PoolPct,0)) -> 3170.9436 | BO12: =IF(B12="","",BN12*K12) -> 3170.9436 | BP12: =IF(B12="","",BN12*J12*K12) -> 292.99519 | BQ12: =IF(B12="","",(AD12+BN12)*(1+J12)*K12) -> 90062.409 | BR12: =IF(B12="","",RateBelow*MIN(BQ12,Ceiling)+AboveCeilingTier1*MIN(MAX(0,BQ12-Ceiling),0.1*Ceiling)+AboveCeilingTier2*MIN(MAX(0,BQ12-1.1*Ceiling),0.4*Ceiling)+AboveCeilingTier3*MAX(0,BQ12-1.5*Ceiling)) -> 19975.552 | BS12: =IF(B12="","",BR12-BD12) -> 36.024963 | BT12: =IF(B12="","",AD12*(1+J12)) -> 86598.47 | BU12: =IF(B12="","",AY12*(1+J12)) -> 88730.19 | BV12: =IF(B12="","",E12*BU12) -> 976032.09 | BW12: =IF(B12="","",P12*BU12) -> 585704.28 | BX12: =IF(B12="","",IF(COUNTIF($C$5:C12,C12)=1,MAX($BX$4:BX11)+1,""))
A13: =ROW()-4 -> 9 | B13: =IF(INDEX(Employees!$A:$A,A13+1)="","",INDEX(Employees!$A:$A,A13+1)) -> E009 | C13: =IF(B13="","",INDEX(Employees!$A:$Z,MATCH(B13,Employees!$A:$A,0),MATCH("category",Employees!$1:$1,0))) -> Engineering | D13: =IF(B13="","",INDEX(Employees!$A:$Z,MATCH(B13,Employees!$A:$A,0),MATCH("gender",Employees!$1:$1,0))) -> M | E13: =IF(B13="","",INDEX(Employees!$A:$Z,MATCH(B13,Employees!$A:$A,0),MATCH("grade",Employees!$1:$1,0))) -> 8 | F13: =IF(B13="","",INDEX(Employees!$A:$Z,MATCH(B13,Employees!$A:$A,0),MATCH("rating",Employees!$1:$1,0))) -> 3 | G13: =IF(B13="","",INDEX(Employees!$A:$Z,MATCH(B13,Employees!$A:$A,0),MATCH("hire_date",Employees!$1:$1,0))) -> 44323 | H13: =IF(B13="","",INDEX(Employees!$A:$Z,MATCH(B13,Employees!$A:$A,0),MATCH("last_change_date",Employees!$1:$1,0))) -> 46113 | I13: =IF(B13="","",INDEX(Employees!$A:$Z,MATCH(B13,Employees!$A:$A,0),MATCH("base_salary",Employees!$1:$1,0))) -> 56597.91 | J13: =IF(B13="","",INDEX(Employees!$A:$Z,MATCH(B13,Employees!$A:$A,0),MATCH("bonus_pct",Employees!$1:$1,0))/100) -> 0.1073 | K13: =IF(B13="","",INDEX(Employees!$A:$Z,MATCH(B13,Employees!$A:$A,0),MATCH("fte",Employees!$1:$1,0))) -> 1 | L13: =IF(B13="","",IF(ISNA(MATCH(C13&"|"&E13,Bands!$F:$F,0)),0,1)) -> 1 | M13: =IF(B13="","",INDEX(Bands!$C:$C,MATCH(C13&"|"&E13,Bands!$F:$F,0))) -> 47700 | N13: =IF(B13="","",INDEX(Bands!$D:$D,MATCH(C13&"|"&E13,Bands!$F:$F,0))) -> 57200 | O13: =IF(B13="","",INDEX(Bands!$E:$E,MATCH(C13&"|"&E13,Bands!$F:$F,0))) -> 66800 | P13: =IF(B13="","",(EffDate-G13)/365.25) -> 5.9000684 | Q13: =IF(B13="","",I13*(1+J13)) -> 62670.866 | R13: =IF(B13="","",E13^2) -> 64 | S13: =IF(B13="","",P13^2) -> 34.810808 | T13: =IF(B13="","",E13*P13) -> 47.200548 | U13: =IF(B13="","",E13*Q13) -> 501366.93 | V13: =IF(B13="","",P13*Q13) -> 369762.4 | W13: =IF(B13="","",ROUND(Q13,2)) -> 62670.87 | X13: =IF(B13="","",COUNTIFS($C:$C,C13,$W:$W,"<"&W13)+COUNTIFS($C:$C,C13,$W:$W,W13,$B:$B,"<"&B13)+1) -> 15 | Y13: =IF(B13="","",INDEX(Categories!$AH:$AH,MATCH(C13,Categories!$A:$A,0))) -> 71955.394 | Z13: =IF(B13="","",IF(AND(D13="F",Q13<Y13,INDEX(Categories!$AI:$AI,MATCH(C13,Categories!$A:$A,0))>0),1,0)) -> 0 | AA13: =IF(B13="","",IF(Z13=1,Y13-Q13,0)) -> 0 | AB13: =IF(B13="","",IF(Z13=1,INDEX(Categories!$AI:$AI,MATCH(C13,Categories!$A:$A,0))*AA13/INDEX(Categories!$AJ:$AJ,MATCH(C13,Categories!$A:$A,0)),0)) -> 0 | AC13: =IF(B13="","",AB13/(1+J13)) -> 0 | AD13: =IF(B13="","",I13+AC13) -> 56597.91 | AE13: =IF(B13="","",IF(AND(AC13>0,AD13>O13),1,0)) -> 0 | AF13: =IF(B13="","",IF(G13>EffDate,-1,DATEDIF(G13,EffDate,"m"))) -> 70 | AG13: =IF(B13="","",IF(H13>EffDate,-1,DATEDIF(H13,EffDate,"m"))) -> 12 | AH13: =IF(B13="","",IF(AND(AF13>=MinMonthsHire,AG13>=MinMonthsChange),1,0)) -> 1 | AI13: =IF(B13="","",AD13/N13) -> 0.98947395 | AJ13: =IF(B13="","",MATCH(AI13,Inputs!$B$31:$B$34,1)) -> 2 | AK13: =IF(B13="","",INDEX(Inputs!$C$21:$C$25,MATCH(F13,Inputs!$A$21:$A$25,0))) -> 1 | AL13: =IF(B13="","",INDEX(Inputs!$D$21:$D$25,MATCH(F13,Inputs!$A$21:$A$25,0))) -> 0 | AM13: =IF(B13="","",N13*CompanyTarget*AK13) -> 57200 | AN13: =IF(B13="","",MAX(0,AM13-AD13)) -> 602.09 | AO13: =IF(B13="","",IF(AND(ISNUMBER(MaxIncrease),MaxIncrease>0),1,0)) -> 1 | AP13: =IF(B13="","",IF(AO13=1,AD13*MaxIncrease,0)) -> 16979.373 | AQ13: =IF(B13="","",AD13*AL13) -> 0 | AR13: =IF(B13="","",IF(AK13=0,0,IF(AO13=1,MIN(MAX(AN13,AQ13),AP13),MAX(AN13,AQ13)))) -> 602.09 | AS13: =IF(B13="","",IF(AD13>=O13,1,0)) -> 0 | AT13: =IF(B13="","",IF(AS13=1,0,AR13)) -> 602.09 | AU13: =IF(B13="","",MAX(0,O13-AD13)) -> 10202.09 | AV13: =IF(B13="","",IF(ClipAtMax="No",AT13,MIN(AT13,AU13))) -> 602.09 | AW13: =IF(B13="","",IF(AH13=1,AV13,0)) -> 602.09 | AX13: =IF(B13="","",IF(AD13>0,AW13/AD13,0)) -> 0.010638025 | AY13: =IF(B13="","",AD13+AW13) -> 57200 | AZ13: =IF(B13="","",IF(AY13<M13,1,0)) -> 0 | BA13: =IF(B13="","",Q13*K13) -> 62670.866 | BB13: =IF(B13="","",RateBelow*MIN(BA13,Ceiling)+AboveCeilingTier1*MIN(MAX(0,BA13-Ceiling),0.1*Ceiling)+AboveCeilingTier2*MIN(MAX(0,BA13-1.1*Ceiling),0.4*Ceiling)+AboveCeilingTier3*MAX(0,BA13-1.5*Ceiling)) -> 19694.412 | BC13: =IF(B13="","",AD13*(1+J13)*K13) -> 62670.866 | BD13: =IF(B13="","",RateBelow*MIN(BC13,Ceiling)+AboveCeilingTier1*MIN(MAX(0,BC13-Ceiling),0.1*Ceiling)+AboveCeilingTier2*MIN(MAX(0,BC13-1.1*Ceiling),0.4*Ceiling)+AboveCeilingTier3*MAX(0,BC13-1.5*Ceiling)) -> 19694.412 | BE13: =IF(B13="","",AY13*(1+J13)*K13) -> 63337.56 | BF13: =IF(B13="","",RateBelow*MIN(BE13,Ceiling)+AboveCeilingTier1*MIN(MAX(0,BE13-Ceiling),0.1*Ceiling)+AboveCeilingTier2*MIN(MAX(0,BE13-1.1*Ceiling),0.4*Ceiling)+AboveCeilingTier3*MAX(0,BE13-1.5*Ceiling)) -> 19700.812 | BG13: =IF(B13="","",AC13*K13) -> 0 | BH13: =IF(B13="","",AC13*J13*K13) -> 0 | BI13: =IF(B13="","",BD13-BB13) -> 0 | BJ13: =IF(B13="","",AW13*K13) -> 602.09 | BK13: =IF(B13="","",AW13*J13*K13) -> 64.604257 | BL13: =IF(B13="","",BF13-BD13) -> 6.4002649 | BM13: =IF(B13="","",IF(AH13=1,AD13*K13,0)) -> 56597.91 | BN13: =IF(B13="","",IF(AH13=1,AD13*PoolPct,0)) -> 2263.9164 | BO13: =IF(B13="","",BN13*K13) -> 2263.9164 | BP13: =IF(B13="","",BN13*J13*K13) -> 242.91823 | BQ13: =IF(B13="","",(AD13+BN13)*(1+J13)*K13) -> 65177.7 | BR13: =IF(B13="","",RateBelow*MIN(BQ13,Ceiling)+AboveCeilingTier1*MIN(MAX(0,BQ13-Ceiling),0.1*Ceiling)+AboveCeilingTier2*MIN(MAX(0,BQ13-1.1*Ceiling),0.4*Ceiling)+AboveCeilingTier3*MAX(0,BQ13-1.5*Ceiling)) -> 19718.477 | BS13: =IF(B13="","",BR13-BD13) -> 24.065612 | BT13: =IF(B13="","",AD13*(1+J13)) -> 62670.866 | BU13: =IF(B13="","",AY13*(1+J13)) -> 63337.56 | BV13: =IF(B13="","",E13*BU13) -> 506700.48 | BW13: =IF(B13="","",P13*BU13) -> 373695.94 | BX13: =IF(B13="","",IF(COUNTIF($C$5:C13,C13)=1,MAX($BX$4:BX12)+1,""))
A14: =ROW()-4 -> 10 | B14: =IF(INDEX(Employees!$A:$A,A14+1)="","",INDEX(Employees!$A:$A,A14+1)) -> E010 | C14: =IF(B14="","",INDEX(Employees!$A:$Z,MATCH(B14,Employees!$A:$A,0),MATCH("category",Employees!$1:$1,0))) -> Engineering | D14: =IF(B14="","",INDEX(Employees!$A:$Z,MATCH(B14,Employees!$A:$A,0),MATCH("gender",Employees!$1:$1,0))) -> M | E14: =IF(B14="","",INDEX(Employees!$A:$Z,MATCH(B14,Employees!$A:$A,0),MATCH("grade",Employees!$1:$1,0))) -> 10 | F14: =IF(B14="","",INDEX(Employees!$A:$Z,MATCH(B14,Employees!$A:$A,0),MATCH("rating",Employees!$1:$1,0))) -> 3 | G14: =IF(B14="","",INDEX(Employees!$A:$Z,MATCH(B14,Employees!$A:$A,0),MATCH("hire_date",Employees!$1:$1,0))) -> 42935 | H14: =IF(B14="","",INDEX(Employees!$A:$Z,MATCH(B14,Employees!$A:$A,0),MATCH("last_change_date",Employees!$1:$1,0))) -> 46113 | I14: =IF(B14="","",INDEX(Employees!$A:$Z,MATCH(B14,Employees!$A:$A,0),MATCH("base_salary",Employees!$1:$1,0))) -> 75607.45 | J14: =IF(B14="","",INDEX(Employees!$A:$Z,MATCH(B14,Employees!$A:$A,0),MATCH("bonus_pct",Employees!$1:$1,0))/100) -> 0.1199 | K14: =IF(B14="","",INDEX(Employees!$A:$Z,MATCH(B14,Employees!$A:$A,0),MATCH("fte",Employees!$1:$1,0))) -> 1 | L14: =IF(B14="","",IF(ISNA(MATCH(C14&"|"&E14,Bands!$F:$F,0)),0,1)) -> 1 | M14: =IF(B14="","",INDEX(Bands!$C:$C,MATCH(C14&"|"&E14,Bands!$F:$F,0))) -> 59800 | N14: =IF(B14="","",INDEX(Bands!$D:$D,MATCH(C14&"|"&E14,Bands!$F:$F,0))) -> 74800 | O14: =IF(B14="","",INDEX(Bands!$E:$E,MATCH(C14&"|"&E14,Bands!$F:$F,0))) -> 89700 | P14: =IF(B14="","",(EffDate-G14)/365.25) -> 9.7002053 | Q14: =IF(B14="","",I14*(1+J14)) -> 84672.783 | R14: =IF(B14="","",E14^2) -> 100 | S14: =IF(B14="","",P14^2) -> 94.093984 | T14: =IF(B14="","",E14*P14) -> 97.002053 | U14: =IF(B14="","",E14*Q14) -> 846727.83 | V14: =IF(B14="","",P14*Q14) -> 821343.38 | W14: =IF(B14="","",ROUND(Q14,2)) -> 84672.78 | X14: =IF(B14="","",COUNTIFS($C:$C,C14,$W:$W,"<"&W14)+COUNTIFS($C:$C,C14,$W:$W,W14,$B:$B,"<"&B14)+1) -> 36 | Y14: =IF(B14="","",INDEX(Categories!$AH:$AH,MATCH(C14,Categories!$A:$A,0))) -> 71955.394 | Z14: =IF(B14="","",IF(AND(D14="F",Q14<Y14,INDEX(Categories!$AI:$AI,MATCH(C14,Categories!$A:$A,0))>0),1,0)) -> 0 | AA14: =IF(B14="","",IF(Z14=1,Y14-Q14,0)) -> 0 | AB14: =IF(B14="","",IF(Z14=1,INDEX(Categories!$AI:$AI,MATCH(C14,Categories!$A:$A,0))*AA14/INDEX(Categories!$AJ:$AJ,MATCH(C14,Categories!$A:$A,0)),0)) -> 0 | AC14: =IF(B14="","",AB14/(1+J14)) -> 0 | AD14: =IF(B14="","",I14+AC14) -> 75607.45 | AE14: =IF(B14="","",IF(AND(AC14>0,AD14>O14),1,0)) -> 0 | AF14: =IF(B14="","",IF(G14>EffDate,-1,DATEDIF(G14,EffDate,"m"))) -> 116 | AG14: =IF(B14="","",IF(H14>EffDate,-1,DATEDIF(H14,EffDate,"m"))) -> 12 | AH14: =IF(B14="","",IF(AND(AF14>=MinMonthsHire,AG14>=MinMonthsChange),1,0)) -> 1 | AI14: =IF(B14="","",AD14/N14) -> 1.0107948 | AJ14: =IF(B14="","",MATCH(AI14,Inputs!$B$31:$B$34,1)) -> 3 | AK14: =IF(B14="","",INDEX(Inputs!$C$21:$C$25,MATCH(F14,Inputs!$A$21:$A$25,0))) -> 1 | AL14: =IF(B14="","",INDEX(Inputs!$D$21:$D$25,MATCH(F14,Inputs!$A$21:$A$25,0))) -> 0 | AM14: =IF(B14="","",N14*CompanyTarget*AK14) -> 74800 | AN14: =IF(B14="","",MAX(0,AM14-AD14)) -> 0 | AO14: =IF(B14="","",IF(AND(ISNUMBER(MaxIncrease),MaxIncrease>0),1,0)) -> 1 | AP14: =IF(B14="","",IF(AO14=1,AD14*MaxIncrease,0)) -> 22682.235 | AQ14: =IF(B14="","",AD14*AL14) -> 0 | AR14: =IF(B14="","",IF(AK14=0,0,IF(AO14=1,MIN(MAX(AN14,AQ14),AP14),MAX(AN14,AQ14)))) -> 0 | AS14: =IF(B14="","",IF(AD14>=O14,1,0)) -> 0 | AT14: =IF(B14="","",IF(AS14=1,0,AR14)) -> 0 | AU14: =IF(B14="","",MAX(0,O14-AD14)) -> 14092.55 | AV14: =IF(B14="","",IF(ClipAtMax="No",AT14,MIN(AT14,AU14))) -> 0 | AW14: =IF(B14="","",IF(AH14=1,AV14,0)) -> 0 | AX14: =IF(B14="","",IF(AD14>0,AW14/AD14,0)) -> 0 | AY14: =IF(B14="","",AD14+AW14) -> 75607.45 | AZ14: =IF(B14="","",IF(AY14<M14,1,0)) -> 0 | BA14: =IF(B14="","",Q14*K14) -> 84672.783 | BB14: =IF(B14="","",RateBelow*MIN(BA14,Ceiling)+AboveCeilingTier1*MIN(MAX(0,BA14-Ceiling),0.1*Ceiling)+AboveCeilingTier2*MIN(MAX(0,BA14-1.1*Ceiling),0.4*Ceiling)+AboveCeilingTier3*MAX(0,BA14-1.5*Ceiling)) -> 19919.5 | BC14: =IF(B14="","",AD14*(1+J14)*K14) -> 84672.783 | BD14: =IF(B14="","",RateBelow*MIN(BC14,Ceiling)+AboveCeilingTier1*MIN(MAX(0,BC14-Ceiling),0.1*Ceiling)+AboveCeilingTier2*MIN(MAX(0,BC14-1.1*Ceiling),0.4*Ceiling)+AboveCeilingTier3*MAX(0,BC14-1.5*Ceiling)) -> 19919.5 | BE14: =IF(B14="","",AY14*(1+J14)*K14) -> 84672.783 | BF14: =IF(B14="","",RateBelow*MIN(BE14,Ceiling)+AboveCeilingTier1*MIN(MAX(0,BE14-Ceiling),0.1*Ceiling)+AboveCeilingTier2*MIN(MAX(0,BE14-1.1*Ceiling),0.4*Ceiling)+AboveCeilingTier3*MAX(0,BE14-1.5*Ceiling)) -> 19919.5 | BG14: =IF(B14="","",AC14*K14) -> 0 | BH14: =IF(B14="","",AC14*J14*K14) -> 0 | BI14: =IF(B14="","",BD14-BB14) -> 0 | BJ14: =IF(B14="","",AW14*K14) -> 0 | BK14: =IF(B14="","",AW14*J14*K14) -> 0 | BL14: =IF(B14="","",BF14-BD14) -> 0 | BM14: =IF(B14="","",IF(AH14=1,AD14*K14,0)) -> 75607.45 | BN14: =IF(B14="","",IF(AH14=1,AD14*PoolPct,0)) -> 3024.298 | BO14: =IF(B14="","",BN14*K14) -> 3024.298 | BP14: =IF(B14="","",BN14*J14*K14) -> 362.61333 | BQ14: =IF(B14="","",(AD14+BN14)*(1+J14)*K14) -> 88059.695 | BR14: =IF(B14="","",RateBelow*MIN(BQ14,Ceiling)+AboveCeilingTier1*MIN(MAX(0,BQ14-Ceiling),0.1*Ceiling)+AboveCeilingTier2*MIN(MAX(0,BQ14-1.1*Ceiling),0.4*Ceiling)+AboveCeilingTier3*MAX(0,BQ14-1.5*Ceiling)) -> 19954.724 | BS14: =IF(B14="","",BR14-BD14) -> 35.223878 | BT14: =IF(B14="","",AD14*(1+J14)) -> 84672.783 | BU14: =IF(B14="","",AY14*(1+J14)) -> 84672.783 | BV14: =IF(B14="","",E14*BU14) -> 846727.83 | BW14: =IF(B14="","",P14*BU14) -> 821343.38 | BX14: =IF(B14="","",IF(COUNTIF($C$5:C14,C14)=1,MAX($BX$4:BX13)+1,""))
A15: =ROW()-4 -> 11 | B15: =IF(INDEX(Employees!$A:$A,A15+1)="","",INDEX(Employees!$A:$A,A15+1)) -> E011 | C15: =IF(B15="","",INDEX(Employees!$A:$Z,MATCH(B15,Employees!$A:$A,0),MATCH("category",Employees!$1:$1,0))) -> Engineering | D15: =IF(B15="","",INDEX(Employees!$A:$Z,MATCH(B15,Employees!$A:$A,0),MATCH("gender",Employees!$1:$1,0))) -> M | E15: =IF(B15="","",INDEX(Employees!$A:$Z,MATCH(B15,Employees!$A:$A,0),MATCH("grade",Employees!$1:$1,0))) -> 7 | F15: =IF(B15="","",INDEX(Employees!$A:$Z,MATCH(B15,Employees!$A:$A,0),MATCH("rating",Employees!$1:$1,0))) -> 2 | G15: =IF(B15="","",INDEX(Employees!$A:$Z,MATCH(B15,Employees!$A:$A,0),MATCH("hire_date",Employees!$1:$1,0))) -> 45455 | H15: =IF(B15="","",INDEX(Employees!$A:$Z,MATCH(B15,Employees!$A:$A,0),MATCH("last_change_date",Employees!$1:$1,0))) -> 46113 | I15: =IF(B15="","",INDEX(Employees!$A:$Z,MATCH(B15,Employees!$A:$A,0),MATCH("base_salary",Employees!$1:$1,0))) -> 37697.15 | J15: =IF(B15="","",INDEX(Employees!$A:$Z,MATCH(B15,Employees!$A:$A,0),MATCH("bonus_pct",Employees!$1:$1,0))/100) -> 0.1404 | K15: =IF(B15="","",INDEX(Employees!$A:$Z,MATCH(B15,Employees!$A:$A,0),MATCH("fte",Employees!$1:$1,0))) -> 1 | L15: =IF(B15="","",IF(ISNA(MATCH(C15&"|"&E15,Bands!$F:$F,0)),0,1)) -> 1 | M15: =IF(B15="","",INDEX(Bands!$C:$C,MATCH(C15&"|"&E15,Bands!$F:$F,0))) -> 41600 | N15: =IF(B15="","",INDEX(Bands!$D:$D,MATCH(C15&"|"&E15,Bands!$F:$F,0))) -> 49900 | O15: =IF(B15="","",INDEX(Bands!$E:$E,MATCH(C15&"|"&E15,Bands!$F:$F,0))) -> 58200 | P15: =IF(B15="","",(EffDate-G15)/365.25) -> 2.8008214 | Q15: =IF(B15="","",I15*(1+J15)) -> 42989.83 | R15: =IF(B15="","",E15^2) -> 49 | S15: =IF(B15="","",P15^2) -> 7.8446003 | T15: =IF(B15="","",E15*P15) -> 19.605749 | U15: =IF(B15="","",E15*Q15) -> 300928.81 | V15: =IF(B15="","",P15*Q15) -> 120406.83 | W15: =IF(B15="","",ROUND(Q15,2)) -> 42989.83 | X15: =IF(B15="","",COUNTIFS($C:$C,C15,$W:$W,"<"&W15)+COUNTIFS($C:$C,C15,$W:$W,W15,$B:$B,"<"&B15)+1) -> 1 | Y15: =IF(B15="","",INDEX(Categories!$AH:$AH,MATCH(C15,Categories!$A:$A,0))) -> 71955.394 | Z15: =IF(B15="","",IF(AND(D15="F",Q15<Y15,INDEX(Categories!$AI:$AI,MATCH(C15,Categories!$A:$A,0))>0),1,0)) -> 0 | AA15: =IF(B15="","",IF(Z15=1,Y15-Q15,0)) -> 0 | AB15: =IF(B15="","",IF(Z15=1,INDEX(Categories!$AI:$AI,MATCH(C15,Categories!$A:$A,0))*AA15/INDEX(Categories!$AJ:$AJ,MATCH(C15,Categories!$A:$A,0)),0)) -> 0 | AC15: =IF(B15="","",AB15/(1+J15)) -> 0 | AD15: =IF(B15="","",I15+AC15) -> 37697.15 | AE15: =IF(B15="","",IF(AND(AC15>0,AD15>O15),1,0)) -> 0 | AF15: =IF(B15="","",IF(G15>EffDate,-1,DATEDIF(G15,EffDate,"m"))) -> 33 | AG15: =IF(B15="","",IF(H15>EffDate,-1,DATEDIF(H15,EffDate,"m"))) -> 12 | AH15: =IF(B15="","",IF(AND(AF15>=MinMonthsHire,AG15>=MinMonthsChange),1,0)) -> 1 | AI15: =IF(B15="","",AD15/N15) -> 0.75545391 | AJ15: =IF(B15="","",MATCH(AI15,Inputs!$B$31:$B$34,1)) -> 1 | AK15: =IF(B15="","",INDEX(Inputs!$C$21:$C$25,MATCH(F15,Inputs!$A$21:$A$25,0))) -> 0.95 | AL15: =IF(B15="","",INDEX(Inputs!$D$21:$D$25,MATCH(F15,Inputs!$A$21:$A$25,0))) -> 0 | AM15: =IF(B15="","",N15*CompanyTarget*AK15) -> 47405 | AN15: =IF(B15="","",MAX(0,AM15-AD15)) -> 9707.85 | AO15: =IF(B15="","",IF(AND(ISNUMBER(MaxIncrease),MaxIncrease>0),1,0)) -> 1 | AP15: =IF(B15="","",IF(AO15=1,AD15*MaxIncrease,0)) -> 11309.145 | AQ15: =IF(B15="","",AD15*AL15) -> 0 | AR15: =IF(B15="","",IF(AK15=0,0,IF(AO15=1,MIN(MAX(AN15,AQ15),AP15),MAX(AN15,AQ15)))) -> 9707.85 | AS15: =IF(B15="","",IF(AD15>=O15,1,0)) -> 0 | AT15: =IF(B15="","",IF(AS15=1,0,AR15)) -> 9707.85 | AU15: =IF(B15="","",MAX(0,O15-AD15)) -> 20502.85 | AV15: =IF(B15="","",IF(ClipAtMax="No",AT15,MIN(AT15,AU15))) -> 9707.85 | AW15: =IF(B15="","",IF(AH15=1,AV15,0)) -> 9707.85 | AX15: =IF(B15="","",IF(AD15>0,AW15/AD15,0)) -> 0.25752212 | AY15: =IF(B15="","",AD15+AW15) -> 47405 | AZ15: =IF(B15="","",IF(AY15<M15,1,0)) -> 0 | BA15: =IF(B15="","",Q15*K15) -> 42989.83 | BB15: =IF(B15="","",RateBelow*MIN(BA15,Ceiling)+AboveCeilingTier1*MIN(MAX(0,BA15-Ceiling),0.1*Ceiling)+AboveCeilingTier2*MIN(MAX(0,BA15-1.1*Ceiling),0.4*Ceiling)+AboveCeilingTier3*MAX(0,BA15-1.5*Ceiling)) -> 13821.23 | BC15: =IF(B15="","",AD15*(1+J15)*K15) -> 42989.83 | BD15: =IF(B15="","",RateBelow*MIN(BC15,Ceiling)+AboveCeilingTier1*MIN(MAX(0,BC15-Ceiling),0.1*Ceiling)+AboveCeilingTier2*MIN(MAX(0,BC15-1.1*Ceiling),0.4*Ceiling)+AboveCeilingTier3*MAX(0,BC15-1.5*Ceiling)) -> 13821.23 | BE15: =IF(B15="","",AY15*(1+J15)*K15) -> 54060.662 | BF15: =IF(B15="","",RateBelow*MIN(BE15,Ceiling)+AboveCeilingTier1*MIN(MAX(0,BE15-Ceiling),0.1*Ceiling)+AboveCeilingTier2*MIN(MAX(0,BE15-1.1*Ceiling),0.4*Ceiling)+AboveCeilingTier3*MAX(0,BE15-1.5*Ceiling)) -> 17380.503 | BG15: =IF(B15="","",AC15*K15) -> 0 | BH15: =IF(B15="","",AC15*J15*K15) -> 0 | BI15: =IF(B15="","",BD15-BB15) -> 0 | BJ15: =IF(B15="","",AW15*K15) -> 9707.85 | BK15: =IF(B15="","",AW15*J15*K15) -> 1362.9821 | BL15: =IF(B15="","",BF15-BD15) -> 3559.2725 | BM15: =IF(B15="","",IF(AH15=1,AD15*K15,0)) -> 37697.15 | BN15: =IF(B15="","",IF(AH15=1,AD15*PoolPct,0)) -> 1507.886 | BO15: =IF(B15="","",BN15*K15) -> 1507.886 | BP15: =IF(B15="","",BN15*J15*K15) -> 211.70719 | BQ15: =IF(B15="","",(AD15+BN15)*(1+J15)*K15) -> 44709.423 | BR15: =IF(B15="","",RateBelow*MIN(BQ15,Ceiling)+AboveCeilingTier1*MIN(MAX(0,BQ15-Ceiling),0.1*Ceiling)+AboveCeilingTier2*MIN(MAX(0,BQ15-1.1*Ceiling),0.4*Ceiling)+AboveCeilingTier3*MAX(0,BQ15-1.5*Ceiling)) -> 14374.08 | BS15: =IF(B15="","",BR15-BD15) -> 552.84921 | BT15: =IF(B15="","",AD15*(1+J15)) -> 42989.83 | BU15: =IF(B15="","",AY15*(1+J15)) -> 54060.662 | BV15: =IF(B15="","",E15*BU15) -> 378424.63 | BW15: =IF(B15="","",P15*BU15) -> 151414.26 | BX15: =IF(B15="","",IF(COUNTIF($C$5:C15,C15)=1,MAX($BX$4:BX14)+1,""))
A16: =ROW()-4 -> 12 | B16: =IF(INDEX(Employees!$A:$A,A16+1)="","",INDEX(Employees!$A:$A,A16+1)) -> E012 | C16: =IF(B16="","",INDEX(Employees!$A:$Z,MATCH(B16,Employees!$A:$A,0),MATCH("category",Employees!$1:$1,0))) -> Engineering | D16: =IF(B16="","",INDEX(Employees!$A:$Z,MATCH(B16,Employees!$A:$A,0),MATCH("gender",Employees!$1:$1,0))) -> M | E16: =IF(B16="","",INDEX(Employees!$A:$Z,MATCH(B16,Employees!$A:$A,0),MATCH("grade",Employees!$1:$1,0))) -> 9 | F16: =IF(B16="","",INDEX(Employees!$A:$Z,MATCH(B16,Employees!$A:$A,0),MATCH("rating",Employees!$1:$1,0))) -> 3 | G16: =IF(B16="","",INDEX(Employees!$A:$Z,MATCH(B16,Employees!$A:$A,0),MATCH("hire_date",Employees!$1:$1,0))) -> 43666 | H16: =IF(B16="","",INDEX(Employees!$A:$Z,MATCH(B16,Employees!$A:$A,0),MATCH("last_change_date",Employees!$1:$1,0))) -> 46113 | I16: =IF(B16="","",INDEX(Employees!$A:$Z,MATCH(B16,Employees!$A:$A,0),MATCH("base_salary",Employees!$1:$1,0))) -> 60920.28 | J16: =IF(B16="","",INDEX(Employees!$A:$Z,MATCH(B16,Employees!$A:$A,0),MATCH("bonus_pct",Employees!$1:$1,0))/100) -> 0.1228 | K16: =IF(B16="","",INDEX(Employees!$A:$Z,MATCH(B16,Employees!$A:$A,0),MATCH("fte",Employees!$1:$1,0))) -> 1 | L16: =IF(B16="","",IF(ISNA(MATCH(C16&"|"&E16,Bands!$F:$F,0)),0,1)) -> 1 | M16: =IF(B16="","",INDEX(Bands!$C:$C,MATCH(C16&"|"&E16,Bands!$F:$F,0))) -> 54500 | N16: =IF(B16="","",INDEX(Bands!$D:$D,MATCH(C16&"|"&E16,Bands!$F:$F,0))) -> 65400 | O16: =IF(B16="","",INDEX(Bands!$E:$E,MATCH(C16&"|"&E16,Bands!$F:$F,0))) -> 76300 | P16: =IF(B16="","",(EffDate-G16)/365.25) -> 7.6988364 | Q16: =IF(B16="","",I16*(1+J16)) -> 68401.29 | R16: =IF(B16="","",E16^2) -> 81 | S16: =IF(B16="","",P16^2) -> 59.272082 | T16: =IF(B16="","",E16*P16) -> 69.289528 | U16: =IF(B16="","",E16*Q16) -> 615611.61 | V16: =IF(B16="","",P16*Q16) -> 526610.35 | W16: =IF(B16="","",ROUND(Q16,2)) -> 68401.29 | X16: =IF(B16="","",COUNTIFS($C:$C,C16,$W:$W,"<"&W16)+COUNTIFS($C:$C,C16,$W:$W,W16,$B:$B,"<"&B16)+1) -> 21 | Y16: =IF(B16="","",INDEX(Categories!$AH:$AH,MATCH(C16,Categories!$A:$A,0))) -> 71955.394 | Z16: =IF(B16="","",IF(AND(D16="F",Q16<Y16,INDEX(Categories!$AI:$AI,MATCH(C16,Categories!$A:$A,0))>0),1,0)) -> 0 | AA16: =IF(B16="","",IF(Z16=1,Y16-Q16,0)) -> 0 | AB16: =IF(B16="","",IF(Z16=1,INDEX(Categories!$AI:$AI,MATCH(C16,Categories!$A:$A,0))*AA16/INDEX(Categories!$AJ:$AJ,MATCH(C16,Categories!$A:$A,0)),0)) -> 0 | AC16: =IF(B16="","",AB16/(1+J16)) -> 0 | AD16: =IF(B16="","",I16+AC16) -> 60920.28 | AE16: =IF(B16="","",IF(AND(AC16>0,AD16>O16),1,0)) -> 0 | AF16: =IF(B16="","",IF(G16>EffDate,-1,DATEDIF(G16,EffDate,"m"))) -> 92 | AG16: =IF(B16="","",IF(H16>EffDate,-1,DATEDIF(H16,EffDate,"m"))) -> 12 | AH16: =IF(B16="","",IF(AND(AF16>=MinMonthsHire,AG16>=MinMonthsChange),1,0)) -> 1 | AI16: =IF(B16="","",AD16/N16) -> 0.93150275 | AJ16: =IF(B16="","",MATCH(AI16,Inputs!$B$31:$B$34,1)) -> 2 | AK16: =IF(B16="","",INDEX(Inputs!$C$21:$C$25,MATCH(F16,Inputs!$A$21:$A$25,0))) -> 1 | AL16: =IF(B16="","",INDEX(Inputs!$D$21:$D$25,MATCH(F16,Inputs!$A$21:$A$25,0))) -> 0 | AM16: =IF(B16="","",N16*CompanyTarget*AK16) -> 65400 | AN16: =IF(B16="","",MAX(0,AM16-AD16)) -> 4479.72 | AO16: =IF(B16="","",IF(AND(ISNUMBER(MaxIncrease),MaxIncrease>0),1,0)) -> 1 | AP16: =IF(B16="","",IF(AO16=1,AD16*MaxIncrease,0)) -> 18276.084 | AQ16: =IF(B16="","",AD16*AL16) -> 0 | AR16: =IF(B16="","",IF(AK16=0,0,IF(AO16=1,MIN(MAX(AN16,AQ16),AP16),MAX(AN16,AQ16)))) -> 4479.72 | AS16: =IF(B16="","",IF(AD16>=O16,1,0)) -> 0 | AT16: =IF(B16="","",IF(AS16=1,0,AR16)) -> 4479.72 | AU16: =IF(B16="","",MAX(0,O16-AD16)) -> 15379.72 | AV16: =IF(B16="","",IF(ClipAtMax="No",AT16,MIN(AT16,AU16))) -> 4479.72 | AW16: =IF(B16="","",IF(AH16=1,AV16,0)) -> 4479.72 | AX16: =IF(B16="","",IF(AD16>0,AW16/AD16,0)) -> 0.073534133 | AY16: =IF(B16="","",AD16+AW16) -> 65400 | AZ16: =IF(B16="","",IF(AY16<M16,1,0)) -> 0 | BA16: =IF(B16="","",Q16*K16) -> 68401.29 | BB16: =IF(B16="","",RateBelow*MIN(BA16,Ceiling)+AboveCeilingTier1*MIN(MAX(0,BA16-Ceiling),0.1*Ceiling)+AboveCeilingTier2*MIN(MAX(0,BA16-1.1*Ceiling),0.4*Ceiling)+AboveCeilingTier3*MAX(0,BA16-1.5*Ceiling)) -> 19750.276 | BC16: =IF(B16="","",AD16*(1+J16)*K16) -> 68401.29 | BD16: =IF(B16="","",RateBelow*MIN(BC16,Ceiling)+AboveCeilingTier1*MIN(MAX(0,BC16-Ceiling),0.1*Ceiling)+AboveCeilingTier2*MIN(MAX(0,BC16-1.1*Ceiling),0.4*Ceiling)+AboveCeilingTier3*MAX(0,BC16-1.5*Ceiling)) -> 19750.276 | BE16: =IF(B16="","",AY16*(1+J16)*K16) -> 73431.12 | BF16: =IF(B16="","",RateBelow*MIN(BE16,Ceiling)+AboveCeilingTier1*MIN(MAX(0,BE16-Ceiling),0.1*Ceiling)+AboveCeilingTier2*MIN(MAX(0,BE16-1.1*Ceiling),0.4*Ceiling)+AboveCeilingTier3*MAX(0,BE16-1.5*Ceiling)) -> 19802.586 | BG16: =IF(B16="","",AC16*K16) -> 0 | BH16: =IF(B16="","",AC16*J16*K16) -> 0 | BI16: =IF(B16="","",BD16-BB16) -> 0 | BJ16: =IF(B16="","",AW16*K16) -> 4479.72 | BK16: =IF(B16="","",AW16*J16*K16) -> 550.10962 | BL16: =IF(B16="","",BF16-BD16) -> 52.310228 | BM16: =IF(B16="","",IF(AH16=1,AD16*K16,0)) -> 60920.28 | BN16: =IF(B16="","",IF(AH16=1,AD16*PoolPct,0)) -> 2436.8112 | BO16: =IF(B16="","",BN16*K16) -> 2436.8112 | BP16: =IF(B16="","",BN16*J16*K16) -> 299.24042 | BQ16: =IF(B16="","",(AD16+BN16)*(1+J16)*K16) -> 71137.342 | BR16: =IF(B16="","",RateBelow*MIN(BQ16,Ceiling)+AboveCeilingTier1*MIN(MAX(0,BQ16-Ceiling),0.1*Ceiling)+AboveCeilingTier2*MIN(MAX(0,BQ16-1.1*Ceiling),0.4*Ceiling)+AboveCeilingTier3*MAX(0,BQ16-1.5*Ceiling)) -> 19778.731 | BS16: =IF(B16="","",BR16-BD16) -> 28.454937 | BT16: =IF(B16="","",AD16*(1+J16)) -> 68401.29 | BU16: =IF(B16="","",AY16*(1+J16)) -> 73431.12 | BV16: =IF(B16="","",E16*BU16) -> 660880.08 | BW16: =IF(B16="","",P16*BU16) -> 565334.18 | BX16: =IF(B16="","",IF(COUNTIF($C$5:C16,C16)=1,MAX($BX$4:BX15)+1,""))
... A2004: =ROW()-4 -> 2000 | B2004: =IF(INDEX(Employees!$A:$A,A2004+1)="","",INDEX(Employees!$A:$A,A2004+1)) | C2004: =IF(B2004="","",INDEX(Employees!$A:$Z,MATCH(B2004,Employees!$A:$A,0),MATCH("category",Employees!$1:$1,0))) | D2004: =IF(B2004="","",INDEX(Employees!$A:$Z,MATCH(B2004,Employees!$A:$A,0),MATCH("gender",Employees!$1:$1,0))) | E2004: =IF(B2004="","",INDEX(Employees!$A:$Z,MATCH(B2004,Employees!$A:$A,0),MATCH("grade",Employees!$1:$1,0))) | F2004: =IF(B2004="","",INDEX(Employees!$A:$Z,MATCH(B2004,Employees!$A:$A,0),MATCH("rating",Employees!$1:$1,0))) | G2004: =IF(B2004="","",INDEX(Employees!$A:$Z,MATCH(B2004,Employees!$A:$A,0),MATCH("hire_date",Employees!$1:$1,0))) | H2004: =IF(B2004="","",INDEX(Employees!$A:$Z,MATCH(B2004,Employees!$A:$A,0),MATCH("last_change_date",Employees!$1:$1,0))) | I2004: =IF(B2004="","",INDEX(Employees!$A:$Z,MATCH(B2004,Employees!$A:$A,0),MATCH("base_salary",Employees!$1:$1,0))) | J2004: =IF(B2004="","",INDEX(Employees!$A:$Z,MATCH(B2004,Employees!$A:$A,0),MATCH("bonus_pct",Employees!$1:$1,0))/100) | K2004: =IF(B2004="","",INDEX(Employees!$A:$Z,MATCH(B2004,Employees!$A:$A,0),MATCH("fte",Employees!$1:$1,0))) | L2004: =IF(B2004="","",IF(ISNA(MATCH(C2004&"|"&E2004,Bands!$F:$F,0)),0,1)) | M2004: =IF(B2004="","",INDEX(Bands!$C:$C,MATCH(C2004&"|"&E2004,Bands!$F:$F,0))) | N2004: =IF(B2004="","",INDEX(Bands!$D:$D,MATCH(C2004&"|"&E2004,Bands!$F:$F,0))) | O2004: =IF(B2004="","",INDEX(Bands!$E:$E,MATCH(C2004&"|"&E2004,Bands!$F:$F,0))) | P2004: =IF(B2004="","",(EffDate-G2004)/365.25) | Q2004: =IF(B2004="","",I2004*(1+J2004)) | R2004: =IF(B2004="","",E2004^2) | S2004: =IF(B2004="","",P2004^2) | T2004: =IF(B2004="","",E2004*P2004) | U2004: =IF(B2004="","",E2004*Q2004) | V2004: =IF(B2004="","",P2004*Q2004) | W2004: =IF(B2004="","",ROUND(Q2004,2)) | X2004: =IF(B2004="","",COUNTIFS($C:$C,C2004,$W:$W,"<"&W2004)+COUNTIFS($C:$C,C2004,$W:$W,W2004,$B:$B,"<"&B2004)+1) | Y2004: =IF(B2004="","",INDEX(Categories!$AH:$AH,MATCH(C2004,Categories!$A:$A,0))) | Z2004: =IF(B2004="","",IF(AND(D2004="F",Q2004<Y2004,INDEX(Categories!$AI:$AI,MATCH(C2004,Categories!$A:$A,0))>0),1,0)) | AA2004: =IF(B2004="","",IF(Z2004=1,Y2004-Q2004,0)) | AB2004: =IF(B2004="","",IF(Z2004=1,INDEX(Categories!$AI:$AI,MATCH(C2004,Categories!$A:$A,0))*AA2004/INDEX(Categories!$AJ:$AJ,MATCH(C2004,Categories!$A:$A,0)),0)) | AC2004: =IF(B2004="","",AB2004/(1+J2004)) | AD2004: =IF(B2004="","",I2004+AC2004) | AE2004: =IF(B2004="","",IF(AND(AC2004>0,AD2004>O2004),1,0)) | AF2004: =IF(B2004="","",IF(G2004>EffDate,-1,DATEDIF(G2004,EffDate,"m"))) | AG2004: =IF(B2004="","",IF(H2004>EffDate,-1,DATEDIF(H2004,EffDate,"m"))) | AH2004: =IF(B2004="","",IF(AND(AF2004>=MinMonthsHire,AG2004>=MinMonthsChange),1,0)) | AI2004: =IF(B2004="","",AD2004/N2004) | AJ2004: =IF(B2004="","",MATCH(AI2004,Inputs!$B$31:$B$34,1)) | AK2004: =IF(B2004="","",INDEX(Inputs!$C$21:$C$25,MATCH(F2004,Inputs!$A$21:$A$25,0))) | AL2004: =IF(B2004="","",INDEX(Inputs!$D$21:$D$25,MATCH(F2004,Inputs!$A$21:$A$25,0))) | AM2004: =IF(B2004="","",N2004*CompanyTarget*AK2004) | AN2004: =IF(B2004="","",MAX(0,AM2004-AD2004)) | AO2004: =IF(B2004="","",IF(AND(ISNUMBER(MaxIncrease),MaxIncrease>0),1,0)) | AP2004: =IF(B2004="","",IF(AO2004=1,AD2004*MaxIncrease,0)) | AQ2004: =IF(B2004="","",AD2004*AL2004) | AR2004: =IF(B2004="","",IF(AK2004=0,0,IF(AO2004=1,MIN(MAX(AN2004,AQ2004),AP2004),MAX(AN2004,AQ2004)))) | AS2004: =IF(B2004="","",IF(AD2004>=O2004,1,0)) | AT2004: =IF(B2004="","",IF(AS2004=1,0,AR2004)) | AU2004: =IF(B2004="","",MAX(0,O2004-AD2004)) | AV2004: =IF(B2004="","",IF(ClipAtMax="No",AT2004,MIN(AT2004,AU2004))) | AW2004: =IF(B2004="","",IF(AH2004=1,AV2004,0)) | AX2004: =IF(B2004="","",IF(AD2004>0,AW2004/AD2004,0)) | AY2004: =IF(B2004="","",AD2004+AW2004) | AZ2004: =IF(B2004="","",IF(AY2004<M2004,1,0)) | BA2004: =IF(B2004="","",Q2004*K2004) | BB2004: =IF(B2004="","",RateBelow*MIN(BA2004,Ceiling)+AboveCeilingTier1*MIN(MAX(0,BA2004-Ceiling),0.1*Ceiling)+AboveCeilingTier2*MIN(MAX(0,BA2004-1.1*Ceiling),0.4*Ceiling)+AboveCeilingTier3*MAX(0,BA2004-1.5*Ceiling)) | BC2004: =IF(B2004="","",AD2004*(1+J2004)*K2004) | BD2004: =IF(B2004="","",RateBelow*MIN(BC2004,Ceiling)+AboveCeilingTier1*MIN(MAX(0,BC2004-Ceiling),0.1*Ceiling)+AboveCeilingTier2*MIN(MAX(0,BC2004-1.1*Ceiling),0.4*Ceiling)+AboveCeilingTier3*MAX(0,BC2004-1.5*Ceiling)) | BE2004: =IF(B2004="","",AY2004*(1+J2004)*K2004) | BF2004: =IF(B2004="","",RateBelow*MIN(BE2004,Ceiling)+AboveCeilingTier1*MIN(MAX(0,BE2004-Ceiling),0.1*Ceiling)+AboveCeilingTier2*MIN(MAX(0,BE2004-1.1*Ceiling),0.4*Ceiling)+AboveCeilingTier3*MAX(0,BE2004-1.5*Ceiling)) | BG2004: =IF(B2004="","",AC2004*K2004) | BH2004: =IF(B2004="","",AC2004*J2004*K2004) | BI2004: =IF(B2004="","",BD2004-BB2004) | BJ2004: =IF(B2004="","",AW2004*K2004) | BK2004: =IF(B2004="","",AW2004*J2004*K2004) | BL2004: =IF(B2004="","",BF2004-BD2004) | BM2004: =IF(B2004="","",IF(AH2004=1,AD2004*K2004,0)) | BN2004: =IF(B2004="","",IF(AH2004=1,AD2004*PoolPct,0)) | BO2004: =IF(B2004="","",BN2004*K2004) | BP2004: =IF(B2004="","",BN2004*J2004*K2004) | BQ2004: =IF(B2004="","",(AD2004+BN2004)*(1+J2004)*K2004) | BR2004: =IF(B2004="","",RateBelow*MIN(BQ2004,Ceiling)+AboveCeilingTier1*MIN(MAX(0,BQ2004-Ceiling),0.1*Ceiling)+AboveCeilingTier2*MIN(MAX(0,BQ2004-1.1*Ceiling),0.4*Ceiling)+AboveCeilingTier3*MAX(0,BQ2004-1.5*Ceiling)) | BS2004: =IF(B2004="","",BR2004-BD2004) | BT2004: =IF(B2004="","",AD2004*(1+J2004)) | BU2004: =IF(B2004="","",AY2004*(1+J2004)) | BV2004: =IF(B2004="","",E2004*BU2004) | BW2004: =IF(B2004="","",P2004*BU2004) | BX2004: =IF(B2004="","",IF(COUNTIF($C$5:C2004,C2004)=1,MAX($BX$4:BX2003)+1,""))

Sheet Categories
A1: Pay equity per category: unexplained gap closed in full | H1: Regression of total cash on grade and tenure (explicit sums) | Y1: Explained and unexplained gap | AF1: Who receives it and how much | AK1: Gap after each step | AQ1: Unexplained gap after each step
A2: Filled in from Employees, in the order each category first appears. | E2: Base + bonus, full time. | G2: (men − women) / men. | H2: Sums over the category. | P2: Centred sums. | U2: Cramer's rule. | AC2: Part of the gap explained by differences in grade and tenure. | AD2: Kept between 0 and the raw gap. | AE2: Closed in full when it is against women (positive). A gap in women's favour is not adjusted. | AF2: The middle place(s) in the category list sorted by total cash. Odd headcount: both ranks are the same person. | AH2: Category median of total cash: the average of the two middle values (one value twice if the headcount is odd). | AI2: Unexplained gap × men's mean total cash × number of women. | AP2: Did the review widen the gap again? | AQ2: Zero where pay equity closed it; otherwise unchanged. | AR2: The same regression, re-run on total cash after merit. | AZ2: Kept between 0 and the raw gap. | BA2: Did the review open an unexplained gap again?
A4: Category | B4: Headcount | C4: Women | D4: Men | E4: Mean total cash, men | F4: Mean total cash, women | G4: Raw gap | H4: Σ grade | I4: Σ tenure | J4: Σ total cash | K4: Σ grade² | L4: Σ tenure² | M4: Σ grade×tenure | N4: Σ grade×cash | O4: Σ tenure×cash | P4: Sgg | Q4: Stt | R4: Sgt | S4: Sgy | T4: Sty | U4: Determinant | V4: Regression usable | W4: € per grade | X4: € per tenure year | Y4: Mean grade, men | Z4: Mean grade, women | AA4: Mean tenure, men | AB4: Mean tenure, women | AC4: Explained, before bounds | AD4: Explained | AE4: Unexplained | AF4: Median rank 1 | AG4: Median rank 2 | AH4: Median total cash | AI4: Amount to close | AJ4: Sum of shortfalls | AK4: Mean men, after equity | AL4: Mean women, after equity | AM4: Raw gap after equity | AN4: Mean men, after merit | AO4: Mean women, after merit | AP4: Raw gap after merit | AQ4: Unexplained after equity | AR4: Σ total cash after merit | AS4: Σ grade×cash after merit | AT4: Σ tenure×cash after merit | AU4: Sgy after merit | AV4: Sty after merit | AW4: € per grade after merit | AX4: € per tenure year after merit | AY4: Explained after merit, before bounds | AZ4: Explained after merit | BA4: Unexplained after merit
A5: =IFERROR(INDEX(Calc!$C:$C,MATCH(1,Calc!$BX:$BX,0)),"") -> Engineering | B5: =IF($A5="","",COUNTIFS(Calc!$C:$C,$A5)) -> 44 | C5: =IF($A5="","",COUNTIFS(Calc!$C:$C,$A5,Calc!$D:$D,"F")) -> 12 | D5: =IF($A5="","",COUNTIFS(Calc!$C:$C,$A5,Calc!$D:$D,"M")) -> 32 | E5: =IF($A5="","",IF(D5>0,SUMIFS(Calc!$Q:$Q,Calc!$C:$C,$A5,Calc!$D:$D,"M")/D5,0)) -> 74136.058 | F5: =IF($A5="","",IF(C5>0,SUMIFS(Calc!$Q:$Q,Calc!$C:$C,$A5,Calc!$D:$D,"F")/C5,0)) -> 65301.371 | G5: =IF($A5="","",IF(AND(C5>0,D5>0,E5>0),(E5-F5)/E5,0)) -> 0.11916856 | H5: =IF($A5="","",SUMIFS(Calc!$E:$E,Calc!$C:$C,$A5)) -> 401 | I5: =IF($A5="","",SUMIFS(Calc!$P:$P,Calc!$C:$C,$A5)) -> 305.00753 | J5: =IF($A5="","",SUMIFS(Calc!$Q:$Q,Calc!$C:$C,$A5)) -> 3155970.3 | K5: =IF($A5="","",SUMIFS(Calc!$R:$R,Calc!$C:$C,$A5)) -> 3745 | L5: =IF($A5="","",SUMIFS(Calc!$S:$S,Calc!$C:$C,$A5)) -> 2444.4562 | M5: =IF($A5="","",SUMIFS(Calc!$T:$T,Calc!$C:$C,$A5)) -> 2917.18 | N5: =IF($A5="","",SUMIFS(Calc!$U:$U,Calc!$C:$C,$A5)) -> 29671258 | O5: =IF($A5="","",SUMIFS(Calc!$V:$V,Calc!$C:$C,$A5)) -> 23394903 | P5: =IF($A5="","",IF(B5>0,K5-H5^2/B5,0)) -> 90.431818 | Q5: =IF($A5="","",IF(B5>0,L5-I5^2/B5,0)) -> 330.14726 | R5: =IF($A5="","",IF(B5>0,M5-H5*I5/B5,0)) -> 137.45231 | S5: =IF($A5="","",IF(B5>0,N5-H5*J5/B5,0)) -> 908891.88 | T5: =IF($A5="","",IF(B5>0,O5-I5*J5/B5,0)) -> 1517750.9 | U5: =IF($A5="","",P5*Q5-R5^2) -> 10962.681 | V5: =IF($A5="","",IF(AND(B5>=4,ABS(U5)>0.000000001),1,0)) -> 1 | W5: =IF($A5="","",IF(V5=1,(S5*Q5-T5*R5)/U5,0)) -> 8341.9196 | X5: =IF($A5="","",IF(V5=1,(T5*P5-S5*R5)/U5,0)) -> 1124.1494 | Y5: =IF($A5="","",IF(D5>0,SUMIFS(Calc!$E:$E,Calc!$C:$C,$A5,Calc!$D:$D,"M")/D5,0)) -> 9.15625 | Z5: =IF($A5="","",IF(C5>0,SUMIFS(Calc!$E:$E,Calc!$C:$C,$A5,Calc!$D:$D,"F")/C5,0)) -> 9 | AA5: =IF($A5="","",IF(D5>0,SUMIFS(Calc!$P:$P,Calc!$C:$C,$A5,Calc!$D:$D,"M")/D5,0)) -> 7.012577 | AB5: =IF($A5="","",IF(C5>0,SUMIFS(Calc!$P:$P,Calc!$C:$C,$A5,Calc!$D:$D,"F")/C5,0)) -> 6.7170888 | AC5: =IF($A5="","",IF(AND(V5=1,C5>0,D5>0,E5>0),(W5*(Y5-Z5)+X5*(AA5-AB5))/E5,0)) -> 0.02206211 | AD5: =IF($A5="","",IF(G5>=0,MAX(0,MIN(AC5,G5)),MIN(0,MAX(AC5,G5)))) -> 0.02206211 | AE5: =IF($A5="","",G5-AD5) -> 0.097106451 | AF5: =IF($A5="","",INT((B5+1)/2)) -> 22 | AG5: =IF($A5="","",INT(B5/2)+1) -> 23 | AH5: =IF($A5="","",(SUMIFS(Calc!$Q:$Q,Calc!$C:$C,$A5,Calc!$X:$X,AF5)+SUMIFS(Calc!$Q:$Q,Calc!$C:$C,$A5,Calc!$X:$X,AG5))/2) -> 71955.394 | AI5: =IF($A5="","",IF(AND(G5>=0,AE5>0.000000000001),AE5*E5*C5,0)) -> 86389.074 | AJ5: =IF($A5="","",SUMIFS(Calc!$AA:$AA,Calc!$C:$C,$A5)) -> 110188.28 | AK5: =IF($A5="","",IF(D5>0,SUMIFS(Calc!$BT:$BT,Calc!$C:$C,$A5,Calc!$D:$D,"M")/D5,0)) -> 74136.058 | AL5: =IF($A5="","",IF(C5>0,SUMIFS(Calc!$BT:$BT,Calc!$C:$C,$A5,Calc!$D:$D,"F")/C5,0)) -> 72500.46 | AM5: =IF($A5="","",IF(AK5>0,(AK5-AL5)/AK5,0)) -> 0.02206211 | AN5: =IF($A5="","",IF(D5>0,SUMIFS(Calc!$BU:$BU,Calc!$C:$C,$A5,Calc!$D:$D,"M")/D5,0)) -> 77950.866 | AO5: =IF($A5="","",IF(C5>0,SUMIFS(Calc!$BU:$BU,Calc!$C:$C,$A5,Calc!$D:$D,"F")/C5,0)) -> 78644.759 | AP5: =IF($A5="","",IF(AN5>0,(AN5-AO5)/AN5,0)) -> -0.0089016648 | AQ5: =IF($A5="","",IF(AND(AI5>0,AJ5>0),0,AE5)) -> 0 | AR5: =IF($A5="","",SUMIFS(Calc!$BU:$BU,Calc!$C:$C,$A5)) -> 3438164.8 | AS5: =IF($A5="","",SUMIFS(Calc!$BV:$BV,Calc!$C:$C,$A5)) -> 32198699 | AT5: =IF($A5="","",SUMIFS(Calc!$BW:$BW,Calc!$C:$C,$A5)) -> 25165041 | AU5: =IF($A5="","",IF(B5>0,AS5-H5*AR5/B5,0)) -> 864515.41 | AV5: =IF($A5="","",IF(B5>0,AT5-I5*AR5/B5,0)) -> 1331719.3 | AW5: =IF($A5="","",IF(V5=1,(AU5*Q5-AV5*R5)/U5,0)) -> 9337.999 | AX5: =IF($A5="","",IF(V5=1,(AV5*P5-AU5*R5)/U5,0)) -> 145.96464 | AY5: =IF($A5="","",IF(AND(V5=1,C5>0,D5>0,AN5>0),(AW5*(Y5-Z5)+AX5*(AA5-AB5))/AN5,0)) -> 0.019271026 | AZ5: =IF($A5="","",IF(AP5>=0,MAX(0,MIN(AY5,AP5)),MIN(0,MAX(AY5,AP5)))) -> 0 | BA5: =IF($A5="","",AP5-AZ5) -> -0.0089016648
A6: =IFERROR(INDEX(Calc!$C:$C,MATCH(2,Calc!$BX:$BX,0)),"") -> Operations | B6: =IF($A6="","",COUNTIFS(Calc!$C:$C,$A6)) -> 38 | C6: =IF($A6="","",COUNTIFS(Calc!$C:$C,$A6,Calc!$D:$D,"F")) -> 19 | D6: =IF($A6="","",COUNTIFS(Calc!$C:$C,$A6,Calc!$D:$D,"M")) -> 19 | E6: =IF($A6="","",IF(D6>0,SUMIFS(Calc!$Q:$Q,Calc!$C:$C,$A6,Calc!$D:$D,"M")/D6,0)) -> 57158.66 | F6: =IF($A6="","",IF(C6>0,SUMIFS(Calc!$Q:$Q,Calc!$C:$C,$A6,Calc!$D:$D,"F")/C6,0)) -> 50601.223 | G6: =IF($A6="","",IF(AND(C6>0,D6>0,E6>0),(E6-F6)/E6,0)) -> 0.11472342 | H6: =IF($A6="","",SUMIFS(Calc!$E:$E,Calc!$C:$C,$A6)) -> 253 | I6: =IF($A6="","",SUMIFS(Calc!$P:$P,Calc!$C:$C,$A6)) -> 212.59138 | J6: =IF($A6="","",SUMIFS(Calc!$Q:$Q,Calc!$C:$C,$A6)) -> 2047437.8 | K6: =IF($A6="","",SUMIFS(Calc!$R:$R,Calc!$C:$C,$A6)) -> 1767 | L6: =IF($A6="","",SUMIFS(Calc!$S:$S,Calc!$C:$C,$A6)) -> 1428.4607 | M6: =IF($A6="","",SUMIFS(Calc!$T:$T,Calc!$C:$C,$A6)) -> 1520.4764 | N6: =IF($A6="","",SUMIFS(Calc!$U:$U,Calc!$C:$C,$A6)) -> 14274209 | O6: =IF($A6="","",SUMIFS(Calc!$V:$V,Calc!$C:$C,$A6)) -> 12360230 | P6: =IF($A6="","",IF(B6>0,K6-H6^2/B6,0)) -> 82.552632 | Q6: =IF($A6="","",IF(B6>0,L6-I6^2/B6,0)) -> 239.11615 | R6: =IF($A6="","",IF(B6>0,M6-H6*I6/B6,0)) -> 105.06538 | S6: =IF($A6="","",IF(B6>0,N6-H6*J6/B6,0)) -> 642583.86 | T6: =IF($A6="","",IF(B6>0,O6-I6*J6/B6,0)) -> 905819.33 | U6: =IF($A6="","",P6*Q6-R6^2) -> 8700.9327 | V6: =IF($A6="","",IF(AND(B6>=4,ABS(U6)>0.000000001),1,0)) -> 1 | W6: =IF($A6="","",IF(V6=1,(S6*Q6-T6*R6)/U6,0)) -> 6721.3398 | X6: =IF($A6="","",IF(V6=1,(T6*P6-S6*R6)/U6,0)) -> 834.90463 | Y6: =IF($A6="","",IF(D6>0,SUMIFS(Calc!$E:$E,Calc!$C:$C,$A6,Calc!$D:$D,"M")/D6,0)) -> 7 | Z6: =IF($A6="","",IF(C6>0,SUMIFS(Calc!$E:$E,Calc!$C:$C,$A6,Calc!$D:$D,"F")/C6,0)) -> 6.3157895 | AA6: =IF($A6="","",IF(D6>0,SUMIFS(Calc!$P:$P,Calc!$C:$C,$A6,Calc!$D:$D,"M")/D6,0)) -> 6.5205519 | AB6: =IF($A6="","",IF(C6>0,SUMIFS(Calc!$P:$P,Calc!$C:$C,$A6,Calc!$D:$D,"F")/C6,0)) -> 4.6684679 | AC6: =IF($A6="","",IF(AND(V6=1,C6>0,D6>0,E6>0),(W6*(Y6-Z6)+X6*(AA6-AB6))/E6,0)) -> 0.10750996 | AD6: =IF($A6="","",IF(G6>=0,MAX(0,MIN(AC6,G6)),MIN(0,MAX(AC6,G6)))) -> 0.10750996 | AE6: =IF($A6="","",G6-AD6) -> 0.007213465 | AF6: =IF($A6="","",INT((B6+1)/2)) -> 19 | AG6: =IF($A6="","",INT(B6/2)+1) -> 20 | AH6: =IF($A6="","",(SUMIFS(Calc!$Q:$Q,Calc!$C:$C,$A6,Calc!$X:$X,AF6)+SUMIFS(Calc!$Q:$Q,Calc!$C:$C,$A6,Calc!$X:$X,AG6))/2) -> 51811.839 | AI6: =IF($A6="","",IF(AND(G6>=0,AE6>0.000000000001),AE6*E6*C6,0)) -> 7833.9278 | AJ6: =IF($A6="","",SUMIFS(Calc!$AA:$AA,Calc!$C:$C,$A6)) -> 99523.989 | AK6: =IF($A6="","",IF(D6>0,SUMIFS(Calc!$BT:$BT,Calc!$C:$C,$A6,Calc!$D:$D,"M")/D6,0)) -> 57158.66 | AL6: =IF($A6="","",IF(C6>0,SUMIFS(Calc!$BT:$BT,Calc!$C:$C,$A6,Calc!$D:$D,"F")/C6,0)) -> 51013.535 | AM6: =IF($A6="","",IF(AK6>0,(AK6-AL6)/AK6,0)) -> 0.10750996 | AN6: =IF($A6="","",IF(D6>0,SUMIFS(Calc!$BU:$BU,Calc!$C:$C,$A6,Calc!$D:$D,"M")/D6,0)) -> 58547.605 | AO6: =IF($A6="","",IF(C6>0,SUMIFS(Calc!$BU:$BU,Calc!$C:$C,$A6,Calc!$D:$D,"F")/C6,0)) -> 52621.372 | AP6: =IF($A6="","",IF(AN6>0,(AN6-AO6)/AN6,0)) -> 0.10122076 | AQ6: =IF($A6="","",IF(AND(AI6>0,AJ6>0),0,AE6)) -> 0 | AR6: =IF($A6="","",SUMIFS(Calc!$BU:$BU,Calc!$C:$C,$A6)) -> 2112210.6 | AS6: =IF($A6="","",SUMIFS(Calc!$BV:$BV,Calc!$C:$C,$A6)) -> 14715813 | AT6: =IF($A6="","",SUMIFS(Calc!$BW:$BW,Calc!$C:$C,$A6)) -> 12691167 | AU6: =IF($A6="","",IF(B6>0,AS6-H6*AR6/B6,0)) -> 652936.85 | AV6: =IF($A6="","",IF(B6>0,AT6-I6*AR6/B6,0)) -> 874383.81 | AW6: =IF($A6="","",IF(V6=1,(AU6*Q6-AV6*R6)/U6,0)) -> 7385.4471 | AX6: =IF($A6="","",IF(V6=1,(AV6*P6-AU6*R6)/U6,0)) -> 411.63666 | AY6: =IF($A6="","",IF(AND(V6=1,C6>0,D6>0,AN6>0),(AW6*(Y6-Z6)+AX6*(AA6-AB6))/AN6,0)) -> 0.099330899 | AZ6: =IF($A6="","",IF(AP6>=0,MAX(0,MIN(AY6,AP6)),MIN(0,MAX(AY6,AP6)))) -> 0.099330899 | BA6: =IF($A6="","",AP6-AZ6) -> 0.0018898639
A7: =IFERROR(INDEX(Calc!$C:$C,MATCH(3,Calc!$BX:$BX,0)),"") -> Legal | B7: =IF($A7="","",COUNTIFS(Calc!$C:$C,$A7)) -> 8 | C7: =IF($A7="","",COUNTIFS(Calc!$C:$C,$A7,Calc!$D:$D,"F")) -> 3 | D7: =IF($A7="","",COUNTIFS(Calc!$C:$C,$A7,Calc!$D:$D,"M")) -> 5 | E7: =IF($A7="","",IF(D7>0,SUMIFS(Calc!$Q:$Q,Calc!$C:$C,$A7,Calc!$D:$D,"M")/D7,0)) -> 88370.57 | F7: =IF($A7="","",IF(C7>0,SUMIFS(Calc!$Q:$Q,Calc!$C:$C,$A7,Calc!$D:$D,"F")/C7,0)) -> 78581.026 | G7: =IF($A7="","",IF(AND(C7>0,D7>0,E7>0),(E7-F7)/E7,0)) -> 0.11077833 | H7: =IF($A7="","",SUMIFS(Calc!$E:$E,Calc!$C:$C,$A7)) -> 81 | I7: =IF($A7="","",SUMIFS(Calc!$P:$P,Calc!$C:$C,$A7)) -> 44.276523 | J7: =IF($A7="","",SUMIFS(Calc!$Q:$Q,Calc!$C:$C,$A7)) -> 677595.93 | K7: =IF($A7="","",SUMIFS(Calc!$R:$R,Calc!$C:$C,$A7)) -> 827 | L7: =IF($A7="","",SUMIFS(Calc!$S:$S,Calc!$C:$C,$A7)) -> 299.01135 | M7: =IF($A7="","",SUMIFS(Calc!$T:$T,Calc!$C:$C,$A7)) -> 458.29158 | N7: =IF($A7="","",SUMIFS(Calc!$U:$U,Calc!$C:$C,$A7)) -> 6956476.2 | O7: =IF($A7="","",SUMIFS(Calc!$V:$V,Calc!$C:$C,$A7)) -> 3983109.1 | P7: =IF($A7="","",IF(B7>0,K7-H7^2/B7,0)) -> 6.875 | Q7: =IF($A7="","",IF(B7>0,L7-I7^2/B7,0)) -> 53.960044 | R7: =IF($A7="","",IF(B7>0,M7-H7*I7/B7,0)) -> 9.9917864 | S7: =IF($A7="","",IF(B7>0,N7-H7*J7/B7,0)) -> 95817.447 | T7: =IF($A7="","",IF(B7>0,O7-I7*J7/B7,0)) -> 232910.11 | U7: =IF($A7="","",P7*Q7-R7^2) -> 271.13951 | V7: =IF($A7="","",IF(AND(B7>=4,ABS(U7)>0.000000001),1,0)) -> 1 | W7: =IF($A7="","",IF(V7=1,(S7*Q7-T7*R7)/U7,0)) -> 10485.84 | X7: =IF($A7="","",IF(V7=1,(T7*P7-S7*R7)/U7,0)) -> 2374.68 | Y7: =IF($A7="","",IF(D7>0,SUMIFS(Calc!$E:$E,Calc!$C:$C,$A7,Calc!$D:$D,"M")/D7,0)) -> 10.4 | Z7: =IF($A7="","",IF(C7>0,SUMIFS(Calc!$E:$E,Calc!$C:$C,$A7,Calc!$D:$D,"F")/C7,0)) -> 9.6666667 | AA7: =IF($A7="","",IF(D7>0,SUMIFS(Calc!$P:$P,Calc!$C:$C,$A7,Calc!$D:$D,"M")/D7,0)) -> 5.1953457 | AB7: =IF($A7="","",IF(C7>0,SUMIFS(Calc!$P:$P,Calc!$C:$C,$A7,Calc!$D:$D,"F")/C7,0)) -> 6.0999316 | AC7: =IF($A7="","",IF(AND(V7=1,C7>0,D7>0,E7>0),(W7*(Y7-Z7)+X7*(AA7-AB7))/E7,0)) -> 0.062707689 | AD7: =IF($A7="","",IF(G7>=0,MAX(0,MIN(AC7,G7)),MIN(0,MAX(AC7,G7)))) -> 0.062707689 | AE7: =IF($A7="","",G7-AD7) -> 0.048070638 | AF7: =IF($A7="","",INT((B7+1)/2)) -> 4 | AG7: =IF($A7="","",INT(B7/2)+1) -> 5 | AH7: =IF($A7="","",(SUMIFS(Calc!$Q:$Q,Calc!$C:$C,$A7,Calc!$X:$X,AF7)+SUMIFS(Calc!$Q:$Q,Calc!$C:$C,$A7,Calc!$X:$X,AG7))/2) -> 80332.662 | AI7: =IF($A7="","",IF(AND(G7>=0,AE7>0.000000000001),AE7*E7*C7,0)) -> 12744.089 | AJ7: =IF($A7="","",SUMIFS(Calc!$AA:$AA,Calc!$C:$C,$A7)) -> 6404.207 | AK7: =IF($A7="","",IF(D7>0,SUMIFS(Calc!$BT:$BT,Calc!$C:$C,$A7,Calc!$D:$D,"M")/D7,0)) -> 88370.57 | AL7: =IF($A7="","",IF(C7>0,SUMIFS(Calc!$BT:$BT,Calc!$C:$C,$A7,Calc!$D:$D,"F")/C7,0)) -> 82829.056 | AM7: =IF($A7="","",IF(AK7>0,(AK7-AL7)/AK7,0)) -> 0.062707689 | AN7: =IF($A7="","",IF(D7>0,SUMIFS(Calc!$BU:$BU,Calc!$C:$C,$A7,Calc!$D:$D,"M")/D7,0)) -> 92652.76 | AO7: =IF($A7="","",IF(C7>0,SUMIFS(Calc!$BU:$BU,Calc!$C:$C,$A7,Calc!$D:$D,"F")/C7,0)) -> 89540.367 | AP7: =IF($A7="","",IF(AN7>0,(AN7-AO7)/AN7,0)) -> 0.033592008 | AQ7: =IF($A7="","",IF(AND(AI7>0,AJ7>0),0,AE7)) -> 0 | AR7: =IF($A7="","",SUMIFS(Calc!$BU:$BU,Calc!$C:$C,$A7)) -> 731884.9 | AS7: =IF($A7="","",SUMIFS(Calc!$BV:$BV,Calc!$C:$C,$A7)) -> 7490546.7 | AT7: =IF($A7="","",SUMIFS(Calc!$BW:$BW,Calc!$C:$C,$A7)) -> 4248745.9 | AU7: =IF($A7="","",IF(B7>0,AS7-H7*AR7/B7,0)) -> 80212.116 | AV7: =IF($A7="","",IF(B7>0,AT7-I7*AR7/B7,0)) -> 198081.11 | AW7: =IF($A7="","",IF(V7=1,(AU7*Q7-AV7*R7)/U7,0)) -> 8663.6771 | AX7: =IF($A7="","",IF(V7=1,(AV7*P7-AU7*R7)/U7,0)) -> 2066.631 | AY7: =IF($A7="","",IF(AND(V7=1,C7>0,D7>0,AN7>0),(AW7*(Y7-Z7)+AX7*(AA7-AB7))/AN7,0)) -> 0.048394866 | AZ7: =IF($A7="","",IF(AP7>=0,MAX(0,MIN(AY7,AP7)),MIN(0,MAX(AY7,AP7)))) -> 0.033592008 | BA7: =IF($A7="","",AP7-AZ7) -> 0
A8: =IFERROR(INDEX(Calc!$C:$C,MATCH(4,Calc!$BX:$BX,0)),"") -> Marketing | B8: =IF($A8="","",COUNTIFS(Calc!$C:$C,$A8)) -> 26 | C8: =IF($A8="","",COUNTIFS(Calc!$C:$C,$A8,Calc!$D:$D,"F")) -> 12 | D8: =IF($A8="","",COUNTIFS(Calc!$C:$C,$A8,Calc!$D:$D,"M")) -> 14 | E8: =IF($A8="","",IF(D8>0,SUMIFS(Calc!$Q:$Q,Calc!$C:$C,$A8,Calc!$D:$D,"M")/D8,0)) -> 68396.187 | F8: =IF($A8="","",IF(C8>0,SUMIFS(Calc!$Q:$Q,Calc!$C:$C,$A8,Calc!$D:$D,"F")/C8,0)) -> 77723.673 | G8: =IF($A8="","",IF(AND(C8>0,D8>0,E8>0),(E8-F8)/E8,0)) -> -0.13637435 | H8: =IF($A8="","",SUMIFS(Calc!$E:$E,Calc!$C:$C,$A8)) -> 223 | I8: =IF($A8="","",SUMIFS(Calc!$P:$P,Calc!$C:$C,$A8)) -> 204.30664 | J8: =IF($A8="","",SUMIFS(Calc!$Q:$Q,Calc!$C:$C,$A8)) -> 1890230.7 | K8: =IF($A8="","",SUMIFS(Calc!$R:$R,Calc!$C:$C,$A8)) -> 1957 | L8: =IF($A8="","",SUMIFS(Calc!$S:$S,Calc!$C:$C,$A8)) -> 1795.2459 | M8: =IF($A8="","",SUMIFS(Calc!$T:$T,Calc!$C:$C,$A8)) -> 1821.7522 | N8: =IF($A8="","",SUMIFS(Calc!$U:$U,Calc!$C:$C,$A8)) -> 16567959 | O8: =IF($A8="","",SUMIFS(Calc!$V:$V,Calc!$C:$C,$A8)) -> 15479768 | P8: =IF($A8="","",IF(B8>0,K8-H8^2/B8,0)) -> 44.346154 | Q8: =IF($A8="","",IF(B8>0,L8-I8^2/B8,0)) -> 189.81502 | R8: =IF($A8="","",IF(B8>0,M8-H8*I8/B8,0)) -> 69.429895 | S8: =IF($A8="","",IF(B8>0,N8-H8*J8/B8,0)) -> 355595.86 | T8: =IF($A8="","",IF(B8>0,O8-I8*J8/B8,0)) -> 626434.5 | U8: =IF($A8="","",P8*Q8-R8^2) -> 3597.0556 | V8: =IF($A8="","",IF(AND(B8>=4,ABS(U8)>0.000000001),1,0)) -> 1 | W8: =IF($A8="","",IF(V8=1,(S8*Q8-T8*R8)/U8,0)) -> 6673.2784 | X8: =IF($A8="","",IF(V8=1,(T8*P8-S8*R8)/U8,0)) -> 859.30756 | Y8: =IF($A8="","",IF(D8>0,SUMIFS(Calc!$E:$E,Calc!$C:$C,$A8,Calc!$D:$D,"M")/D8,0)) -> 8.3571429 | Z8: =IF($A8="","",IF(C8>0,SUMIFS(Calc!$E:$E,Calc!$C:$C,$A8,Calc!$D:$D,"F")/C8,0)) -> 8.8333333 | AA8: =IF($A8="","",IF(D8>0,SUMIFS(Calc!$P:$P,Calc!$C:$C,$A8,Calc!$D:$D,"M")/D8,0)) -> 7.2359441 | AB8: =IF($A8="","",IF(C8>0,SUMIFS(Calc!$P:$P,Calc!$C:$C,$A8,Calc!$D:$D,"F")/C8,0)) -> 8.5836185 | AC8: =IF($A8="","",IF(AND(V8=1,C8>0,D8>0,E8>0),(W8*(Y8-Z8)+X8*(AA8-AB8))/E8,0)) -> -0.063392692 | AD8: =IF($A8="","",IF(G8>=0,MAX(0,MIN(AC8,G8)),MIN(0,MAX(AC8,G8)))) -> -0.063392692 | AE8: =IF($A8="","",G8-AD8) -> -0.072981661 | AF8: =IF($A8="","",INT((B8+1)/2)) -> 13 | AG8: =IF($A8="","",INT(B8/2)+1) -> 14 | AH8: =IF($A8="","",(SUMIFS(Calc!$Q:$Q,Calc!$C:$C,$A8,Calc!$X:$X,AF8)+SUMIFS(Calc!$Q:$Q,Calc!$C:$C,$A8,Calc!$X:$X,AG8))/2) -> 75605.018 | AI8: =IF($A8="","",IF(AND(G8>=0,AE8>0.000000000001),AE8*E8*C8,0)) -> 0 | AJ8: =IF($A8="","",SUMIFS(Calc!$AA:$AA,Calc!$C:$C,$A8)) -> 0 | AK8: =IF($A8="","",IF(D8>0,SUMIFS(Calc!$BT:$BT,Calc!$C:$C,$A8,Calc!$D:$D,"M")/D8,0)) -> 68396.187 | AL8: =IF($A8="","",IF(C8>0,SUMIFS(Calc!$BT:$BT,Calc!$C:$C,$A8,Calc!$D:$D,"F")/C8,0)) -> 77723.673 | AM8: =IF($A8="","",IF(AK8>0,(AK8-AL8)/AK8,0)) -> -0.13637435 | AN8: =IF($A8="","",IF(D8>0,SUMIFS(Calc!$BU:$BU,Calc!$C:$C,$A8,Calc!$D:$D,"M")/D8,0)) -> 74102.994 | AO8: =IF($A8="","",IF(C8>0,SUMIFS(Calc!$BU:$BU,Calc!$C:$C,$A8,Calc!$D:$D,"F")/C8,0)) -> 80239.983 | AP8: =IF($A8="","",IF(AN8>0,(AN8-AO8)/AN8,0)) -> -0.082817019 | AQ8: =IF($A8="","",IF(AND(AI8>0,AJ8>0),0,AE8)) -> -0.072981661 | AR8: =IF($A8="","",SUMIFS(Calc!$BU:$BU,Calc!$C:$C,$A8)) -> 2000321.7 | AS8: =IF($A8="","",SUMIFS(Calc!$BV:$BV,Calc!$C:$C,$A8)) -> 17586574 | AT8: =IF($A8="","",SUMIFS(Calc!$BW:$BW,Calc!$C:$C,$A8)) -> 16398310 | AU8: =IF($A8="","",IF(B8>0,AS8-H8*AR8/B8,0)) -> 429968.89 | AV8: =IF($A8="","",IF(B8>0,AT8-I8*AR8/B8,0)) -> 679886.64 | AW8: =IF($A8="","",IF(V8=1,(AU8*Q8-AV8*R8)/U8,0)) -> 9566.1836 | AX8: =IF($A8="","",IF(V8=1,(AV8*P8-AU8*R8)/U8,0)) -> 82.751679 | AY8: =IF($A8="","",IF(AND(V8=1,C8>0,D8>0,AN8>0),(AW8*(Y8-Z8)+AX8*(AA8-AB8))/AN8,0)) -> -0.062977858 | AZ8: =IF($A8="","",IF(AP8>=0,MAX(0,MIN(AY8,AP8)),MIN(0,MAX(AY8,AP8)))) -> -0.062977858 | BA8: =IF($A8="","",AP8-AZ8) -> -0.019839161
A9: =IFERROR(INDEX(Calc!$C:$C,MATCH(5,Calc!$BX:$BX,0)),"") -> Manufacturing | B9: =IF($A9="","",COUNTIFS(Calc!$C:$C,$A9)) -> 40 | C9: =IF($A9="","",COUNTIFS(Calc!$C:$C,$A9,Calc!$D:$D,"F")) -> 19 | D9: =IF($A9="","",COUNTIFS(Calc!$C:$C,$A9,Calc!$D:$D,"M")) -> 21 | E9: =IF($A9="","",IF(D9>0,SUMIFS(Calc!$Q:$Q,Calc!$C:$C,$A9,Calc!$D:$D,"M")/D9,0)) -> 54294.289 | F9: =IF($A9="","",IF(C9>0,SUMIFS(Calc!$Q:$Q,Calc!$C:$C,$A9,Calc!$D:$D,"F")/C9,0)) -> 45818.939 | G9: =IF($A9="","",IF(AND(C9>0,D9>0,E9>0),(E9-F9)/E9,0)) -> 0.1561002 | H9: =IF($A9="","",SUMIFS(Calc!$E:$E,Calc!$C:$C,$A9)) -> 230 | I9: =IF($A9="","",SUMIFS(Calc!$P:$P,Calc!$C:$C,$A9)) -> 411.10198 | J9: =IF($A9="","",SUMIFS(Calc!$Q:$Q,Calc!$C:$C,$A9)) -> 2010739.9 | K9: =IF($A9="","",SUMIFS(Calc!$R:$R,Calc!$C:$C,$A9)) -> 1386 | L9: =IF($A9="","",SUMIFS(Calc!$S:$S,Calc!$C:$C,$A9)) -> 5002.5323 | M9: =IF($A9="","",SUMIFS(Calc!$T:$T,Calc!$C:$C,$A9)) -> 2527.0062 | N9: =IF($A9="","",SUMIFS(Calc!$U:$U,Calc!$C:$C,$A9)) -> 12046070 | O9: =IF($A9="","",SUMIFS(Calc!$V:$V,Calc!$C:$C,$A9)) -> 22170648 | P9: =IF($A9="","",IF(B9>0,K9-H9^2/B9,0)) -> 63.5 | Q9: =IF($A9="","",IF(B9>0,L9-I9^2/B9,0)) -> 777.41125 | R9: =IF($A9="","",IF(B9>0,M9-H9*I9/B9,0)) -> 163.16975 | S9: =IF($A9="","",IF(B9>0,N9-H9*J9/B9,0)) -> 484315.98 | T9: =IF($A9="","",IF(B9>0,O9-I9*J9/B9,0)) -> 1505169 | U9: =IF($A9="","",P9*Q9-R9^2) -> 22741.248 | V9: =IF($A9="","",IF(AND(B9>=4,ABS(U9)>0.000000001),1,0)) -> 1 | W9: =IF($A9="","",IF(V9=1,(S9*Q9-T9*R9)/U9,0)) -> 5756.705 | X9: =IF($A9="","",IF(V9=1,(T9*P9-S9*R9)/U9,0)) -> 727.86296 | Y9: =IF($A9="","",IF(D9>0,SUMIFS(Calc!$E:$E,Calc!$C:$C,$A9,Calc!$D:$D,"M")/D9,0)) -> 6 | Z9: =IF($A9="","",IF(C9>0,SUMIFS(Calc!$E:$E,Calc!$C:$C,$A9,Calc!$D:$D,"F")/C9,0)) -> 5.4736842 | AA9: =IF($A9="","",IF(D9>0,SUMIFS(Calc!$P:$P,Calc!$C:$C,$A9,Calc!$D:$D,"M")/D9,0)) -> 11.471464 | AB9: =IF($A9="","",IF(C9>0,SUMIFS(Calc!$P:$P,Calc!$C:$C,$A9,Calc!$D:$D,"F")/C9,0)) -> 8.9579596 | AC9: =IF($A9="","",IF(AND(V9=1,C9>0,D9>0,E9>0),(W9*(Y9-Z9)+X9*(AA9-AB9))/E9,0)) -> 0.089499871 | AD9: =IF($A9="","",IF(G9>=0,MAX(0,MIN(AC9,G9)),MIN(0,MAX(AC9,G9)))) -> 0.089499871 | AE9: =IF($A9="","",G9-AD9) -> 0.066600326 | AF9: =IF($A9="","",INT((B9+1)/2)) -> 20 | AG9: =IF($A9="","",INT(B9/2)+1) -> 21 | AH9: =IF($A9="","",(SUMIFS(Calc!$Q:$Q,Calc!$C:$C,$A9,Calc!$X:$X,AF9)+SUMIFS(Calc!$Q:$Q,Calc!$C:$C,$A9,Calc!$X:$X,AG9))/2) -> 48803.731 | AI9: =IF($A9="","",IF(AND(G9>=0,AE9>0.000000000001),AE9*E9*C9,0)) -> 68704.329 | AJ9: =IF($A9="","",SUMIFS(Calc!$AA:$AA,Calc!$C:$C,$A9)) -> 105697.83 | AK9: =IF($A9="","",IF(D9>0,SUMIFS(Calc!$BT:$BT,Calc!$C:$C,$A9,Calc!$D:$D,"M")/D9,0)) -> 54294.289 | AL9: =IF($A9="","",IF(C9>0,SUMIFS(Calc!$BT:$BT,Calc!$C:$C,$A9,Calc!$D:$D,"F")/C9,0)) -> 49434.957 | AM9: =IF($A9="","",IF(AK9>0,(AK9-AL9)/AK9,0)) -> 0.089499871 | AN9: =IF($A9="","",IF(D9>0,SUMIFS(Calc!$BU:$BU,Calc!$C:$C,$A9,Calc!$D:$D,"M")/D9,0)) -> 54445.174 | AO9: =IF($A9="","",IF(C9>0,SUMIFS(Calc!$BU:$BU,Calc!$C:$C,$A9,Calc!$D:$D,"F")/C9,0)) -> 50691.717 | AP9: =IF($A9="","",IF(AN9>0,(AN9-AO9)/AN9,0)) -> 0.068940134 | AQ9: =IF($A9="","",IF(AND(AI9>0,AJ9>0),0,AE9)) -> 0 | AR9: =IF($A9="","",SUMIFS(Calc!$BU:$BU,Calc!$C:$C,$A9)) -> 2106491.3 | AS9: =IF($A9="","",SUMIFS(Calc!$BV:$BV,Calc!$C:$C,$A9)) -> 12531895 | AT9: =IF($A9="","",SUMIFS(Calc!$BW:$BW,Calc!$C:$C,$A9)) -> 22938437 | AU9: =IF($A9="","",IF(B9>0,AS9-H9*AR9/B9,0)) -> 419569.74 | AV9: =IF($A9="","",IF(B9>0,AT9-I9*AR9/B9,0)) -> 1288868.6 | AW9: =IF($A9="","",IF(V9=1,(AU9*Q9-AV9*R9)/U9,0)) -> 5095.3172 | AX9: =IF($A9="","",IF(V9=1,(AV9*P9-AU9*R9)/U9,0)) -> 588.44918 | AY9: =IF($A9="","",IF(AND(V9=1,C9>0,D9>0,AN9>0),(AW9*(Y9-Z9)+AX9*(AA9-AB9))/AN9,0)) -> 0.076422122 | AZ9: =IF($A9="","",IF(AP9>=0,MAX(0,MIN(AY9,AP9)),MIN(0,MAX(AY9,AP9)))) -> 0.068940134 | BA9: =IF($A9="","",AP9-AZ9) -> 0
A10: =IFERROR(INDEX(Calc!$C:$C,MATCH(6,Calc!$BX:$BX,0)),"") -> Customer Support | B10: =IF($A10="","",COUNTIFS(Calc!$C:$C,$A10)) -> 30 | C10: =IF($A10="","",COUNTIFS(Calc!$C:$C,$A10,Calc!$D:$D,"F")) -> 13 | D10: =IF($A10="","",COUNTIFS(Calc!$C:$C,$A10,Calc!$D:$D,"M")) -> 17 | E10: =IF($A10="","",IF(D10>0,SUMIFS(Calc!$Q:$Q,Calc!$C:$C,$A10,Calc!$D:$D,"M")/D10,0)) -> 40975.545 | F10: =IF($A10="","",IF(C10>0,SUMIFS(Calc!$Q:$Q,Calc!$C:$C,$A10,Calc!$D:$D,"F")/C10,0)) -> 34745.224 | G10: =IF($A10="","",IF(AND(C10>0,D10>0,E10>0),(E10-F10)/E10,0)) -> 0.15204975 | H10: =IF($A10="","",SUMIFS(Calc!$E:$E,Calc!$C:$C,$A10)) -> 129 | I10: =IF($A10="","",SUMIFS(Calc!$P:$P,Calc!$C:$C,$A10)) -> 190.04244 | J10: =IF($A10="","",SUMIFS(Calc!$Q:$Q,Calc!$C:$C,$A10)) -> 1148272.2 | K10: =IF($A10="","",SUMIFS(Calc!$R:$R,Calc!$C:$C,$A10)) -> 589 | L10: =IF($A10="","",SUMIFS(Calc!$S:$S,Calc!$C:$C,$A10)) -> 1474.0321 | M10: =IF($A10="","",SUMIFS(Calc!$T:$T,Calc!$C:$C,$A10)) -> 889.92745 | N10: =IF($A10="","",SUMIFS(Calc!$U:$U,Calc!$C:$C,$A10)) -> 5166324.9 | O10: =IF($A10="","",SUMIFS(Calc!$V:$V,Calc!$C:$C,$A10)) -> 7877652.6 | P10: =IF($A10="","",IF(B10>0,K10-H10^2/B10,0)) -> 34.3 | Q10: =IF($A10="","",IF(B10>0,L10-I10^2/B10,0)) -> 270.16119 | R10: =IF($A10="","",IF(B10>0,M10-H10*I10/B10,0)) -> 72.744969 | S10: =IF($A10="","",IF(B10>0,N10-H10*J10/B10,0)) -> 228754.58 | T10: =IF($A10="","",IF(B10>0,O10-I10*J10/B10,0)) -> 603637.9 | U10: =IF($A10="","",P10*Q10-R10^2) -> 3974.6982 | V10: =IF($A10="","",IF(AND(B10>=4,ABS(U10)>0.000000001),1,0)) -> 1 | W10: =IF($A10="","",IF(V10=1,(S10*Q10-T10*R10)/U10,0)) -> 4500.7161 | X10: =IF($A10="","",IF(V10=1,(T10*P10-S10*R10)/U10,0)) -> 1022.4764 | Y10: =IF($A10="","",IF(D10>0,SUMIFS(Calc!$E:$E,Calc!$C:$C,$A10,Calc!$D:$D,"M")/D10,0)) -> 4.6470588 | Z10: =IF($A10="","",IF(C10>0,SUMIFS(Calc!$E:$E,Calc!$C:$C,$A10,Calc!$D:$D,"F")/C10,0)) -> 3.8461538 | AA10: =IF($A10="","",IF(D10>0,SUMIFS(Calc!$P:$P,Calc!$C:$C,$A10,Calc!$D:$D,"M")/D10,0)) -> 6.9998792 | AB10: =IF($A10="","",IF(C10>0,SUMIFS(Calc!$P:$P,Calc!$C:$C,$A10,Calc!$D:$D,"F")/C10,0)) -> 5.4649608 | AC10: =IF($A10="","",IF(AND(V10=1,C10>0,D10>0,E10>0),(W10*(Y10-Z10)+X10*(AA10-AB10))/E10,0)) -> 0.126272 | AD10: =IF($A10="","",IF(G10>=0,MAX(0,MIN(AC10,G10)),MIN(0,MAX(AC10,G10)))) -> 0.126272 | AE10: =IF($A10="","",G10-AD10) -> 0.025777752 | AF10: =IF($A10="","",INT((B10+1)/2)) -> 15 | AG10: =IF($A10="","",INT(B10/2)+1) -> 16 | AH10: =IF($A10="","",(SUMIFS(Calc!$Q:$Q,Calc!$C:$C,$A10,Calc!$X:$X,AF10)+SUMIFS(Calc!$Q:$Q,Calc!$C:$C,$A10,Calc!$X:$X,AG10))/2) -> 37853.452 | AI10: =IF($A10="","",IF(AND(G10>=0,AE10>0.000000000001),AE10*E10*C10,0)) -> 13731.346 | AJ10: =IF($A10="","",SUMIFS(Calc!$AA:$AA,Calc!$C:$C,$A10)) -> 57617.545 | AK10: =IF($A10="","",IF(D10>0,SUMIFS(Calc!$BT:$BT,Calc!$C:$C,$A10,Calc!$D:$D,"M")/D10,0)) -> 40975.545 | AL10: =IF($A10="","",IF(C10>0,SUMIFS(Calc!$BT:$BT,Calc!$C:$C,$A10,Calc!$D:$D,"F")/C10,0)) -> 35801.481 | AM10: =IF($A10="","",IF(AK10>0,(AK10-AL10)/AK10,0)) -> 0.126272 | AN10: =IF($A10="","",IF(D10>0,SUMIFS(Calc!$BU:$BU,Calc!$C:$C,$A10,Calc!$D:$D,"M")/D10,0)) -> 42382.121 | AO10: =IF($A10="","",IF(C10>0,SUMIFS(Calc!$BU:$BU,Calc!$C:$C,$A10,Calc!$D:$D,"F")/C10,0)) -> 37590.237 | AP10: =IF($A10="","",IF(AN10>0,(AN10-AO10)/AN10,0)) -> 0.11306382 | AQ10: =IF($A10="","",IF(AND(AI10>0,AJ10>0),0,AE10)) -> 0 | AR10: =IF($A10="","",SUMIFS(Calc!$BU:$BU,Calc!$C:$C,$A10)) -> 1209169.1 | AS10: =IF($A10="","",SUMIFS(Calc!$BV:$BV,Calc!$C:$C,$A10)) -> 5415853.8 | AT10: =IF($A10="","",SUMIFS(Calc!$BW:$BW,Calc!$C:$C,$A10)) -> 8186338.2 | AU10: =IF($A10="","",IF(B10>0,AS10-H10*AR10/B10,0)) -> 216426.46 | AV10: =IF($A10="","",IF(B10>0,AT10-I10*AR10/B10,0)) -> 526556.5 | AW10: =IF($A10="","",IF(V10=1,(AU10*Q10-AV10*R10)/U10,0)) -> 5073.5158 | AX10: =IF($A10="","",IF(V10=1,(AV10*P10-AU10*R10)/U10,0)) -> 582.92515 | AY10: =IF($A10="","",IF(AND(V10=1,C10>0,D10>0,AN10>0),(AW10*(Y10-Z10)+AX10*(AA10-AB10))/AN10,0)) -> 0.11698675 | AZ10: =IF($A10="","",IF(AP10>=0,MAX(0,MIN(AY10,AP10)),MIN(0,MAX(AY10,AP10)))) -> 0.11306382 | BA10: =IF($A10="","",AP10-AZ10) -> 0
A11: =IFERROR(INDEX(Calc!$C:$C,MATCH(7,Calc!$BX:$BX,0)),"") -> Sales | B11: =IF($A11="","",COUNTIFS(Calc!$C:$C,$A11)) -> 26 | C11: =IF($A11="","",COUNTIFS(Calc!$C:$C,$A11,Calc!$D:$D,"F")) -> 13 | D11: =IF($A11="","",COUNTIFS(Calc!$C:$C,$A11,Calc!$D:$D,"M")) -> 13 | E11: =IF($A11="","",IF(D11>0,SUMIFS(Calc!$Q:$Q,Calc!$C:$C,$A11,Calc!$D:$D,"M")/D11,0)) -> 90492.929 | F11: =IF($A11="","",IF(C11>0,SUMIFS(Calc!$Q:$Q,Calc!$C:$C,$A11,Calc!$D:$D,"F")/C11,0)) -> 82623.244 | G11: =IF($A11="","",IF(AND(C11>0,D11>0,E11>0),(E11-F11)/E11,0)) -> 0.086964632 | H11: =IF($A11="","",SUMIFS(Calc!$E:$E,Calc!$C:$C,$A11)) -> 252 | I11: =IF($A11="","",SUMIFS(Calc!$P:$P,Calc!$C:$C,$A11)) -> 160.19165 | J11: =IF($A11="","",SUMIFS(Calc!$Q:$Q,Calc!$C:$C,$A11)) -> 2250510.2 | K11: =IF($A11="","",SUMIFS(Calc!$R:$R,Calc!$C:$C,$A11)) -> 2484 | L11: =IF($A11="","",SUMIFS(Calc!$S:$S,Calc!$C:$C,$A11)) -> 1269.4043 | M11: =IF($A11="","",SUMIFS(Calc!$T:$T,Calc!$C:$C,$A11)) -> 1647.3101 | N11: =IF($A11="","",SUMIFS(Calc!$U:$U,Calc!$C:$C,$A11)) -> 22402660 | O11: =IF($A11="","",SUMIFS(Calc!$V:$V,Calc!$C:$C,$A11)) -> 15303025 | P11: =IF($A11="","",IF(B11>0,K11-H11^2/B11,0)) -> 41.538462 | Q11: =IF($A11="","",IF(B11>0,L11-I11^2/B11,0)) -> 282.42871 | R11: =IF($A11="","",IF(B11>0,M11-H11*I11/B11,0)) -> 94.683304 | S11: =IF($A11="","",IF(B11>0,N11-H11*J11/B11,0)) -> 590022.16 | T11: =IF($A11="","",IF(B11>0,O11-I11*J11/B11,0)) -> 1437142.2 | U11: =IF($A11="","",P11*Q11-R11^2) -> 2766.7261 | V11: =IF($A11="","",IF(AND(B11>=4,ABS(U11)>0.000000001),1,0)) -> 1 | W11: =IF($A11="","",IF(V11=1,(S11*Q11-T11*R11)/U11,0)) -> 11047.653 | X11: =IF($A11="","",IF(V11=1,(T11*P11-S11*R11)/U11,0)) -> 1384.8235 | Y11: =IF($A11="","",IF(D11>0,SUMIFS(Calc!$E:$E,Calc!$C:$C,$A11,Calc!$D:$D,"M")/D11,0)) -> 9.6923077 | Z11: =IF($A11="","",IF(C11>0,SUMIFS(Calc!$E:$E,Calc!$C:$C,$A11,Calc!$D:$D,"F")/C11,0)) -> 9.6923077 | AA11: =IF($A11="","",IF(D11>0,SUMIFS(Calc!$P:$P,Calc!$C:$C,$A11,Calc!$D:$D,"M")/D11,0)) -> 6.1612173 | AB11: =IF($A11="","",IF(C11>0,SUMIFS(Calc!$P:$P,Calc!$C:$C,$A11,Calc!$D:$D,"F")/C11,0)) -> 6.1612173 | AC11: =IF($A11="","",IF(AND(V11=1,C11>0,D11>0,E11>0),(W11*(Y11-Z11)+X11*(AA11-AB11))/E11,0)) -> 0 | AD11: =IF($A11="","",IF(G11>=0,MAX(0,MIN(AC11,G11)),MIN(0,MAX(AC11,G11)))) -> 0 | AE11: =IF($A11="","",G11-AD11) -> 0.086964632 | AF11: =IF($A11="","",INT((B11+1)/2)) -> 13 | AG11: =IF($A11="","",INT(B11/2)+1) -> 14 | AH11: =IF($A11="","",(SUMIFS(Calc!$Q:$Q,Calc!$C:$C,$A11,Calc!$X:$X,AF11)+SUMIFS(Calc!$Q:$Q,Calc!$C:$C,$A11,Calc!$X:$X,AG11))/2) -> 85035.918 | AI11: =IF($A11="","",IF(AND(G11>=0,AE11>0.000000000001),AE11*E11*C11,0)) -> 102305.9 | AJ11: =IF($A11="","",SUMIFS(Calc!$AA:$AA,Calc!$C:$C,$A11)) -> 109270.76 | AK11: =IF($A11="","",IF(D11>0,SUMIFS(Calc!$BT:$BT,Calc!$C:$C,$A11,Calc!$D:$D,"M")/D11,0)) -> 90492.929 | AL11: =IF($A11="","",IF(C11>0,SUMIFS(Calc!$BT:$BT,Calc!$C:$C,$A11,Calc!$D:$D,"F")/C11,0)) -> 90492.929 | AM11: =IF($A11="","",IF(AK11>0,(AK11-AL11)/AK11,0)) -> 0 | AN11: =IF($A11="","",IF(D11>0,SUMIFS(Calc!$BU:$BU,Calc!$C:$C,$A11,Calc!$D:$D,"M")/D11,0)) -> 104399.12 | AO11: =IF($A11="","",IF(C11>0,SUMIFS(Calc!$BU:$BU,Calc!$C:$C,$A11,Calc!$D:$D,"F")/C11,0)) -> 96182.02 | AP11: =IF($A11="","",IF(AN11>0,(AN11-AO11)/AN11,0)) -> 0.078708557 | AQ11: =IF($A11="","",IF(AND(AI11>0,AJ11>0),0,AE11)) -> 0 | AR11: =IF($A11="","",SUMIFS(Calc!$BU:$BU,Calc!$C:$C,$A11)) -> 2607554.9 | AS11: =IF($A11="","",SUMIFS(Calc!$BV:$BV,Calc!$C:$C,$A11)) -> 25858042 | AT11: =IF($A11="","",SUMIFS(Calc!$BW:$BW,Calc!$C:$C,$A11)) -> 17454661 | AU11: =IF($A11="","",IF(B11>0,AS11-H11*AR11/B11,0)) -> 584817.9 | AV11: =IF($A11="","",IF(B11>0,AT11-I11*AR11/B11,0)) -> 1388949.1 | AW11: =IF($A11="","",IF(V11=1,(AU11*Q11-AV11*R11)/U11,0)) -> 12165.668 | AX11: =IF($A11="","",IF(V11=1,(AV11*P11-AU11*R11)/U11,0)) -> 839.37455 | AY11: =IF($A11="","",IF(AND(V11=1,C11>0,D11>0,AN11>0),(AW11*(Y11-Z11)+AX11*(AA11-AB11))/AN11,0)) -> 0 | AZ11: =IF($A11="","",IF(AP11>=0,MAX(0,MIN(AY11,AP11)),MIN(0,MAX(AY11,AP11)))) -> 0 | BA11: =IF($A11="","",AP11-AZ11) -> 0.078708557
A12: =IFERROR(INDEX(Calc!$C:$C,MATCH(8,Calc!$BX:$BX,0)),"") | B12: =IF($A12="","",COUNTIFS(Calc!$C:$C,$A12)) | C12: =IF($A12="","",COUNTIFS(Calc!$C:$C,$A12,Calc!$D:$D,"F")) | D12: =IF($A12="","",COUNTIFS(Calc!$C:$C,$A12,Calc!$D:$D,"M")) | E12: =IF($A12="","",IF(D12>0,SUMIFS(Calc!$Q:$Q,Calc!$C:$C,$A12,Calc!$D:$D,"M")/D12,0)) | F12: =IF($A12="","",IF(C12>0,SUMIFS(Calc!$Q:$Q,Calc!$C:$C,$A12,Calc!$D:$D,"F")/C12,0)) | G12: =IF($A12="","",IF(AND(C12>0,D12>0,E12>0),(E12-F12)/E12,0)) | H12: =IF($A12="","",SUMIFS(Calc!$E:$E,Calc!$C:$C,$A12)) | I12: =IF($A12="","",SUMIFS(Calc!$P:$P,Calc!$C:$C,$A12)) | J12: =IF($A12="","",SUMIFS(Calc!$Q:$Q,Calc!$C:$C,$A12)) | K12: =IF($A12="","",SUMIFS(Calc!$R:$R,Calc!$C:$C,$A12)) | L12: =IF($A12="","",SUMIFS(Calc!$S:$S,Calc!$C:$C,$A12)) | M12: =IF($A12="","",SUMIFS(Calc!$T:$T,Calc!$C:$C,$A12)) | N12: =IF($A12="","",SUMIFS(Calc!$U:$U,Calc!$C:$C,$A12)) | O12: =IF($A12="","",SUMIFS(Calc!$V:$V,Calc!$C:$C,$A12)) | P12: =IF($A12="","",IF(B12>0,K12-H12^2/B12,0)) | Q12: =IF($A12="","",IF(B12>0,L12-I12^2/B12,0)) | R12: =IF($A12="","",IF(B12>0,M12-H12*I12/B12,0)) | S12: =IF($A12="","",IF(B12>0,N12-H12*J12/B12,0)) | T12: =IF($A12="","",IF(B12>0,O12-I12*J12/B12,0)) | U12: =IF($A12="","",P12*Q12-R12^2) | V12: =IF($A12="","",IF(AND(B12>=4,ABS(U12)>0.000000001),1,0)) | W12: =IF($A12="","",IF(V12=1,(S12*Q12-T12*R12)/U12,0)) | X12: =IF($A12="","",IF(V12=1,(T12*P12-S12*R12)/U12,0)) | Y12: =IF($A12="","",IF(D12>0,SUMIFS(Calc!$E:$E,Calc!$C:$C,$A12,Calc!$D:$D,"M")/D12,0)) | Z12: =IF($A12="","",IF(C12>0,SUMIFS(Calc!$E:$E,Calc!$C:$C,$A12,Calc!$D:$D,"F")/C12,0)) | AA12: =IF($A12="","",IF(D12>0,SUMIFS(Calc!$P:$P,Calc!$C:$C,$A12,Calc!$D:$D,"M")/D12,0)) | AB12: =IF($A12="","",IF(C12>0,SUMIFS(Calc!$P:$P,Calc!$C:$C,$A12,Calc!$D:$D,"F")/C12,0)) | AC12: =IF($A12="","",IF(AND(V12=1,C12>0,D12>0,E12>0),(W12*(Y12-Z12)+X12*(AA12-AB12))/E12,0)) | AD12: =IF($A12="","",IF(G12>=0,MAX(0,MIN(AC12,G12)),MIN(0,MAX(AC12,G12)))) | AE12: =IF($A12="","",G12-AD12) | AF12: =IF($A12="","",INT((B12+1)/2)) | AG12: =IF($A12="","",INT(B12/2)+1) | AH12: =IF($A12="","",(SUMIFS(Calc!$Q:$Q,Calc!$C:$C,$A12,Calc!$X:$X,AF12)+SUMIFS(Calc!$Q:$Q,Calc!$C:$C,$A12,Calc!$X:$X,AG12))/2) | AI12: =IF($A12="","",IF(AND(G12>=0,AE12>0.000000000001),AE12*E12*C12,0)) | AJ12: =IF($A12="","",SUMIFS(Calc!$AA:$AA,Calc!$C:$C,$A12)) | AK12: =IF($A12="","",IF(D12>0,SUMIFS(Calc!$BT:$BT,Calc!$C:$C,$A12,Calc!$D:$D,"M")/D12,0)) | AL12: =IF($A12="","",IF(C12>0,SUMIFS(Calc!$BT:$BT,Calc!$C:$C,$A12,Calc!$D:$D,"F")/C12,0)) | AM12: =IF($A12="","",IF(AK12>0,(AK12-AL12)/AK12,0)) | AN12: =IF($A12="","",IF(D12>0,SUMIFS(Calc!$BU:$BU,Calc!$C:$C,$A12,Calc!$D:$D,"M")/D12,0)) | AO12: =IF($A12="","",IF(C12>0,SUMIFS(Calc!$BU:$BU,Calc!$C:$C,$A12,Calc!$D:$D,"F")/C12,0)) | AP12: =IF($A12="","",IF(AN12>0,(AN12-AO12)/AN12,0)) | AQ12: =IF($A12="","",IF(AND(AI12>0,AJ12>0),0,AE12)) | AR12: =IF($A12="","",SUMIFS(Calc!$BU:$BU,Calc!$C:$C,$A12)) | AS12: =IF($A12="","",SUMIFS(Calc!$BV:$BV,Calc!$C:$C,$A12)) | AT12: =IF($A12="","",SUMIFS(Calc!$BW:$BW,Calc!$C:$C,$A12)) | AU12: =IF($A12="","",IF(B12>0,AS12-H12*AR12/B12,0)) | AV12: =IF($A12="","",IF(B12>0,AT12-I12*AR12/B12,0)) | AW12: =IF($A12="","",IF(V12=1,(AU12*Q12-AV12*R12)/U12,0)) | AX12: =IF($A12="","",IF(V12=1,(AV12*P12-AU12*R12)/U12,0)) | AY12: =IF($A12="","",IF(AND(V12=1,C12>0,D12>0,AN12>0),(AW12*(Y12-Z12)+AX12*(AA12-AB12))/AN12,0)) | AZ12: =IF($A12="","",IF(AP12>=0,MAX(0,MIN(AY12,AP12)),MIN(0,MAX(AY12,AP12)))) | BA12: =IF($A12="","",AP12-AZ12)
A13: =IFERROR(INDEX(Calc!$C:$C,MATCH(9,Calc!$BX:$BX,0)),"") | B13: =IF($A13="","",COUNTIFS(Calc!$C:$C,$A13)) | C13: =IF($A13="","",COUNTIFS(Calc!$C:$C,$A13,Calc!$D:$D,"F")) | D13: =IF($A13="","",COUNTIFS(Calc!$C:$C,$A13,Calc!$D:$D,"M")) | E13: =IF($A13="","",IF(D13>0,SUMIFS(Calc!$Q:$Q,Calc!$C:$C,$A13,Calc!$D:$D,"M")/D13,0)) | F13: =IF($A13="","",IF(C13>0,SUMIFS(Calc!$Q:$Q,Calc!$C:$C,$A13,Calc!$D:$D,"F")/C13,0)) | G13: =IF($A13="","",IF(AND(C13>0,D13>0,E13>0),(E13-F13)/E13,0)) | H13: =IF($A13="","",SUMIFS(Calc!$E:$E,Calc!$C:$C,$A13)) | I13: =IF($A13="","",SUMIFS(Calc!$P:$P,Calc!$C:$C,$A13)) | J13: =IF($A13="","",SUMIFS(Calc!$Q:$Q,Calc!$C:$C,$A13)) | K13: =IF($A13="","",SUMIFS(Calc!$R:$R,Calc!$C:$C,$A13)) | L13: =IF($A13="","",SUMIFS(Calc!$S:$S,Calc!$C:$C,$A13)) | M13: =IF($A13="","",SUMIFS(Calc!$T:$T,Calc!$C:$C,$A13)) | N13: =IF($A13="","",SUMIFS(Calc!$U:$U,Calc!$C:$C,$A13)) | O13: =IF($A13="","",SUMIFS(Calc!$V:$V,Calc!$C:$C,$A13)) | P13: =IF($A13="","",IF(B13>0,K13-H13^2/B13,0)) | Q13: =IF($A13="","",IF(B13>0,L13-I13^2/B13,0)) | R13: =IF($A13="","",IF(B13>0,M13-H13*I13/B13,0)) | S13: =IF($A13="","",IF(B13>0,N13-H13*J13/B13,0)) | T13: =IF($A13="","",IF(B13>0,O13-I13*J13/B13,0)) | U13: =IF($A13="","",P13*Q13-R13^2) | V13: =IF($A13="","",IF(AND(B13>=4,ABS(U13)>0.000000001),1,0)) | W13: =IF($A13="","",IF(V13=1,(S13*Q13-T13*R13)/U13,0)) | X13: =IF($A13="","",IF(V13=1,(T13*P13-S13*R13)/U13,0)) | Y13: =IF($A13="","",IF(D13>0,SUMIFS(Calc!$E:$E,Calc!$C:$C,$A13,Calc!$D:$D,"M")/D13,0)) | Z13: =IF($A13="","",IF(C13>0,SUMIFS(Calc!$E:$E,Calc!$C:$C,$A13,Calc!$D:$D,"F")/C13,0)) | AA13: =IF($A13="","",IF(D13>0,SUMIFS(Calc!$P:$P,Calc!$C:$C,$A13,Calc!$D:$D,"M")/D13,0)) | AB13: =IF($A13="","",IF(C13>0,SUMIFS(Calc!$P:$P,Calc!$C:$C,$A13,Calc!$D:$D,"F")/C13,0)) | AC13: =IF($A13="","",IF(AND(V13=1,C13>0,D13>0,E13>0),(W13*(Y13-Z13)+X13*(AA13-AB13))/E13,0)) | AD13: =IF($A13="","",IF(G13>=0,MAX(0,MIN(AC13,G13)),MIN(0,MAX(AC13,G13)))) | AE13: =IF($A13="","",G13-AD13) | AF13: =IF($A13="","",INT((B13+1)/2)) | AG13: =IF($A13="","",INT(B13/2)+1) | AH13: =IF($A13="","",(SUMIFS(Calc!$Q:$Q,Calc!$C:$C,$A13,Calc!$X:$X,AF13)+SUMIFS(Calc!$Q:$Q,Calc!$C:$C,$A13,Calc!$X:$X,AG13))/2) | AI13: =IF($A13="","",IF(AND(G13>=0,AE13>0.000000000001),AE13*E13*C13,0)) | AJ13: =IF($A13="","",SUMIFS(Calc!$AA:$AA,Calc!$C:$C,$A13)) | AK13: =IF($A13="","",IF(D13>0,SUMIFS(Calc!$BT:$BT,Calc!$C:$C,$A13,Calc!$D:$D,"M")/D13,0)) | AL13: =IF($A13="","",IF(C13>0,SUMIFS(Calc!$BT:$BT,Calc!$C:$C,$A13,Calc!$D:$D,"F")/C13,0)) | AM13: =IF($A13="","",IF(AK13>0,(AK13-AL13)/AK13,0)) | AN13: =IF($A13="","",IF(D13>0,SUMIFS(Calc!$BU:$BU,Calc!$C:$C,$A13,Calc!$D:$D,"M")/D13,0)) | AO13: =IF($A13="","",IF(C13>0,SUMIFS(Calc!$BU:$BU,Calc!$C:$C,$A13,Calc!$D:$D,"F")/C13,0)) | AP13: =IF($A13="","",IF(AN13>0,(AN13-AO13)/AN13,0)) | AQ13: =IF($A13="","",IF(AND(AI13>0,AJ13>0),0,AE13)) | AR13: =IF($A13="","",SUMIFS(Calc!$BU:$BU,Calc!$C:$C,$A13)) | AS13: =IF($A13="","",SUMIFS(Calc!$BV:$BV,Calc!$C:$C,$A13)) | AT13: =IF($A13="","",SUMIFS(Calc!$BW:$BW,Calc!$C:$C,$A13)) | AU13: =IF($A13="","",IF(B13>0,AS13-H13*AR13/B13,0)) | AV13: =IF($A13="","",IF(B13>0,AT13-I13*AR13/B13,0)) | AW13: =IF($A13="","",IF(V13=1,(AU13*Q13-AV13*R13)/U13,0)) | AX13: =IF($A13="","",IF(V13=1,(AV13*P13-AU13*R13)/U13,0)) | AY13: =IF($A13="","",IF(AND(V13=1,C13>0,D13>0,AN13>0),(AW13*(Y13-Z13)+AX13*(AA13-AB13))/AN13,0)) | AZ13: =IF($A13="","",IF(AP13>=0,MAX(0,MIN(AY13,AP13)),MIN(0,MAX(AY13,AP13)))) | BA13: =IF($A13="","",AP13-AZ13)
A14: =IFERROR(INDEX(Calc!$C:$C,MATCH(10,Calc!$BX:$BX,0)),"") | B14: =IF($A14="","",COUNTIFS(Calc!$C:$C,$A14)) | C14: =IF($A14="","",COUNTIFS(Calc!$C:$C,$A14,Calc!$D:$D,"F")) | D14: =IF($A14="","",COUNTIFS(Calc!$C:$C,$A14,Calc!$D:$D,"M")) | E14: =IF($A14="","",IF(D14>0,SUMIFS(Calc!$Q:$Q,Calc!$C:$C,$A14,Calc!$D:$D,"M")/D14,0)) | F14: =IF($A14="","",IF(C14>0,SUMIFS(Calc!$Q:$Q,Calc!$C:$C,$A14,Calc!$D:$D,"F")/C14,0)) | G14: =IF($A14="","",IF(AND(C14>0,D14>0,E14>0),(E14-F14)/E14,0)) | H14: =IF($A14="","",SUMIFS(Calc!$E:$E,Calc!$C:$C,$A14)) | I14: =IF($A14="","",SUMIFS(Calc!$P:$P,Calc!$C:$C,$A14)) | J14: =IF($A14="","",SUMIFS(Calc!$Q:$Q,Calc!$C:$C,$A14)) | K14: =IF($A14="","",SUMIFS(Calc!$R:$R,Calc!$C:$C,$A14)) | L14: =IF($A14="","",SUMIFS(Calc!$S:$S,Calc!$C:$C,$A14)) | M14: =IF($A14="","",SUMIFS(Calc!$T:$T,Calc!$C:$C,$A14)) | N14: =IF($A14="","",SUMIFS(Calc!$U:$U,Calc!$C:$C,$A14)) | O14: =IF($A14="","",SUMIFS(Calc!$V:$V,Calc!$C:$C,$A14)) | P14: =IF($A14="","",IF(B14>0,K14-H14^2/B14,0)) | Q14: =IF($A14="","",IF(B14>0,L14-I14^2/B14,0)) | R14: =IF($A14="","",IF(B14>0,M14-H14*I14/B14,0)) | S14: =IF($A14="","",IF(B14>0,N14-H14*J14/B14,0)) | T14: =IF($A14="","",IF(B14>0,O14-I14*J14/B14,0)) | U14: =IF($A14="","",P14*Q14-R14^2) | V14: =IF($A14="","",IF(AND(B14>=4,ABS(U14)>0.000000001),1,0)) | W14: =IF($A14="","",IF(V14=1,(S14*Q14-T14*R14)/U14,0)) | X14: =IF($A14="","",IF(V14=1,(T14*P14-S14*R14)/U14,0)) | Y14: =IF($A14="","",IF(D14>0,SUMIFS(Calc!$E:$E,Calc!$C:$C,$A14,Calc!$D:$D,"M")/D14,0)) | Z14: =IF($A14="","",IF(C14>0,SUMIFS(Calc!$E:$E,Calc!$C:$C,$A14,Calc!$D:$D,"F")/C14,0)) | AA14: =IF($A14="","",IF(D14>0,SUMIFS(Calc!$P:$P,Calc!$C:$C,$A14,Calc!$D:$D,"M")/D14,0)) | AB14: =IF($A14="","",IF(C14>0,SUMIFS(Calc!$P:$P,Calc!$C:$C,$A14,Calc!$D:$D,"F")/C14,0)) | AC14: =IF($A14="","",IF(AND(V14=1,C14>0,D14>0,E14>0),(W14*(Y14-Z14)+X14*(AA14-AB14))/E14,0)) | AD14: =IF($A14="","",IF(G14>=0,MAX(0,MIN(AC14,G14)),MIN(0,MAX(AC14,G14)))) | AE14: =IF($A14="","",G14-AD14) | AF14: =IF($A14="","",INT((B14+1)/2)) | AG14: =IF($A14="","",INT(B14/2)+1) | AH14: =IF($A14="","",(SUMIFS(Calc!$Q:$Q,Calc!$C:$C,$A14,Calc!$X:$X,AF14)+SUMIFS(Calc!$Q:$Q,Calc!$C:$C,$A14,Calc!$X:$X,AG14))/2) | AI14: =IF($A14="","",IF(AND(G14>=0,AE14>0.000000000001),AE14*E14*C14,0)) | AJ14: =IF($A14="","",SUMIFS(Calc!$AA:$AA,Calc!$C:$C,$A14)) | AK14: =IF($A14="","",IF(D14>0,SUMIFS(Calc!$BT:$BT,Calc!$C:$C,$A14,Calc!$D:$D,"M")/D14,0)) | AL14: =IF($A14="","",IF(C14>0,SUMIFS(Calc!$BT:$BT,Calc!$C:$C,$A14,Calc!$D:$D,"F")/C14,0)) | AM14: =IF($A14="","",IF(AK14>0,(AK14-AL14)/AK14,0)) | AN14: =IF($A14="","",IF(D14>0,SUMIFS(Calc!$BU:$BU,Calc!$C:$C,$A14,Calc!$D:$D,"M")/D14,0)) | AO14: =IF($A14="","",IF(C14>0,SUMIFS(Calc!$BU:$BU,Calc!$C:$C,$A14,Calc!$D:$D,"F")/C14,0)) | AP14: =IF($A14="","",IF(AN14>0,(AN14-AO14)/AN14,0)) | AQ14: =IF($A14="","",IF(AND(AI14>0,AJ14>0),0,AE14)) | AR14: =IF($A14="","",SUMIFS(Calc!$BU:$BU,Calc!$C:$C,$A14)) | AS14: =IF($A14="","",SUMIFS(Calc!$BV:$BV,Calc!$C:$C,$A14)) | AT14: =IF($A14="","",SUMIFS(Calc!$BW:$BW,Calc!$C:$C,$A14)) | AU14: =IF($A14="","",IF(B14>0,AS14-H14*AR14/B14,0)) | AV14: =IF($A14="","",IF(B14>0,AT14-I14*AR14/B14,0)) | AW14: =IF($A14="","",IF(V14=1,(AU14*Q14-AV14*R14)/U14,0)) | AX14: =IF($A14="","",IF(V14=1,(AV14*P14-AU14*R14)/U14,0)) | AY14: =IF($A14="","",IF(AND(V14=1,C14>0,D14>0,AN14>0),(AW14*(Y14-Z14)+AX14*(AA14-AB14))/AN14,0)) | AZ14: =IF($A14="","",IF(AP14>=0,MAX(0,MIN(AY14,AP14)),MIN(0,MAX(AY14,AP14)))) | BA14: =IF($A14="","",AP14-AZ14)
A15: =IFERROR(INDEX(Calc!$C:$C,MATCH(11,Calc!$BX:$BX,0)),"") | B15: =IF($A15="","",COUNTIFS(Calc!$C:$C,$A15)) | C15: =IF($A15="","",COUNTIFS(Calc!$C:$C,$A15,Calc!$D:$D,"F")) | D15: =IF($A15="","",COUNTIFS(Calc!$C:$C,$A15,Calc!$D:$D,"M")) | E15: =IF($A15="","",IF(D15>0,SUMIFS(Calc!$Q:$Q,Calc!$C:$C,$A15,Calc!$D:$D,"M")/D15,0)) | F15: =IF($A15="","",IF(C15>0,SUMIFS(Calc!$Q:$Q,Calc!$C:$C,$A15,Calc!$D:$D,"F")/C15,0)) | G15: =IF($A15="","",IF(AND(C15>0,D15>0,E15>0),(E15-F15)/E15,0)) | H15: =IF($A15="","",SUMIFS(Calc!$E:$E,Calc!$C:$C,$A15)) | I15: =IF($A15="","",SUMIFS(Calc!$P:$P,Calc!$C:$C,$A15)) | J15: =IF($A15="","",SUMIFS(Calc!$Q:$Q,Calc!$C:$C,$A15)) | K15: =IF($A15="","",SUMIFS(Calc!$R:$R,Calc!$C:$C,$A15)) | L15: =IF($A15="","",SUMIFS(Calc!$S:$S,Calc!$C:$C,$A15)) | M15: =IF($A15="","",SUMIFS(Calc!$T:$T,Calc!$C:$C,$A15)) | N15: =IF($A15="","",SUMIFS(Calc!$U:$U,Calc!$C:$C,$A15)) | O15: =IF($A15="","",SUMIFS(Calc!$V:$V,Calc!$C:$C,$A15)) | P15: =IF($A15="","",IF(B15>0,K15-H15^2/B15,0)) | Q15: =IF($A15="","",IF(B15>0,L15-I15^2/B15,0)) | R15: =IF($A15="","",IF(B15>0,M15-H15*I15/B15,0)) | S15: =IF($A15="","",IF(B15>0,N15-H15*J15/B15,0)) | T15: =IF($A15="","",IF(B15>0,O15-I15*J15/B15,0)) | U15: =IF($A15="","",P15*Q15-R15^2) | V15: =IF($A15="","",IF(AND(B15>=4,ABS(U15)>0.000000001),1,0)) | W15: =IF($A15="","",IF(V15=1,(S15*Q15-T15*R15)/U15,0)) | X15: =IF($A15="","",IF(V15=1,(T15*P15-S15*R15)/U15,0)) | Y15: =IF($A15="","",IF(D15>0,SUMIFS(Calc!$E:$E,Calc!$C:$C,$A15,Calc!$D:$D,"M")/D15,0)) | Z15: =IF($A15="","",IF(C15>0,SUMIFS(Calc!$E:$E,Calc!$C:$C,$A15,Calc!$D:$D,"F")/C15,0)) | AA15: =IF($A15="","",IF(D15>0,SUMIFS(Calc!$P:$P,Calc!$C:$C,$A15,Calc!$D:$D,"M")/D15,0)) | AB15: =IF($A15="","",IF(C15>0,SUMIFS(Calc!$P:$P,Calc!$C:$C,$A15,Calc!$D:$D,"F")/C15,0)) | AC15: =IF($A15="","",IF(AND(V15=1,C15>0,D15>0,E15>0),(W15*(Y15-Z15)+X15*(AA15-AB15))/E15,0)) | AD15: =IF($A15="","",IF(G15>=0,MAX(0,MIN(AC15,G15)),MIN(0,MAX(AC15,G15)))) | AE15: =IF($A15="","",G15-AD15) | AF15: =IF($A15="","",INT((B15+1)/2)) | AG15: =IF($A15="","",INT(B15/2)+1) | AH15: =IF($A15="","",(SUMIFS(Calc!$Q:$Q,Calc!$C:$C,$A15,Calc!$X:$X,AF15)+SUMIFS(Calc!$Q:$Q,Calc!$C:$C,$A15,Calc!$X:$X,AG15))/2) | AI15: =IF($A15="","",IF(AND(G15>=0,AE15>0.000000000001),AE15*E15*C15,0)) | AJ15: =IF($A15="","",SUMIFS(Calc!$AA:$AA,Calc!$C:$C,$A15)) | AK15: =IF($A15="","",IF(D15>0,SUMIFS(Calc!$BT:$BT,Calc!$C:$C,$A15,Calc!$D:$D,"M")/D15,0)) | AL15: =IF($A15="","",IF(C15>0,SUMIFS(Calc!$BT:$BT,Calc!$C:$C,$A15,Calc!$D:$D,"F")/C15,0)) | AM15: =IF($A15="","",IF(AK15>0,(AK15-AL15)/AK15,0)) | AN15: =IF($A15="","",IF(D15>0,SUMIFS(Calc!$BU:$BU,Calc!$C:$C,$A15,Calc!$D:$D,"M")/D15,0)) | AO15: =IF($A15="","",IF(C15>0,SUMIFS(Calc!$BU:$BU,Calc!$C:$C,$A15,Calc!$D:$D,"F")/C15,0)) | AP15: =IF($A15="","",IF(AN15>0,(AN15-AO15)/AN15,0)) | AQ15: =IF($A15="","",IF(AND(AI15>0,AJ15>0),0,AE15)) | AR15: =IF($A15="","",SUMIFS(Calc!$BU:$BU,Calc!$C:$C,$A15)) | AS15: =IF($A15="","",SUMIFS(Calc!$BV:$BV,Calc!$C:$C,$A15)) | AT15: =IF($A15="","",SUMIFS(Calc!$BW:$BW,Calc!$C:$C,$A15)) | AU15: =IF($A15="","",IF(B15>0,AS15-H15*AR15/B15,0)) | AV15: =IF($A15="","",IF(B15>0,AT15-I15*AR15/B15,0)) | AW15: =IF($A15="","",IF(V15=1,(AU15*Q15-AV15*R15)/U15,0)) | AX15: =IF($A15="","",IF(V15=1,(AV15*P15-AU15*R15)/U15,0)) | AY15: =IF($A15="","",IF(AND(V15=1,C15>0,D15>0,AN15>0),(AW15*(Y15-Z15)+AX15*(AA15-AB15))/AN15,0)) | AZ15: =IF($A15="","",IF(AP15>=0,MAX(0,MIN(AY15,AP15)),MIN(0,MAX(AY15,AP15)))) | BA15: =IF($A15="","",AP15-AZ15)
A16: =IFERROR(INDEX(Calc!$C:$C,MATCH(12,Calc!$BX:$BX,0)),"") | B16: =IF($A16="","",COUNTIFS(Calc!$C:$C,$A16)) | C16: =IF($A16="","",COUNTIFS(Calc!$C:$C,$A16,Calc!$D:$D,"F")) | D16: =IF($A16="","",COUNTIFS(Calc!$C:$C,$A16,Calc!$D:$D,"M")) | E16: =IF($A16="","",IF(D16>0,SUMIFS(Calc!$Q:$Q,Calc!$C:$C,$A16,Calc!$D:$D,"M")/D16,0)) | F16: =IF($A16="","",IF(C16>0,SUMIFS(Calc!$Q:$Q,Calc!$C:$C,$A16,Calc!$D:$D,"F")/C16,0)) | G16: =IF($A16="","",IF(AND(C16>0,D16>0,E16>0),(E16-F16)/E16,0)) | H16: =IF($A16="","",SUMIFS(Calc!$E:$E,Calc!$C:$C,$A16)) | I16: =IF($A16="","",SUMIFS(Calc!$P:$P,Calc!$C:$C,$A16)) | J16: =IF($A16="","",SUMIFS(Calc!$Q:$Q,Calc!$C:$C,$A16)) | K16: =IF($A16="","",SUMIFS(Calc!$R:$R,Calc!$C:$C,$A16)) | L16: =IF($A16="","",SUMIFS(Calc!$S:$S,Calc!$C:$C,$A16)) | M16: =IF($A16="","",SUMIFS(Calc!$T:$T,Calc!$C:$C,$A16)) | N16: =IF($A16="","",SUMIFS(Calc!$U:$U,Calc!$C:$C,$A16)) | O16: =IF($A16="","",SUMIFS(Calc!$V:$V,Calc!$C:$C,$A16)) | P16: =IF($A16="","",IF(B16>0,K16-H16^2/B16,0)) | Q16: =IF($A16="","",IF(B16>0,L16-I16^2/B16,0)) | R16: =IF($A16="","",IF(B16>0,M16-H16*I16/B16,0)) | S16: =IF($A16="","",IF(B16>0,N16-H16*J16/B16,0)) | T16: =IF($A16="","",IF(B16>0,O16-I16*J16/B16,0)) | U16: =IF($A16="","",P16*Q16-R16^2) | V16: =IF($A16="","",IF(AND(B16>=4,ABS(U16)>0.000000001),1,0)) | W16: =IF($A16="","",IF(V16=1,(S16*Q16-T16*R16)/U16,0)) | X16: =IF($A16="","",IF(V16=1,(T16*P16-S16*R16)/U16,0)) | Y16: =IF($A16="","",IF(D16>0,SUMIFS(Calc!$E:$E,Calc!$C:$C,$A16,Calc!$D:$D,"M")/D16,0)) | Z16: =IF($A16="","",IF(C16>0,SUMIFS(Calc!$E:$E,Calc!$C:$C,$A16,Calc!$D:$D,"F")/C16,0)) | AA16: =IF($A16="","",IF(D16>0,SUMIFS(Calc!$P:$P,Calc!$C:$C,$A16,Calc!$D:$D,"M")/D16,0)) | AB16: =IF($A16="","",IF(C16>0,SUMIFS(Calc!$P:$P,Calc!$C:$C,$A16,Calc!$D:$D,"F")/C16,0)) | AC16: =IF($A16="","",IF(AND(V16=1,C16>0,D16>0,E16>0),(W16*(Y16-Z16)+X16*(AA16-AB16))/E16,0)) | AD16: =IF($A16="","",IF(G16>=0,MAX(0,MIN(AC16,G16)),MIN(0,MAX(AC16,G16)))) | AE16: =IF($A16="","",G16-AD16) | AF16: =IF($A16="","",INT((B16+1)/2)) | AG16: =IF($A16="","",INT(B16/2)+1) | AH16: =IF($A16="","",(SUMIFS(Calc!$Q:$Q,Calc!$C:$C,$A16,Calc!$X:$X,AF16)+SUMIFS(Calc!$Q:$Q,Calc!$C:$C,$A16,Calc!$X:$X,AG16))/2) | AI16: =IF($A16="","",IF(AND(G16>=0,AE16>0.000000000001),AE16*E16*C16,0)) | AJ16: =IF($A16="","",SUMIFS(Calc!$AA:$AA,Calc!$C:$C,$A16)) | AK16: =IF($A16="","",IF(D16>0,SUMIFS(Calc!$BT:$BT,Calc!$C:$C,$A16,Calc!$D:$D,"M")/D16,0)) | AL16: =IF($A16="","",IF(C16>0,SUMIFS(Calc!$BT:$BT,Calc!$C:$C,$A16,Calc!$D:$D,"F")/C16,0)) | AM16: =IF($A16="","",IF(AK16>0,(AK16-AL16)/AK16,0)) | AN16: =IF($A16="","",IF(D16>0,SUMIFS(Calc!$BU:$BU,Calc!$C:$C,$A16,Calc!$D:$D,"M")/D16,0)) | AO16: =IF($A16="","",IF(C16>0,SUMIFS(Calc!$BU:$BU,Calc!$C:$C,$A16,Calc!$D:$D,"F")/C16,0)) | AP16: =IF($A16="","",IF(AN16>0,(AN16-AO16)/AN16,0)) | AQ16: =IF($A16="","",IF(AND(AI16>0,AJ16>0),0,AE16)) | AR16: =IF($A16="","",SUMIFS(Calc!$BU:$BU,Calc!$C:$C,$A16)) | AS16: =IF($A16="","",SUMIFS(Calc!$BV:$BV,Calc!$C:$C,$A16)) | AT16: =IF($A16="","",SUMIFS(Calc!$BW:$BW,Calc!$C:$C,$A16)) | AU16: =IF($A16="","",IF(B16>0,AS16-H16*AR16/B16,0)) | AV16: =IF($A16="","",IF(B16>0,AT16-I16*AR16/B16,0)) | AW16: =IF($A16="","",IF(V16=1,(AU16*Q16-AV16*R16)/U16,0)) | AX16: =IF($A16="","",IF(V16=1,(AV16*P16-AU16*R16)/U16,0)) | AY16: =IF($A16="","",IF(AND(V16=1,C16>0,D16>0,AN16>0),(AW16*(Y16-Z16)+AX16*(AA16-AB16))/AN16,0)) | AZ16: =IF($A16="","",IF(AP16>=0,MAX(0,MIN(AY16,AP16)),MIN(0,MAX(AY16,AP16)))) | BA16: =IF($A16="","",AP16-AZ16)
A17: =IFERROR(INDEX(Calc!$C:$C,MATCH(13,Calc!$BX:$BX,0)),"") | B17: =IF($A17="","",COUNTIFS(Calc!$C:$C,$A17)) | C17: =IF($A17="","",COUNTIFS(Calc!$C:$C,$A17,Calc!$D:$D,"F")) | D17: =IF($A17="","",COUNTIFS(Calc!$C:$C,$A17,Calc!$D:$D,"M")) | E17: =IF($A17="","",IF(D17>0,SUMIFS(Calc!$Q:$Q,Calc!$C:$C,$A17,Calc!$D:$D,"M")/D17,0)) | F17: =IF($A17="","",IF(C17>0,SUMIFS(Calc!$Q:$Q,Calc!$C:$C,$A17,Calc!$D:$D,"F")/C17,0)) | G17: =IF($A17="","",IF(AND(C17>0,D17>0,E17>0),(E17-F17)/E17,0)) | H17: =IF($A17="","",SUMIFS(Calc!$E:$E,Calc!$C:$C,$A17)) | I17: =IF($A17="","",SUMIFS(Calc!$P:$P,Calc!$C:$C,$A17)) | J17: =IF($A17="","",SUMIFS(Calc!$Q:$Q,Calc!$C:$C,$A17)) | K17: =IF($A17="","",SUMIFS(Calc!$R:$R,Calc!$C:$C,$A17)) | L17: =IF($A17="","",SUMIFS(Calc!$S:$S,Calc!$C:$C,$A17)) | M17: =IF($A17="","",SUMIFS(Calc!$T:$T,Calc!$C:$C,$A17)) | N17: =IF($A17="","",SUMIFS(Calc!$U:$U,Calc!$C:$C,$A17)) | O17: =IF($A17="","",SUMIFS(Calc!$V:$V,Calc!$C:$C,$A17)) | P17: =IF($A17="","",IF(B17>0,K17-H17^2/B17,0)) | Q17: =IF($A17="","",IF(B17>0,L17-I17^2/B17,0)) | R17: =IF($A17="","",IF(B17>0,M17-H17*I17/B17,0)) | S17: =IF($A17="","",IF(B17>0,N17-H17*J17/B17,0)) | T17: =IF($A17="","",IF(B17>0,O17-I17*J17/B17,0)) | U17: =IF($A17="","",P17*Q17-R17^2) | V17: =IF($A17="","",IF(AND(B17>=4,ABS(U17)>0.000000001),1,0)) | W17: =IF($A17="","",IF(V17=1,(S17*Q17-T17*R17)/U17,0)) | X17: =IF($A17="","",IF(V17=1,(T17*P17-S17*R17)/U17,0)) | Y17: =IF($A17="","",IF(D17>0,SUMIFS(Calc!$E:$E,Calc!$C:$C,$A17,Calc!$D:$D,"M")/D17,0)) | Z17: =IF($A17="","",IF(C17>0,SUMIFS(Calc!$E:$E,Calc!$C:$C,$A17,Calc!$D:$D,"F")/C17,0)) | AA17: =IF($A17="","",IF(D17>0,SUMIFS(Calc!$P:$P,Calc!$C:$C,$A17,Calc!$D:$D,"M")/D17,0)) | AB17: =IF($A17="","",IF(C17>0,SUMIFS(Calc!$P:$P,Calc!$C:$C,$A17,Calc!$D:$D,"F")/C17,0)) | AC17: =IF($A17="","",IF(AND(V17=1,C17>0,D17>0,E17>0),(W17*(Y17-Z17)+X17*(AA17-AB17))/E17,0)) | AD17: =IF($A17="","",IF(G17>=0,MAX(0,MIN(AC17,G17)),MIN(0,MAX(AC17,G17)))) | AE17: =IF($A17="","",G17-AD17) | AF17: =IF($A17="","",INT((B17+1)/2)) | AG17: =IF($A17="","",INT(B17/2)+1) | AH17: =IF($A17="","",(SUMIFS(Calc!$Q:$Q,Calc!$C:$C,$A17,Calc!$X:$X,AF17)+SUMIFS(Calc!$Q:$Q,Calc!$C:$C,$A17,Calc!$X:$X,AG17))/2) | AI17: =IF($A17="","",IF(AND(G17>=0,AE17>0.000000000001),AE17*E17*C17,0)) | AJ17: =IF($A17="","",SUMIFS(Calc!$AA:$AA,Calc!$C:$C,$A17)) | AK17: =IF($A17="","",IF(D17>0,SUMIFS(Calc!$BT:$BT,Calc!$C:$C,$A17,Calc!$D:$D,"M")/D17,0)) | AL17: =IF($A17="","",IF(C17>0,SUMIFS(Calc!$BT:$BT,Calc!$C:$C,$A17,Calc!$D:$D,"F")/C17,0)) | AM17: =IF($A17="","",IF(AK17>0,(AK17-AL17)/AK17,0)) | AN17: =IF($A17="","",IF(D17>0,SUMIFS(Calc!$BU:$BU,Calc!$C:$C,$A17,Calc!$D:$D,"M")/D17,0)) | AO17: =IF($A17="","",IF(C17>0,SUMIFS(Calc!$BU:$BU,Calc!$C:$C,$A17,Calc!$D:$D,"F")/C17,0)) | AP17: =IF($A17="","",IF(AN17>0,(AN17-AO17)/AN17,0)) | AQ17: =IF($A17="","",IF(AND(AI17>0,AJ17>0),0,AE17)) | AR17: =IF($A17="","",SUMIFS(Calc!$BU:$BU,Calc!$C:$C,$A17)) | AS17: =IF($A17="","",SUMIFS(Calc!$BV:$BV,Calc!$C:$C,$A17)) | AT17: =IF($A17="","",SUMIFS(Calc!$BW:$BW,Calc!$C:$C,$A17)) | AU17: =IF($A17="","",IF(B17>0,AS17-H17*AR17/B17,0)) | AV17: =IF($A17="","",IF(B17>0,AT17-I17*AR17/B17,0)) | AW17: =IF($A17="","",IF(V17=1,(AU17*Q17-AV17*R17)/U17,0)) | AX17: =IF($A17="","",IF(V17=1,(AV17*P17-AU17*R17)/U17,0)) | AY17: =IF($A17="","",IF(AND(V17=1,C17>0,D17>0,AN17>0),(AW17*(Y17-Z17)+AX17*(AA17-AB17))/AN17,0)) | AZ17: =IF($A17="","",IF(AP17>=0,MAX(0,MIN(AY17,AP17)),MIN(0,MAX(AY17,AP17)))) | BA17: =IF($A17="","",AP17-AZ17)
A18: =IFERROR(INDEX(Calc!$C:$C,MATCH(14,Calc!$BX:$BX,0)),"") | B18: =IF($A18="","",COUNTIFS(Calc!$C:$C,$A18)) | C18: =IF($A18="","",COUNTIFS(Calc!$C:$C,$A18,Calc!$D:$D,"F")) | D18: =IF($A18="","",COUNTIFS(Calc!$C:$C,$A18,Calc!$D:$D,"M")) | E18: =IF($A18="","",IF(D18>0,SUMIFS(Calc!$Q:$Q,Calc!$C:$C,$A18,Calc!$D:$D,"M")/D18,0)) | F18: =IF($A18="","",IF(C18>0,SUMIFS(Calc!$Q:$Q,Calc!$C:$C,$A18,Calc!$D:$D,"F")/C18,0)) | G18: =IF($A18="","",IF(AND(C18>0,D18>0,E18>0),(E18-F18)/E18,0)) | H18: =IF($A18="","",SUMIFS(Calc!$E:$E,Calc!$C:$C,$A18)) | I18: =IF($A18="","",SUMIFS(Calc!$P:$P,Calc!$C:$C,$A18)) | J18: =IF($A18="","",SUMIFS(Calc!$Q:$Q,Calc!$C:$C,$A18)) | K18: =IF($A18="","",SUMIFS(Calc!$R:$R,Calc!$C:$C,$A18)) | L18: =IF($A18="","",SUMIFS(Calc!$S:$S,Calc!$C:$C,$A18)) | M18: =IF($A18="","",SUMIFS(Calc!$T:$T,Calc!$C:$C,$A18)) | N18: =IF($A18="","",SUMIFS(Calc!$U:$U,Calc!$C:$C,$A18)) | O18: =IF($A18="","",SUMIFS(Calc!$V:$V,Calc!$C:$C,$A18)) | P18: =IF($A18="","",IF(B18>0,K18-H18^2/B18,0)) | Q18: =IF($A18="","",IF(B18>0,L18-I18^2/B18,0)) | R18: =IF($A18="","",IF(B18>0,M18-H18*I18/B18,0)) | S18: =IF($A18="","",IF(B18>0,N18-H18*J18/B18,0)) | T18: =IF($A18="","",IF(B18>0,O18-I18*J18/B18,0)) | U18: =IF($A18="","",P18*Q18-R18^2) | V18: =IF($A18="","",IF(AND(B18>=4,ABS(U18)>0.000000001),1,0)) | W18: =IF($A18="","",IF(V18=1,(S18*Q18-T18*R18)/U18,0)) | X18: =IF($A18="","",IF(V18=1,(T18*P18-S18*R18)/U18,0)) | Y18: =IF($A18="","",IF(D18>0,SUMIFS(Calc!$E:$E,Calc!$C:$C,$A18,Calc!$D:$D,"M")/D18,0)) | Z18: =IF($A18="","",IF(C18>0,SUMIFS(Calc!$E:$E,Calc!$C:$C,$A18,Calc!$D:$D,"F")/C18,0)) | AA18: =IF($A18="","",IF(D18>0,SUMIFS(Calc!$P:$P,Calc!$C:$C,$A18,Calc!$D:$D,"M")/D18,0)) | AB18: =IF($A18="","",IF(C18>0,SUMIFS(Calc!$P:$P,Calc!$C:$C,$A18,Calc!$D:$D,"F")/C18,0)) | AC18: =IF($A18="","",IF(AND(V18=1,C18>0,D18>0,E18>0),(W18*(Y18-Z18)+X18*(AA18-AB18))/E18,0)) | AD18: =IF($A18="","",IF(G18>=0,MAX(0,MIN(AC18,G18)),MIN(0,MAX(AC18,G18)))) | AE18: =IF($A18="","",G18-AD18) | AF18: =IF($A18="","",INT((B18+1)/2)) | AG18: =IF($A18="","",INT(B18/2)+1) | AH18: =IF($A18="","",(SUMIFS(Calc!$Q:$Q,Calc!$C:$C,$A18,Calc!$X:$X,AF18)+SUMIFS(Calc!$Q:$Q,Calc!$C:$C,$A18,Calc!$X:$X,AG18))/2) | AI18: =IF($A18="","",IF(AND(G18>=0,AE18>0.000000000001),AE18*E18*C18,0)) | AJ18: =IF($A18="","",SUMIFS(Calc!$AA:$AA,Calc!$C:$C,$A18)) | AK18: =IF($A18="","",IF(D18>0,SUMIFS(Calc!$BT:$BT,Calc!$C:$C,$A18,Calc!$D:$D,"M")/D18,0)) | AL18: =IF($A18="","",IF(C18>0,SUMIFS(Calc!$BT:$BT,Calc!$C:$C,$A18,Calc!$D:$D,"F")/C18,0)) | AM18: =IF($A18="","",IF(AK18>0,(AK18-AL18)/AK18,0)) | AN18: =IF($A18="","",IF(D18>0,SUMIFS(Calc!$BU:$BU,Calc!$C:$C,$A18,Calc!$D:$D,"M")/D18,0)) | AO18: =IF($A18="","",IF(C18>0,SUMIFS(Calc!$BU:$BU,Calc!$C:$C,$A18,Calc!$D:$D,"F")/C18,0)) | AP18: =IF($A18="","",IF(AN18>0,(AN18-AO18)/AN18,0)) | AQ18: =IF($A18="","",IF(AND(AI18>0,AJ18>0),0,AE18)) | AR18: =IF($A18="","",SUMIFS(Calc!$BU:$BU,Calc!$C:$C,$A18)) | AS18: =IF($A18="","",SUMIFS(Calc!$BV:$BV,Calc!$C:$C,$A18)) | AT18: =IF($A18="","",SUMIFS(Calc!$BW:$BW,Calc!$C:$C,$A18)) | AU18: =IF($A18="","",IF(B18>0,AS18-H18*AR18/B18,0)) | AV18: =IF($A18="","",IF(B18>0,AT18-I18*AR18/B18,0)) | AW18: =IF($A18="","",IF(V18=1,(AU18*Q18-AV18*R18)/U18,0)) | AX18: =IF($A18="","",IF(V18=1,(AV18*P18-AU18*R18)/U18,0)) | AY18: =IF($A18="","",IF(AND(V18=1,C18>0,D18>0,AN18>0),(AW18*(Y18-Z18)+AX18*(AA18-AB18))/AN18,0)) | AZ18: =IF($A18="","",IF(AP18>=0,MAX(0,MIN(AY18,AP18)),MIN(0,MAX(AY18,AP18)))) | BA18: =IF($A18="","",AP18-AZ18)
A19: =IFERROR(INDEX(Calc!$C:$C,MATCH(15,Calc!$BX:$BX,0)),"") | B19: =IF($A19="","",COUNTIFS(Calc!$C:$C,$A19)) | C19: =IF($A19="","",COUNTIFS(Calc!$C:$C,$A19,Calc!$D:$D,"F")) | D19: =IF($A19="","",COUNTIFS(Calc!$C:$C,$A19,Calc!$D:$D,"M")) | E19: =IF($A19="","",IF(D19>0,SUMIFS(Calc!$Q:$Q,Calc!$C:$C,$A19,Calc!$D:$D,"M")/D19,0)) | F19: =IF($A19="","",IF(C19>0,SUMIFS(Calc!$Q:$Q,Calc!$C:$C,$A19,Calc!$D:$D,"F")/C19,0)) | G19: =IF($A19="","",IF(AND(C19>0,D19>0,E19>0),(E19-F19)/E19,0)) | H19: =IF($A19="","",SUMIFS(Calc!$E:$E,Calc!$C:$C,$A19)) | I19: =IF($A19="","",SUMIFS(Calc!$P:$P,Calc!$C:$C,$A19)) | J19: =IF($A19="","",SUMIFS(Calc!$Q:$Q,Calc!$C:$C,$A19)) | K19: =IF($A19="","",SUMIFS(Calc!$R:$R,Calc!$C:$C,$A19)) | L19: =IF($A19="","",SUMIFS(Calc!$S:$S,Calc!$C:$C,$A19)) | M19: =IF($A19="","",SUMIFS(Calc!$T:$T,Calc!$C:$C,$A19)) | N19: =IF($A19="","",SUMIFS(Calc!$U:$U,Calc!$C:$C,$A19)) | O19: =IF($A19="","",SUMIFS(Calc!$V:$V,Calc!$C:$C,$A19)) | P19: =IF($A19="","",IF(B19>0,K19-H19^2/B19,0)) | Q19: =IF($A19="","",IF(B19>0,L19-I19^2/B19,0)) | R19: =IF($A19="","",IF(B19>0,M19-H19*I19/B19,0)) | S19: =IF($A19="","",IF(B19>0,N19-H19*J19/B19,0)) | T19: =IF($A19="","",IF(B19>0,O19-I19*J19/B19,0)) | U19: =IF($A19="","",P19*Q19-R19^2) | V19: =IF($A19="","",IF(AND(B19>=4,ABS(U19)>0.000000001),1,0)) | W19: =IF($A19="","",IF(V19=1,(S19*Q19-T19*R19)/U19,0)) | X19: =IF($A19="","",IF(V19=1,(T19*P19-S19*R19)/U19,0)) | Y19: =IF($A19="","",IF(D19>0,SUMIFS(Calc!$E:$E,Calc!$C:$C,$A19,Calc!$D:$D,"M")/D19,0)) | Z19: =IF($A19="","",IF(C19>0,SUMIFS(Calc!$E:$E,Calc!$C:$C,$A19,Calc!$D:$D,"F")/C19,0)) | AA19: =IF($A19="","",IF(D19>0,SUMIFS(Calc!$P:$P,Calc!$C:$C,$A19,Calc!$D:$D,"M")/D19,0)) | AB19: =IF($A19="","",IF(C19>0,SUMIFS(Calc!$P:$P,Calc!$C:$C,$A19,Calc!$D:$D,"F")/C19,0)) | AC19: =IF($A19="","",IF(AND(V19=1,C19>0,D19>0,E19>0),(W19*(Y19-Z19)+X19*(AA19-AB19))/E19,0)) | AD19: =IF($A19="","",IF(G19>=0,MAX(0,MIN(AC19,G19)),MIN(0,MAX(AC19,G19)))) | AE19: =IF($A19="","",G19-AD19) | AF19: =IF($A19="","",INT((B19+1)/2)) | AG19: =IF($A19="","",INT(B19/2)+1) | AH19: =IF($A19="","",(SUMIFS(Calc!$Q:$Q,Calc!$C:$C,$A19,Calc!$X:$X,AF19)+SUMIFS(Calc!$Q:$Q,Calc!$C:$C,$A19,Calc!$X:$X,AG19))/2) | AI19: =IF($A19="","",IF(AND(G19>=0,AE19>0.000000000001),AE19*E19*C19,0)) | AJ19: =IF($A19="","",SUMIFS(Calc!$AA:$AA,Calc!$C:$C,$A19)) | AK19: =IF($A19="","",IF(D19>0,SUMIFS(Calc!$BT:$BT,Calc!$C:$C,$A19,Calc!$D:$D,"M")/D19,0)) | AL19: =IF($A19="","",IF(C19>0,SUMIFS(Calc!$BT:$BT,Calc!$C:$C,$A19,Calc!$D:$D,"F")/C19,0)) | AM19: =IF($A19="","",IF(AK19>0,(AK19-AL19)/AK19,0)) | AN19: =IF($A19="","",IF(D19>0,SUMIFS(Calc!$BU:$BU,Calc!$C:$C,$A19,Calc!$D:$D,"M")/D19,0)) | AO19: =IF($A19="","",IF(C19>0,SUMIFS(Calc!$BU:$BU,Calc!$C:$C,$A19,Calc!$D:$D,"F")/C19,0)) | AP19: =IF($A19="","",IF(AN19>0,(AN19-AO19)/AN19,0)) | AQ19: =IF($A19="","",IF(AND(AI19>0,AJ19>0),0,AE19)) | AR19: =IF($A19="","",SUMIFS(Calc!$BU:$BU,Calc!$C:$C,$A19)) | AS19: =IF($A19="","",SUMIFS(Calc!$BV:$BV,Calc!$C:$C,$A19)) | AT19: =IF($A19="","",SUMIFS(Calc!$BW:$BW,Calc!$C:$C,$A19)) | AU19: =IF($A19="","",IF(B19>0,AS19-H19*AR19/B19,0)) | AV19: =IF($A19="","",IF(B19>0,AT19-I19*AR19/B19,0)) | AW19: =IF($A19="","",IF(V19=1,(AU19*Q19-AV19*R19)/U19,0)) | AX19: =IF($A19="","",IF(V19=1,(AV19*P19-AU19*R19)/U19,0)) | AY19: =IF($A19="","",IF(AND(V19=1,C19>0,D19>0,AN19>0),(AW19*(Y19-Z19)+AX19*(AA19-AB19))/AN19,0)) | AZ19: =IF($A19="","",IF(AP19>=0,MAX(0,MIN(AY19,AP19)),MIN(0,MAX(AY19,AP19)))) | BA19: =IF($A19="","",AP19-AZ19)
A20: =IFERROR(INDEX(Calc!$C:$C,MATCH(16,Calc!$BX:$BX,0)),"") | B20: =IF($A20="","",COUNTIFS(Calc!$C:$C,$A20)) | C20: =IF($A20="","",COUNTIFS(Calc!$C:$C,$A20,Calc!$D:$D,"F")) | D20: =IF($A20="","",COUNTIFS(Calc!$C:$C,$A20,Calc!$D:$D,"M")) | E20: =IF($A20="","",IF(D20>0,SUMIFS(Calc!$Q:$Q,Calc!$C:$C,$A20,Calc!$D:$D,"M")/D20,0)) | F20: =IF($A20="","",IF(C20>0,SUMIFS(Calc!$Q:$Q,Calc!$C:$C,$A20,Calc!$D:$D,"F")/C20,0)) | G20: =IF($A20="","",IF(AND(C20>0,D20>0,E20>0),(E20-F20)/E20,0)) | H20: =IF($A20="","",SUMIFS(Calc!$E:$E,Calc!$C:$C,$A20)) | I20: =IF($A20="","",SUMIFS(Calc!$P:$P,Calc!$C:$C,$A20)) | J20: =IF($A20="","",SUMIFS(Calc!$Q:$Q,Calc!$C:$C,$A20)) | K20: =IF($A20="","",SUMIFS(Calc!$R:$R,Calc!$C:$C,$A20)) | L20: =IF($A20="","",SUMIFS(Calc!$S:$S,Calc!$C:$C,$A20)) | M20: =IF($A20="","",SUMIFS(Calc!$T:$T,Calc!$C:$C,$A20)) | N20: =IF($A20="","",SUMIFS(Calc!$U:$U,Calc!$C:$C,$A20)) | O20: =IF($A20="","",SUMIFS(Calc!$V:$V,Calc!$C:$C,$A20)) | P20: =IF($A20="","",IF(B20>0,K20-H20^2/B20,0)) | Q20: =IF($A20="","",IF(B20>0,L20-I20^2/B20,0)) | R20: =IF($A20="","",IF(B20>0,M20-H20*I20/B20,0)) | S20: =IF($A20="","",IF(B20>0,N20-H20*J20/B20,0)) | T20: =IF($A20="","",IF(B20>0,O20-I20*J20/B20,0)) | U20: =IF($A20="","",P20*Q20-R20^2) | V20: =IF($A20="","",IF(AND(B20>=4,ABS(U20)>0.000000001),1,0)) | W20: =IF($A20="","",IF(V20=1,(S20*Q20-T20*R20)/U20,0)) | X20: =IF($A20="","",IF(V20=1,(T20*P20-S20*R20)/U20,0)) | Y20: =IF($A20="","",IF(D20>0,SUMIFS(Calc!$E:$E,Calc!$C:$C,$A20,Calc!$D:$D,"M")/D20,0)) | Z20: =IF($A20="","",IF(C20>0,SUMIFS(Calc!$E:$E,Calc!$C:$C,$A20,Calc!$D:$D,"F")/C20,0)) | AA20: =IF($A20="","",IF(D20>0,SUMIFS(Calc!$P:$P,Calc!$C:$C,$A20,Calc!$D:$D,"M")/D20,0)) | AB20: =IF($A20="","",IF(C20>0,SUMIFS(Calc!$P:$P,Calc!$C:$C,$A20,Calc!$D:$D,"F")/C20,0)) | AC20: =IF($A20="","",IF(AND(V20=1,C20>0,D20>0,E20>0),(W20*(Y20-Z20)+X20*(AA20-AB20))/E20,0)) | AD20: =IF($A20="","",IF(G20>=0,MAX(0,MIN(AC20,G20)),MIN(0,MAX(AC20,G20)))) | AE20: =IF($A20="","",G20-AD20) | AF20: =IF($A20="","",INT((B20+1)/2)) | AG20: =IF($A20="","",INT(B20/2)+1) | AH20: =IF($A20="","",(SUMIFS(Calc!$Q:$Q,Calc!$C:$C,$A20,Calc!$X:$X,AF20)+SUMIFS(Calc!$Q:$Q,Calc!$C:$C,$A20,Calc!$X:$X,AG20))/2) | AI20: =IF($A20="","",IF(AND(G20>=0,AE20>0.000000000001),AE20*E20*C20,0)) | AJ20: =IF($A20="","",SUMIFS(Calc!$AA:$AA,Calc!$C:$C,$A20)) | AK20: =IF($A20="","",IF(D20>0,SUMIFS(Calc!$BT:$BT,Calc!$C:$C,$A20,Calc!$D:$D,"M")/D20,0)) | AL20: =IF($A20="","",IF(C20>0,SUMIFS(Calc!$BT:$BT,Calc!$C:$C,$A20,Calc!$D:$D,"F")/C20,0)) | AM20: =IF($A20="","",IF(AK20>0,(AK20-AL20)/AK20,0)) | AN20: =IF($A20="","",IF(D20>0,SUMIFS(Calc!$BU:$BU,Calc!$C:$C,$A20,Calc!$D:$D,"M")/D20,0)) | AO20: =IF($A20="","",IF(C20>0,SUMIFS(Calc!$BU:$BU,Calc!$C:$C,$A20,Calc!$D:$D,"F")/C20,0)) | AP20: =IF($A20="","",IF(AN20>0,(AN20-AO20)/AN20,0)) | AQ20: =IF($A20="","",IF(AND(AI20>0,AJ20>0),0,AE20)) | AR20: =IF($A20="","",SUMIFS(Calc!$BU:$BU,Calc!$C:$C,$A20)) | AS20: =IF($A20="","",SUMIFS(Calc!$BV:$BV,Calc!$C:$C,$A20)) | AT20: =IF($A20="","",SUMIFS(Calc!$BW:$BW,Calc!$C:$C,$A20)) | AU20: =IF($A20="","",IF(B20>0,AS20-H20*AR20/B20,0)) | AV20: =IF($A20="","",IF(B20>0,AT20-I20*AR20/B20,0)) | AW20: =IF($A20="","",IF(V20=1,(AU20*Q20-AV20*R20)/U20,0)) | AX20: =IF($A20="","",IF(V20=1,(AV20*P20-AU20*R20)/U20,0)) | AY20: =IF($A20="","",IF(AND(V20=1,C20>0,D20>0,AN20>0),(AW20*(Y20-Z20)+AX20*(AA20-AB20))/AN20,0)) | AZ20: =IF($A20="","",IF(AP20>=0,MAX(0,MIN(AY20,AP20)),MIN(0,MAX(AY20,AP20)))) | BA20: =IF($A20="","",AP20-AZ20)
A21: =IFERROR(INDEX(Calc!$C:$C,MATCH(17,Calc!$BX:$BX,0)),"") | B21: =IF($A21="","",COUNTIFS(Calc!$C:$C,$A21)) | C21: =IF($A21="","",COUNTIFS(Calc!$C:$C,$A21,Calc!$D:$D,"F")) | D21: =IF($A21="","",COUNTIFS(Calc!$C:$C,$A21,Calc!$D:$D,"M")) | E21: =IF($A21="","",IF(D21>0,SUMIFS(Calc!$Q:$Q,Calc!$C:$C,$A21,Calc!$D:$D,"M")/D21,0)) | F21: =IF($A21="","",IF(C21>0,SUMIFS(Calc!$Q:$Q,Calc!$C:$C,$A21,Calc!$D:$D,"F")/C21,0)) | G21: =IF($A21="","",IF(AND(C21>0,D21>0,E21>0),(E21-F21)/E21,0)) | H21: =IF($A21="","",SUMIFS(Calc!$E:$E,Calc!$C:$C,$A21)) | I21: =IF($A21="","",SUMIFS(Calc!$P:$P,Calc!$C:$C,$A21)) | J21: =IF($A21="","",SUMIFS(Calc!$Q:$Q,Calc!$C:$C,$A21)) | K21: =IF($A21="","",SUMIFS(Calc!$R:$R,Calc!$C:$C,$A21)) | L21: =IF($A21="","",SUMIFS(Calc!$S:$S,Calc!$C:$C,$A21)) | M21: =IF($A21="","",SUMIFS(Calc!$T:$T,Calc!$C:$C,$A21)) | N21: =IF($A21="","",SUMIFS(Calc!$U:$U,Calc!$C:$C,$A21)) | O21: =IF($A21="","",SUMIFS(Calc!$V:$V,Calc!$C:$C,$A21)) | P21: =IF($A21="","",IF(B21>0,K21-H21^2/B21,0)) | Q21: =IF($A21="","",IF(B21>0,L21-I21^2/B21,0)) | R21: =IF($A21="","",IF(B21>0,M21-H21*I21/B21,0)) | S21: =IF($A21="","",IF(B21>0,N21-H21*J21/B21,0)) | T21: =IF($A21="","",IF(B21>0,O21-I21*J21/B21,0)) | U21: =IF($A21="","",P21*Q21-R21^2) | V21: =IF($A21="","",IF(AND(B21>=4,ABS(U21)>0.000000001),1,0)) | W21: =IF($A21="","",IF(V21=1,(S21*Q21-T21*R21)/U21,0)) | X21: =IF($A21="","",IF(V21=1,(T21*P21-S21*R21)/U21,0)) | Y21: =IF($A21="","",IF(D21>0,SUMIFS(Calc!$E:$E,Calc!$C:$C,$A21,Calc!$D:$D,"M")/D21,0)) | Z21: =IF($A21="","",IF(C21>0,SUMIFS(Calc!$E:$E,Calc!$C:$C,$A21,Calc!$D:$D,"F")/C21,0)) | AA21: =IF($A21="","",IF(D21>0,SUMIFS(Calc!$P:$P,Calc!$C:$C,$A21,Calc!$D:$D,"M")/D21,0)) | AB21: =IF($A21="","",IF(C21>0,SUMIFS(Calc!$P:$P,Calc!$C:$C,$A21,Calc!$D:$D,"F")/C21,0)) | AC21: =IF($A21="","",IF(AND(V21=1,C21>0,D21>0,E21>0),(W21*(Y21-Z21)+X21*(AA21-AB21))/E21,0)) | AD21: =IF($A21="","",IF(G21>=0,MAX(0,MIN(AC21,G21)),MIN(0,MAX(AC21,G21)))) | AE21: =IF($A21="","",G21-AD21) | AF21: =IF($A21="","",INT((B21+1)/2)) | AG21: =IF($A21="","",INT(B21/2)+1) | AH21: =IF($A21="","",(SUMIFS(Calc!$Q:$Q,Calc!$C:$C,$A21,Calc!$X:$X,AF21)+SUMIFS(Calc!$Q:$Q,Calc!$C:$C,$A21,Calc!$X:$X,AG21))/2) | AI21: =IF($A21="","",IF(AND(G21>=0,AE21>0.000000000001),AE21*E21*C21,0)) | AJ21: =IF($A21="","",SUMIFS(Calc!$AA:$AA,Calc!$C:$C,$A21)) | AK21: =IF($A21="","",IF(D21>0,SUMIFS(Calc!$BT:$BT,Calc!$C:$C,$A21,Calc!$D:$D,"M")/D21,0)) | AL21: =IF($A21="","",IF(C21>0,SUMIFS(Calc!$BT:$BT,Calc!$C:$C,$A21,Calc!$D:$D,"F")/C21,0)) | AM21: =IF($A21="","",IF(AK21>0,(AK21-AL21)/AK21,0)) | AN21: =IF($A21="","",IF(D21>0,SUMIFS(Calc!$BU:$BU,Calc!$C:$C,$A21,Calc!$D:$D,"M")/D21,0)) | AO21: =IF($A21="","",IF(C21>0,SUMIFS(Calc!$BU:$BU,Calc!$C:$C,$A21,Calc!$D:$D,"F")/C21,0)) | AP21: =IF($A21="","",IF(AN21>0,(AN21-AO21)/AN21,0)) | AQ21: =IF($A21="","",IF(AND(AI21>0,AJ21>0),0,AE21)) | AR21: =IF($A21="","",SUMIFS(Calc!$BU:$BU,Calc!$C:$C,$A21)) | AS21: =IF($A21="","",SUMIFS(Calc!$BV:$BV,Calc!$C:$C,$A21)) | AT21: =IF($A21="","",SUMIFS(Calc!$BW:$BW,Calc!$C:$C,$A21)) | AU21: =IF($A21="","",IF(B21>0,AS21-H21*AR21/B21,0)) | AV21: =IF($A21="","",IF(B21>0,AT21-I21*AR21/B21,0)) | AW21: =IF($A21="","",IF(V21=1,(AU21*Q21-AV21*R21)/U21,0)) | AX21: =IF($A21="","",IF(V21=1,(AV21*P21-AU21*R21)/U21,0)) | AY21: =IF($A21="","",IF(AND(V21=1,C21>0,D21>0,AN21>0),(AW21*(Y21-Z21)+AX21*(AA21-AB21))/AN21,0)) | AZ21: =IF($A21="","",IF(AP21>=0,MAX(0,MIN(AY21,AP21)),MIN(0,MAX(AY21,AP21)))) | BA21: =IF($A21="","",AP21-AZ21)
A22: =IFERROR(INDEX(Calc!$C:$C,MATCH(18,Calc!$BX:$BX,0)),"") | B22: =IF($A22="","",COUNTIFS(Calc!$C:$C,$A22)) | C22: =IF($A22="","",COUNTIFS(Calc!$C:$C,$A22,Calc!$D:$D,"F")) | D22: =IF($A22="","",COUNTIFS(Calc!$C:$C,$A22,Calc!$D:$D,"M")) | E22: =IF($A22="","",IF(D22>0,SUMIFS(Calc!$Q:$Q,Calc!$C:$C,$A22,Calc!$D:$D,"M")/D22,0)) | F22: =IF($A22="","",IF(C22>0,SUMIFS(Calc!$Q:$Q,Calc!$C:$C,$A22,Calc!$D:$D,"F")/C22,0)) | G22: =IF($A22="","",IF(AND(C22>0,D22>0,E22>0),(E22-F22)/E22,0)) | H22: =IF($A22="","",SUMIFS(Calc!$E:$E,Calc!$C:$C,$A22)) | I22: =IF($A22="","",SUMIFS(Calc!$P:$P,Calc!$C:$C,$A22)) | J22: =IF($A22="","",SUMIFS(Calc!$Q:$Q,Calc!$C:$C,$A22)) | K22: =IF($A22="","",SUMIFS(Calc!$R:$R,Calc!$C:$C,$A22)) | L22: =IF($A22="","",SUMIFS(Calc!$S:$S,Calc!$C:$C,$A22)) | M22: =IF($A22="","",SUMIFS(Calc!$T:$T,Calc!$C:$C,$A22)) | N22: =IF($A22="","",SUMIFS(Calc!$U:$U,Calc!$C:$C,$A22)) | O22: =IF($A22="","",SUMIFS(Calc!$V:$V,Calc!$C:$C,$A22)) | P22: =IF($A22="","",IF(B22>0,K22-H22^2/B22,0)) | Q22: =IF($A22="","",IF(B22>0,L22-I22^2/B22,0)) | R22: =IF($A22="","",IF(B22>0,M22-H22*I22/B22,0)) | S22: =IF($A22="","",IF(B22>0,N22-H22*J22/B22,0)) | T22: =IF($A22="","",IF(B22>0,O22-I22*J22/B22,0)) | U22: =IF($A22="","",P22*Q22-R22^2) | V22: =IF($A22="","",IF(AND(B22>=4,ABS(U22)>0.000000001),1,0)) | W22: =IF($A22="","",IF(V22=1,(S22*Q22-T22*R22)/U22,0)) | X22: =IF($A22="","",IF(V22=1,(T22*P22-S22*R22)/U22,0)) | Y22: =IF($A22="","",IF(D22>0,SUMIFS(Calc!$E:$E,Calc!$C:$C,$A22,Calc!$D:$D,"M")/D22,0)) | Z22: =IF($A22="","",IF(C22>0,SUMIFS(Calc!$E:$E,Calc!$C:$C,$A22,Calc!$D:$D,"F")/C22,0)) | AA22: =IF($A22="","",IF(D22>0,SUMIFS(Calc!$P:$P,Calc!$C:$C,$A22,Calc!$D:$D,"M")/D22,0)) | AB22: =IF($A22="","",IF(C22>0,SUMIFS(Calc!$P:$P,Calc!$C:$C,$A22,Calc!$D:$D,"F")/C22,0)) | AC22: =IF($A22="","",IF(AND(V22=1,C22>0,D22>0,E22>0),(W22*(Y22-Z22)+X22*(AA22-AB22))/E22,0)) | AD22: =IF($A22="","",IF(G22>=0,MAX(0,MIN(AC22,G22)),MIN(0,MAX(AC22,G22)))) | AE22: =IF($A22="","",G22-AD22) | AF22: =IF($A22="","",INT((B22+1)/2)) | AG22: =IF($A22="","",INT(B22/2)+1) | AH22: =IF($A22="","",(SUMIFS(Calc!$Q:$Q,Calc!$C:$C,$A22,Calc!$X:$X,AF22)+SUMIFS(Calc!$Q:$Q,Calc!$C:$C,$A22,Calc!$X:$X,AG22))/2) | AI22: =IF($A22="","",IF(AND(G22>=0,AE22>0.000000000001),AE22*E22*C22,0)) | AJ22: =IF($A22="","",SUMIFS(Calc!$AA:$AA,Calc!$C:$C,$A22)) | AK22: =IF($A22="","",IF(D22>0,SUMIFS(Calc!$BT:$BT,Calc!$C:$C,$A22,Calc!$D:$D,"M")/D22,0)) | AL22: =IF($A22="","",IF(C22>0,SUMIFS(Calc!$BT:$BT,Calc!$C:$C,$A22,Calc!$D:$D,"F")/C22,0)) | AM22: =IF($A22="","",IF(AK22>0,(AK22-AL22)/AK22,0)) | AN22: =IF($A22="","",IF(D22>0,SUMIFS(Calc!$BU:$BU,Calc!$C:$C,$A22,Calc!$D:$D,"M")/D22,0)) | AO22: =IF($A22="","",IF(C22>0,SUMIFS(Calc!$BU:$BU,Calc!$C:$C,$A22,Calc!$D:$D,"F")/C22,0)) | AP22: =IF($A22="","",IF(AN22>0,(AN22-AO22)/AN22,0)) | AQ22: =IF($A22="","",IF(AND(AI22>0,AJ22>0),0,AE22)) | AR22: =IF($A22="","",SUMIFS(Calc!$BU:$BU,Calc!$C:$C,$A22)) | AS22: =IF($A22="","",SUMIFS(Calc!$BV:$BV,Calc!$C:$C,$A22)) | AT22: =IF($A22="","",SUMIFS(Calc!$BW:$BW,Calc!$C:$C,$A22)) | AU22: =IF($A22="","",IF(B22>0,AS22-H22*AR22/B22,0)) | AV22: =IF($A22="","",IF(B22>0,AT22-I22*AR22/B22,0)) | AW22: =IF($A22="","",IF(V22=1,(AU22*Q22-AV22*R22)/U22,0)) | AX22: =IF($A22="","",IF(V22=1,(AV22*P22-AU22*R22)/U22,0)) | AY22: =IF($A22="","",IF(AND(V22=1,C22>0,D22>0,AN22>0),(AW22*(Y22-Z22)+AX22*(AA22-AB22))/AN22,0)) | AZ22: =IF($A22="","",IF(AP22>=0,MAX(0,MIN(AY22,AP22)),MIN(0,MAX(AY22,AP22)))) | BA22: =IF($A22="","",AP22-AZ22)
A23: =IFERROR(INDEX(Calc!$C:$C,MATCH(19,Calc!$BX:$BX,0)),"") | B23: =IF($A23="","",COUNTIFS(Calc!$C:$C,$A23)) | C23: =IF($A23="","",COUNTIFS(Calc!$C:$C,$A23,Calc!$D:$D,"F")) | D23: =IF($A23="","",COUNTIFS(Calc!$C:$C,$A23,Calc!$D:$D,"M")) | E23: =IF($A23="","",IF(D23>0,SUMIFS(Calc!$Q:$Q,Calc!$C:$C,$A23,Calc!$D:$D,"M")/D23,0)) | F23: =IF($A23="","",IF(C23>0,SUMIFS(Calc!$Q:$Q,Calc!$C:$C,$A23,Calc!$D:$D,"F")/C23,0)) | G23: =IF($A23="","",IF(AND(C23>0,D23>0,E23>0),(E23-F23)/E23,0)) | H23: =IF($A23="","",SUMIFS(Calc!$E:$E,Calc!$C:$C,$A23)) | I23: =IF($A23="","",SUMIFS(Calc!$P:$P,Calc!$C:$C,$A23)) | J23: =IF($A23="","",SUMIFS(Calc!$Q:$Q,Calc!$C:$C,$A23)) | K23: =IF($A23="","",SUMIFS(Calc!$R:$R,Calc!$C:$C,$A23)) | L23: =IF($A23="","",SUMIFS(Calc!$S:$S,Calc!$C:$C,$A23)) | M23: =IF($A23="","",SUMIFS(Calc!$T:$T,Calc!$C:$C,$A23)) | N23: =IF($A23="","",SUMIFS(Calc!$U:$U,Calc!$C:$C,$A23)) | O23: =IF($A23="","",SUMIFS(Calc!$V:$V,Calc!$C:$C,$A23)) | P23: =IF($A23="","",IF(B23>0,K23-H23^2/B23,0)) | Q23: =IF($A23="","",IF(B23>0,L23-I23^2/B23,0)) | R23: =IF($A23="","",IF(B23>0,M23-H23*I23/B23,0)) | S23: =IF($A23="","",IF(B23>0,N23-H23*J23/B23,0)) | T23: =IF($A23="","",IF(B23>0,O23-I23*J23/B23,0)) | U23: =IF($A23="","",P23*Q23-R23^2) | V23: =IF($A23="","",IF(AND(B23>=4,ABS(U23)>0.000000001),1,0)) | W23: =IF($A23="","",IF(V23=1,(S23*Q23-T23*R23)/U23,0)) | X23: =IF($A23="","",IF(V23=1,(T23*P23-S23*R23)/U23,0)) | Y23: =IF($A23="","",IF(D23>0,SUMIFS(Calc!$E:$E,Calc!$C:$C,$A23,Calc!$D:$D,"M")/D23,0)) | Z23: =IF($A23="","",IF(C23>0,SUMIFS(Calc!$E:$E,Calc!$C:$C,$A23,Calc!$D:$D,"F")/C23,0)) | AA23: =IF($A23="","",IF(D23>0,SUMIFS(Calc!$P:$P,Calc!$C:$C,$A23,Calc!$D:$D,"M")/D23,0)) | AB23: =IF($A23="","",IF(C23>0,SUMIFS(Calc!$P:$P,Calc!$C:$C,$A23,Calc!$D:$D,"F")/C23,0)) | AC23: =IF($A23="","",IF(AND(V23=1,C23>0,D23>0,E23>0),(W23*(Y23-Z23)+X23*(AA23-AB23))/E23,0)) | AD23: =IF($A23="","",IF(G23>=0,MAX(0,MIN(AC23,G23)),MIN(0,MAX(AC23,G23)))) | AE23: =IF($A23="","",G23-AD23) | AF23: =IF($A23="","",INT((B23+1)/2)) | AG23: =IF($A23="","",INT(B23/2)+1) | AH23: =IF($A23="","",(SUMIFS(Calc!$Q:$Q,Calc!$C:$C,$A23,Calc!$X:$X,AF23)+SUMIFS(Calc!$Q:$Q,Calc!$C:$C,$A23,Calc!$X:$X,AG23))/2) | AI23: =IF($A23="","",IF(AND(G23>=0,AE23>0.000000000001),AE23*E23*C23,0)) | AJ23: =IF($A23="","",SUMIFS(Calc!$AA:$AA,Calc!$C:$C,$A23)) | AK23: =IF($A23="","",IF(D23>0,SUMIFS(Calc!$BT:$BT,Calc!$C:$C,$A23,Calc!$D:$D,"M")/D23,0)) | AL23: =IF($A23="","",IF(C23>0,SUMIFS(Calc!$BT:$BT,Calc!$C:$C,$A23,Calc!$D:$D,"F")/C23,0)) | AM23: =IF($A23="","",IF(AK23>0,(AK23-AL23)/AK23,0)) | AN23: =IF($A23="","",IF(D23>0,SUMIFS(Calc!$BU:$BU,Calc!$C:$C,$A23,Calc!$D:$D,"M")/D23,0)) | AO23: =IF($A23="","",IF(C23>0,SUMIFS(Calc!$BU:$BU,Calc!$C:$C,$A23,Calc!$D:$D,"F")/C23,0)) | AP23: =IF($A23="","",IF(AN23>0,(AN23-AO23)/AN23,0)) | AQ23: =IF($A23="","",IF(AND(AI23>0,AJ23>0),0,AE23)) | AR23: =IF($A23="","",SUMIFS(Calc!$BU:$BU,Calc!$C:$C,$A23)) | AS23: =IF($A23="","",SUMIFS(Calc!$BV:$BV,Calc!$C:$C,$A23)) | AT23: =IF($A23="","",SUMIFS(Calc!$BW:$BW,Calc!$C:$C,$A23)) | AU23: =IF($A23="","",IF(B23>0,AS23-H23*AR23/B23,0)) | AV23: =IF($A23="","",IF(B23>0,AT23-I23*AR23/B23,0)) | AW23: =IF($A23="","",IF(V23=1,(AU23*Q23-AV23*R23)/U23,0)) | AX23: =IF($A23="","",IF(V23=1,(AV23*P23-AU23*R23)/U23,0)) | AY23: =IF($A23="","",IF(AND(V23=1,C23>0,D23>0,AN23>0),(AW23*(Y23-Z23)+AX23*(AA23-AB23))/AN23,0)) | AZ23: =IF($A23="","",IF(AP23>=0,MAX(0,MIN(AY23,AP23)),MIN(0,MAX(AY23,AP23)))) | BA23: =IF($A23="","",AP23-AZ23)
A24: =IFERROR(INDEX(Calc!$C:$C,MATCH(20,Calc!$BX:$BX,0)),"") | B24: =IF($A24="","",COUNTIFS(Calc!$C:$C,$A24)) | C24: =IF($A24="","",COUNTIFS(Calc!$C:$C,$A24,Calc!$D:$D,"F")) | D24: =IF($A24="","",COUNTIFS(Calc!$C:$C,$A24,Calc!$D:$D,"M")) | E24: =IF($A24="","",IF(D24>0,SUMIFS(Calc!$Q:$Q,Calc!$C:$C,$A24,Calc!$D:$D,"M")/D24,0)) | F24: =IF($A24="","",IF(C24>0,SUMIFS(Calc!$Q:$Q,Calc!$C:$C,$A24,Calc!$D:$D,"F")/C24,0)) | G24: =IF($A24="","",IF(AND(C24>0,D24>0,E24>0),(E24-F24)/E24,0)) | H24: =IF($A24="","",SUMIFS(Calc!$E:$E,Calc!$C:$C,$A24)) | I24: =IF($A24="","",SUMIFS(Calc!$P:$P,Calc!$C:$C,$A24)) | J24: =IF($A24="","",SUMIFS(Calc!$Q:$Q,Calc!$C:$C,$A24)) | K24: =IF($A24="","",SUMIFS(Calc!$R:$R,Calc!$C:$C,$A24)) | L24: =IF($A24="","",SUMIFS(Calc!$S:$S,Calc!$C:$C,$A24)) | M24: =IF($A24="","",SUMIFS(Calc!$T:$T,Calc!$C:$C,$A24)) | N24: =IF($A24="","",SUMIFS(Calc!$U:$U,Calc!$C:$C,$A24)) | O24: =IF($A24="","",SUMIFS(Calc!$V:$V,Calc!$C:$C,$A24)) | P24: =IF($A24="","",IF(B24>0,K24-H24^2/B24,0)) | Q24: =IF($A24="","",IF(B24>0,L24-I24^2/B24,0)) | R24: =IF($A24="","",IF(B24>0,M24-H24*I24/B24,0)) | S24: =IF($A24="","",IF(B24>0,N24-H24*J24/B24,0)) | T24: =IF($A24="","",IF(B24>0,O24-I24*J24/B24,0)) | U24: =IF($A24="","",P24*Q24-R24^2) | V24: =IF($A24="","",IF(AND(B24>=4,ABS(U24)>0.000000001),1,0)) | W24: =IF($A24="","",IF(V24=1,(S24*Q24-T24*R24)/U24,0)) | X24: =IF($A24="","",IF(V24=1,(T24*P24-S24*R24)/U24,0)) | Y24: =IF($A24="","",IF(D24>0,SUMIFS(Calc!$E:$E,Calc!$C:$C,$A24,Calc!$D:$D,"M")/D24,0)) | Z24: =IF($A24="","",IF(C24>0,SUMIFS(Calc!$E:$E,Calc!$C:$C,$A24,Calc!$D:$D,"F")/C24,0)) | AA24: =IF($A24="","",IF(D24>0,SUMIFS(Calc!$P:$P,Calc!$C:$C,$A24,Calc!$D:$D,"M")/D24,0)) | AB24: =IF($A24="","",IF(C24>0,SUMIFS(Calc!$P:$P,Calc!$C:$C,$A24,Calc!$D:$D,"F")/C24,0)) | AC24: =IF($A24="","",IF(AND(V24=1,C24>0,D24>0,E24>0),(W24*(Y24-Z24)+X24*(AA24-AB24))/E24,0)) | AD24: =IF($A24="","",IF(G24>=0,MAX(0,MIN(AC24,G24)),MIN(0,MAX(AC24,G24)))) | AE24: =IF($A24="","",G24-AD24) | AF24: =IF($A24="","",INT((B24+1)/2)) | AG24: =IF($A24="","",INT(B24/2)+1) | AH24: =IF($A24="","",(SUMIFS(Calc!$Q:$Q,Calc!$C:$C,$A24,Calc!$X:$X,AF24)+SUMIFS(Calc!$Q:$Q,Calc!$C:$C,$A24,Calc!$X:$X,AG24))/2) | AI24: =IF($A24="","",IF(AND(G24>=0,AE24>0.000000000001),AE24*E24*C24,0)) | AJ24: =IF($A24="","",SUMIFS(Calc!$AA:$AA,Calc!$C:$C,$A24)) | AK24: =IF($A24="","",IF(D24>0,SUMIFS(Calc!$BT:$BT,Calc!$C:$C,$A24,Calc!$D:$D,"M")/D24,0)) | AL24: =IF($A24="","",IF(C24>0,SUMIFS(Calc!$BT:$BT,Calc!$C:$C,$A24,Calc!$D:$D,"F")/C24,0)) | AM24: =IF($A24="","",IF(AK24>0,(AK24-AL24)/AK24,0)) | AN24: =IF($A24="","",IF(D24>0,SUMIFS(Calc!$BU:$BU,Calc!$C:$C,$A24,Calc!$D:$D,"M")/D24,0)) | AO24: =IF($A24="","",IF(C24>0,SUMIFS(Calc!$BU:$BU,Calc!$C:$C,$A24,Calc!$D:$D,"F")/C24,0)) | AP24: =IF($A24="","",IF(AN24>0,(AN24-AO24)/AN24,0)) | AQ24: =IF($A24="","",IF(AND(AI24>0,AJ24>0),0,AE24)) | AR24: =IF($A24="","",SUMIFS(Calc!$BU:$BU,Calc!$C:$C,$A24)) | AS24: =IF($A24="","",SUMIFS(Calc!$BV:$BV,Calc!$C:$C,$A24)) | AT24: =IF($A24="","",SUMIFS(Calc!$BW:$BW,Calc!$C:$C,$A24)) | AU24: =IF($A24="","",IF(B24>0,AS24-H24*AR24/B24,0)) | AV24: =IF($A24="","",IF(B24>0,AT24-I24*AR24/B24,0)) | AW24: =IF($A24="","",IF(V24=1,(AU24*Q24-AV24*R24)/U24,0)) | AX24: =IF($A24="","",IF(V24=1,(AV24*P24-AU24*R24)/U24,0)) | AY24: =IF($A24="","",IF(AND(V24=1,C24>0,D24>0,AN24>0),(AW24*(Y24-Z24)+AX24*(AA24-AB24))/AN24,0)) | AZ24: =IF($A24="","",IF(AP24>=0,MAX(0,MIN(AY24,AP24)),MIN(0,MAX(AY24,AP24)))) | BA24: =IF($A24="","",AP24-AZ24)
A25: =IFERROR(INDEX(Calc!$C:$C,MATCH(21,Calc!$BX:$BX,0)),"") | B25: =IF($A25="","",COUNTIFS(Calc!$C:$C,$A25)) | C25: =IF($A25="","",COUNTIFS(Calc!$C:$C,$A25,Calc!$D:$D,"F")) | D25: =IF($A25="","",COUNTIFS(Calc!$C:$C,$A25,Calc!$D:$D,"M")) | E25: =IF($A25="","",IF(D25>0,SUMIFS(Calc!$Q:$Q,Calc!$C:$C,$A25,Calc!$D:$D,"M")/D25,0)) | F25: =IF($A25="","",IF(C25>0,SUMIFS(Calc!$Q:$Q,Calc!$C:$C,$A25,Calc!$D:$D,"F")/C25,0)) | G25: =IF($A25="","",IF(AND(C25>0,D25>0,E25>0),(E25-F25)/E25,0)) | H25: =IF($A25="","",SUMIFS(Calc!$E:$E,Calc!$C:$C,$A25)) | I25: =IF($A25="","",SUMIFS(Calc!$P:$P,Calc!$C:$C,$A25)) | J25: =IF($A25="","",SUMIFS(Calc!$Q:$Q,Calc!$C:$C,$A25)) | K25: =IF($A25="","",SUMIFS(Calc!$R:$R,Calc!$C:$C,$A25)) | L25: =IF($A25="","",SUMIFS(Calc!$S:$S,Calc!$C:$C,$A25)) | M25: =IF($A25="","",SUMIFS(Calc!$T:$T,Calc!$C:$C,$A25)) | N25: =IF($A25="","",SUMIFS(Calc!$U:$U,Calc!$C:$C,$A25)) | O25: =IF($A25="","",SUMIFS(Calc!$V:$V,Calc!$C:$C,$A25)) | P25: =IF($A25="","",IF(B25>0,K25-H25^2/B25,0)) | Q25: =IF($A25="","",IF(B25>0,L25-I25^2/B25,0)) | R25: =IF($A25="","",IF(B25>0,M25-H25*I25/B25,0)) | S25: =IF($A25="","",IF(B25>0,N25-H25*J25/B25,0)) | T25: =IF($A25="","",IF(B25>0,O25-I25*J25/B25,0)) | U25: =IF($A25="","",P25*Q25-R25^2) | V25: =IF($A25="","",IF(AND(B25>=4,ABS(U25)>0.000000001),1,0)) | W25: =IF($A25="","",IF(V25=1,(S25*Q25-T25*R25)/U25,0)) | X25: =IF($A25="","",IF(V25=1,(T25*P25-S25*R25)/U25,0)) | Y25: =IF($A25="","",IF(D25>0,SUMIFS(Calc!$E:$E,Calc!$C:$C,$A25,Calc!$D:$D,"M")/D25,0)) | Z25: =IF($A25="","",IF(C25>0,SUMIFS(Calc!$E:$E,Calc!$C:$C,$A25,Calc!$D:$D,"F")/C25,0)) | AA25: =IF($A25="","",IF(D25>0,SUMIFS(Calc!$P:$P,Calc!$C:$C,$A25,Calc!$D:$D,"M")/D25,0)) | AB25: =IF($A25="","",IF(C25>0,SUMIFS(Calc!$P:$P,Calc!$C:$C,$A25,Calc!$D:$D,"F")/C25,0)) | AC25: =IF($A25="","",IF(AND(V25=1,C25>0,D25>0,E25>0),(W25*(Y25-Z25)+X25*(AA25-AB25))/E25,0)) | AD25: =IF($A25="","",IF(G25>=0,MAX(0,MIN(AC25,G25)),MIN(0,MAX(AC25,G25)))) | AE25: =IF($A25="","",G25-AD25) | AF25: =IF($A25="","",INT((B25+1)/2)) | AG25: =IF($A25="","",INT(B25/2)+1) | AH25: =IF($A25="","",(SUMIFS(Calc!$Q:$Q,Calc!$C:$C,$A25,Calc!$X:$X,AF25)+SUMIFS(Calc!$Q:$Q,Calc!$C:$C,$A25,Calc!$X:$X,AG25))/2) | AI25: =IF($A25="","",IF(AND(G25>=0,AE25>0.000000000001),AE25*E25*C25,0)) | AJ25: =IF($A25="","",SUMIFS(Calc!$AA:$AA,Calc!$C:$C,$A25)) | AK25: =IF($A25="","",IF(D25>0,SUMIFS(Calc!$BT:$BT,Calc!$C:$C,$A25,Calc!$D:$D,"M")/D25,0)) | AL25: =IF($A25="","",IF(C25>0,SUMIFS(Calc!$BT:$BT,Calc!$C:$C,$A25,Calc!$D:$D,"F")/C25,0)) | AM25: =IF($A25="","",IF(AK25>0,(AK25-AL25)/AK25,0)) | AN25: =IF($A25="","",IF(D25>0,SUMIFS(Calc!$BU:$BU,Calc!$C:$C,$A25,Calc!$D:$D,"M")/D25,0)) | AO25: =IF($A25="","",IF(C25>0,SUMIFS(Calc!$BU:$BU,Calc!$C:$C,$A25,Calc!$D:$D,"F")/C25,0)) | AP25: =IF($A25="","",IF(AN25>0,(AN25-AO25)/AN25,0)) | AQ25: =IF($A25="","",IF(AND(AI25>0,AJ25>0),0,AE25)) | AR25: =IF($A25="","",SUMIFS(Calc!$BU:$BU,Calc!$C:$C,$A25)) | AS25: =IF($A25="","",SUMIFS(Calc!$BV:$BV,Calc!$C:$C,$A25)) | AT25: =IF($A25="","",SUMIFS(Calc!$BW:$BW,Calc!$C:$C,$A25)) | AU25: =IF($A25="","",IF(B25>0,AS25-H25*AR25/B25,0)) | AV25: =IF($A25="","",IF(B25>0,AT25-I25*AR25/B25,0)) | AW25: =IF($A25="","",IF(V25=1,(AU25*Q25-AV25*R25)/U25,0)) | AX25: =IF($A25="","",IF(V25=1,(AV25*P25-AU25*R25)/U25,0)) | AY25: =IF($A25="","",IF(AND(V25=1,C25>0,D25>0,AN25>0),(AW25*(Y25-Z25)+AX25*(AA25-AB25))/AN25,0)) | AZ25: =IF($A25="","",IF(AP25>=0,MAX(0,MIN(AY25,AP25)),MIN(0,MAX(AY25,AP25)))) | BA25: =IF($A25="","",AP25-AZ25)
A26: =IFERROR(INDEX(Calc!$C:$C,MATCH(22,Calc!$BX:$BX,0)),"") | B26: =IF($A26="","",COUNTIFS(Calc!$C:$C,$A26)) | C26: =IF($A26="","",COUNTIFS(Calc!$C:$C,$A26,Calc!$D:$D,"F")) | D26: =IF($A26="","",COUNTIFS(Calc!$C:$C,$A26,Calc!$D:$D,"M")) | E26: =IF($A26="","",IF(D26>0,SUMIFS(Calc!$Q:$Q,Calc!$C:$C,$A26,Calc!$D:$D,"M")/D26,0)) | F26: =IF($A26="","",IF(C26>0,SUMIFS(Calc!$Q:$Q,Calc!$C:$C,$A26,Calc!$D:$D,"F")/C26,0)) | G26: =IF($A26="","",IF(AND(C26>0,D26>0,E26>0),(E26-F26)/E26,0)) | H26: =IF($A26="","",SUMIFS(Calc!$E:$E,Calc!$C:$C,$A26)) | I26: =IF($A26="","",SUMIFS(Calc!$P:$P,Calc!$C:$C,$A26)) | J26: =IF($A26="","",SUMIFS(Calc!$Q:$Q,Calc!$C:$C,$A26)) | K26: =IF($A26="","",SUMIFS(Calc!$R:$R,Calc!$C:$C,$A26)) | L26: =IF($A26="","",SUMIFS(Calc!$S:$S,Calc!$C:$C,$A26)) | M26: =IF($A26="","",SUMIFS(Calc!$T:$T,Calc!$C:$C,$A26)) | N26: =IF($A26="","",SUMIFS(Calc!$U:$U,Calc!$C:$C,$A26)) | O26: =IF($A26="","",SUMIFS(Calc!$V:$V,Calc!$C:$C,$A26)) | P26: =IF($A26="","",IF(B26>0,K26-H26^2/B26,0)) | Q26: =IF($A26="","",IF(B26>0,L26-I26^2/B26,0)) | R26: =IF($A26="","",IF(B26>0,M26-H26*I26/B26,0)) | S26: =IF($A26="","",IF(B26>0,N26-H26*J26/B26,0)) | T26: =IF($A26="","",IF(B26>0,O26-I26*J26/B26,0)) | U26: =IF($A26="","",P26*Q26-R26^2) | V26: =IF($A26="","",IF(AND(B26>=4,ABS(U26)>0.000000001),1,0)) | W26: =IF($A26="","",IF(V26=1,(S26*Q26-T26*R26)/U26,0)) | X26: =IF($A26="","",IF(V26=1,(T26*P26-S26*R26)/U26,0)) | Y26: =IF($A26="","",IF(D26>0,SUMIFS(Calc!$E:$E,Calc!$C:$C,$A26,Calc!$D:$D,"M")/D26,0)) | Z26: =IF($A26="","",IF(C26>0,SUMIFS(Calc!$E:$E,Calc!$C:$C,$A26,Calc!$D:$D,"F")/C26,0)) | AA26: =IF($A26="","",IF(D26>0,SUMIFS(Calc!$P:$P,Calc!$C:$C,$A26,Calc!$D:$D,"M")/D26,0)) | AB26: =IF($A26="","",IF(C26>0,SUMIFS(Calc!$P:$P,Calc!$C:$C,$A26,Calc!$D:$D,"F")/C26,0)) | AC26: =IF($A26="","",IF(AND(V26=1,C26>0,D26>0,E26>0),(W26*(Y26-Z26)+X26*(AA26-AB26))/E26,0)) | AD26: =IF($A26="","",IF(G26>=0,MAX(0,MIN(AC26,G26)),MIN(0,MAX(AC26,G26)))) | AE26: =IF($A26="","",G26-AD26) | AF26: =IF($A26="","",INT((B26+1)/2)) | AG26: =IF($A26="","",INT(B26/2)+1) | AH26: =IF($A26="","",(SUMIFS(Calc!$Q:$Q,Calc!$C:$C,$A26,Calc!$X:$X,AF26)+SUMIFS(Calc!$Q:$Q,Calc!$C:$C,$A26,Calc!$X:$X,AG26))/2) | AI26: =IF($A26="","",IF(AND(G26>=0,AE26>0.000000000001),AE26*E26*C26,0)) | AJ26: =IF($A26="","",SUMIFS(Calc!$AA:$AA,Calc!$C:$C,$A26)) | AK26: =IF($A26="","",IF(D26>0,SUMIFS(Calc!$BT:$BT,Calc!$C:$C,$A26,Calc!$D:$D,"M")/D26,0)) | AL26: =IF($A26="","",IF(C26>0,SUMIFS(Calc!$BT:$BT,Calc!$C:$C,$A26,Calc!$D:$D,"F")/C26,0)) | AM26: =IF($A26="","",IF(AK26>0,(AK26-AL26)/AK26,0)) | AN26: =IF($A26="","",IF(D26>0,SUMIFS(Calc!$BU:$BU,Calc!$C:$C,$A26,Calc!$D:$D,"M")/D26,0)) | AO26: =IF($A26="","",IF(C26>0,SUMIFS(Calc!$BU:$BU,Calc!$C:$C,$A26,Calc!$D:$D,"F")/C26,0)) | AP26: =IF($A26="","",IF(AN26>0,(AN26-AO26)/AN26,0)) | AQ26: =IF($A26="","",IF(AND(AI26>0,AJ26>0),0,AE26)) | AR26: =IF($A26="","",SUMIFS(Calc!$BU:$BU,Calc!$C:$C,$A26)) | AS26: =IF($A26="","",SUMIFS(Calc!$BV:$BV,Calc!$C:$C,$A26)) | AT26: =IF($A26="","",SUMIFS(Calc!$BW:$BW,Calc!$C:$C,$A26)) | AU26: =IF($A26="","",IF(B26>0,AS26-H26*AR26/B26,0)) | AV26: =IF($A26="","",IF(B26>0,AT26-I26*AR26/B26,0)) | AW26: =IF($A26="","",IF(V26=1,(AU26*Q26-AV26*R26)/U26,0)) | AX26: =IF($A26="","",IF(V26=1,(AV26*P26-AU26*R26)/U26,0)) | AY26: =IF($A26="","",IF(AND(V26=1,C26>0,D26>0,AN26>0),(AW26*(Y26-Z26)+AX26*(AA26-AB26))/AN26,0)) | AZ26: =IF($A26="","",IF(AP26>=0,MAX(0,MIN(AY26,AP26)),MIN(0,MAX(AY26,AP26)))) | BA26: =IF($A26="","",AP26-AZ26)
A27: =IFERROR(INDEX(Calc!$C:$C,MATCH(23,Calc!$BX:$BX,0)),"") | B27: =IF($A27="","",COUNTIFS(Calc!$C:$C,$A27)) | C27: =IF($A27="","",COUNTIFS(Calc!$C:$C,$A27,Calc!$D:$D,"F")) | D27: =IF($A27="","",COUNTIFS(Calc!$C:$C,$A27,Calc!$D:$D,"M")) | E27: =IF($A27="","",IF(D27>0,SUMIFS(Calc!$Q:$Q,Calc!$C:$C,$A27,Calc!$D:$D,"M")/D27,0)) | F27: =IF($A27="","",IF(C27>0,SUMIFS(Calc!$Q:$Q,Calc!$C:$C,$A27,Calc!$D:$D,"F")/C27,0)) | G27: =IF($A27="","",IF(AND(C27>0,D27>0,E27>0),(E27-F27)/E27,0)) | H27: =IF($A27="","",SUMIFS(Calc!$E:$E,Calc!$C:$C,$A27)) | I27: =IF($A27="","",SUMIFS(Calc!$P:$P,Calc!$C:$C,$A27)) | J27: =IF($A27="","",SUMIFS(Calc!$Q:$Q,Calc!$C:$C,$A27)) | K27: =IF($A27="","",SUMIFS(Calc!$R:$R,Calc!$C:$C,$A27)) | L27: =IF($A27="","",SUMIFS(Calc!$S:$S,Calc!$C:$C,$A27)) | M27: =IF($A27="","",SUMIFS(Calc!$T:$T,Calc!$C:$C,$A27)) | N27: =IF($A27="","",SUMIFS(Calc!$U:$U,Calc!$C:$C,$A27)) | O27: =IF($A27="","",SUMIFS(Calc!$V:$V,Calc!$C:$C,$A27)) | P27: =IF($A27="","",IF(B27>0,K27-H27^2/B27,0)) | Q27: =IF($A27="","",IF(B27>0,L27-I27^2/B27,0)) | R27: =IF($A27="","",IF(B27>0,M27-H27*I27/B27,0)) | S27: =IF($A27="","",IF(B27>0,N27-H27*J27/B27,0)) | T27: =IF($A27="","",IF(B27>0,O27-I27*J27/B27,0)) | U27: =IF($A27="","",P27*Q27-R27^2) | V27: =IF($A27="","",IF(AND(B27>=4,ABS(U27)>0.000000001),1,0)) | W27: =IF($A27="","",IF(V27=1,(S27*Q27-T27*R27)/U27,0)) | X27: =IF($A27="","",IF(V27=1,(T27*P27-S27*R27)/U27,0)) | Y27: =IF($A27="","",IF(D27>0,SUMIFS(Calc!$E:$E,Calc!$C:$C,$A27,Calc!$D:$D,"M")/D27,0)) | Z27: =IF($A27="","",IF(C27>0,SUMIFS(Calc!$E:$E,Calc!$C:$C,$A27,Calc!$D:$D,"F")/C27,0)) | AA27: =IF($A27="","",IF(D27>0,SUMIFS(Calc!$P:$P,Calc!$C:$C,$A27,Calc!$D:$D,"M")/D27,0)) | AB27: =IF($A27="","",IF(C27>0,SUMIFS(Calc!$P:$P,Calc!$C:$C,$A27,Calc!$D:$D,"F")/C27,0)) | AC27: =IF($A27="","",IF(AND(V27=1,C27>0,D27>0,E27>0),(W27*(Y27-Z27)+X27*(AA27-AB27))/E27,0)) | AD27: =IF($A27="","",IF(G27>=0,MAX(0,MIN(AC27,G27)),MIN(0,MAX(AC27,G27)))) | AE27: =IF($A27="","",G27-AD27) | AF27: =IF($A27="","",INT((B27+1)/2)) | AG27: =IF($A27="","",INT(B27/2)+1) | AH27: =IF($A27="","",(SUMIFS(Calc!$Q:$Q,Calc!$C:$C,$A27,Calc!$X:$X,AF27)+SUMIFS(Calc!$Q:$Q,Calc!$C:$C,$A27,Calc!$X:$X,AG27))/2) | AI27: =IF($A27="","",IF(AND(G27>=0,AE27>0.000000000001),AE27*E27*C27,0)) | AJ27: =IF($A27="","",SUMIFS(Calc!$AA:$AA,Calc!$C:$C,$A27)) | AK27: =IF($A27="","",IF(D27>0,SUMIFS(Calc!$BT:$BT,Calc!$C:$C,$A27,Calc!$D:$D,"M")/D27,0)) | AL27: =IF($A27="","",IF(C27>0,SUMIFS(Calc!$BT:$BT,Calc!$C:$C,$A27,Calc!$D:$D,"F")/C27,0)) | AM27: =IF($A27="","",IF(AK27>0,(AK27-AL27)/AK27,0)) | AN27: =IF($A27="","",IF(D27>0,SUMIFS(Calc!$BU:$BU,Calc!$C:$C,$A27,Calc!$D:$D,"M")/D27,0)) | AO27: =IF($A27="","",IF(C27>0,SUMIFS(Calc!$BU:$BU,Calc!$C:$C,$A27,Calc!$D:$D,"F")/C27,0)) | AP27: =IF($A27="","",IF(AN27>0,(AN27-AO27)/AN27,0)) | AQ27: =IF($A27="","",IF(AND(AI27>0,AJ27>0),0,AE27)) | AR27: =IF($A27="","",SUMIFS(Calc!$BU:$BU,Calc!$C:$C,$A27)) | AS27: =IF($A27="","",SUMIFS(Calc!$BV:$BV,Calc!$C:$C,$A27)) | AT27: =IF($A27="","",SUMIFS(Calc!$BW:$BW,Calc!$C:$C,$A27)) | AU27: =IF($A27="","",IF(B27>0,AS27-H27*AR27/B27,0)) | AV27: =IF($A27="","",IF(B27>0,AT27-I27*AR27/B27,0)) | AW27: =IF($A27="","",IF(V27=1,(AU27*Q27-AV27*R27)/U27,0)) | AX27: =IF($A27="","",IF(V27=1,(AV27*P27-AU27*R27)/U27,0)) | AY27: =IF($A27="","",IF(AND(V27=1,C27>0,D27>0,AN27>0),(AW27*(Y27-Z27)+AX27*(AA27-AB27))/AN27,0)) | AZ27: =IF($A27="","",IF(AP27>=0,MAX(0,MIN(AY27,AP27)),MIN(0,MAX(AY27,AP27)))) | BA27: =IF($A27="","",AP27-AZ27)
A28: =IFERROR(INDEX(Calc!$C:$C,MATCH(24,Calc!$BX:$BX,0)),"") | B28: =IF($A28="","",COUNTIFS(Calc!$C:$C,$A28)) | C28: =IF($A28="","",COUNTIFS(Calc!$C:$C,$A28,Calc!$D:$D,"F")) | D28: =IF($A28="","",COUNTIFS(Calc!$C:$C,$A28,Calc!$D:$D,"M")) | E28: =IF($A28="","",IF(D28>0,SUMIFS(Calc!$Q:$Q,Calc!$C:$C,$A28,Calc!$D:$D,"M")/D28,0)) | F28: =IF($A28="","",IF(C28>0,SUMIFS(Calc!$Q:$Q,Calc!$C:$C,$A28,Calc!$D:$D,"F")/C28,0)) | G28: =IF($A28="","",IF(AND(C28>0,D28>0,E28>0),(E28-F28)/E28,0)) | H28: =IF($A28="","",SUMIFS(Calc!$E:$E,Calc!$C:$C,$A28)) | I28: =IF($A28="","",SUMIFS(Calc!$P:$P,Calc!$C:$C,$A28)) | J28: =IF($A28="","",SUMIFS(Calc!$Q:$Q,Calc!$C:$C,$A28)) | K28: =IF($A28="","",SUMIFS(Calc!$R:$R,Calc!$C:$C,$A28)) | L28: =IF($A28="","",SUMIFS(Calc!$S:$S,Calc!$C:$C,$A28)) | M28: =IF($A28="","",SUMIFS(Calc!$T:$T,Calc!$C:$C,$A28)) | N28: =IF($A28="","",SUMIFS(Calc!$U:$U,Calc!$C:$C,$A28)) | O28: =IF($A28="","",SUMIFS(Calc!$V:$V,Calc!$C:$C,$A28)) | P28: =IF($A28="","",IF(B28>0,K28-H28^2/B28,0)) | Q28: =IF($A28="","",IF(B28>0,L28-I28^2/B28,0)) | R28: =IF($A28="","",IF(B28>0,M28-H28*I28/B28,0)) | S28: =IF($A28="","",IF(B28>0,N28-H28*J28/B28,0)) | T28: =IF($A28="","",IF(B28>0,O28-I28*J28/B28,0)) | U28: =IF($A28="","",P28*Q28-R28^2) | V28: =IF($A28="","",IF(AND(B28>=4,ABS(U28)>0.000000001),1,0)) | W28: =IF($A28="","",IF(V28=1,(S28*Q28-T28*R28)/U28,0)) | X28: =IF($A28="","",IF(V28=1,(T28*P28-S28*R28)/U28,0)) | Y28: =IF($A28="","",IF(D28>0,SUMIFS(Calc!$E:$E,Calc!$C:$C,$A28,Calc!$D:$D,"M")/D28,0)) | Z28: =IF($A28="","",IF(C28>0,SUMIFS(Calc!$E:$E,Calc!$C:$C,$A28,Calc!$D:$D,"F")/C28,0)) | AA28: =IF($A28="","",IF(D28>0,SUMIFS(Calc!$P:$P,Calc!$C:$C,$A28,Calc!$D:$D,"M")/D28,0)) | AB28: =IF($A28="","",IF(C28>0,SUMIFS(Calc!$P:$P,Calc!$C:$C,$A28,Calc!$D:$D,"F")/C28,0)) | AC28: =IF($A28="","",IF(AND(V28=1,C28>0,D28>0,E28>0),(W28*(Y28-Z28)+X28*(AA28-AB28))/E28,0)) | AD28: =IF($A28="","",IF(G28>=0,MAX(0,MIN(AC28,G28)),MIN(0,MAX(AC28,G28)))) | AE28: =IF($A28="","",G28-AD28) | AF28: =IF($A28="","",INT((B28+1)/2)) | AG28: =IF($A28="","",INT(B28/2)+1) | AH28: =IF($A28="","",(SUMIFS(Calc!$Q:$Q,Calc!$C:$C,$A28,Calc!$X:$X,AF28)+SUMIFS(Calc!$Q:$Q,Calc!$C:$C,$A28,Calc!$X:$X,AG28))/2) | AI28: =IF($A28="","",IF(AND(G28>=0,AE28>0.000000000001),AE28*E28*C28,0)) | AJ28: =IF($A28="","",SUMIFS(Calc!$AA:$AA,Calc!$C:$C,$A28)) | AK28: =IF($A28="","",IF(D28>0,SUMIFS(Calc!$BT:$BT,Calc!$C:$C,$A28,Calc!$D:$D,"M")/D28,0)) | AL28: =IF($A28="","",IF(C28>0,SUMIFS(Calc!$BT:$BT,Calc!$C:$C,$A28,Calc!$D:$D,"F")/C28,0)) | AM28: =IF($A28="","",IF(AK28>0,(AK28-AL28)/AK28,0)) | AN28: =IF($A28="","",IF(D28>0,SUMIFS(Calc!$BU:$BU,Calc!$C:$C,$A28,Calc!$D:$D,"M")/D28,0)) | AO28: =IF($A28="","",IF(C28>0,SUMIFS(Calc!$BU:$BU,Calc!$C:$C,$A28,Calc!$D:$D,"F")/C28,0)) | AP28: =IF($A28="","",IF(AN28>0,(AN28-AO28)/AN28,0)) | AQ28: =IF($A28="","",IF(AND(AI28>0,AJ28>0),0,AE28)) | AR28: =IF($A28="","",SUMIFS(Calc!$BU:$BU,Calc!$C:$C,$A28)) | AS28: =IF($A28="","",SUMIFS(Calc!$BV:$BV,Calc!$C:$C,$A28)) | AT28: =IF($A28="","",SUMIFS(Calc!$BW:$BW,Calc!$C:$C,$A28)) | AU28: =IF($A28="","",IF(B28>0,AS28-H28*AR28/B28,0)) | AV28: =IF($A28="","",IF(B28>0,AT28-I28*AR28/B28,0)) | AW28: =IF($A28="","",IF(V28=1,(AU28*Q28-AV28*R28)/U28,0)) | AX28: =IF($A28="","",IF(V28=1,(AV28*P28-AU28*R28)/U28,0)) | AY28: =IF($A28="","",IF(AND(V28=1,C28>0,D28>0,AN28>0),(AW28*(Y28-Z28)+AX28*(AA28-AB28))/AN28,0)) | AZ28: =IF($A28="","",IF(AP28>=0,MAX(0,MIN(AY28,AP28)),MIN(0,MAX(AY28,AP28)))) | BA28: =IF($A28="","",AP28-AZ28)
A29: =IFERROR(INDEX(Calc!$C:$C,MATCH(25,Calc!$BX:$BX,0)),"") | B29: =IF($A29="","",COUNTIFS(Calc!$C:$C,$A29)) | C29: =IF($A29="","",COUNTIFS(Calc!$C:$C,$A29,Calc!$D:$D,"F")) | D29: =IF($A29="","",COUNTIFS(Calc!$C:$C,$A29,Calc!$D:$D,"M")) | E29: =IF($A29="","",IF(D29>0,SUMIFS(Calc!$Q:$Q,Calc!$C:$C,$A29,Calc!$D:$D,"M")/D29,0)) | F29: =IF($A29="","",IF(C29>0,SUMIFS(Calc!$Q:$Q,Calc!$C:$C,$A29,Calc!$D:$D,"F")/C29,0)) | G29: =IF($A29="","",IF(AND(C29>0,D29>0,E29>0),(E29-F29)/E29,0)) | H29: =IF($A29="","",SUMIFS(Calc!$E:$E,Calc!$C:$C,$A29)) | I29: =IF($A29="","",SUMIFS(Calc!$P:$P,Calc!$C:$C,$A29)) | J29: =IF($A29="","",SUMIFS(Calc!$Q:$Q,Calc!$C:$C,$A29)) | K29: =IF($A29="","",SUMIFS(Calc!$R:$R,Calc!$C:$C,$A29)) | L29: =IF($A29="","",SUMIFS(Calc!$S:$S,Calc!$C:$C,$A29)) | M29: =IF($A29="","",SUMIFS(Calc!$T:$T,Calc!$C:$C,$A29)) | N29: =IF($A29="","",SUMIFS(Calc!$U:$U,Calc!$C:$C,$A29)) | O29: =IF($A29="","",SUMIFS(Calc!$V:$V,Calc!$C:$C,$A29)) | P29: =IF($A29="","",IF(B29>0,K29-H29^2/B29,0)) | Q29: =IF($A29="","",IF(B29>0,L29-I29^2/B29,0)) | R29: =IF($A29="","",IF(B29>0,M29-H29*I29/B29,0)) | S29: =IF($A29="","",IF(B29>0,N29-H29*J29/B29,0)) | T29: =IF($A29="","",IF(B29>0,O29-I29*J29/B29,0)) | U29: =IF($A29="","",P29*Q29-R29^2) | V29: =IF($A29="","",IF(AND(B29>=4,ABS(U29)>0.000000001),1,0)) | W29: =IF($A29="","",IF(V29=1,(S29*Q29-T29*R29)/U29,0)) | X29: =IF($A29="","",IF(V29=1,(T29*P29-S29*R29)/U29,0)) | Y29: =IF($A29="","",IF(D29>0,SUMIFS(Calc!$E:$E,Calc!$C:$C,$A29,Calc!$D:$D,"M")/D29,0)) | Z29: =IF($A29="","",IF(C29>0,SUMIFS(Calc!$E:$E,Calc!$C:$C,$A29,Calc!$D:$D,"F")/C29,0)) | AA29: =IF($A29="","",IF(D29>0,SUMIFS(Calc!$P:$P,Calc!$C:$C,$A29,Calc!$D:$D,"M")/D29,0)) | AB29: =IF($A29="","",IF(C29>0,SUMIFS(Calc!$P:$P,Calc!$C:$C,$A29,Calc!$D:$D,"F")/C29,0)) | AC29: =IF($A29="","",IF(AND(V29=1,C29>0,D29>0,E29>0),(W29*(Y29-Z29)+X29*(AA29-AB29))/E29,0)) | AD29: =IF($A29="","",IF(G29>=0,MAX(0,MIN(AC29,G29)),MIN(0,MAX(AC29,G29)))) | AE29: =IF($A29="","",G29-AD29) | AF29: =IF($A29="","",INT((B29+1)/2)) | AG29: =IF($A29="","",INT(B29/2)+1) | AH29: =IF($A29="","",(SUMIFS(Calc!$Q:$Q,Calc!$C:$C,$A29,Calc!$X:$X,AF29)+SUMIFS(Calc!$Q:$Q,Calc!$C:$C,$A29,Calc!$X:$X,AG29))/2) | AI29: =IF($A29="","",IF(AND(G29>=0,AE29>0.000000000001),AE29*E29*C29,0)) | AJ29: =IF($A29="","",SUMIFS(Calc!$AA:$AA,Calc!$C:$C,$A29)) | AK29: =IF($A29="","",IF(D29>0,SUMIFS(Calc!$BT:$BT,Calc!$C:$C,$A29,Calc!$D:$D,"M")/D29,0)) | AL29: =IF($A29="","",IF(C29>0,SUMIFS(Calc!$BT:$BT,Calc!$C:$C,$A29,Calc!$D:$D,"F")/C29,0)) | AM29: =IF($A29="","",IF(AK29>0,(AK29-AL29)/AK29,0)) | AN29: =IF($A29="","",IF(D29>0,SUMIFS(Calc!$BU:$BU,Calc!$C:$C,$A29,Calc!$D:$D,"M")/D29,0)) | AO29: =IF($A29="","",IF(C29>0,SUMIFS(Calc!$BU:$BU,Calc!$C:$C,$A29,Calc!$D:$D,"F")/C29,0)) | AP29: =IF($A29="","",IF(AN29>0,(AN29-AO29)/AN29,0)) | AQ29: =IF($A29="","",IF(AND(AI29>0,AJ29>0),0,AE29)) | AR29: =IF($A29="","",SUMIFS(Calc!$BU:$BU,Calc!$C:$C,$A29)) | AS29: =IF($A29="","",SUMIFS(Calc!$BV:$BV,Calc!$C:$C,$A29)) | AT29: =IF($A29="","",SUMIFS(Calc!$BW:$BW,Calc!$C:$C,$A29)) | AU29: =IF($A29="","",IF(B29>0,AS29-H29*AR29/B29,0)) | AV29: =IF($A29="","",IF(B29>0,AT29-I29*AR29/B29,0)) | AW29: =IF($A29="","",IF(V29=1,(AU29*Q29-AV29*R29)/U29,0)) | AX29: =IF($A29="","",IF(V29=1,(AV29*P29-AU29*R29)/U29,0)) | AY29: =IF($A29="","",IF(AND(V29=1,C29>0,D29>0,AN29>0),(AW29*(Y29-Z29)+AX29*(AA29-AB29))/AN29,0)) | AZ29: =IF($A29="","",IF(AP29>=0,MAX(0,MIN(AY29,AP29)),MIN(0,MAX(AY29,AP29)))) | BA29: =IF($A29="","",AP29-AZ29)
A30: =IFERROR(INDEX(Calc!$C:$C,MATCH(26,Calc!$BX:$BX,0)),"") | B30: =IF($A30="","",COUNTIFS(Calc!$C:$C,$A30)) | C30: =IF($A30="","",COUNTIFS(Calc!$C:$C,$A30,Calc!$D:$D,"F")) | D30: =IF($A30="","",COUNTIFS(Calc!$C:$C,$A30,Calc!$D:$D,"M")) | E30: =IF($A30="","",IF(D30>0,SUMIFS(Calc!$Q:$Q,Calc!$C:$C,$A30,Calc!$D:$D,"M")/D30,0)) | F30: =IF($A30="","",IF(C30>0,SUMIFS(Calc!$Q:$Q,Calc!$C:$C,$A30,Calc!$D:$D,"F")/C30,0)) | G30: =IF($A30="","",IF(AND(C30>0,D30>0,E30>0),(E30-F30)/E30,0)) | H30: =IF($A30="","",SUMIFS(Calc!$E:$E,Calc!$C:$C,$A30)) | I30: =IF($A30="","",SUMIFS(Calc!$P:$P,Calc!$C:$C,$A30)) | J30: =IF($A30="","",SUMIFS(Calc!$Q:$Q,Calc!$C:$C,$A30)) | K30: =IF($A30="","",SUMIFS(Calc!$R:$R,Calc!$C:$C,$A30)) | L30: =IF($A30="","",SUMIFS(Calc!$S:$S,Calc!$C:$C,$A30)) | M30: =IF($A30="","",SUMIFS(Calc!$T:$T,Calc!$C:$C,$A30)) | N30: =IF($A30="","",SUMIFS(Calc!$U:$U,Calc!$C:$C,$A30)) | O30: =IF($A30="","",SUMIFS(Calc!$V:$V,Calc!$C:$C,$A30)) | P30: =IF($A30="","",IF(B30>0,K30-H30^2/B30,0)) | Q30: =IF($A30="","",IF(B30>0,L30-I30^2/B30,0)) | R30: =IF($A30="","",IF(B30>0,M30-H30*I30/B30,0)) | S30: =IF($A30="","",IF(B30>0,N30-H30*J30/B30,0)) | T30: =IF($A30="","",IF(B30>0,O30-I30*J30/B30,0)) | U30: =IF($A30="","",P30*Q30-R30^2) | V30: =IF($A30="","",IF(AND(B30>=4,ABS(U30)>0.000000001),1,0)) | W30: =IF($A30="","",IF(V30=1,(S30*Q30-T30*R30)/U30,0)) | X30: =IF($A30="","",IF(V30=1,(T30*P30-S30*R30)/U30,0)) | Y30: =IF($A30="","",IF(D30>0,SUMIFS(Calc!$E:$E,Calc!$C:$C,$A30,Calc!$D:$D,"M")/D30,0)) | Z30: =IF($A30="","",IF(C30>0,SUMIFS(Calc!$E:$E,Calc!$C:$C,$A30,Calc!$D:$D,"F")/C30,0)) | AA30: =IF($A30="","",IF(D30>0,SUMIFS(Calc!$P:$P,Calc!$C:$C,$A30,Calc!$D:$D,"M")/D30,0)) | AB30: =IF($A30="","",IF(C30>0,SUMIFS(Calc!$P:$P,Calc!$C:$C,$A30,Calc!$D:$D,"F")/C30,0)) | AC30: =IF($A30="","",IF(AND(V30=1,C30>0,D30>0,E30>0),(W30*(Y30-Z30)+X30*(AA30-AB30))/E30,0)) | AD30: =IF($A30="","",IF(G30>=0,MAX(0,MIN(AC30,G30)),MIN(0,MAX(AC30,G30)))) | AE30: =IF($A30="","",G30-AD30) | AF30: =IF($A30="","",INT((B30+1)/2)) | AG30: =IF($A30="","",INT(B30/2)+1) | AH30: =IF($A30="","",(SUMIFS(Calc!$Q:$Q,Calc!$C:$C,$A30,Calc!$X:$X,AF30)+SUMIFS(Calc!$Q:$Q,Calc!$C:$C,$A30,Calc!$X:$X,AG30))/2) | AI30: =IF($A30="","",IF(AND(G30>=0,AE30>0.000000000001),AE30*E30*C30,0)) | AJ30: =IF($A30="","",SUMIFS(Calc!$AA:$AA,Calc!$C:$C,$A30)) | AK30: =IF($A30="","",IF(D30>0,SUMIFS(Calc!$BT:$BT,Calc!$C:$C,$A30,Calc!$D:$D,"M")/D30,0)) | AL30: =IF($A30="","",IF(C30>0,SUMIFS(Calc!$BT:$BT,Calc!$C:$C,$A30,Calc!$D:$D,"F")/C30,0)) | AM30: =IF($A30="","",IF(AK30>0,(AK30-AL30)/AK30,0)) | AN30: =IF($A30="","",IF(D30>0,SUMIFS(Calc!$BU:$BU,Calc!$C:$C,$A30,Calc!$D:$D,"M")/D30,0)) | AO30: =IF($A30="","",IF(C30>0,SUMIFS(Calc!$BU:$BU,Calc!$C:$C,$A30,Calc!$D:$D,"F")/C30,0)) | AP30: =IF($A30="","",IF(AN30>0,(AN30-AO30)/AN30,0)) | AQ30: =IF($A30="","",IF(AND(AI30>0,AJ30>0),0,AE30)) | AR30: =IF($A30="","",SUMIFS(Calc!$BU:$BU,Calc!$C:$C,$A30)) | AS30: =IF($A30="","",SUMIFS(Calc!$BV:$BV,Calc!$C:$C,$A30)) | AT30: =IF($A30="","",SUMIFS(Calc!$BW:$BW,Calc!$C:$C,$A30)) | AU30: =IF($A30="","",IF(B30>0,AS30-H30*AR30/B30,0)) | AV30: =IF($A30="","",IF(B30>0,AT30-I30*AR30/B30,0)) | AW30: =IF($A30="","",IF(V30=1,(AU30*Q30-AV30*R30)/U30,0)) | AX30: =IF($A30="","",IF(V30=1,(AV30*P30-AU30*R30)/U30,0)) | AY30: =IF($A30="","",IF(AND(V30=1,C30>0,D30>0,AN30>0),(AW30*(Y30-Z30)+AX30*(AA30-AB30))/AN30,0)) | AZ30: =IF($A30="","",IF(AP30>=0,MAX(0,MIN(AY30,AP30)),MIN(0,MAX(AY30,AP30)))) | BA30: =IF($A30="","",AP30-AZ30)
A31: =IFERROR(INDEX(Calc!$C:$C,MATCH(27,Calc!$BX:$BX,0)),"") | B31: =IF($A31="","",COUNTIFS(Calc!$C:$C,$A31)) | C31: =IF($A31="","",COUNTIFS(Calc!$C:$C,$A31,Calc!$D:$D,"F")) | D31: =IF($A31="","",COUNTIFS(Calc!$C:$C,$A31,Calc!$D:$D,"M")) | E31: =IF($A31="","",IF(D31>0,SUMIFS(Calc!$Q:$Q,Calc!$C:$C,$A31,Calc!$D:$D,"M")/D31,0)) | F31: =IF($A31="","",IF(C31>0,SUMIFS(Calc!$Q:$Q,Calc!$C:$C,$A31,Calc!$D:$D,"F")/C31,0)) | G31: =IF($A31="","",IF(AND(C31>0,D31>0,E31>0),(E31-F31)/E31,0)) | H31: =IF($A31="","",SUMIFS(Calc!$E:$E,Calc!$C:$C,$A31)) | I31: =IF($A31="","",SUMIFS(Calc!$P:$P,Calc!$C:$C,$A31)) | J31: =IF($A31="","",SUMIFS(Calc!$Q:$Q,Calc!$C:$C,$A31)) | K31: =IF($A31="","",SUMIFS(Calc!$R:$R,Calc!$C:$C,$A31)) | L31: =IF($A31="","",SUMIFS(Calc!$S:$S,Calc!$C:$C,$A31)) | M31: =IF($A31="","",SUMIFS(Calc!$T:$T,Calc!$C:$C,$A31)) | N31: =IF($A31="","",SUMIFS(Calc!$U:$U,Calc!$C:$C,$A31)) | O31: =IF($A31="","",SUMIFS(Calc!$V:$V,Calc!$C:$C,$A31)) | P31: =IF($A31="","",IF(B31>0,K31-H31^2/B31,0)) | Q31: =IF($A31="","",IF(B31>0,L31-I31^2/B31,0)) | R31: =IF($A31="","",IF(B31>0,M31-H31*I31/B31,0)) | S31: =IF($A31="","",IF(B31>0,N31-H31*J31/B31,0)) | T31: =IF($A31="","",IF(B31>0,O31-I31*J31/B31,0)) | U31: =IF($A31="","",P31*Q31-R31^2) | V31: =IF($A31="","",IF(AND(B31>=4,ABS(U31)>0.000000001),1,0)) | W31: =IF($A31="","",IF(V31=1,(S31*Q31-T31*R31)/U31,0)) | X31: =IF($A31="","",IF(V31=1,(T31*P31-S31*R31)/U31,0)) | Y31: =IF($A31="","",IF(D31>0,SUMIFS(Calc!$E:$E,Calc!$C:$C,$A31,Calc!$D:$D,"M")/D31,0)) | Z31: =IF($A31="","",IF(C31>0,SUMIFS(Calc!$E:$E,Calc!$C:$C,$A31,Calc!$D:$D,"F")/C31,0)) | AA31: =IF($A31="","",IF(D31>0,SUMIFS(Calc!$P:$P,Calc!$C:$C,$A31,Calc!$D:$D,"M")/D31,0)) | AB31: =IF($A31="","",IF(C31>0,SUMIFS(Calc!$P:$P,Calc!$C:$C,$A31,Calc!$D:$D,"F")/C31,0)) | AC31: =IF($A31="","",IF(AND(V31=1,C31>0,D31>0,E31>0),(W31*(Y31-Z31)+X31*(AA31-AB31))/E31,0)) | AD31: =IF($A31="","",IF(G31>=0,MAX(0,MIN(AC31,G31)),MIN(0,MAX(AC31,G31)))) | AE31: =IF($A31="","",G31-AD31) | AF31: =IF($A31="","",INT((B31+1)/2)) | AG31: =IF($A31="","",INT(B31/2)+1) | AH31: =IF($A31="","",(SUMIFS(Calc!$Q:$Q,Calc!$C:$C,$A31,Calc!$X:$X,AF31)+SUMIFS(Calc!$Q:$Q,Calc!$C:$C,$A31,Calc!$X:$X,AG31))/2) | AI31: =IF($A31="","",IF(AND(G31>=0,AE31>0.000000000001),AE31*E31*C31,0)) | AJ31: =IF($A31="","",SUMIFS(Calc!$AA:$AA,Calc!$C:$C,$A31)) | AK31: =IF($A31="","",IF(D31>0,SUMIFS(Calc!$BT:$BT,Calc!$C:$C,$A31,Calc!$D:$D,"M")/D31,0)) | AL31: =IF($A31="","",IF(C31>0,SUMIFS(Calc!$BT:$BT,Calc!$C:$C,$A31,Calc!$D:$D,"F")/C31,0)) | AM31: =IF($A31="","",IF(AK31>0,(AK31-AL31)/AK31,0)) | AN31: =IF($A31="","",IF(D31>0,SUMIFS(Calc!$BU:$BU,Calc!$C:$C,$A31,Calc!$D:$D,"M")/D31,0)) | AO31: =IF($A31="","",IF(C31>0,SUMIFS(Calc!$BU:$BU,Calc!$C:$C,$A31,Calc!$D:$D,"F")/C31,0)) | AP31: =IF($A31="","",IF(AN31>0,(AN31-AO31)/AN31,0)) | AQ31: =IF($A31="","",IF(AND(AI31>0,AJ31>0),0,AE31)) | AR31: =IF($A31="","",SUMIFS(Calc!$BU:$BU,Calc!$C:$C,$A31)) | AS31: =IF($A31="","",SUMIFS(Calc!$BV:$BV,Calc!$C:$C,$A31)) | AT31: =IF($A31="","",SUMIFS(Calc!$BW:$BW,Calc!$C:$C,$A31)) | AU31: =IF($A31="","",IF(B31>0,AS31-H31*AR31/B31,0)) | AV31: =IF($A31="","",IF(B31>0,AT31-I31*AR31/B31,0)) | AW31: =IF($A31="","",IF(V31=1,(AU31*Q31-AV31*R31)/U31,0)) | AX31: =IF($A31="","",IF(V31=1,(AV31*P31-AU31*R31)/U31,0)) | AY31: =IF($A31="","",IF(AND(V31=1,C31>0,D31>0,AN31>0),(AW31*(Y31-Z31)+AX31*(AA31-AB31))/AN31,0)) | AZ31: =IF($A31="","",IF(AP31>=0,MAX(0,MIN(AY31,AP31)),MIN(0,MAX(AY31,AP31)))) | BA31: =IF($A31="","",AP31-AZ31)
A32: =IFERROR(INDEX(Calc!$C:$C,MATCH(28,Calc!$BX:$BX,0)),"") | B32: =IF($A32="","",COUNTIFS(Calc!$C:$C,$A32)) | C32: =IF($A32="","",COUNTIFS(Calc!$C:$C,$A32,Calc!$D:$D,"F")) | D32: =IF($A32="","",COUNTIFS(Calc!$C:$C,$A32,Calc!$D:$D,"M")) | E32: =IF($A32="","",IF(D32>0,SUMIFS(Calc!$Q:$Q,Calc!$C:$C,$A32,Calc!$D:$D,"M")/D32,0)) | F32: =IF($A32="","",IF(C32>0,SUMIFS(Calc!$Q:$Q,Calc!$C:$C,$A32,Calc!$D:$D,"F")/C32,0)) | G32: =IF($A32="","",IF(AND(C32>0,D32>0,E32>0),(E32-F32)/E32,0)) | H32: =IF($A32="","",SUMIFS(Calc!$E:$E,Calc!$C:$C,$A32)) | I32: =IF($A32="","",SUMIFS(Calc!$P:$P,Calc!$C:$C,$A32)) | J32: =IF($A32="","",SUMIFS(Calc!$Q:$Q,Calc!$C:$C,$A32)) | K32: =IF($A32="","",SUMIFS(Calc!$R:$R,Calc!$C:$C,$A32)) | L32: =IF($A32="","",SUMIFS(Calc!$S:$S,Calc!$C:$C,$A32)) | M32: =IF($A32="","",SUMIFS(Calc!$T:$T,Calc!$C:$C,$A32)) | N32: =IF($A32="","",SUMIFS(Calc!$U:$U,Calc!$C:$C,$A32)) | O32: =IF($A32="","",SUMIFS(Calc!$V:$V,Calc!$C:$C,$A32)) | P32: =IF($A32="","",IF(B32>0,K32-H32^2/B32,0)) | Q32: =IF($A32="","",IF(B32>0,L32-I32^2/B32,0)) | R32: =IF($A32="","",IF(B32>0,M32-H32*I32/B32,0)) | S32: =IF($A32="","",IF(B32>0,N32-H32*J32/B32,0)) | T32: =IF($A32="","",IF(B32>0,O32-I32*J32/B32,0)) | U32: =IF($A32="","",P32*Q32-R32^2) | V32: =IF($A32="","",IF(AND(B32>=4,ABS(U32)>0.000000001),1,0)) | W32: =IF($A32="","",IF(V32=1,(S32*Q32-T32*R32)/U32,0)) | X32: =IF($A32="","",IF(V32=1,(T32*P32-S32*R32)/U32,0)) | Y32: =IF($A32="","",IF(D32>0,SUMIFS(Calc!$E:$E,Calc!$C:$C,$A32,Calc!$D:$D,"M")/D32,0)) | Z32: =IF($A32="","",IF(C32>0,SUMIFS(Calc!$E:$E,Calc!$C:$C,$A32,Calc!$D:$D,"F")/C32,0)) | AA32: =IF($A32="","",IF(D32>0,SUMIFS(Calc!$P:$P,Calc!$C:$C,$A32,Calc!$D:$D,"M")/D32,0)) | AB32: =IF($A32="","",IF(C32>0,SUMIFS(Calc!$P:$P,Calc!$C:$C,$A32,Calc!$D:$D,"F")/C32,0)) | AC32: =IF($A32="","",IF(AND(V32=1,C32>0,D32>0,E32>0),(W32*(Y32-Z32)+X32*(AA32-AB32))/E32,0)) | AD32: =IF($A32="","",IF(G32>=0,MAX(0,MIN(AC32,G32)),MIN(0,MAX(AC32,G32)))) | AE32: =IF($A32="","",G32-AD32) | AF32: =IF($A32="","",INT((B32+1)/2)) | AG32: =IF($A32="","",INT(B32/2)+1) | AH32: =IF($A32="","",(SUMIFS(Calc!$Q:$Q,Calc!$C:$C,$A32,Calc!$X:$X,AF32)+SUMIFS(Calc!$Q:$Q,Calc!$C:$C,$A32,Calc!$X:$X,AG32))/2) | AI32: =IF($A32="","",IF(AND(G32>=0,AE32>0.000000000001),AE32*E32*C32,0)) | AJ32: =IF($A32="","",SUMIFS(Calc!$AA:$AA,Calc!$C:$C,$A32)) | AK32: =IF($A32="","",IF(D32>0,SUMIFS(Calc!$BT:$BT,Calc!$C:$C,$A32,Calc!$D:$D,"M")/D32,0)) | AL32: =IF($A32="","",IF(C32>0,SUMIFS(Calc!$BT:$BT,Calc!$C:$C,$A32,Calc!$D:$D,"F")/C32,0)) | AM32: =IF($A32="","",IF(AK32>0,(AK32-AL32)/AK32,0)) | AN32: =IF($A32="","",IF(D32>0,SUMIFS(Calc!$BU:$BU,Calc!$C:$C,$A32,Calc!$D:$D,"M")/D32,0)) | AO32: =IF($A32="","",IF(C32>0,SUMIFS(Calc!$BU:$BU,Calc!$C:$C,$A32,Calc!$D:$D,"F")/C32,0)) | AP32: =IF($A32="","",IF(AN32>0,(AN32-AO32)/AN32,0)) | AQ32: =IF($A32="","",IF(AND(AI32>0,AJ32>0),0,AE32)) | AR32: =IF($A32="","",SUMIFS(Calc!$BU:$BU,Calc!$C:$C,$A32)) | AS32: =IF($A32="","",SUMIFS(Calc!$BV:$BV,Calc!$C:$C,$A32)) | AT32: =IF($A32="","",SUMIFS(Calc!$BW:$BW,Calc!$C:$C,$A32)) | AU32: =IF($A32="","",IF(B32>0,AS32-H32*AR32/B32,0)) | AV32: =IF($A32="","",IF(B32>0,AT32-I32*AR32/B32,0)) | AW32: =IF($A32="","",IF(V32=1,(AU32*Q32-AV32*R32)/U32,0)) | AX32: =IF($A32="","",IF(V32=1,(AV32*P32-AU32*R32)/U32,0)) | AY32: =IF($A32="","",IF(AND(V32=1,C32>0,D32>0,AN32>0),(AW32*(Y32-Z32)+AX32*(AA32-AB32))/AN32,0)) | AZ32: =IF($A32="","",IF(AP32>=0,MAX(0,MIN(AY32,AP32)),MIN(0,MAX(AY32,AP32)))) | BA32: =IF($A32="","",AP32-AZ32)
A33: =IFERROR(INDEX(Calc!$C:$C,MATCH(29,Calc!$BX:$BX,0)),"") | B33: =IF($A33="","",COUNTIFS(Calc!$C:$C,$A33)) | C33: =IF($A33="","",COUNTIFS(Calc!$C:$C,$A33,Calc!$D:$D,"F")) | D33: =IF($A33="","",COUNTIFS(Calc!$C:$C,$A33,Calc!$D:$D,"M")) | E33: =IF($A33="","",IF(D33>0,SUMIFS(Calc!$Q:$Q,Calc!$C:$C,$A33,Calc!$D:$D,"M")/D33,0)) | F33: =IF($A33="","",IF(C33>0,SUMIFS(Calc!$Q:$Q,Calc!$C:$C,$A33,Calc!$D:$D,"F")/C33,0)) | G33: =IF($A33="","",IF(AND(C33>0,D33>0,E33>0),(E33-F33)/E33,0)) | H33: =IF($A33="","",SUMIFS(Calc!$E:$E,Calc!$C:$C,$A33)) | I33: =IF($A33="","",SUMIFS(Calc!$P:$P,Calc!$C:$C,$A33)) | J33: =IF($A33="","",SUMIFS(Calc!$Q:$Q,Calc!$C:$C,$A33)) | K33: =IF($A33="","",SUMIFS(Calc!$R:$R,Calc!$C:$C,$A33)) | L33: =IF($A33="","",SUMIFS(Calc!$S:$S,Calc!$C:$C,$A33)) | M33: =IF($A33="","",SUMIFS(Calc!$T:$T,Calc!$C:$C,$A33)) | N33: =IF($A33="","",SUMIFS(Calc!$U:$U,Calc!$C:$C,$A33)) | O33: =IF($A33="","",SUMIFS(Calc!$V:$V,Calc!$C:$C,$A33)) | P33: =IF($A33="","",IF(B33>0,K33-H33^2/B33,0)) | Q33: =IF($A33="","",IF(B33>0,L33-I33^2/B33,0)) | R33: =IF($A33="","",IF(B33>0,M33-H33*I33/B33,0)) | S33: =IF($A33="","",IF(B33>0,N33-H33*J33/B33,0)) | T33: =IF($A33="","",IF(B33>0,O33-I33*J33/B33,0)) | U33: =IF($A33="","",P33*Q33-R33^2) | V33: =IF($A33="","",IF(AND(B33>=4,ABS(U33)>0.000000001),1,0)) | W33: =IF($A33="","",IF(V33=1,(S33*Q33-T33*R33)/U33,0)) | X33: =IF($A33="","",IF(V33=1,(T33*P33-S33*R33)/U33,0)) | Y33: =IF($A33="","",IF(D33>0,SUMIFS(Calc!$E:$E,Calc!$C:$C,$A33,Calc!$D:$D,"M")/D33,0)) | Z33: =IF($A33="","",IF(C33>0,SUMIFS(Calc!$E:$E,Calc!$C:$C,$A33,Calc!$D:$D,"F")/C33,0)) | AA33: =IF($A33="","",IF(D33>0,SUMIFS(Calc!$P:$P,Calc!$C:$C,$A33,Calc!$D:$D,"M")/D33,0)) | AB33: =IF($A33="","",IF(C33>0,SUMIFS(Calc!$P:$P,Calc!$C:$C,$A33,Calc!$D:$D,"F")/C33,0)) | AC33: =IF($A33="","",IF(AND(V33=1,C33>0,D33>0,E33>0),(W33*(Y33-Z33)+X33*(AA33-AB33))/E33,0)) | AD33: =IF($A33="","",IF(G33>=0,MAX(0,MIN(AC33,G33)),MIN(0,MAX(AC33,G33)))) | AE33: =IF($A33="","",G33-AD33) | AF33: =IF($A33="","",INT((B33+1)/2)) | AG33: =IF($A33="","",INT(B33/2)+1) | AH33: =IF($A33="","",(SUMIFS(Calc!$Q:$Q,Calc!$C:$C,$A33,Calc!$X:$X,AF33)+SUMIFS(Calc!$Q:$Q,Calc!$C:$C,$A33,Calc!$X:$X,AG33))/2) | AI33: =IF($A33="","",IF(AND(G33>=0,AE33>0.000000000001),AE33*E33*C33,0)) | AJ33: =IF($A33="","",SUMIFS(Calc!$AA:$AA,Calc!$C:$C,$A33)) | AK33: =IF($A33="","",IF(D33>0,SUMIFS(Calc!$BT:$BT,Calc!$C:$C,$A33,Calc!$D:$D,"M")/D33,0)) | AL33: =IF($A33="","",IF(C33>0,SUMIFS(Calc!$BT:$BT,Calc!$C:$C,$A33,Calc!$D:$D,"F")/C33,0)) | AM33: =IF($A33="","",IF(AK33>0,(AK33-AL33)/AK33,0)) | AN33: =IF($A33="","",IF(D33>0,SUMIFS(Calc!$BU:$BU,Calc!$C:$C,$A33,Calc!$D:$D,"M")/D33,0)) | AO33: =IF($A33="","",IF(C33>0,SUMIFS(Calc!$BU:$BU,Calc!$C:$C,$A33,Calc!$D:$D,"F")/C33,0)) | AP33: =IF($A33="","",IF(AN33>0,(AN33-AO33)/AN33,0)) | AQ33: =IF($A33="","",IF(AND(AI33>0,AJ33>0),0,AE33)) | AR33: =IF($A33="","",SUMIFS(Calc!$BU:$BU,Calc!$C:$C,$A33)) | AS33: =IF($A33="","",SUMIFS(Calc!$BV:$BV,Calc!$C:$C,$A33)) | AT33: =IF($A33="","",SUMIFS(Calc!$BW:$BW,Calc!$C:$C,$A33)) | AU33: =IF($A33="","",IF(B33>0,AS33-H33*AR33/B33,0)) | AV33: =IF($A33="","",IF(B33>0,AT33-I33*AR33/B33,0)) | AW33: =IF($A33="","",IF(V33=1,(AU33*Q33-AV33*R33)/U33,0)) | AX33: =IF($A33="","",IF(V33=1,(AV33*P33-AU33*R33)/U33,0)) | AY33: =IF($A33="","",IF(AND(V33=1,C33>0,D33>0,AN33>0),(AW33*(Y33-Z33)+AX33*(AA33-AB33))/AN33,0)) | AZ33: =IF($A33="","",IF(AP33>=0,MAX(0,MIN(AY33,AP33)),MIN(0,MAX(AY33,AP33)))) | BA33: =IF($A33="","",AP33-AZ33)
A34: =IFERROR(INDEX(Calc!$C:$C,MATCH(30,Calc!$BX:$BX,0)),"") | B34: =IF($A34="","",COUNTIFS(Calc!$C:$C,$A34)) | C34: =IF($A34="","",COUNTIFS(Calc!$C:$C,$A34,Calc!$D:$D,"F")) | D34: =IF($A34="","",COUNTIFS(Calc!$C:$C,$A34,Calc!$D:$D,"M")) | E34: =IF($A34="","",IF(D34>0,SUMIFS(Calc!$Q:$Q,Calc!$C:$C,$A34,Calc!$D:$D,"M")/D34,0)) | F34: =IF($A34="","",IF(C34>0,SUMIFS(Calc!$Q:$Q,Calc!$C:$C,$A34,Calc!$D:$D,"F")/C34,0)) | G34: =IF($A34="","",IF(AND(C34>0,D34>0,E34>0),(E34-F34)/E34,0)) | H34: =IF($A34="","",SUMIFS(Calc!$E:$E,Calc!$C:$C,$A34)) | I34: =IF($A34="","",SUMIFS(Calc!$P:$P,Calc!$C:$C,$A34)) | J34: =IF($A34="","",SUMIFS(Calc!$Q:$Q,Calc!$C:$C,$A34)) | K34: =IF($A34="","",SUMIFS(Calc!$R:$R,Calc!$C:$C,$A34)) | L34: =IF($A34="","",SUMIFS(Calc!$S:$S,Calc!$C:$C,$A34)) | M34: =IF($A34="","",SUMIFS(Calc!$T:$T,Calc!$C:$C,$A34)) | N34: =IF($A34="","",SUMIFS(Calc!$U:$U,Calc!$C:$C,$A34)) | O34: =IF($A34="","",SUMIFS(Calc!$V:$V,Calc!$C:$C,$A34)) | P34: =IF($A34="","",IF(B34>0,K34-H34^2/B34,0)) | Q34: =IF($A34="","",IF(B34>0,L34-I34^2/B34,0)) | R34: =IF($A34="","",IF(B34>0,M34-H34*I34/B34,0)) | S34: =IF($A34="","",IF(B34>0,N34-H34*J34/B34,0)) | T34: =IF($A34="","",IF(B34>0,O34-I34*J34/B34,0)) | U34: =IF($A34="","",P34*Q34-R34^2) | V34: =IF($A34="","",IF(AND(B34>=4,ABS(U34)>0.000000001),1,0)) | W34: =IF($A34="","",IF(V34=1,(S34*Q34-T34*R34)/U34,0)) | X34: =IF($A34="","",IF(V34=1,(T34*P34-S34*R34)/U34,0)) | Y34: =IF($A34="","",IF(D34>0,SUMIFS(Calc!$E:$E,Calc!$C:$C,$A34,Calc!$D:$D,"M")/D34,0)) | Z34: =IF($A34="","",IF(C34>0,SUMIFS(Calc!$E:$E,Calc!$C:$C,$A34,Calc!$D:$D,"F")/C34,0)) | AA34: =IF($A34="","",IF(D34>0,SUMIFS(Calc!$P:$P,Calc!$C:$C,$A34,Calc!$D:$D,"M")/D34,0)) | AB34: =IF($A34="","",IF(C34>0,SUMIFS(Calc!$P:$P,Calc!$C:$C,$A34,Calc!$D:$D,"F")/C34,0)) | AC34: =IF($A34="","",IF(AND(V34=1,C34>0,D34>0,E34>0),(W34*(Y34-Z34)+X34*(AA34-AB34))/E34,0)) | AD34: =IF($A34="","",IF(G34>=0,MAX(0,MIN(AC34,G34)),MIN(0,MAX(AC34,G34)))) | AE34: =IF($A34="","",G34-AD34) | AF34: =IF($A34="","",INT((B34+1)/2)) | AG34: =IF($A34="","",INT(B34/2)+1) | AH34: =IF($A34="","",(SUMIFS(Calc!$Q:$Q,Calc!$C:$C,$A34,Calc!$X:$X,AF34)+SUMIFS(Calc!$Q:$Q,Calc!$C:$C,$A34,Calc!$X:$X,AG34))/2) | AI34: =IF($A34="","",IF(AND(G34>=0,AE34>0.000000000001),AE34*E34*C34,0)) | AJ34: =IF($A34="","",SUMIFS(Calc!$AA:$AA,Calc!$C:$C,$A34)) | AK34: =IF($A34="","",IF(D34>0,SUMIFS(Calc!$BT:$BT,Calc!$C:$C,$A34,Calc!$D:$D,"M")/D34,0)) | AL34: =IF($A34="","",IF(C34>0,SUMIFS(Calc!$BT:$BT,Calc!$C:$C,$A34,Calc!$D:$D,"F")/C34,0)) | AM34: =IF($A34="","",IF(AK34>0,(AK34-AL34)/AK34,0)) | AN34: =IF($A34="","",IF(D34>0,SUMIFS(Calc!$BU:$BU,Calc!$C:$C,$A34,Calc!$D:$D,"M")/D34,0)) | AO34: =IF($A34="","",IF(C34>0,SUMIFS(Calc!$BU:$BU,Calc!$C:$C,$A34,Calc!$D:$D,"F")/C34,0)) | AP34: =IF($A34="","",IF(AN34>0,(AN34-AO34)/AN34,0)) | AQ34: =IF($A34="","",IF(AND(AI34>0,AJ34>0),0,AE34)) | AR34: =IF($A34="","",SUMIFS(Calc!$BU:$BU,Calc!$C:$C,$A34)) | AS34: =IF($A34="","",SUMIFS(Calc!$BV:$BV,Calc!$C:$C,$A34)) | AT34: =IF($A34="","",SUMIFS(Calc!$BW:$BW,Calc!$C:$C,$A34)) | AU34: =IF($A34="","",IF(B34>0,AS34-H34*AR34/B34,0)) | AV34: =IF($A34="","",IF(B34>0,AT34-I34*AR34/B34,0)) | AW34: =IF($A34="","",IF(V34=1,(AU34*Q34-AV34*R34)/U34,0)) | AX34: =IF($A34="","",IF(V34=1,(AV34*P34-AU34*R34)/U34,0)) | AY34: =IF($A34="","",IF(AND(V34=1,C34>0,D34>0,AN34>0),(AW34*(Y34-Z34)+AX34*(AA34-AB34))/AN34,0)) | AZ34: =IF($A34="","",IF(AP34>=0,MAX(0,MIN(AY34,AP34)),MIN(0,MAX(AY34,AP34)))) | BA34: =IF($A34="","",AP34-AZ34)
